{
  "type": "FeatureCollection",
  "features": [
    {
      "type": "Feature",
      "properties": {
        "nummer": 21535,
        "objectid": 8,
        "baumbezeichnung_deutsch": "Bergahorn",
        "baumbezeichnung_botanisch": "Acer pseudoplatanus",
        "baumtyp": "Laub",
        "bemerkung": null,
        "pflanzjahr": null,
        "entnahmejahr": null,
        "baumpatenschaft": null,
        "altersklassifizierung": "mittel"
      },
      "geometry": {
        "type": "Point",
        "coordinates": [
          15.429307112495856,
          47.112924511718084
        ]
      }
    },
    {
      "type": "Feature",
      "properties": {
        "nummer": 21527,
        "objectid": 647,
        "baumbezeichnung_deutsch": "Rotfichte",
        "baumbezeichnung_botanisch": "Picea abies",
        "baumtyp": "Nadel",
        "bemerkung": null,
        "pflanzjahr": null,
        "entnahmejahr": null,
        "baumpatenschaft": null,
        "altersklassifizierung": "jung"
      },
      "geometry": {
        "type": "Point",
        "coordinates": [
          15.429502366303376,
          47.11306802794467
        ]
      }
    },
    {
      "type": "Feature",
      "properties": {
        "nummer": 21515,
        "objectid": 777,
        "baumbezeichnung_deutsch": "Rotfichte",
        "baumbezeichnung_botanisch": "Picea abies",
        "baumtyp": "Nadel",
        "bemerkung": null,
        "pflanzjahr": null,
        "entnahmejahr": null,
        "baumpatenschaft": null,
        "altersklassifizierung": "jung"
      },
      "geometry": {
        "type": "Point",
        "coordinates": [
          15.430144736516821,
          47.11318878895198
        ]
      }
    },
    {
      "type": "Feature",
      "properties": {
        "nummer": 10601,
        "objectid": 960,
        "baumbezeichnung_deutsch": "Rotfichte",
        "baumbezeichnung_botanisch": "Picea abies",
        "baumtyp": "Nadel",
        "bemerkung": null,
        "pflanzjahr": null,
        "entnahmejahr": null,
        "baumpatenschaft": null,
        "altersklassifizierung": "mittel"
      },
      "geometry": {
        "type": "Point",
        "coordinates": [
          15.424878782010818,
          47.10768441096814
        ]
      }
    },
    {
      "type": "Feature",
      "properties": {
        "nummer": 10616,
        "objectid": 962,
        "baumbezeichnung_deutsch": "Sandbirke, Weißbirke",
        "baumbezeichnung_botanisch": "Betula pendula",
        "baumtyp": "Laub",
        "bemerkung": null,
        "pflanzjahr": null,
        "entnahmejahr": null,
        "baumpatenschaft": null,
        "altersklassifizierung": "mittel"
      },
      "geometry": {
        "type": "Point",
        "coordinates": [
          15.426790166253921,
          47.11193728577884
        ]
      }
    },
    {
      "type": "Feature",
      "properties": {
        "nummer": 27538,
        "objectid": 1067,
        "baumbezeichnung_deutsch": "Trauerweide",
        "baumbezeichnung_botanisch": "Salix alba 'Tristis'",
        "baumtyp": "Laub",
        "bemerkung": null,
        "pflanzjahr": "2007",
        "entnahmejahr": null,
        "baumpatenschaft": null,
        "altersklassifizierung": "jung"
      },
      "geometry": {
        "type": "Point",
        "coordinates": [
          15.42900526374834,
          47.11320255371674
        ]
      }
    },
    {
      "type": "Feature",
      "properties": {
        "nummer": 21510,
        "objectid": 1069,
        "baumbezeichnung_deutsch": "Bergahorn",
        "baumbezeichnung_botanisch": "Acer pseudoplatanus",
        "baumtyp": "Laub",
        "bemerkung": null,
        "pflanzjahr": null,
        "entnahmejahr": null,
        "baumpatenschaft": null,
        "altersklassifizierung": "mittel"
      },
      "geometry": {
        "type": "Point",
        "coordinates": [
          15.42957701310156,
          47.113510303116975
        ]
      }
    },
    {
      "type": "Feature",
      "properties": {
        "nummer": 10612,
        "objectid": 1222,
        "baumbezeichnung_deutsch": "Sandbirke, Weißbirke",
        "baumbezeichnung_botanisch": "Betula pendula",
        "baumtyp": "Laub",
        "bemerkung": null,
        "pflanzjahr": null,
        "entnahmejahr": null,
        "baumpatenschaft": null,
        "altersklassifizierung": "mittel"
      },
      "geometry": {
        "type": "Point",
        "coordinates": [
          15.426141565177474,
          47.11209719266096
        ]
      }
    }
  ]
}