{
  "type": "FeatureCollection",
  "features": [
    {
      "type": "Feature",
      "properties": {
        "NUMMER": 27052,
        "BAUMBEZEICHNUNG_BOTANISCH": "Tilia cordata",
        "BAUMBEZEICHNUNG_DEUTSCH": "Winterlinde",
        "BAUMTYP": "Laub",
        "BEMERKUNG": null,
        "PFLANZJAHR": null,
        "ENTNAHMEJAHR": null,
        "BAUMPATENSCHAFT": null,
        "ALTERSKLASSIZIERUNG": "alt",
        "OBJECTID": 1030
      },
      "geometry": {
        "type": "Point",
        "coordinates": [
          15.425895381622638,
          47.1063783795713
        ]
      }
    }
  ]
}