{"type":"FeatureCollection","features":[{"type":"Feature","properties":{"nummer":27035,"baumbezeichnung_botanisch":"Quercus robur 'Fastigiata'","baumbezeichnung_deutsch":"Säulenstieleiche","baumtyp":"Laub","bemerkung":null,"pflanzjahr":"2008","entnahmejahr":null,"marker-size":"small","marker-symbol":"park2","marker-color":"#A3DDAD"},"geometry":{"type":"Point","coordinates":[15.41817066763639,47.09265991111963],"bbox":[15.41817066763639,47.09265991111963,15.41817066763639,47.09265991111963]}},{"type":"Feature","properties":{"nummer":27027,"baumbezeichnung_botanisch":"Quercus robur 'Fastigiata'","baumbezeichnung_deutsch":"Säulenstieleiche","baumtyp":"Laub","bemerkung":null,"pflanzjahr":"2008","entnahmejahr":null,"marker-size":"small","marker-symbol":"park2","marker-color":"#A3DDAD"},"geometry":{"type":"Point","coordinates":[15.41817658396537,47.09260841503783],"bbox":[15.41817658396537,47.09260841503783,15.41817658396537,47.09260841503783]}},{"type":"Feature","properties":{"nummer":27875,"baumbezeichnung_botanisch":"Alnus glutinosa","baumbezeichnung_deutsch":"Schwarzerle","baumtyp":"Laub","bemerkung":null,"pflanzjahr":"2005","entnahmejahr":null,"marker-size":"small","marker-symbol":"park2","marker-color":"#A3DDAD"},"geometry":{"type":"Point","coordinates":[15.41878658758441,47.09266065467897],"bbox":[15.41878658758441,47.09266065467897,15.41878658758441,47.09266065467897]}},{"type":"Feature","properties":{"nummer":9535,"baumbezeichnung_botanisch":"Gleditsia triacanthos","baumbezeichnung_deutsch":"Christusdorn","baumtyp":"Laub","bemerkung":null,"pflanzjahr":null,"entnahmejahr":null,"marker-size":"small","marker-symbol":"park2","marker-color":"#A3DDAD"},"geometry":{"type":"Point","coordinates":[15.41820081593027,47.09324463027579],"bbox":[15.41820081593027,47.09324463027579,15.41820081593027,47.09324463027579]}}]}