{"type":"FeatureCollection","features":[{"type":"Feature","properties":{"nummer":3251,"baumbezeichnung_botanisch":"Aesculus hippocastanum","baumbezeichnung_deutsch":"Gemeine Roßkastanie","baumtyp":"Laub","bemerkung":null,"pflanzjahr":null,"entnahmejahr":null,"marker-size":"small","marker-symbol":"park2","marker-color":"#A3DDAD"},"geometry":{"type":"Point","coordinates":[15.41839248293245,47.08487778530665],"bbox":[15.41839248293245,47.08487778530665,15.41839248293245,47.08487778530665]}},{"type":"Feature","properties":{"nummer":9637,"baumbezeichnung_botanisch":"Aesculus hippocastanum","baumbezeichnung_deutsch":"Gemeine Roßkastanie","baumtyp":"Laub","bemerkung":null,"pflanzjahr":null,"entnahmejahr":null,"marker-size":"small","marker-symbol":"park2","marker-color":"#A3DDAD"},"geometry":{"type":"Point","coordinates":[15.41848566987294,47.084914467365],"bbox":[15.41848566987294,47.084914467365,15.41848566987294,47.084914467365]}},{"type":"Feature","properties":{"nummer":7726,"baumbezeichnung_botanisch":"Aesculus hippocastanum","baumbezeichnung_deutsch":"Gemeine Roßkastanie","baumtyp":"Laub","bemerkung":null,"pflanzjahr":null,"entnahmejahr":null,"marker-size":"small","marker-symbol":"park2","marker-color":"#A3DDAD"},"geometry":{"type":"Point","coordinates":[15.4186368588861,47.08499227178474],"bbox":[15.4186368588861,47.08499227178474,15.4186368588861,47.08499227178474]}},{"type":"Feature","properties":{"nummer":29381,"baumbezeichnung_botanisch":"Aesculus hippocastanum","baumbezeichnung_deutsch":"Gemeine Roßkastanie","baumtyp":"Laub","bemerkung":null,"pflanzjahr":null,"entnahmejahr":null,"marker-size":"small","marker-symbol":"park2","marker-color":"#A3DDAD"},"geometry":{"type":"Point","coordinates":[15.418701821021,47.08502149549737],"bbox":[15.418701821021,47.08502149549737,15.418701821021,47.08502149549737]}},{"type":"Feature","properties":{"nummer":7808,"baumbezeichnung_botanisch":"Acer platanoides","baumbezeichnung_deutsch":"Spitzahorn","baumtyp":"Laub","bemerkung":null,"pflanzjahr":"2009","entnahmejahr":null,"marker-size":"small","marker-symbol":"park2","marker-color":"#A3DDAD"},"geometry":{"type":"Point","coordinates":[15.41832498724462,47.08484427744769],"bbox":[15.41832498724462,47.08484427744769,15.41832498724462,47.08484427744769]}},{"type":"Feature","properties":{"nummer":22354,"baumbezeichnung_botanisch":"Acer platanoides","baumbezeichnung_deutsch":"Spitzahorn","baumtyp":"Laub","bemerkung":null,"pflanzjahr":"2006","entnahmejahr":null,"marker-size":"small","marker-symbol":"park2","marker-color":"#A3DDAD"},"geometry":{"type":"Point","coordinates":[15.41813323963519,47.08454334850859],"bbox":[15.41813323963519,47.08454334850859,15.41813323963519,47.08454334850859]}},{"type":"Feature","properties":{"nummer":17507,"baumbezeichnung_botanisch":"Aesculus hippocastanum","baumbezeichnung_deutsch":"Gemeine Roßkastanie","baumtyp":"Laub","bemerkung":null,"pflanzjahr":"2006","entnahmejahr":null,"marker-size":"small","marker-symbol":"park2","marker-color":"#A3DDAD"},"geometry":{"type":"Point","coordinates":[15.41824365346867,47.08480831991737],"bbox":[15.41824365346867,47.08480831991737,15.41824365346867,47.08480831991737]}},{"type":"Feature","properties":{"nummer":14700,"baumbezeichnung_botanisch":"Aesculus hippocastanum","baumbezeichnung_deutsch":"Gemeine Roßkastanie","baumtyp":"Laub","bemerkung":null,"pflanzjahr":"1998","entnahmejahr":null,"marker-size":"small","marker-symbol":"park2","marker-color":"#A3DDAD"},"geometry":{"type":"Point","coordinates":[15.41857150922716,47.08495670790072],"bbox":[15.41857150922716,47.08495670790072,15.41857150922716,47.08495670790072]}},{"type":"Feature","properties":{"nummer":8053,"baumbezeichnung_botanisch":"Acer platanoides","baumbezeichnung_deutsch":"Spitzahorn","baumtyp":"Laub","bemerkung":null,"pflanzjahr":null,"entnahmejahr":null,"marker-size":"small","marker-symbol":"park2","marker-color":"#A3DDAD"},"geometry":{"type":"Point","coordinates":[15.41817461232174,47.08452138135581],"bbox":[15.41817461232174,47.08452138135581,15.41817461232174,47.08452138135581]}},{"type":"Feature","properties":{"nummer":3090,"baumbezeichnung_botanisch":"Acer platanoides","baumbezeichnung_deutsch":"Spitzahorn","baumtyp":"Laub","bemerkung":null,"pflanzjahr":null,"entnahmejahr":null,"marker-size":"small","marker-symbol":"park2","marker-color":"#A3DDAD"},"geometry":{"type":"Point","coordinates":[15.41809141056948,47.08456198381038],"bbox":[15.41809141056948,47.08456198381038,15.41809141056948,47.08456198381038]}},{"type":"Feature","properties":{"nummer":5108,"baumbezeichnung_botanisch":"Acer platanoides","baumbezeichnung_deutsch":"Spitzahorn","baumtyp":"Laub","bemerkung":null,"pflanzjahr":null,"entnahmejahr":"2011","marker-size":"small","marker-symbol":"park2","marker-color":"#B3B3B3"},"geometry":{"type":"Point","coordinates":[15.41805626932626,47.08457997109539],"bbox":[15.41805626932626,47.08457997109539,15.41805626932626,47.08457997109539]}}]}