{"type":"FeatureCollection","features":[{"type":"Feature","properties":{"nummer":9642,"baumbezeichnung_botanisch":"Tilia cordata","baumbezeichnung_deutsch":"Winterlinde","baumtyp":"Laub","bemerkung":null,"pflanzjahr":"1986","entnahmejahr":null,"marker-size":"small","marker-symbol":"park2","marker-color":"#A3DDAD"},"geometry":{"type":"Point","coordinates":[15.41916606116506,47.07692715023968],"bbox":[15.41916606116506,47.07692715023968,15.41916606116506,47.07692715023968]}},{"type":"Feature","properties":{"nummer":3439,"baumbezeichnung_botanisch":"Tilia cordata","baumbezeichnung_deutsch":"Winterlinde","baumtyp":"Laub","bemerkung":null,"pflanzjahr":"1986","entnahmejahr":null,"marker-size":"small","marker-symbol":"park2","marker-color":"#A3DDAD"},"geometry":{"type":"Point","coordinates":[15.41911683528375,47.07708026620392],"bbox":[15.41911683528375,47.07708026620392,15.41911683528375,47.07708026620392]}},{"type":"Feature","properties":{"nummer":3171,"baumbezeichnung_botanisch":"Tilia cordata","baumbezeichnung_deutsch":"Winterlinde","baumtyp":"Laub","bemerkung":null,"pflanzjahr":"1986","entnahmejahr":null,"marker-size":"small","marker-symbol":"park2","marker-color":"#A3DDAD"},"geometry":{"type":"Point","coordinates":[15.41906013642956,47.07725373214824],"bbox":[15.41906013642956,47.07725373214824,15.41906013642956,47.07725373214824]}},{"type":"Feature","properties":{"nummer":26139,"baumbezeichnung_botanisch":"Tilia cordata","baumbezeichnung_deutsch":"Winterlinde","baumtyp":"Laub","bemerkung":null,"pflanzjahr":"1986","entnahmejahr":null,"marker-size":"small","marker-symbol":"park2","marker-color":"#A3DDAD"},"geometry":{"type":"Point","coordinates":[15.41901484041291,47.0773796064329],"bbox":[15.41901484041291,47.0773796064329,15.41901484041291,47.0773796064329]}},{"type":"Feature","properties":{"nummer":15435,"baumbezeichnung_botanisch":"Tilia cordata","baumbezeichnung_deutsch":"Winterlinde","baumtyp":"Laub","bemerkung":null,"pflanzjahr":"1986","entnahmejahr":null,"marker-size":"small","marker-symbol":"park2","marker-color":"#A3DDAD"},"geometry":{"type":"Point","coordinates":[15.41897568253598,47.07749997089398],"bbox":[15.41897568253598,47.07749997089398,15.41897568253598,47.07749997089398]}},{"type":"Feature","properties":{"nummer":22433,"baumbezeichnung_botanisch":"Tilia cordata","baumbezeichnung_deutsch":"Winterlinde","baumtyp":"Laub","bemerkung":null,"pflanzjahr":"1986","entnahmejahr":null,"marker-size":"small","marker-symbol":"park2","marker-color":"#A3DDAD"},"geometry":{"type":"Point","coordinates":[15.41925461810723,47.07697966199476],"bbox":[15.41925461810723,47.07697966199476,15.41925461810723,47.07697966199476]}},{"type":"Feature","properties":{"nummer":3440,"baumbezeichnung_botanisch":"Tilia cordata","baumbezeichnung_deutsch":"Winterlinde","baumtyp":"Laub","bemerkung":null,"pflanzjahr":"1986","entnahmejahr":null,"marker-size":"small","marker-symbol":"park2","marker-color":"#A3DDAD"},"geometry":{"type":"Point","coordinates":[15.41921880812174,47.07710141160867],"bbox":[15.41921880812174,47.07710141160867,15.41921880812174,47.07710141160867]}},{"type":"Feature","properties":{"nummer":18974,"baumbezeichnung_botanisch":"Tilia cordata","baumbezeichnung_deutsch":"Winterlinde","baumtyp":"Laub","bemerkung":null,"pflanzjahr":"1986","entnahmejahr":null,"marker-size":"small","marker-symbol":"park2","marker-color":"#A3DDAD"},"geometry":{"type":"Point","coordinates":[15.41917614974009,47.07723474601426],"bbox":[15.41917614974009,47.07723474601426,15.41917614974009,47.07723474601426]}},{"type":"Feature","properties":{"nummer":24730,"baumbezeichnung_botanisch":"Tilia cordata","baumbezeichnung_deutsch":"Winterlinde","baumtyp":"Laub","bemerkung":null,"pflanzjahr":"1986","entnahmejahr":null,"marker-size":"small","marker-symbol":"park2","marker-color":"#A3DDAD"},"geometry":{"type":"Point","coordinates":[15.41911977521571,47.0773831722632],"bbox":[15.41911977521571,47.0773831722632,15.41911977521571,47.0773831722632]}},{"type":"Feature","properties":{"nummer":21856,"baumbezeichnung_botanisch":"Tilia cordata","baumbezeichnung_deutsch":"Winterlinde","baumtyp":"Laub","bemerkung":null,"pflanzjahr":"1986","entnahmejahr":null,"marker-size":"small","marker-symbol":"park2","marker-color":"#A3DDAD"},"geometry":{"type":"Point","coordinates":[15.41907737738333,47.07750973541342],"bbox":[15.41907737738333,47.07750973541342,15.41907737738333,47.07750973541342]}}]}