{"type":"FeatureCollection","features":[{"type":"Feature","properties":{"nummer":9886,"baumbezeichnung_botanisch":"Populus nigra 'Italica'","baumbezeichnung_deutsch":"Säulenpappel","baumtyp":"Laub","bemerkung":null,"pflanzjahr":null,"entnahmejahr":null,"marker-size":"small","marker-symbol":"park2","marker-color":"#A3DDAD"},"geometry":{"type":"Point","coordinates":[15.41849259923028,47.07356588606466],"bbox":[15.41849259923028,47.07356588606466,15.41849259923028,47.07356588606466]}},{"type":"Feature","properties":{"nummer":15589,"baumbezeichnung_botanisch":"Populus nigra 'Italica'","baumbezeichnung_deutsch":"Säulenpappel","baumtyp":"Laub","bemerkung":null,"pflanzjahr":null,"entnahmejahr":null,"marker-size":"small","marker-symbol":"park2","marker-color":"#A3DDAD"},"geometry":{"type":"Point","coordinates":[15.41836374944409,47.0738467596562],"bbox":[15.41836374944409,47.0738467596562,15.41836374944409,47.0738467596562]}},{"type":"Feature","properties":{"nummer":21013,"baumbezeichnung_botanisch":"Populus nigra 'Italica'","baumbezeichnung_deutsch":"Säulenpappel","baumtyp":"Laub","bemerkung":null,"pflanzjahr":"2006","entnahmejahr":null,"marker-size":"small","marker-symbol":"park2","marker-color":"#A3DDAD"},"geometry":{"type":"Point","coordinates":[15.41839040258175,47.07378976447992],"bbox":[15.41839040258175,47.07378976447992,15.41839040258175,47.07378976447992]}},{"type":"Feature","properties":{"nummer":16394,"baumbezeichnung_botanisch":"Populus nigra 'Italica'","baumbezeichnung_deutsch":"Säulenpappel","baumtyp":"Laub","bemerkung":null,"pflanzjahr":"2006","entnahmejahr":null,"marker-size":"small","marker-symbol":"park2","marker-color":"#A3DDAD"},"geometry":{"type":"Point","coordinates":[15.41843889571096,47.07368769900785],"bbox":[15.41843889571096,47.07368769900785,15.41843889571096,47.07368769900785]}},{"type":"Feature","properties":{"nummer":24513,"baumbezeichnung_botanisch":"Populus nigra 'Italica'","baumbezeichnung_deutsch":"Säulenpappel","baumtyp":"Laub","bemerkung":null,"pflanzjahr":"2006","entnahmejahr":null,"marker-size":"small","marker-symbol":"park2","marker-color":"#A3DDAD"},"geometry":{"type":"Point","coordinates":[15.41846342487779,47.07362480310344],"bbox":[15.41846342487779,47.07362480310344,15.41846342487779,47.07362480310344]}},{"type":"Feature","properties":{"nummer":23755,"baumbezeichnung_botanisch":"Populus nigra 'Italica'","baumbezeichnung_deutsch":"Säulenpappel","baumtyp":"Laub","bemerkung":null,"pflanzjahr":"2006","entnahmejahr":null,"marker-size":"small","marker-symbol":"park2","marker-color":"#A3DDAD"},"geometry":{"type":"Point","coordinates":[15.41850814413509,47.07353470770929],"bbox":[15.41850814413509,47.07353470770929,15.41850814413509,47.07353470770929]}},{"type":"Feature","properties":{"nummer":15300,"baumbezeichnung_botanisch":"Populus nigra 'Italica'","baumbezeichnung_deutsch":"Säulenpappel","baumtyp":"Laub","bemerkung":null,"pflanzjahr":"2006","entnahmejahr":null,"marker-size":"small","marker-symbol":"park2","marker-color":"#A3DDAD"},"geometry":{"type":"Point","coordinates":[15.41853973844819,47.07346596851929],"bbox":[15.41853973844819,47.07346596851929,15.41853973844819,47.07346596851929]}},{"type":"Feature","properties":{"nummer":9494,"baumbezeichnung_botanisch":"Acer pseudoplatanus 'Negenia'","baumbezeichnung_deutsch":"Schmalkegelförmiger Bergahorn","baumtyp":"Laub","bemerkung":null,"pflanzjahr":"2004","entnahmejahr":"2011","marker-size":"small","marker-symbol":"park2","marker-color":"#B3B3B3"},"geometry":{"type":"Point","coordinates":[15.41794562010248,47.07302385522346],"bbox":[15.41794562010248,47.07302385522346,15.41794562010248,47.07302385522346]}},{"type":"Feature","properties":{"nummer":12125,"baumbezeichnung_botanisch":"Acer pseudoplatanus 'Negenia'","baumbezeichnung_deutsch":"Schmalkegelförmiger Bergahorn","baumtyp":"Laub","bemerkung":null,"pflanzjahr":"2004","entnahmejahr":"2011","marker-size":"small","marker-symbol":"park2","marker-color":"#B3B3B3"},"geometry":{"type":"Point","coordinates":[15.41813789389446,47.07305715026966],"bbox":[15.41813789389446,47.07305715026966,15.41813789389446,47.07305715026966]}},{"type":"Feature","properties":{"nummer":23810,"baumbezeichnung_botanisch":"Populus nigra 'Italica'","baumbezeichnung_deutsch":"Säulenpappel","baumtyp":"Laub","bemerkung":null,"pflanzjahr":"2012","entnahmejahr":null,"marker-size":"small","marker-symbol":"park2","marker-color":"#A3DDAD"},"geometry":{"type":"Point","coordinates":[15.41841254611863,47.07374235790523],"bbox":[15.41841254611863,47.07374235790523,15.41841254611863,47.07374235790523]}}]}