{"type":"FeatureCollection","features":[{"type":"Feature","properties":{"nummer":8348,"baumbezeichnung_botanisch":"Thuja sp.","baumbezeichnung_deutsch":"Lebensbaum","baumtyp":"Nadel","bemerkung":null,"pflanzjahr":null,"entnahmejahr":null,"marker-size":"small","marker-symbol":"park","marker-color":"#3BB451"},"geometry":{"type":"Point","coordinates":[15.42954638041522,47.06545893082177],"bbox":[15.42954638041522,47.06545893082177,15.42954638041522,47.06545893082177]}}]}