{"type":"FeatureCollection","features":[{"type":"Feature","properties":{"nummer":22798,"baumbezeichnung_botanisch":"Celtis occidentalis","baumbezeichnung_deutsch":"Nesselbaum","baumtyp":"Laub","bemerkung":null,"pflanzjahr":"2007","entnahmejahr":null,"marker-size":"small","marker-symbol":"park2","marker-color":"#A3DDAD"},"geometry":{"type":"Point","coordinates":[15.42955055307771,47.04483988771948],"bbox":[15.42955055307771,47.04483988771948,15.42955055307771,47.04483988771948]}}]}