{"type":"FeatureCollection","features":[{"type":"Feature","properties":{"nummer":12849,"baumbezeichnung_botanisch":"Abies sp.","baumbezeichnung_deutsch":"Tanne","baumtyp":"Nadel","bemerkung":null,"pflanzjahr":null,"entnahmejahr":null,"marker-size":"small","marker-symbol":"park","marker-color":"#3BB451"},"geometry":{"type":"Point","coordinates":[15.42929781525379,47.04858065235607],"bbox":[15.42929781525379,47.04858065235607,15.42929781525379,47.04858065235607]}},{"type":"Feature","properties":{"nummer":666,"baumbezeichnung_botanisch":"Abies sp.","baumbezeichnung_deutsch":"Tanne","baumtyp":"Nadel","bemerkung":null,"pflanzjahr":null,"entnahmejahr":null,"marker-size":"small","marker-symbol":"park","marker-color":"#3BB451"},"geometry":{"type":"Point","coordinates":[15.42930203182699,47.0485481197879],"bbox":[15.42930203182699,47.0485481197879,15.42930203182699,47.0485481197879]}},{"type":"Feature","properties":{"nummer":20132,"baumbezeichnung_botanisch":"Abies sp.","baumbezeichnung_deutsch":"Tanne","baumtyp":"Nadel","bemerkung":null,"pflanzjahr":null,"entnahmejahr":null,"marker-size":"small","marker-symbol":"park","marker-color":"#3BB451"},"geometry":{"type":"Point","coordinates":[15.42930258377581,47.04851555819844],"bbox":[15.42930258377581,47.04851555819844,15.42930258377581,47.04851555819844]}},{"type":"Feature","properties":{"nummer":5190,"baumbezeichnung_botanisch":"Abies sp.","baumbezeichnung_deutsch":"Tanne","baumtyp":"Nadel","bemerkung":null,"pflanzjahr":null,"entnahmejahr":null,"marker-size":"small","marker-symbol":"park","marker-color":"#3BB451"},"geometry":{"type":"Point","coordinates":[15.42930688525738,47.04847801601597],"bbox":[15.42930688525738,47.04847801601597,15.42930688525738,47.04847801601597]}},{"type":"Feature","properties":{"nummer":667,"baumbezeichnung_botanisch":"Abies sp.","baumbezeichnung_deutsch":"Tanne","baumtyp":"Nadel","bemerkung":null,"pflanzjahr":null,"entnahmejahr":null,"marker-size":"small","marker-symbol":"park","marker-color":"#3BB451"},"geometry":{"type":"Point","coordinates":[15.42929635844151,47.04845037697681],"bbox":[15.42929635844151,47.04845037697681,15.42929635844151,47.04845037697681]}},{"type":"Feature","properties":{"nummer":25876,"baumbezeichnung_botanisch":"Abies sp.","baumbezeichnung_deutsch":"Tanne","baumtyp":"Nadel","bemerkung":null,"pflanzjahr":null,"entnahmejahr":null,"marker-size":"small","marker-symbol":"park","marker-color":"#3BB451"},"geometry":{"type":"Point","coordinates":[15.42929316086154,47.04842279597939],"bbox":[15.42929316086154,47.04842279597939,15.42929316086154,47.04842279597939]}},{"type":"Feature","properties":{"nummer":11637,"baumbezeichnung_botanisch":"Abies sp.","baumbezeichnung_deutsch":"Tanne","baumtyp":"Nadel","bemerkung":null,"pflanzjahr":null,"entnahmejahr":null,"marker-size":"small","marker-symbol":"park","marker-color":"#3BB451"},"geometry":{"type":"Point","coordinates":[15.4292972075885,47.04840028263802],"bbox":[15.4292972075885,47.04840028263802,15.4292972075885,47.04840028263802]}},{"type":"Feature","properties":{"nummer":21150,"baumbezeichnung_botanisch":"Populus nigra 'Italica'","baumbezeichnung_deutsch":"Säulenpappel","baumtyp":"Laub","bemerkung":null,"pflanzjahr":null,"entnahmejahr":null,"marker-size":"small","marker-symbol":"park2","marker-color":"#A3DDAD"},"geometry":{"type":"Point","coordinates":[15.4294112311067,47.04837613503497],"bbox":[15.4294112311067,47.04837613503497,15.4294112311067,47.04837613503497]}},{"type":"Feature","properties":{"nummer":24630,"baumbezeichnung_botanisch":"Populus nigra 'Italica'","baumbezeichnung_deutsch":"Säulenpappel","baumtyp":"Laub","bemerkung":null,"pflanzjahr":null,"entnahmejahr":null,"marker-size":"small","marker-symbol":"park2","marker-color":"#A3DDAD"},"geometry":{"type":"Point","coordinates":[15.42947340080228,47.04838414272558],"bbox":[15.42947340080228,47.04838414272558,15.42947340080228,47.04838414272558]}},{"type":"Feature","properties":{"nummer":668,"baumbezeichnung_botanisch":"Ailanthus altissima","baumbezeichnung_deutsch":"Götterbaum","baumtyp":"Laub","bemerkung":null,"pflanzjahr":null,"entnahmejahr":null,"marker-size":"small","marker-symbol":"park2","marker-color":"#A3DDAD"},"geometry":{"type":"Point","coordinates":[15.42979511218253,47.0484317802819],"bbox":[15.42979511218253,47.0484317802819,15.42979511218253,47.0484317802819]}},{"type":"Feature","properties":{"nummer":28862,"baumbezeichnung_botanisch":"Acer platanoides","baumbezeichnung_deutsch":"Spitzahorn","baumtyp":"Laub","bemerkung":null,"pflanzjahr":"2005","entnahmejahr":null,"marker-size":"small","marker-symbol":"park2","marker-color":"#A3DDAD"},"geometry":{"type":"Point","coordinates":[15.42931938788836,47.04837084722638],"bbox":[15.42931938788836,47.04837084722638,15.42931938788836,47.04837084722638]}}]}