{"type":"FeatureCollection","features":[{"type":"Feature","properties":{"nummer":34292,"baumbezeichnung_botanisch":"Acer platanoides","baumbezeichnung_deutsch":"Spitzahorn","baumtyp":"Laub","bemerkung":null,"pflanzjahr":null,"entnahmejahr":null,"marker-size":"small","marker-symbol":"park2","marker-color":"#A3DDAD"},"geometry":{"type":"Point","coordinates":[15.42897203185071,47.0296173661577],"bbox":[15.42897203185071,47.0296173661577,15.42897203185071,47.0296173661577]}},{"type":"Feature","properties":{"nummer":34293,"baumbezeichnung_botanisch":"Acer platanoides","baumbezeichnung_deutsch":"Spitzahorn","baumtyp":"Laub","bemerkung":null,"pflanzjahr":null,"entnahmejahr":null,"marker-size":"small","marker-symbol":"park2","marker-color":"#A3DDAD"},"geometry":{"type":"Point","coordinates":[15.42982725049601,47.02937067112588],"bbox":[15.42982725049601,47.02937067112588,15.42982725049601,47.02937067112588]}}]}