{"type":"FeatureCollection","features":[{"type":"Feature","properties":{"nummer":13600,"baumbezeichnung_botanisch":"Tilia cordata","baumbezeichnung_deutsch":"Winterlinde","baumtyp":"Laub","bemerkung":null,"pflanzjahr":null,"entnahmejahr":null,"marker-size":"small","marker-symbol":"park2","marker-color":"#A3DDAD"},"geometry":{"type":"Point","coordinates":[15.42141420181697,47.10319738041142],"bbox":[15.42141420181697,47.10319738041142,15.42141420181697,47.10319738041142]}},{"type":"Feature","properties":{"nummer":10442,"baumbezeichnung_botanisch":"Acer rubrum","baumbezeichnung_deutsch":"Rotahorn","baumtyp":"Laub","bemerkung":null,"pflanzjahr":"2006","entnahmejahr":null,"marker-size":"small","marker-symbol":"park2","marker-color":"#A3DDAD"},"geometry":{"type":"Point","coordinates":[15.42104659437394,47.10286510815664],"bbox":[15.42104659437394,47.10286510815664,15.42104659437394,47.10286510815664]}},{"type":"Feature","properties":{"nummer":18262,"baumbezeichnung_botanisch":"Acer rubrum","baumbezeichnung_deutsch":"Rotahorn","baumtyp":"Laub","bemerkung":null,"pflanzjahr":"2006","entnahmejahr":null,"marker-size":"small","marker-symbol":"park2","marker-color":"#A3DDAD"},"geometry":{"type":"Point","coordinates":[15.42107275875539,47.10290190905747],"bbox":[15.42107275875539,47.10290190905747,15.42107275875539,47.10290190905747]}},{"type":"Feature","properties":{"nummer":17536,"baumbezeichnung_botanisch":"Magnolia kobus","baumbezeichnung_deutsch":"Baummagnolie","baumtyp":"Laub","bemerkung":null,"pflanzjahr":null,"entnahmejahr":null,"marker-size":"small","marker-symbol":"park2","marker-color":"#A3DDAD"},"geometry":{"type":"Point","coordinates":[15.42157039705536,47.10308460123991],"bbox":[15.42157039705536,47.10308460123991,15.42157039705536,47.10308460123991]}},{"type":"Feature","properties":{"nummer":2881,"baumbezeichnung_botanisch":"Tilia cordata","baumbezeichnung_deutsch":"Winterlinde","baumtyp":"Laub","bemerkung":null,"pflanzjahr":"2001","entnahmejahr":null,"marker-size":"small","marker-symbol":"park2","marker-color":"#A3DDAD"},"geometry":{"type":"Point","coordinates":[15.42152317941394,47.10341265485143],"bbox":[15.42152317941394,47.10341265485143,15.42152317941394,47.10341265485143]}},{"type":"Feature","properties":{"nummer":8833,"baumbezeichnung_botanisch":"Acer rubrum","baumbezeichnung_deutsch":"Rotahorn","baumtyp":"Laub","bemerkung":null,"pflanzjahr":"2012","entnahmejahr":null,"marker-size":"small","marker-symbol":"park2","marker-color":"#A3DDAD"},"geometry":{"type":"Point","coordinates":[15.42109947536901,47.1029310865656],"bbox":[15.42109947536901,47.1029310865656,15.42109947536901,47.1029310865656]}}]}