{"type":"FeatureCollection","features":[{"type":"Feature","properties":{"nummer":11947,"baumbezeichnung_botanisch":"Fraxinus excelsior","baumbezeichnung_deutsch":"Esche","baumtyp":"Laub","bemerkung":null,"pflanzjahr":null,"entnahmejahr":null,"marker-size":"small","marker-symbol":"park2","marker-color":"#A3DDAD"},"geometry":{"type":"Point","coordinates":[15.4211162688915,47.09034953110871],"bbox":[15.4211162688915,47.09034953110871,15.4211162688915,47.09034953110871]}}]}