{"type":"FeatureCollection","features":[{"type":"Feature","properties":{"nummer":11378,"baumbezeichnung_botanisch":"Aesculus hippocastanum","baumbezeichnung_deutsch":"Gemeine Roßkastanie","baumtyp":"Laub","bemerkung":null,"pflanzjahr":null,"entnahmejahr":null,"marker-size":"small","marker-symbol":"park2","marker-color":"#A3DDAD"},"geometry":{"type":"Point","coordinates":[15.42113274380693,47.07851183948681],"bbox":[15.42113274380693,47.07851183948681,15.42113274380693,47.07851183948681]}},{"type":"Feature","properties":{"nummer":23361,"baumbezeichnung_botanisch":"Aesculus hippocastanum","baumbezeichnung_deutsch":"Gemeine Roßkastanie","baumtyp":"Laub","bemerkung":null,"pflanzjahr":null,"entnahmejahr":null,"marker-size":"small","marker-symbol":"park2","marker-color":"#A3DDAD"},"geometry":{"type":"Point","coordinates":[15.42114531254734,47.0784482969978],"bbox":[15.42114531254734,47.0784482969978,15.42114531254734,47.0784482969978]}},{"type":"Feature","properties":{"nummer":14760,"baumbezeichnung_botanisch":"Aesculus hippocastanum","baumbezeichnung_deutsch":"Gemeine Roßkastanie","baumtyp":"Laub","bemerkung":null,"pflanzjahr":null,"entnahmejahr":null,"marker-size":"small","marker-symbol":"park2","marker-color":"#A3DDAD"},"geometry":{"type":"Point","coordinates":[15.42115634386825,47.07838779695346],"bbox":[15.42115634386825,47.07838779695346,15.42115634386825,47.07838779695346]}}]}