{"type":"FeatureCollection","features":[{"type":"Feature","properties":{"nummer":9645,"baumbezeichnung_botanisch":"Tilia tomentosa","baumbezeichnung_deutsch":"Silberlinde","baumtyp":"Laub","bemerkung":null,"pflanzjahr":"1983","entnahmejahr":null,"marker-size":"small","marker-symbol":"park2","marker-color":"#A3DDAD"},"geometry":{"type":"Point","coordinates":[15.42102199365628,47.07696375506371],"bbox":[15.42102199365628,47.07696375506371,15.42102199365628,47.07696375506371]}},{"type":"Feature","properties":{"nummer":14280,"baumbezeichnung_botanisch":"Tilia tomentosa","baumbezeichnung_deutsch":"Silberlinde","baumtyp":"Laub","bemerkung":null,"pflanzjahr":"1983","entnahmejahr":null,"marker-size":"small","marker-symbol":"park2","marker-color":"#A3DDAD"},"geometry":{"type":"Point","coordinates":[15.42074287775969,47.07728573418189],"bbox":[15.42074287775969,47.07728573418189,15.42074287775969,47.07728573418189]}},{"type":"Feature","properties":{"nummer":13662,"baumbezeichnung_botanisch":"Tilia cordata","baumbezeichnung_deutsch":"Winterlinde","baumtyp":"Laub","bemerkung":null,"pflanzjahr":null,"entnahmejahr":null,"marker-size":"small","marker-symbol":"park2","marker-color":"#A3DDAD"},"geometry":{"type":"Point","coordinates":[15.42145001705918,47.07675694143808],"bbox":[15.42145001705918,47.07675694143808,15.42145001705918,47.07675694143808]}},{"type":"Feature","properties":{"nummer":3141,"baumbezeichnung_botanisch":"Tilia cordata","baumbezeichnung_deutsch":"Winterlinde","baumtyp":"Laub","bemerkung":null,"pflanzjahr":"2005","entnahmejahr":null,"marker-size":"small","marker-symbol":"park2","marker-color":"#A3DDAD"},"geometry":{"type":"Point","coordinates":[15.4208537516288,47.0771539428795],"bbox":[15.4208537516288,47.0771539428795,15.4208537516288,47.0771539428795]}}]}