{"type":"FeatureCollection","features":[{"type":"Feature","properties":{"nummer":27171,"baumbezeichnung_botanisch":"Tilia cordata 'Greenspire'","baumbezeichnung_deutsch":"Amerikanische Stadtlinde","baumtyp":"Laub","bemerkung":null,"pflanzjahr":"2007","entnahmejahr":null,"marker-size":"small","marker-symbol":"park2","marker-color":"#A3DDAD"},"geometry":{"type":"Point","coordinates":[15.42086004292624,47.05988955303551],"bbox":[15.42086004292624,47.05988955303551,15.42086004292624,47.05988955303551]}},{"type":"Feature","properties":{"nummer":27193,"baumbezeichnung_botanisch":"Tilia cordata 'Greenspire'","baumbezeichnung_deutsch":"Amerikanische Stadtlinde","baumtyp":"Laub","bemerkung":null,"pflanzjahr":"2007","entnahmejahr":null,"marker-size":"small","marker-symbol":"park2","marker-color":"#A3DDAD"},"geometry":{"type":"Point","coordinates":[15.42091209002788,47.05994081389152],"bbox":[15.42091209002788,47.05994081389152,15.42091209002788,47.05994081389152]}},{"type":"Feature","properties":{"nummer":27192,"baumbezeichnung_botanisch":"Tilia cordata 'Greenspire'","baumbezeichnung_deutsch":"Amerikanische Stadtlinde","baumtyp":"Laub","bemerkung":null,"pflanzjahr":"2007","entnahmejahr":null,"marker-size":"small","marker-symbol":"park2","marker-color":"#A3DDAD"},"geometry":{"type":"Point","coordinates":[15.42101515549756,47.06003047149656],"bbox":[15.42101515549756,47.06003047149656,15.42101515549756,47.06003047149656]}},{"type":"Feature","properties":{"nummer":54626,"baumbezeichnung_botanisch":"Tilia cordata 'Greenspire'","baumbezeichnung_deutsch":"Amerikanische Stadtlinde","baumtyp":"Laub","bemerkung":null,"pflanzjahr":"2007","entnahmejahr":null,"marker-size":"small","marker-symbol":"park2","marker-color":"#A3DDAD"},"geometry":{"type":"Point","coordinates":[15.42121292249114,47.06022285695831],"bbox":[15.42121292249114,47.06022285695831,15.42121292249114,47.06022285695831]}}]}