{"type":"FeatureCollection","features":[{"type":"Feature","properties":{"nummer":27183,"baumbezeichnung_botanisch":"Prunus serrulata 'Amanogawa'","baumbezeichnung_deutsch":"Japanische Säulenkirsche","baumtyp":"Laub","bemerkung":null,"pflanzjahr":"2007","entnahmejahr":null,"marker-size":"small","marker-symbol":"park2","marker-color":"#A3DDAD"},"geometry":{"type":"Point","coordinates":[15.42071033269787,47.05926853733609],"bbox":[15.42071033269787,47.05926853733609,15.42071033269787,47.05926853733609]}},{"type":"Feature","properties":{"nummer":27184,"baumbezeichnung_botanisch":"Tilia platyphyllos","baumbezeichnung_deutsch":"Sommerlinde","baumtyp":"Laub","bemerkung":null,"pflanzjahr":"2007","entnahmejahr":null,"marker-size":"small","marker-symbol":"park2","marker-color":"#A3DDAD"},"geometry":{"type":"Point","coordinates":[15.42079298141531,47.05922051465525],"bbox":[15.42079298141531,47.05922051465525,15.42079298141531,47.05922051465525]}},{"type":"Feature","properties":{"nummer":27191,"baumbezeichnung_botanisch":"Tilia cordata 'Greenspire'","baumbezeichnung_deutsch":"Amerikanische Stadtlinde","baumtyp":"Laub","bemerkung":null,"pflanzjahr":"2007","entnahmejahr":null,"marker-size":"small","marker-symbol":"park2","marker-color":"#A3DDAD"},"geometry":{"type":"Point","coordinates":[15.42072600396422,47.05976430769712],"bbox":[15.42072600396422,47.05976430769712,15.42072600396422,47.05976430769712]}}]}