{"type":"FeatureCollection","features":[{"type":"Feature","properties":{"nummer":20153,"baumbezeichnung_botanisch":"Liquidambar styraciflua","baumbezeichnung_deutsch":"Amberbaum","baumtyp":"Laub","altersklassifizierung":"jung","bemerkung":null,"pflanzjahr":"1997","entnahmejahr":null,"baumpatenschaft":null,"objectid":3439},"geometry":{"type":"Point","coordinates":[15.466012884990404,47.05323452414077],"bbox":[15.466012884990404,47.05323452414077,15.466012884990404,47.05323452414077]}}]}