{"type":"FeatureCollection","features":[{"type":"Feature","properties":{"nummer":9963,"baumbezeichnung_botanisch":"Liquidambar styraciflua","baumbezeichnung_deutsch":"Amberbaum","baumtyp":"Laub","bemerkung":null,"pflanzjahr":"1997","entnahmejahr":null,"marker-size":"small","marker-symbol":"park2","marker-color":"#A3DDAD"},"geometry":{"type":"Point","coordinates":[15.4660128849904,47.05323452414077],"bbox":[15.4660128849904,47.05323452414077,15.4660128849904,47.05323452414077]}}]}