{"type":"FeatureCollection","features":[{"type":"Feature","properties":{"nummer":41213,"baumbezeichnung_botanisch":"Fraxinus excelsior 'Diversifolia'","baumbezeichnung_deutsch":"Einblättrige Esche","baumtyp":"Laub","bemerkung":null,"pflanzjahr":"2010","entnahmejahr":null,"marker-size":"small","marker-symbol":"park2","marker-color":"#A3DDAD"},"geometry":{"type":"Point","coordinates":[15.47437005525093,47.04491705889384],"bbox":[15.47437005525093,47.04491705889384,15.47437005525093,47.04491705889384]}},{"type":"Feature","properties":{"nummer":41210,"baumbezeichnung_botanisch":"Fraxinus excelsior 'Diversifolia'","baumbezeichnung_deutsch":"Einblättrige Esche","baumtyp":"Laub","bemerkung":null,"pflanzjahr":"2010","entnahmejahr":null,"marker-size":"small","marker-symbol":"park2","marker-color":"#A3DDAD"},"geometry":{"type":"Point","coordinates":[15.47453250762923,47.04499087021082],"bbox":[15.47453250762923,47.04499087021082,15.47453250762923,47.04499087021082]}},{"type":"Feature","properties":{"nummer":41212,"baumbezeichnung_botanisch":"Fraxinus excelsior 'Diversifolia'","baumbezeichnung_deutsch":"Einblättrige Esche","baumtyp":"Laub","bemerkung":null,"pflanzjahr":"2010","entnahmejahr":null,"marker-size":"small","marker-symbol":"park2","marker-color":"#A3DDAD"},"geometry":{"type":"Point","coordinates":[15.47469834620286,47.04507065704512],"bbox":[15.47469834620286,47.04507065704512,15.47469834620286,47.04507065704512]}},{"type":"Feature","properties":{"nummer":41211,"baumbezeichnung_botanisch":"Fraxinus excelsior 'Diversifolia'","baumbezeichnung_deutsch":"Einblättrige Esche","baumtyp":"Laub","bemerkung":null,"pflanzjahr":"2010","entnahmejahr":null,"marker-size":"small","marker-symbol":"park2","marker-color":"#A3DDAD"},"geometry":{"type":"Point","coordinates":[15.47486083912846,47.04514208808834],"bbox":[15.47486083912846,47.04514208808834,15.47486083912846,47.04514208808834]}},{"type":"Feature","properties":{"nummer":41216,"baumbezeichnung_botanisch":"Fraxinus excelsior 'Diversifolia'","baumbezeichnung_deutsch":"Einblättrige Esche","baumtyp":"Laub","bemerkung":null,"pflanzjahr":"2010","entnahmejahr":null,"marker-size":"small","marker-symbol":"park2","marker-color":"#A3DDAD"},"geometry":{"type":"Point","coordinates":[15.47459090688435,47.04493181045235],"bbox":[15.47459090688435,47.04493181045235,15.47459090688435,47.04493181045235]}},{"type":"Feature","properties":{"nummer":41217,"baumbezeichnung_botanisch":"Fraxinus excelsior 'Diversifolia'","baumbezeichnung_deutsch":"Einblättrige Esche","baumtyp":"Laub","bemerkung":null,"pflanzjahr":"2010","entnahmejahr":null,"marker-size":"small","marker-symbol":"park2","marker-color":"#A3DDAD"},"geometry":{"type":"Point","coordinates":[15.47476198681835,47.04501044657499],"bbox":[15.47476198681835,47.04501044657499,15.47476198681835,47.04501044657499]}},{"type":"Feature","properties":{"nummer":41506,"baumbezeichnung_botanisch":"Fraxinus excelsior 'Diversifolia'","baumbezeichnung_deutsch":"Einblättrige Esche","baumtyp":"Laub","bemerkung":null,"pflanzjahr":"2010","entnahmejahr":null,"marker-size":"small","marker-symbol":"park2","marker-color":"#A3DDAD"},"geometry":{"type":"Point","coordinates":[15.47492097895909,47.04508304125481],"bbox":[15.47492097895909,47.04508304125481,15.47492097895909,47.04508304125481]}}]}