{
  "type": "FeatureCollection",
  "features": [
    {
      "type": "Feature",
      "properties": {
        "NUMMER": 4967,
        "BAUMBEZEICHNUNG_BOTANISCH": "Tilia cordata",
        "BAUMBEZEICHNUNG_DEUTSCH": "Winterlinde",
        "BAUMTYP": "Laub",
        "BEMERKUNG": null,
        "PFLANZJAHR": null,
        "ENTNAHMEJAHR": null,
        "BAUMPATENSCHAFT": null,
        "ALTERSKLASSIZIERUNG": "jung",
        "OBJECTID": 57
      },
      "geometry": {
        "type": "Point",
        "coordinates": [
          15.464302899616914,
          47.053352649886
        ]
      }
    },
    {
      "type": "Feature",
      "properties": {
        "NUMMER": 29031,
        "BAUMBEZEICHNUNG_BOTANISCH": "Aesculus hippocastanum",
        "BAUMBEZEICHNUNG_DEUTSCH": "Gemeine Roßkastanie",
        "BAUMTYP": "Laub",
        "BEMERKUNG": null,
        "PFLANZJAHR": "2008",
        "ENTNAHMEJAHR": null,
        "BAUMPATENSCHAFT": null,
        "ALTERSKLASSIZIERUNG": "jung",
        "OBJECTID": 186
      },
      "geometry": {
        "type": "Point",
        "coordinates": [
          15.465349982893601,
          47.05294294092215
        ]
      }
    },
    {
      "type": "Feature",
      "properties": {
        "NUMMER": 4892,
        "BAUMBEZEICHNUNG_BOTANISCH": "Sophora japonica",
        "BAUMBEZEICHNUNG_DEUTSCH": "Schnurbaum",
        "BAUMTYP": "Laub",
        "BEMERKUNG": null,
        "PFLANZJAHR": null,
        "ENTNAHMEJAHR": null,
        "BAUMPATENSCHAFT": null,
        "ALTERSKLASSIZIERUNG": "jung",
        "OBJECTID": 933
      },
      "geometry": {
        "type": "Point",
        "coordinates": [
          15.46518845316136,
          47.05324905439631
        ]
      }
    },
    {
      "type": "Feature",
      "properties": {
        "NUMMER": 4901,
        "BAUMBEZEICHNUNG_BOTANISCH": "Sophora japonica",
        "BAUMBEZEICHNUNG_DEUTSCH": "Schnurbaum",
        "BAUMTYP": "Laub",
        "BEMERKUNG": null,
        "PFLANZJAHR": null,
        "ENTNAHMEJAHR": null,
        "BAUMPATENSCHAFT": null,
        "ALTERSKLASSIZIERUNG": "jung",
        "OBJECTID": 934
      },
      "geometry": {
        "type": "Point",
        "coordinates": [
          15.464829338151564,
          47.05349181444069
        ]
      }
    },
    {
      "type": "Feature",
      "properties": {
        "NUMMER": 27661,
        "BAUMBEZEICHNUNG_BOTANISCH": "Fraxinus excelsior",
        "BAUMBEZEICHNUNG_DEUTSCH": "Esche",
        "BAUMTYP": "Laub",
        "BEMERKUNG": null,
        "PFLANZJAHR": "2008",
        "ENTNAHMEJAHR": null,
        "BAUMPATENSCHAFT": null,
        "ALTERSKLASSIZIERUNG": "jung",
        "OBJECTID": 1592
      },
      "geometry": {
        "type": "Point",
        "coordinates": [
          15.464438618962125,
          47.054245610776654
        ]
      }
    },
    {
      "type": "Feature",
      "properties": {
        "NUMMER": 27662,
        "BAUMBEZEICHNUNG_BOTANISCH": "Fraxinus excelsior",
        "BAUMBEZEICHNUNG_DEUTSCH": "Esche",
        "BAUMTYP": "Laub",
        "BEMERKUNG": null,
        "PFLANZJAHR": "2008",
        "ENTNAHMEJAHR": null,
        "BAUMPATENSCHAFT": null,
        "ALTERSKLASSIZIERUNG": "jung",
        "OBJECTID": 1593
      },
      "geometry": {
        "type": "Point",
        "coordinates": [
          15.464364266868394,
          47.05416751811403
        ]
      }
    },
    {
      "type": "Feature",
      "properties": {
        "NUMMER": 27660,
        "BAUMBEZEICHNUNG_BOTANISCH": "Fraxinus excelsior",
        "BAUMBEZEICHNUNG_DEUTSCH": "Esche",
        "BAUMTYP": "Laub",
        "BEMERKUNG": null,
        "PFLANZJAHR": "2008",
        "ENTNAHMEJAHR": null,
        "BAUMPATENSCHAFT": null,
        "ALTERSKLASSIZIERUNG": "jung",
        "OBJECTID": 1642
      },
      "geometry": {
        "type": "Point",
        "coordinates": [
          15.464280173401066,
          47.05430039716435
        ]
      }
    }
  ]
}