{
  "type": "FeatureCollection",
  "features": [
    {
      "type": "Feature",
      "properties": {
        "nummer": 4967,
        "objectid": 57,
        "baumbezeichnung_deutsch": "Winterlinde",
        "baumbezeichnung_botanisch": "Tilia cordata",
        "baumtyp": "Laub",
        "bemerkung": null,
        "pflanzjahr": null,
        "entnahmejahr": null,
        "baumpatenschaft": null,
        "altersklassifizierung": "jung"
      },
      "geometry": {
        "type": "Point",
        "coordinates": [
          15.464302899616914,
          47.053352649886
        ]
      }
    },
    {
      "type": "Feature",
      "properties": {
        "nummer": 29031,
        "objectid": 186,
        "baumbezeichnung_deutsch": "Gemeine Roßkastanie",
        "baumbezeichnung_botanisch": "Aesculus hippocastanum",
        "baumtyp": "Laub",
        "bemerkung": null,
        "pflanzjahr": "2008",
        "entnahmejahr": null,
        "baumpatenschaft": null,
        "altersklassifizierung": "jung"
      },
      "geometry": {
        "type": "Point",
        "coordinates": [
          15.465349982893601,
          47.05294294092215
        ]
      }
    },
    {
      "type": "Feature",
      "properties": {
        "nummer": 4892,
        "objectid": 933,
        "baumbezeichnung_deutsch": "Schnurbaum",
        "baumbezeichnung_botanisch": "Sophora japonica",
        "baumtyp": "Laub",
        "bemerkung": null,
        "pflanzjahr": null,
        "entnahmejahr": null,
        "baumpatenschaft": null,
        "altersklassifizierung": "jung"
      },
      "geometry": {
        "type": "Point",
        "coordinates": [
          15.46518845316136,
          47.05324905439631
        ]
      }
    },
    {
      "type": "Feature",
      "properties": {
        "nummer": 4901,
        "objectid": 934,
        "baumbezeichnung_deutsch": "Schnurbaum",
        "baumbezeichnung_botanisch": "Sophora japonica",
        "baumtyp": "Laub",
        "bemerkung": null,
        "pflanzjahr": null,
        "entnahmejahr": null,
        "baumpatenschaft": null,
        "altersklassifizierung": "jung"
      },
      "geometry": {
        "type": "Point",
        "coordinates": [
          15.464829338151564,
          47.05349181444069
        ]
      }
    },
    {
      "type": "Feature",
      "properties": {
        "nummer": 27661,
        "objectid": 1592,
        "baumbezeichnung_deutsch": "Esche",
        "baumbezeichnung_botanisch": "Fraxinus excelsior",
        "baumtyp": "Laub",
        "bemerkung": null,
        "pflanzjahr": "2008",
        "entnahmejahr": null,
        "baumpatenschaft": null,
        "altersklassifizierung": "jung"
      },
      "geometry": {
        "type": "Point",
        "coordinates": [
          15.464438618962125,
          47.054245610776654
        ]
      }
    },
    {
      "type": "Feature",
      "properties": {
        "nummer": 27662,
        "objectid": 1593,
        "baumbezeichnung_deutsch": "Esche",
        "baumbezeichnung_botanisch": "Fraxinus excelsior",
        "baumtyp": "Laub",
        "bemerkung": null,
        "pflanzjahr": "2008",
        "entnahmejahr": null,
        "baumpatenschaft": null,
        "altersklassifizierung": "jung"
      },
      "geometry": {
        "type": "Point",
        "coordinates": [
          15.464364266868394,
          47.05416751811403
        ]
      }
    },
    {
      "type": "Feature",
      "properties": {
        "nummer": 27660,
        "objectid": 1642,
        "baumbezeichnung_deutsch": "Esche",
        "baumbezeichnung_botanisch": "Fraxinus excelsior",
        "baumtyp": "Laub",
        "bemerkung": null,
        "pflanzjahr": "2008",
        "entnahmejahr": null,
        "baumpatenschaft": null,
        "altersklassifizierung": "jung"
      },
      "geometry": {
        "type": "Point",
        "coordinates": [
          15.464280173401066,
          47.05430039716435
        ]
      }
    }
  ]
}