{
  "type": "FeatureCollection",
  "features": [
    {
      "type": "Feature",
      "id": 1242,
      "properties": {
        "nummer": 18842,
        "objectid": 1242,
        "baumbezeichnung_deutsch": "Feldahorn",
        "baumbezeichnung_botanisch": "Acer campestre",
        "baumtyp": "Laub",
        "bemerkung": null,
        "pflanzjahr": null,
        "entnahmejahr": null,
        "baumpatenschaft": null,
        "altersklassifizierung": "alt"
      },
      "geometry": {
        "type": "Point",
        "coordinates": [
          15.43882054718211,
          47.07636915758589
        ]
      }
    },
    {
      "type": "Feature",
      "id": 1243,
      "properties": {
        "nummer": 18858,
        "objectid": 1243,
        "baumbezeichnung_deutsch": "Gemeine Roßkastanie",
        "baumbezeichnung_botanisch": "Aesculus hippocastanum",
        "baumtyp": "Laub",
        "bemerkung": null,
        "pflanzjahr": null,
        "entnahmejahr": null,
        "baumpatenschaft": null,
        "altersklassifizierung": "alt"
      },
      "geometry": {
        "type": "Point",
        "coordinates": [
          15.439109106322665,
          47.07665633230722
        ]
      }
    },
    {
      "type": "Feature",
      "id": 1244,
      "properties": {
        "nummer": 18860,
        "objectid": 1244,
        "baumbezeichnung_deutsch": "Gemeine Roßkastanie",
        "baumbezeichnung_botanisch": "Aesculus hippocastanum",
        "baumtyp": "Laub",
        "bemerkung": null,
        "pflanzjahr": null,
        "entnahmejahr": null,
        "baumpatenschaft": null,
        "altersklassifizierung": "alt"
      },
      "geometry": {
        "type": "Point",
        "coordinates": [
          15.439184966716693,
          47.07659208389964
        ]
      }
    },
    {
      "type": "Feature",
      "id": 1245,
      "properties": {
        "nummer": 18865,
        "objectid": 1245,
        "baumbezeichnung_deutsch": "Gemeine Roßkastanie",
        "baumbezeichnung_botanisch": "Aesculus hippocastanum",
        "baumtyp": "Laub",
        "bemerkung": null,
        "pflanzjahr": null,
        "entnahmejahr": null,
        "baumpatenschaft": null,
        "altersklassifizierung": "mittel"
      },
      "geometry": {
        "type": "Point",
        "coordinates": [
          15.439324493527428,
          47.07650475529425
        ]
      }
    },
    {
      "type": "Feature",
      "id": 1251,
      "properties": {
        "nummer": 18887,
        "objectid": 1251,
        "baumbezeichnung_deutsch": "Kirsche",
        "baumbezeichnung_botanisch": "Prunus sp.",
        "baumtyp": "Laub",
        "bemerkung": null,
        "pflanzjahr": null,
        "entnahmejahr": null,
        "baumpatenschaft": null,
        "altersklassifizierung": "mittel"
      },
      "geometry": {
        "type": "Point",
        "coordinates": [
          15.439154917112466,
          47.07581177438981
        ]
      }
    },
    {
      "type": "Feature",
      "id": 1252,
      "properties": {
        "nummer": 18892,
        "objectid": 1252,
        "baumbezeichnung_deutsch": "Esche",
        "baumbezeichnung_botanisch": "Fraxinus excelsior",
        "baumtyp": "Laub",
        "bemerkung": null,
        "pflanzjahr": null,
        "entnahmejahr": null,
        "baumpatenschaft": null,
        "altersklassifizierung": "alt"
      },
      "geometry": {
        "type": "Point",
        "coordinates": [
          15.439502271480148,
          47.07653758578956
        ]
      }
    }
  ]
}