{
  "type": "FeatureCollection",
  "features": [
    {
      "type": "Feature",
      "properties": {
        "NUMMER": 18842,
        "BAUMBEZEICHNUNG_BOTANISCH": "Acer campestre",
        "BAUMBEZEICHNUNG_DEUTSCH": "Feldahorn",
        "BAUMTYP": "Laub",
        "BEMERKUNG": null,
        "PFLANZJAHR": null,
        "ENTNAHMEJAHR": null,
        "BAUMPATENSCHAFT": null,
        "ALTERSKLASSIZIERUNG": "alt",
        "OBJECTID": 1242
      },
      "geometry": {
        "type": "Point",
        "coordinates": [
          15.43882054718211,
          47.07636915758589
        ]
      }
    },
    {
      "type": "Feature",
      "properties": {
        "NUMMER": 18858,
        "BAUMBEZEICHNUNG_BOTANISCH": "Aesculus hippocastanum",
        "BAUMBEZEICHNUNG_DEUTSCH": "Gemeine Roßkastanie",
        "BAUMTYP": "Laub",
        "BEMERKUNG": null,
        "PFLANZJAHR": null,
        "ENTNAHMEJAHR": null,
        "BAUMPATENSCHAFT": null,
        "ALTERSKLASSIZIERUNG": "alt",
        "OBJECTID": 1243
      },
      "geometry": {
        "type": "Point",
        "coordinates": [
          15.439109106322665,
          47.07665633230722
        ]
      }
    },
    {
      "type": "Feature",
      "properties": {
        "NUMMER": 18860,
        "BAUMBEZEICHNUNG_BOTANISCH": "Aesculus hippocastanum",
        "BAUMBEZEICHNUNG_DEUTSCH": "Gemeine Roßkastanie",
        "BAUMTYP": "Laub",
        "BEMERKUNG": null,
        "PFLANZJAHR": null,
        "ENTNAHMEJAHR": null,
        "BAUMPATENSCHAFT": null,
        "ALTERSKLASSIZIERUNG": "alt",
        "OBJECTID": 1244
      },
      "geometry": {
        "type": "Point",
        "coordinates": [
          15.439184966716693,
          47.07659208389964
        ]
      }
    },
    {
      "type": "Feature",
      "properties": {
        "NUMMER": 18865,
        "BAUMBEZEICHNUNG_BOTANISCH": "Aesculus hippocastanum",
        "BAUMBEZEICHNUNG_DEUTSCH": "Gemeine Roßkastanie",
        "BAUMTYP": "Laub",
        "BEMERKUNG": null,
        "PFLANZJAHR": null,
        "ENTNAHMEJAHR": null,
        "BAUMPATENSCHAFT": null,
        "ALTERSKLASSIZIERUNG": "mittel",
        "OBJECTID": 1245
      },
      "geometry": {
        "type": "Point",
        "coordinates": [
          15.439324493527428,
          47.07650475529425
        ]
      }
    },
    {
      "type": "Feature",
      "properties": {
        "NUMMER": 18887,
        "BAUMBEZEICHNUNG_BOTANISCH": "Prunus sp.",
        "BAUMBEZEICHNUNG_DEUTSCH": "Kirsche",
        "BAUMTYP": "Laub",
        "BEMERKUNG": null,
        "PFLANZJAHR": null,
        "ENTNAHMEJAHR": null,
        "BAUMPATENSCHAFT": null,
        "ALTERSKLASSIZIERUNG": "mittel",
        "OBJECTID": 1251
      },
      "geometry": {
        "type": "Point",
        "coordinates": [
          15.439154917112466,
          47.07581177438981
        ]
      }
    },
    {
      "type": "Feature",
      "properties": {
        "NUMMER": 18892,
        "BAUMBEZEICHNUNG_BOTANISCH": "Fraxinus excelsior",
        "BAUMBEZEICHNUNG_DEUTSCH": "Esche",
        "BAUMTYP": "Laub",
        "BEMERKUNG": null,
        "PFLANZJAHR": null,
        "ENTNAHMEJAHR": null,
        "BAUMPATENSCHAFT": null,
        "ALTERSKLASSIZIERUNG": "alt",
        "OBJECTID": 1252
      },
      "geometry": {
        "type": "Point",
        "coordinates": [
          15.439502271480148,
          47.07653758578956
        ]
      }
    }
  ]
}