{"type":"FeatureCollection","features":[{"type":"Feature","properties":{"nummer":25561,"baumbezeichnung_botanisch":"Quercus robur 'Fastigiata'","baumbezeichnung_deutsch":"Säulenstieleiche","baumtyp":"Laub","bemerkung":null,"pflanzjahr":"1990","entnahmejahr":null,"marker-size":"small","marker-symbol":"park2","marker-color":"#A3DDAD"},"geometry":{"type":"Point","coordinates":[15.43869998869821,47.05924716585098],"bbox":[15.43869998869821,47.05924716585098,15.43869998869821,47.05924716585098]}},{"type":"Feature","properties":{"nummer":16972,"baumbezeichnung_botanisch":"Quercus robur 'Fastigiata'","baumbezeichnung_deutsch":"Säulenstieleiche","baumtyp":"Laub","bemerkung":null,"pflanzjahr":"1990","entnahmejahr":null,"marker-size":"small","marker-symbol":"park2","marker-color":"#A3DDAD"},"geometry":{"type":"Point","coordinates":[15.43868892148646,47.05893953631211],"bbox":[15.43868892148646,47.05893953631211,15.43868892148646,47.05893953631211]}},{"type":"Feature","properties":{"nummer":16968,"baumbezeichnung_botanisch":"Quercus robur 'Fastigiata'","baumbezeichnung_deutsch":"Säulenstieleiche","baumtyp":"Laub","bemerkung":null,"pflanzjahr":"2003","entnahmejahr":null,"marker-size":"small","marker-symbol":"park2","marker-color":"#A3DDAD"},"geometry":{"type":"Point","coordinates":[15.43855419625146,47.05932408275191],"bbox":[15.43855419625146,47.05932408275191,15.43855419625146,47.05932408275191]}},{"type":"Feature","properties":{"nummer":5345,"baumbezeichnung_botanisch":"Tilia platyphyllos","baumbezeichnung_deutsch":"Sommerlinde","baumtyp":"Laub","bemerkung":null,"pflanzjahr":null,"entnahmejahr":null,"marker-size":"small","marker-symbol":"park2","marker-color":"#A3DDAD"},"geometry":{"type":"Point","coordinates":[15.4385750033842,47.06056464252469],"bbox":[15.4385750033842,47.06056464252469,15.4385750033842,47.06056464252469]}},{"type":"Feature","properties":{"nummer":861,"baumbezeichnung_botanisch":"Rhus typhina","baumbezeichnung_deutsch":"Essigbaum","baumtyp":"Laub","bemerkung":null,"pflanzjahr":null,"entnahmejahr":null,"marker-size":"small","marker-symbol":"park2","marker-color":"#A3DDAD"},"geometry":{"type":"Point","coordinates":[15.43864595189799,47.06036869597176],"bbox":[15.43864595189799,47.06036869597176,15.43864595189799,47.06036869597176]}},{"type":"Feature","properties":{"nummer":23660,"baumbezeichnung_botanisch":"Thuja sp.","baumbezeichnung_deutsch":"Lebensbaum","baumtyp":"Nadel","bemerkung":null,"pflanzjahr":null,"entnahmejahr":null,"marker-size":"small","marker-symbol":"park","marker-color":"#3BB451"},"geometry":{"type":"Point","coordinates":[15.43859049150926,47.06036165618585],"bbox":[15.43859049150926,47.06036165618585,15.43859049150926,47.06036165618585]}},{"type":"Feature","properties":{"nummer":9559,"baumbezeichnung_botanisch":"Thuja sp.","baumbezeichnung_deutsch":"Lebensbaum","baumtyp":"Nadel","bemerkung":null,"pflanzjahr":null,"entnahmejahr":null,"marker-size":"small","marker-symbol":"park","marker-color":"#3BB451"},"geometry":{"type":"Point","coordinates":[15.43854472455701,47.06035304085147],"bbox":[15.43854472455701,47.06035304085147,15.43854472455701,47.06035304085147]}}]}