{
  "type": "FeatureCollection",
  "features": [
    {
      "type": "Feature",
      "properties": {
        "NUMMER": 13215,
        "BAUMBEZEICHNUNG_BOTANISCH": "Acer platanoides",
        "BAUMBEZEICHNUNG_DEUTSCH": "Spitzahorn",
        "BAUMTYP": "Laub",
        "BEMERKUNG": null,
        "PFLANZJAHR": null,
        "ENTNAHMEJAHR": null,
        "BAUMPATENSCHAFT": null,
        "ALTERSKLASSIZIERUNG": "mittel",
        "OBJECTID": 415
      },
      "geometry": {
        "type": "Point",
        "coordinates": [
          15.429316210364078,
          47.04663920871382
        ]
      }
    },
    {
      "type": "Feature",
      "properties": {
        "NUMMER": 13201,
        "BAUMBEZEICHNUNG_BOTANISCH": "Acer platanoides",
        "BAUMBEZEICHNUNG_DEUTSCH": "Spitzahorn",
        "BAUMTYP": "Laub",
        "BEMERKUNG": null,
        "PFLANZJAHR": null,
        "ENTNAHMEJAHR": null,
        "BAUMPATENSCHAFT": null,
        "ALTERSKLASSIZIERUNG": "mittel",
        "OBJECTID": 776
      },
      "geometry": {
        "type": "Point",
        "coordinates": [
          15.429355015275114,
          47.046295697645796
        ]
      }
    },
    {
      "type": "Feature",
      "properties": {
        "NUMMER": 13166,
        "BAUMBEZEICHNUNG_BOTANISCH": "Acer pseudoplatanus",
        "BAUMBEZEICHNUNG_DEUTSCH": "Bergahorn",
        "BAUMTYP": "Laub",
        "BEMERKUNG": null,
        "PFLANZJAHR": null,
        "ENTNAHMEJAHR": null,
        "BAUMPATENSCHAFT": null,
        "ALTERSKLASSIZIERUNG": "mittel",
        "OBJECTID": 731
      },
      "geometry": {
        "type": "Point",
        "coordinates": [
          15.428810333421799,
          47.047493388898985
        ]
      }
    },
    {
      "type": "Feature",
      "properties": {
        "NUMMER": 13211,
        "BAUMBEZEICHNUNG_BOTANISCH": "Tilia platyphyllos",
        "BAUMBEZEICHNUNG_DEUTSCH": "Sommerlinde",
        "BAUMTYP": "Laub",
        "BEMERKUNG": null,
        "PFLANZJAHR": null,
        "ENTNAHMEJAHR": null,
        "BAUMPATENSCHAFT": null,
        "ALTERSKLASSIZIERUNG": "alt",
        "OBJECTID": 766
      },
      "geometry": {
        "type": "Point",
        "coordinates": [
          15.429176333874153,
          47.046501241669745
        ]
      }
    },
    {
      "type": "Feature",
      "properties": {
        "NUMMER": 13213,
        "BAUMBEZEICHNUNG_BOTANISCH": "Acer platanoides",
        "BAUMBEZEICHNUNG_DEUTSCH": "Spitzahorn",
        "BAUMTYP": "Laub",
        "BEMERKUNG": null,
        "PFLANZJAHR": null,
        "ENTNAHMEJAHR": null,
        "BAUMPATENSCHAFT": null,
        "ALTERSKLASSIZIERUNG": "alt",
        "OBJECTID": 1569
      },
      "geometry": {
        "type": "Point",
        "coordinates": [
          15.429297672645532,
          47.046597728596595
        ]
      }
    }
  ]
}