{"type":"FeatureCollection","features":[{"type":"Feature","properties":{"nummer":45351,"baumbezeichnung_botanisch":"Fagus sylvatica 'Fastigiata'","baumbezeichnung_deutsch":"Säulenbuche","baumtyp":"Laub","bemerkung":null,"pflanzjahr":"2011","entnahmejahr":null,"marker-size":"small","marker-symbol":"park2","marker-color":"#A3DDAD"},"geometry":{"type":"Point","coordinates":[15.45393898953451,47.08149799442564],"bbox":[15.45393898953451,47.08149799442564,15.45393898953451,47.08149799442564]}}]}