{"type":"FeatureCollection","features":[{"type":"Feature","properties":{"nummer":10677,"baumbezeichnung_botanisch":"Tilia cordata","baumbezeichnung_deutsch":"Winterlinde","baumtyp":"Laub","bemerkung":null,"pflanzjahr":"1985","entnahmejahr":null,"marker-size":"small","marker-symbol":"park2","marker-color":"#A3DDAD"},"geometry":{"type":"Point","coordinates":[15.45498146822955,47.06006558079488],"bbox":[15.45498146822955,47.06006558079488,15.45498146822955,47.06006558079488]}},{"type":"Feature","properties":{"nummer":5144,"baumbezeichnung_botanisch":"Tilia cordata","baumbezeichnung_deutsch":"Winterlinde","baumtyp":"Laub","bemerkung":null,"pflanzjahr":"1985","entnahmejahr":null,"marker-size":"small","marker-symbol":"park2","marker-color":"#A3DDAD"},"geometry":{"type":"Point","coordinates":[15.45483696258587,47.06002017687192],"bbox":[15.45483696258587,47.06002017687192,15.45483696258587,47.06002017687192]}},{"type":"Feature","properties":{"nummer":3814,"baumbezeichnung_botanisch":"Tilia cordata","baumbezeichnung_deutsch":"Winterlinde","baumtyp":"Laub","bemerkung":null,"pflanzjahr":"1985","entnahmejahr":null,"marker-size":"small","marker-symbol":"park2","marker-color":"#A3DDAD"},"geometry":{"type":"Point","coordinates":[15.45431679338199,47.059856140544],"bbox":[15.45431679338199,47.059856140544,15.45431679338199,47.059856140544]}},{"type":"Feature","properties":{"nummer":27053,"baumbezeichnung_botanisch":"Pyrus 'Vereins Dechantbirne'","baumbezeichnung_deutsch":"Fruchtbirne","baumtyp":"Laub","bemerkung":null,"pflanzjahr":"2008","entnahmejahr":null,"marker-size":"small","marker-symbol":"park2","marker-color":"#A3DDAD"},"geometry":{"type":"Point","coordinates":[15.45383993219422,47.06072446466676],"bbox":[15.45383993219422,47.06072446466676,15.45383993219422,47.06072446466676]}},{"type":"Feature","properties":{"nummer":28976,"baumbezeichnung_botanisch":"Malus sp.","baumbezeichnung_deutsch":"Apfelbaum","baumtyp":"Laub","bemerkung":null,"pflanzjahr":null,"entnahmejahr":null,"marker-size":"small","marker-symbol":"park2","marker-color":"#A3DDAD"},"geometry":{"type":"Point","coordinates":[15.4539520720548,47.06068248942837],"bbox":[15.4539520720548,47.06068248942837,15.4539520720548,47.06068248942837]}},{"type":"Feature","properties":{"nummer":28978,"baumbezeichnung_botanisch":"Malus sp.","baumbezeichnung_deutsch":"Apfelbaum","baumtyp":"Laub","bemerkung":null,"pflanzjahr":null,"entnahmejahr":null,"marker-size":"small","marker-symbol":"park2","marker-color":"#A3DDAD"},"geometry":{"type":"Point","coordinates":[15.45387197907602,47.06068187238739],"bbox":[15.45387197907602,47.06068187238739,15.45387197907602,47.06068187238739]}},{"type":"Feature","properties":{"nummer":8221,"baumbezeichnung_botanisch":"Malus sp.","baumbezeichnung_deutsch":"Apfelbaum","baumtyp":"Laub","bemerkung":null,"pflanzjahr":null,"entnahmejahr":null,"marker-size":"small","marker-symbol":"park2","marker-color":"#A3DDAD"},"geometry":{"type":"Point","coordinates":[15.45393826993633,47.06072879963918],"bbox":[15.45393826993633,47.06072879963918,15.45393826993633,47.06072879963918]}}]}