{"type":"FeatureCollection","features":[{"type":"Feature","properties":{"nummer":2186,"baumbezeichnung_botanisch":"Platanus x acerifolia","baumbezeichnung_deutsch":"Platane","baumtyp":"Laub","bemerkung":null,"pflanzjahr":null,"entnahmejahr":null,"marker-size":"small","marker-symbol":"park2","marker-color":"#A3DDAD"},"geometry":{"type":"Point","coordinates":[15.45366550504849,47.0668391112863],"bbox":[15.45366550504849,47.0668391112863,15.45366550504849,47.0668391112863]}},{"type":"Feature","properties":{"nummer":4813,"baumbezeichnung_botanisch":"Sophora japonica","baumbezeichnung_deutsch":"Schnurbaum","baumtyp":"Laub","bemerkung":null,"pflanzjahr":null,"entnahmejahr":null,"marker-size":"small","marker-symbol":"park2","marker-color":"#A3DDAD"},"geometry":{"type":"Point","coordinates":[15.4537342228801,47.06682326973766],"bbox":[15.4537342228801,47.06682326973766,15.4537342228801,47.06682326973766]}},{"type":"Feature","properties":{"nummer":13538,"baumbezeichnung_botanisch":"Sophora japonica","baumbezeichnung_deutsch":"Schnurbaum","baumtyp":"Laub","bemerkung":null,"pflanzjahr":null,"entnahmejahr":null,"marker-size":"small","marker-symbol":"park2","marker-color":"#A3DDAD"},"geometry":{"type":"Point","coordinates":[15.45365875728023,47.06672949902572],"bbox":[15.45365875728023,47.06672949902572,15.45365875728023,47.06672949902572]}}]}