{"type":"FeatureCollection","features":[{"type":"Feature","properties":{"nummer":59108,"baumbezeichnung_botanisch":"Picea abies","baumbezeichnung_deutsch":"Rotfichte","baumtyp":"Nadel","bemerkung":null,"pflanzjahr":null,"entnahmejahr":null,"marker-size":"small","marker-symbol":"park","marker-color":"#3BB451"},"geometry":{"type":"Point","coordinates":[15.45398425818945,47.05253568816389],"bbox":[15.45398425818945,47.05253568816389,15.45398425818945,47.05253568816389]}},{"type":"Feature","properties":{"nummer":59107,"baumbezeichnung_botanisch":"Picea abies","baumbezeichnung_deutsch":"Rotfichte","baumtyp":"Nadel","bemerkung":null,"pflanzjahr":null,"entnahmejahr":null,"marker-size":"small","marker-symbol":"park","marker-color":"#3BB451"},"geometry":{"type":"Point","coordinates":[15.45395552045466,47.05258901560865],"bbox":[15.45395552045466,47.05258901560865,15.45395552045466,47.05258901560865]}},{"type":"Feature","properties":{"nummer":59106,"baumbezeichnung_botanisch":"Picea abies","baumbezeichnung_deutsch":"Rotfichte","baumtyp":"Nadel","bemerkung":"starke Nadelverfärbung und Nadelfall im südöstlichen Kronenbereich, massive Wurzelverletzungen durch Hüttenaufstellung 2006 können nicht ausgeschlossen werden, Ersatzpflanzung vorgesehen","pflanzjahr":null,"entnahmejahr":null,"marker-size":"small","marker-symbol":"park","marker-color":"#3BB451"},"geometry":{"type":"Point","coordinates":[15.45393012729628,47.05265069919062],"bbox":[15.45393012729628,47.05265069919062,15.45393012729628,47.05265069919062]}}]}