{
  "type": "FeatureCollection",
  "features": [
    {
      "type": "Feature",
      "properties": {
        "NUMMER": 24186,
        "BAUMBEZEICHNUNG_BOTANISCH": "Tilia platyphyllos",
        "BAUMBEZEICHNUNG_DEUTSCH": "Sommerlinde",
        "BAUMTYP": "Laub",
        "BEMERKUNG": null,
        "PFLANZJAHR": null,
        "ENTNAHMEJAHR": null,
        "BAUMPATENSCHAFT": null,
        "ALTERSKLASSIZIERUNG": "jung",
        "OBJECTID": 487
      },
      "geometry": {
        "type": "Point",
        "coordinates": [
          15.45629555247608,
          47.050936594390606
        ]
      }
    },
    {
      "type": "Feature",
      "properties": {
        "NUMMER": 23525,
        "BAUMBEZEICHNUNG_BOTANISCH": "Platanus x acerifolia",
        "BAUMBEZEICHNUNG_DEUTSCH": "Platane",
        "BAUMTYP": "Laub",
        "BEMERKUNG": null,
        "PFLANZJAHR": "2002",
        "ENTNAHMEJAHR": null,
        "BAUMPATENSCHAFT": null,
        "ALTERSKLASSIZIERUNG": "jung",
        "OBJECTID": 885
      },
      "geometry": {
        "type": "Point",
        "coordinates": [
          15.449003270256732,
          47.05382417843774
        ]
      }
    },
    {
      "type": "Feature",
      "properties": {
        "NUMMER": 5489,
        "BAUMBEZEICHNUNG_BOTANISCH": "Acer campestre",
        "BAUMBEZEICHNUNG_DEUTSCH": "Feldahorn",
        "BAUMTYP": "Laub",
        "BEMERKUNG": null,
        "PFLANZJAHR": null,
        "ENTNAHMEJAHR": null,
        "BAUMPATENSCHAFT": null,
        "ALTERSKLASSIZIERUNG": "mittel",
        "OBJECTID": 1164
      },
      "geometry": {
        "type": "Point",
        "coordinates": [
          15.457001128285485,
          47.05124981724146
        ]
      }
    },
    {
      "type": "Feature",
      "properties": {
        "Naturdenkmal": true,
        "Naturdenkmal_Eigentum": "öffentlich",
        "nummer": "Naturdenkmal-44",
        "objectid": "Naturdenkmal-96",
        "baumbezeichnung_deutsch": "Platane",
        "baumbezeichnung_botanisch": "Platanus orientalis L"
      },
      "geometry": {
        "type": "Point",
        "coordinates": [
          15.45584740322874,
          47.050967127100904
        ]
      }
    }
  ]
}