{
  "type": "FeatureCollection",
  "features": [
    {
      "type": "Feature",
      "properties": {
        "nummer": 24186,
        "objectid": 487,
        "baumbezeichnung_deutsch": "Sommerlinde",
        "baumbezeichnung_botanisch": "Tilia platyphyllos",
        "baumtyp": "Laub",
        "bemerkung": null,
        "pflanzjahr": null,
        "entnahmejahr": null,
        "baumpatenschaft": null,
        "altersklassifizierung": "jung"
      },
      "geometry": {
        "type": "Point",
        "coordinates": [
          15.45629555247608,
          47.050936594390606
        ]
      }
    },
    {
      "type": "Feature",
      "properties": {
        "nummer": 23525,
        "objectid": 885,
        "baumbezeichnung_deutsch": "Platane",
        "baumbezeichnung_botanisch": "Platanus x acerifolia",
        "baumtyp": "Laub",
        "bemerkung": null,
        "pflanzjahr": "2002",
        "entnahmejahr": null,
        "baumpatenschaft": null,
        "altersklassifizierung": "jung"
      },
      "geometry": {
        "type": "Point",
        "coordinates": [
          15.449003270256732,
          47.05382417843774
        ]
      }
    },
    {
      "type": "Feature",
      "properties": {
        "nummer": 5489,
        "objectid": 1164,
        "baumbezeichnung_deutsch": "Feldahorn",
        "baumbezeichnung_botanisch": "Acer campestre",
        "baumtyp": "Laub",
        "bemerkung": null,
        "pflanzjahr": null,
        "entnahmejahr": null,
        "baumpatenschaft": null,
        "altersklassifizierung": "mittel"
      },
      "geometry": {
        "type": "Point",
        "coordinates": [
          15.457001128285485,
          47.05124981724146
        ]
      }
    },
    {
      "type": "Feature",
      "properties": {
        "Naturdenkmal": true,
        "Naturdenkmal_Eigentum": "öffentlich",
        "nummer": "Naturdenkmal-44",
        "objectid": "Naturdenkmal-96",
        "baumbezeichnung_deutsch": "Platane",
        "baumbezeichnung_botanisch": "Platanus orientalis L"
      },
      "geometry": {
        "type": "Point",
        "coordinates": [
          15.45584740322874,
          47.050967127100904
        ]
      }
    }
  ]
}