{"type":"FeatureCollection","features":[{"type":"Feature","properties":{"nummer":6259,"baumbezeichnung_botanisch":"Liriodendron tulipifera","baumbezeichnung_deutsch":"Tulpenbaum","baumtyp":"Laub","bemerkung":null,"pflanzjahr":"2012","entnahmejahr":null,"marker-size":"small","marker-symbol":"park2","marker-color":"#A3DDAD"},"geometry":{"type":"Point","coordinates":[15.40755398554469,47.07760712320768],"bbox":[15.40755398554469,47.07760712320768,15.40755398554469,47.07760712320768]}}]}