{"type":"FeatureCollection","features":[{"type":"Feature","properties":{"nummer":10368,"baumbezeichnung_botanisch":"Tilia sp.","baumbezeichnung_deutsch":"Linde","baumtyp":"Laub","bemerkung":null,"pflanzjahr":null,"entnahmejahr":null,"marker-size":"small","marker-symbol":"park2","marker-color":"#A3DDAD"},"geometry":{"type":"Point","coordinates":[15.4083092762095,47.08215542931841],"bbox":[15.4083092762095,47.08215542931841,15.4083092762095,47.08215542931841]}},{"type":"Feature","properties":{"nummer":10367,"baumbezeichnung_botanisch":"Tilia sp.","baumbezeichnung_deutsch":"Linde","baumtyp":"Laub","bemerkung":null,"pflanzjahr":null,"entnahmejahr":null,"marker-size":"small","marker-symbol":"park2","marker-color":"#A3DDAD"},"geometry":{"type":"Point","coordinates":[15.40807227059977,47.08210308246787],"bbox":[15.40807227059977,47.08210308246787,15.40807227059977,47.08210308246787]}},{"type":"Feature","properties":{"nummer":22941,"baumbezeichnung_botanisch":"Tilia sp.","baumbezeichnung_deutsch":"Linde","baumtyp":"Laub","bemerkung":null,"pflanzjahr":null,"entnahmejahr":null,"marker-size":"small","marker-symbol":"park2","marker-color":"#A3DDAD"},"geometry":{"type":"Point","coordinates":[15.40787165401378,47.0820595934059],"bbox":[15.40787165401378,47.0820595934059,15.40787165401378,47.0820595934059]}},{"type":"Feature","properties":{"nummer":4586,"baumbezeichnung_botanisch":"Tilia sp.","baumbezeichnung_deutsch":"Linde","baumtyp":"Laub","bemerkung":null,"pflanzjahr":null,"entnahmejahr":null,"marker-size":"small","marker-symbol":"park2","marker-color":"#A3DDAD"},"geometry":{"type":"Point","coordinates":[15.4075348503756,47.08198803253182],"bbox":[15.4075348503756,47.08198803253182,15.4075348503756,47.08198803253182]}},{"type":"Feature","properties":{"nummer":1549,"baumbezeichnung_botanisch":"Tilia sp.","baumbezeichnung_deutsch":"Linde","baumtyp":"Laub","bemerkung":null,"pflanzjahr":null,"entnahmejahr":null,"marker-size":"small","marker-symbol":"park2","marker-color":"#A3DDAD"},"geometry":{"type":"Point","coordinates":[15.40716245396374,47.08190659319054],"bbox":[15.40716245396374,47.08190659319054,15.40716245396374,47.08190659319054]}},{"type":"Feature","properties":{"nummer":1550,"baumbezeichnung_botanisch":"Tilia sp.","baumbezeichnung_deutsch":"Linde","baumtyp":"Laub","bemerkung":null,"pflanzjahr":null,"entnahmejahr":null,"marker-size":"small","marker-symbol":"park2","marker-color":"#A3DDAD"},"geometry":{"type":"Point","coordinates":[15.40815495062572,47.08220344494215],"bbox":[15.40815495062572,47.08220344494215,15.40815495062572,47.08220344494215]}},{"type":"Feature","properties":{"nummer":4587,"baumbezeichnung_botanisch":"Tilia sp.","baumbezeichnung_deutsch":"Linde","baumtyp":"Laub","bemerkung":null,"pflanzjahr":null,"entnahmejahr":null,"marker-size":"small","marker-symbol":"park2","marker-color":"#A3DDAD"},"geometry":{"type":"Point","coordinates":[15.40762464089502,47.08208835410254],"bbox":[15.40762464089502,47.08208835410254,15.40762464089502,47.08208835410254]}},{"type":"Feature","properties":{"nummer":13974,"baumbezeichnung_botanisch":"Tilia sp.","baumbezeichnung_deutsch":"Linde","baumtyp":"Laub","bemerkung":null,"pflanzjahr":null,"entnahmejahr":null,"marker-size":"small","marker-symbol":"park2","marker-color":"#A3DDAD"},"geometry":{"type":"Point","coordinates":[15.40718843765717,47.08199280592806],"bbox":[15.40718843765717,47.08199280592806,15.40718843765717,47.08199280592806]}},{"type":"Feature","properties":{"nummer":27026,"baumbezeichnung_botanisch":"Tilia cordata","baumbezeichnung_deutsch":"Winterlinde","baumtyp":"Laub","bemerkung":null,"pflanzjahr":"2008","entnahmejahr":null,"marker-size":"small","marker-symbol":"park2","marker-color":"#A3DDAD"},"geometry":{"type":"Point","coordinates":[15.40786259945193,47.08214039477683],"bbox":[15.40786259945193,47.08214039477683,15.40786259945193,47.08214039477683]}},{"type":"Feature","properties":{"nummer":17821,"baumbezeichnung_botanisch":"Tilia platyphyllos","baumbezeichnung_deutsch":"Sommerlinde","baumtyp":"Laub","bemerkung":null,"pflanzjahr":"2003","entnahmejahr":null,"marker-size":"small","marker-symbol":"park2","marker-color":"#A3DDAD"},"geometry":{"type":"Point","coordinates":[15.40739022866031,47.08195579974415],"bbox":[15.40739022866031,47.08195579974415,15.40739022866031,47.08195579974415]}}]}