{"type":"FeatureCollection","features":[{"type":"Feature","properties":{"nummer":1925,"baumbezeichnung_botanisch":"Sophora japonica","baumbezeichnung_deutsch":"Schnurbaum","baumtyp":"Laub","bemerkung":null,"pflanzjahr":"2006","entnahmejahr":null,"marker-size":"small","marker-symbol":"park2","marker-color":"#A3DDAD"},"geometry":{"type":"Point","coordinates":[15.40707201621293,47.06818422596296],"bbox":[15.40707201621293,47.06818422596296,15.40707201621293,47.06818422596296]}},{"type":"Feature","properties":{"nummer":10193,"baumbezeichnung_botanisch":"Sophora japonica","baumbezeichnung_deutsch":"Schnurbaum","baumtyp":"Laub","bemerkung":null,"pflanzjahr":"2005","entnahmejahr":null,"marker-size":"small","marker-symbol":"park2","marker-color":"#A3DDAD"},"geometry":{"type":"Point","coordinates":[15.40727856127981,47.06818201558761],"bbox":[15.40727856127981,47.06818201558761,15.40727856127981,47.06818201558761]}},{"type":"Feature","properties":{"nummer":23147,"baumbezeichnung_botanisch":"Sophora japonica","baumbezeichnung_deutsch":"Schnurbaum","baumtyp":"Laub","bemerkung":null,"pflanzjahr":null,"entnahmejahr":null,"marker-size":"small","marker-symbol":"park2","marker-color":"#A3DDAD"},"geometry":{"type":"Point","coordinates":[15.40782700096943,47.06816849954431],"bbox":[15.40782700096943,47.06816849954431,15.40782700096943,47.06816849954431]}},{"type":"Feature","properties":{"nummer":7844,"baumbezeichnung_botanisch":"Sophora japonica","baumbezeichnung_deutsch":"Schnurbaum","baumtyp":"Laub","bemerkung":null,"pflanzjahr":null,"entnahmejahr":null,"marker-size":"small","marker-symbol":"park2","marker-color":"#A3DDAD"},"geometry":{"type":"Point","coordinates":[15.40773486232527,47.06816982146962],"bbox":[15.40773486232527,47.06816982146962,15.40773486232527,47.06816982146962]}},{"type":"Feature","properties":{"nummer":23146,"baumbezeichnung_botanisch":"Sophora japonica","baumbezeichnung_deutsch":"Schnurbaum","baumtyp":"Laub","bemerkung":null,"pflanzjahr":null,"entnahmejahr":null,"marker-size":"small","marker-symbol":"park2","marker-color":"#A3DDAD"},"geometry":{"type":"Point","coordinates":[15.40763630013324,47.06817260241564],"bbox":[15.40763630013324,47.06817260241564,15.40763630013324,47.06817260241564]}},{"type":"Feature","properties":{"nummer":1,"baumbezeichnung_botanisch":"Sophora japonica","baumbezeichnung_deutsch":"Schnurbaum","baumtyp":"Laub","bemerkung":null,"pflanzjahr":null,"entnahmejahr":null,"marker-size":"small","marker-symbol":"park2","marker-color":"#A3DDAD"},"geometry":{"type":"Point","coordinates":[15.40755382327588,47.06817710854163],"bbox":[15.40755382327588,47.06817710854163,15.40755382327588,47.06817710854163]}},{"type":"Feature","properties":{"nummer":14577,"baumbezeichnung_botanisch":"Sophora japonica","baumbezeichnung_deutsch":"Schnurbaum","baumtyp":"Laub","bemerkung":null,"pflanzjahr":null,"entnahmejahr":null,"marker-size":"small","marker-symbol":"park2","marker-color":"#A3DDAD"},"geometry":{"type":"Point","coordinates":[15.40746318849037,47.06818113377716],"bbox":[15.40746318849037,47.06818113377716,15.40746318849037,47.06818113377716]}},{"type":"Feature","properties":{"nummer":4134,"baumbezeichnung_botanisch":"Sophora japonica","baumbezeichnung_deutsch":"Schnurbaum","baumtyp":"Laub","bemerkung":null,"pflanzjahr":null,"entnahmejahr":null,"marker-size":"small","marker-symbol":"park2","marker-color":"#A3DDAD"},"geometry":{"type":"Point","coordinates":[15.4073657130871,47.06817796314937],"bbox":[15.4073657130871,47.06817796314937,15.4073657130871,47.06817796314937]}},{"type":"Feature","properties":{"nummer":21101,"baumbezeichnung_botanisch":"Sophora japonica","baumbezeichnung_deutsch":"Schnurbaum","baumtyp":"Laub","bemerkung":null,"pflanzjahr":null,"entnahmejahr":null,"marker-size":"small","marker-symbol":"park2","marker-color":"#A3DDAD"},"geometry":{"type":"Point","coordinates":[15.40716273779969,47.06818263221761],"bbox":[15.40716273779969,47.06818263221761,15.40716273779969,47.06818263221761]}},{"type":"Feature","properties":{"nummer":1924,"baumbezeichnung_botanisch":"Sophora japonica","baumbezeichnung_deutsch":"Schnurbaum","baumtyp":"Laub","bemerkung":null,"pflanzjahr":null,"entnahmejahr":null,"marker-size":"small","marker-symbol":"park2","marker-color":"#A3DDAD"},"geometry":{"type":"Point","coordinates":[15.40697998987169,47.06818514341243],"bbox":[15.40697998987169,47.06818514341243,15.40697998987169,47.06818514341243]}}]}