{"type":"FeatureCollection","features":[{"type":"Feature","properties":{"nummer":17528,"baumbezeichnung_botanisch":"Platanus x acerifolia","baumbezeichnung_deutsch":"Platane","baumtyp":"Laub","bemerkung":null,"pflanzjahr":null,"entnahmejahr":null,"marker-size":"small","marker-symbol":"park2","marker-color":"#A3DDAD"},"geometry":{"type":"Point","coordinates":[15.44959618955265,47.05302708715784],"bbox":[15.44959618955265,47.05302708715784,15.44959618955265,47.05302708715784]}},{"type":"Feature","properties":{"nummer":27673,"baumbezeichnung_botanisch":"Platanus x acerifolia","baumbezeichnung_deutsch":"Platane","baumtyp":"Laub","bemerkung":null,"pflanzjahr":"2005","entnahmejahr":null,"marker-size":"small","marker-symbol":"park2","marker-color":"#A3DDAD"},"geometry":{"type":"Point","coordinates":[15.44957476375089,47.05270036073415],"bbox":[15.44957476375089,47.05270036073415,15.44957476375089,47.05270036073415]}},{"type":"Feature","properties":{"nummer":27674,"baumbezeichnung_botanisch":"Platanus x acerifolia","baumbezeichnung_deutsch":"Platane","baumtyp":"Laub","bemerkung":null,"pflanzjahr":"2005","entnahmejahr":null,"marker-size":"small","marker-symbol":"park2","marker-color":"#A3DDAD"},"geometry":{"type":"Point","coordinates":[15.44972061252004,47.05251466301823],"bbox":[15.44972061252004,47.05251466301823,15.44972061252004,47.05251466301823]}},{"type":"Feature","properties":{"nummer":27675,"baumbezeichnung_botanisch":"Platanus x acerifolia","baumbezeichnung_deutsch":"Platane","baumtyp":"Laub","bemerkung":null,"pflanzjahr":"2005","entnahmejahr":null,"marker-size":"small","marker-symbol":"park2","marker-color":"#A3DDAD"},"geometry":{"type":"Point","coordinates":[15.44982751180348,47.05236793274128],"bbox":[15.44982751180348,47.05236793274128,15.44982751180348,47.05236793274128]}}]}