{"type":"FeatureCollection","features":[{"type":"Feature","properties":{"nummer":27248,"baumbezeichnung_botanisch":"Malus 'Kulturapfel'","baumbezeichnung_deutsch":"Apfelbaum","baumtyp":"Laub","bemerkung":null,"pflanzjahr":null,"entnahmejahr":null,"marker-size":"small","marker-symbol":"park2","marker-color":"#A3DDAD"},"geometry":{"type":"Point","coordinates":[15.42228531948723,47.10091971604458],"bbox":[15.42228531948723,47.10091971604458,15.42228531948723,47.10091971604458]}},{"type":"Feature","properties":{"nummer":27252,"baumbezeichnung_botanisch":"Betula pendula","baumbezeichnung_deutsch":"Sandbirke, Weißbirke","baumtyp":"Laub","bemerkung":null,"pflanzjahr":null,"entnahmejahr":null,"marker-size":"small","marker-symbol":"park2","marker-color":"#A3DDAD"},"geometry":{"type":"Point","coordinates":[15.42227357642692,47.10086355800299],"bbox":[15.42227357642692,47.10086355800299,15.42227357642692,47.10086355800299]}},{"type":"Feature","properties":{"nummer":27257,"baumbezeichnung_botanisch":"Betula pendula","baumbezeichnung_deutsch":"Sandbirke, Weißbirke","baumtyp":"Laub","bemerkung":null,"pflanzjahr":null,"entnahmejahr":null,"marker-size":"small","marker-symbol":"park2","marker-color":"#A3DDAD"},"geometry":{"type":"Point","coordinates":[15.42225794087506,47.10082832916134],"bbox":[15.42225794087506,47.10082832916134,15.42225794087506,47.10082832916134]}},{"type":"Feature","properties":{"nummer":27253,"baumbezeichnung_botanisch":"Malus 'Kulturapfel'","baumbezeichnung_deutsch":"Apfelbaum","baumtyp":"Laub","bemerkung":null,"pflanzjahr":null,"entnahmejahr":null,"marker-size":"small","marker-symbol":"park2","marker-color":"#A3DDAD"},"geometry":{"type":"Point","coordinates":[15.42210961168013,47.10080772694032],"bbox":[15.42210961168013,47.10080772694032,15.42210961168013,47.10080772694032]}}]}