{"type":"FeatureCollection","features":[{"type":"Feature","properties":{"nummer":14995,"baumbezeichnung_botanisch":"Populus x canadensis","baumbezeichnung_deutsch":"Karnadische Pappel","baumtyp":"Laub","bemerkung":null,"pflanzjahr":null,"entnahmejahr":null,"marker-size":"small","marker-symbol":"park2","marker-color":"#A3DDAD"},"geometry":{"type":"Point","coordinates":[15.42211284731395,47.08931889382122],"bbox":[15.42211284731395,47.08931889382122,15.42211284731395,47.08931889382122]}},{"type":"Feature","properties":{"nummer":13180,"baumbezeichnung_botanisch":"Populus x canadensis","baumbezeichnung_deutsch":"Karnadische Pappel","baumtyp":"Laub","bemerkung":null,"pflanzjahr":null,"entnahmejahr":null,"marker-size":"small","marker-symbol":"park2","marker-color":"#A3DDAD"},"geometry":{"type":"Point","coordinates":[15.4220624241396,47.0894021535867],"bbox":[15.4220624241396,47.0894021535867,15.4220624241396,47.0894021535867]}}]}