{"type":"FeatureCollection","features":[{"type":"Feature","properties":{"nummer":20208,"baumbezeichnung_botanisch":"Robinia pseudoacacia","baumbezeichnung_deutsch":"Scheinakazie","baumtyp":"Laub","bemerkung":null,"pflanzjahr":null,"entnahmejahr":null,"marker-size":"small","marker-symbol":"park2","marker-color":"#A3DDAD"},"geometry":{"type":"Point","coordinates":[15.4231099412463,47.09227962827858],"bbox":[15.4231099412463,47.09227962827858,15.4231099412463,47.09227962827858]}},{"type":"Feature","properties":{"nummer":5916,"baumbezeichnung_botanisch":"Robinia pseudoacacia","baumbezeichnung_deutsch":"Scheinakazie","baumtyp":"Laub","bemerkung":null,"pflanzjahr":null,"entnahmejahr":null,"marker-size":"small","marker-symbol":"park2","marker-color":"#A3DDAD"},"geometry":{"type":"Point","coordinates":[15.42305136816646,47.09233983298657],"bbox":[15.42305136816646,47.09233983298657,15.42305136816646,47.09233983298657]}},{"type":"Feature","properties":{"nummer":5364,"baumbezeichnung_botanisch":"Robinia pseudoacacia","baumbezeichnung_deutsch":"Scheinakazie","baumtyp":"Laub","bemerkung":null,"pflanzjahr":null,"entnahmejahr":null,"marker-size":"small","marker-symbol":"park2","marker-color":"#A3DDAD"},"geometry":{"type":"Point","coordinates":[15.42298637547113,47.09241266951431],"bbox":[15.42298637547113,47.09241266951431,15.42298637547113,47.09241266951431]}},{"type":"Feature","properties":{"nummer":19072,"baumbezeichnung_botanisch":"Robinia pseudoacacia","baumbezeichnung_deutsch":"Scheinakazie","baumtyp":"Laub","bemerkung":null,"pflanzjahr":null,"entnahmejahr":null,"marker-size":"small","marker-symbol":"park2","marker-color":"#A3DDAD"},"geometry":{"type":"Point","coordinates":[15.42339604337571,47.09204130892709],"bbox":[15.42339604337571,47.09204130892709,15.42339604337571,47.09204130892709]}},{"type":"Feature","properties":{"nummer":2926,"baumbezeichnung_botanisch":"Robinia pseudoacacia","baumbezeichnung_deutsch":"Scheinakazie","baumtyp":"Laub","bemerkung":null,"pflanzjahr":null,"entnahmejahr":null,"marker-size":"small","marker-symbol":"park2","marker-color":"#A3DDAD"},"geometry":{"type":"Point","coordinates":[15.42329143517168,47.09210787516166],"bbox":[15.42329143517168,47.09210787516166,15.42329143517168,47.09210787516166]}},{"type":"Feature","properties":{"nummer":11945,"baumbezeichnung_botanisch":"Robinia pseudoacacia","baumbezeichnung_deutsch":"Scheinakazie","baumtyp":"Laub","bemerkung":null,"pflanzjahr":null,"entnahmejahr":null,"marker-size":"small","marker-symbol":"park2","marker-color":"#A3DDAD"},"geometry":{"type":"Point","coordinates":[15.42322623605203,47.0921689356466],"bbox":[15.42322623605203,47.0921689356466,15.42322623605203,47.0921689356466]}},{"type":"Feature","properties":{"nummer":15255,"baumbezeichnung_botanisch":"Robinia pseudoacacia","baumbezeichnung_deutsch":"Scheinakazie","baumtyp":"Laub","bemerkung":null,"pflanzjahr":null,"entnahmejahr":null,"marker-size":"small","marker-symbol":"park2","marker-color":"#A3DDAD"},"geometry":{"type":"Point","coordinates":[15.42320647452893,47.0921923541752],"bbox":[15.42320647452893,47.0921923541752,15.42320647452893,47.0921923541752]}},{"type":"Feature","properties":{"nummer":11944,"baumbezeichnung_botanisch":"Robinia pseudoacacia","baumbezeichnung_deutsch":"Scheinakazie","baumtyp":"Laub","bemerkung":null,"pflanzjahr":null,"entnahmejahr":null,"marker-size":"small","marker-symbol":"park2","marker-color":"#A3DDAD"},"geometry":{"type":"Point","coordinates":[15.423175967312,47.09220796028016],"bbox":[15.423175967312,47.09220796028016,15.423175967312,47.09220796028016]}},{"type":"Feature","properties":{"nummer":21844,"baumbezeichnung_botanisch":"Fraxinus ornus","baumbezeichnung_deutsch":"Blumenesche","baumtyp":"Laub","bemerkung":null,"pflanzjahr":"2004","entnahmejahr":null,"marker-size":"small","marker-symbol":"park2","marker-color":"#A3DDAD"},"geometry":{"type":"Point","coordinates":[15.42329373162171,47.09212532589599],"bbox":[15.42329373162171,47.09212532589599,15.42329373162171,47.09212532589599]}},{"type":"Feature","properties":{"nummer":31654,"baumbezeichnung_botanisch":"Fraxinus ornus","baumbezeichnung_deutsch":"Blumenesche","baumtyp":"Laub","bemerkung":null,"pflanzjahr":"2004","entnahmejahr":null,"marker-size":"small","marker-symbol":"park2","marker-color":"#A3DDAD"},"geometry":{"type":"Point","coordinates":[15.42332489721424,47.092105562992],"bbox":[15.42332489721424,47.092105562992,15.42332489721424,47.092105562992]}},{"type":"Feature","properties":{"nummer":19566,"baumbezeichnung_botanisch":"Fraxinus ornus","baumbezeichnung_deutsch":"Blumenesche","baumtyp":"Laub","bemerkung":null,"pflanzjahr":"2004","entnahmejahr":null,"marker-size":"small","marker-symbol":"park2","marker-color":"#A3DDAD"},"geometry":{"type":"Point","coordinates":[15.42334239172059,47.09208639632965],"bbox":[15.42334239172059,47.09208639632965,15.42334239172059,47.09208639632965]}}]}