{"type":"FeatureCollection","features":[{"type":"Feature","properties":{"nummer":19715,"baumbezeichnung_botanisch":"Populus nigra 'Italica'","baumbezeichnung_deutsch":"Säulenpappel","baumtyp":"Laub","bemerkung":null,"pflanzjahr":null,"entnahmejahr":null,"marker-size":"small","marker-symbol":"park2","marker-color":"#A3DDAD"},"geometry":{"type":"Point","coordinates":[15.42304922567246,47.0503513747251],"bbox":[15.42304922567246,47.0503513747251,15.42304922567246,47.0503513747251]}},{"type":"Feature","properties":{"nummer":16898,"baumbezeichnung_botanisch":"Populus nigra 'Italica'","baumbezeichnung_deutsch":"Säulenpappel","baumtyp":"Laub","bemerkung":null,"pflanzjahr":null,"entnahmejahr":null,"marker-size":"small","marker-symbol":"park2","marker-color":"#A3DDAD"},"geometry":{"type":"Point","coordinates":[15.42288766280661,47.05023822294882],"bbox":[15.42288766280661,47.05023822294882,15.42288766280661,47.05023822294882]}},{"type":"Feature","properties":{"nummer":11303,"baumbezeichnung_botanisch":"Tilia tomentosa","baumbezeichnung_deutsch":"Silberlinde","baumtyp":"Laub","bemerkung":null,"pflanzjahr":null,"entnahmejahr":null,"marker-size":"small","marker-symbol":"park2","marker-color":"#A3DDAD"},"geometry":{"type":"Point","coordinates":[15.42279309664358,47.05029799692704],"bbox":[15.42279309664358,47.05029799692704,15.42279309664358,47.05029799692704]}},{"type":"Feature","properties":{"nummer":16110,"baumbezeichnung_botanisch":"Populus nigra 'Italica'","baumbezeichnung_deutsch":"Säulenpappel","baumtyp":"Laub","bemerkung":null,"pflanzjahr":null,"entnahmejahr":null,"marker-size":"small","marker-symbol":"park2","marker-color":"#A3DDAD"},"geometry":{"type":"Point","coordinates":[15.4226260475023,47.05017630962149],"bbox":[15.4226260475023,47.05017630962149,15.4226260475023,47.05017630962149]}},{"type":"Feature","properties":{"nummer":19713,"baumbezeichnung_botanisch":"Platanus x acerifolia","baumbezeichnung_deutsch":"Platane","baumtyp":"Laub","bemerkung":null,"pflanzjahr":null,"entnahmejahr":null,"marker-size":"small","marker-symbol":"park2","marker-color":"#A3DDAD"},"geometry":{"type":"Point","coordinates":[15.42208732217168,47.04996737153071],"bbox":[15.42208732217168,47.04996737153071,15.42208732217168,47.04996737153071]}},{"type":"Feature","properties":{"nummer":19719,"baumbezeichnung_botanisch":"Tilia platyphyllos","baumbezeichnung_deutsch":"Sommerlinde","baumtyp":"Laub","bemerkung":null,"pflanzjahr":"2008","entnahmejahr":null,"marker-size":"small","marker-symbol":"park2","marker-color":"#A3DDAD"},"geometry":{"type":"Point","coordinates":[15.42294565860034,47.05041679525784],"bbox":[15.42294565860034,47.05041679525784,15.42294565860034,47.05041679525784]}},{"type":"Feature","properties":{"nummer":3857,"baumbezeichnung_botanisch":"Populus nigra 'Italica'","baumbezeichnung_deutsch":"Säulenpappel","baumtyp":"Laub","bemerkung":null,"pflanzjahr":"1999","entnahmejahr":null,"marker-size":"small","marker-symbol":"park2","marker-color":"#A3DDAD"},"geometry":{"type":"Point","coordinates":[15.4227137379319,47.05024019990256],"bbox":[15.4227137379319,47.05024019990256,15.4227137379319,47.05024019990256]}},{"type":"Feature","properties":{"nummer":17054,"baumbezeichnung_botanisch":"Populus nigra 'Italica'","baumbezeichnung_deutsch":"Säulenpappel","baumtyp":"Laub","bemerkung":null,"pflanzjahr":"2012","entnahmejahr":null,"marker-size":"small","marker-symbol":"park2","marker-color":"#A3DDAD"},"geometry":{"type":"Point","coordinates":[15.42265031089535,47.05007408467046],"bbox":[15.42265031089535,47.05007408467046,15.42265031089535,47.05007408467046]}},{"type":"Feature","properties":{"nummer":8369,"baumbezeichnung_botanisch":"Populus nigra 'Italica'","baumbezeichnung_deutsch":"Säulenpappel","baumtyp":"Laub","bemerkung":null,"pflanzjahr":"2012","entnahmejahr":null,"marker-size":"small","marker-symbol":"park2","marker-color":"#A3DDAD"},"geometry":{"type":"Point","coordinates":[15.42258126070058,47.05002611150737],"bbox":[15.42258126070058,47.05002611150737,15.42258126070058,47.05002611150737]}},{"type":"Feature","properties":{"nummer":12884,"baumbezeichnung_botanisch":"Populus nigra 'Italica'","baumbezeichnung_deutsch":"Säulenpappel","baumtyp":"Laub","bemerkung":null,"pflanzjahr":"2012","entnahmejahr":null,"marker-size":"small","marker-symbol":"park2","marker-color":"#A3DDAD"},"geometry":{"type":"Point","coordinates":[15.42249683067491,47.0500903647247],"bbox":[15.42249683067491,47.0500903647247,15.42249683067491,47.0500903647247]}},{"type":"Feature","properties":{"nummer":5594,"baumbezeichnung_botanisch":"Populus nigra 'Italica'","baumbezeichnung_deutsch":"Säulenpappel","baumtyp":"Laub","bemerkung":null,"pflanzjahr":"2011","entnahmejahr":null,"marker-size":"small","marker-symbol":"park2","marker-color":"#A3DDAD"},"geometry":{"type":"Point","coordinates":[15.42296653937012,47.0502942079873],"bbox":[15.42296653937012,47.0502942079873,15.42296653937012,47.0502942079873]}}]}