{
  "type": "FeatureCollection",
  "features": [
    {
      "type": "Feature",
      "properties": {
        "NUMMER": 18226,
        "BAUMBEZEICHNUNG_BOTANISCH": "Populus nigra 'Italica'",
        "BAUMBEZEICHNUNG_DEUTSCH": "Säulenpappel",
        "BAUMTYP": "Laub",
        "BEMERKUNG": null,
        "PFLANZJAHR": null,
        "ENTNAHMEJAHR": null,
        "BAUMPATENSCHAFT": null,
        "ALTERSKLASSIZIERUNG": "mittel",
        "OBJECTID": 446
      },
      "geometry": {
        "type": "Point",
        "coordinates": [
          15.407605506406664,
          47.07495829990396
        ]
      }
    },
    {
      "type": "Feature",
      "properties": {
        "NUMMER": 14202,
        "BAUMBEZEICHNUNG_BOTANISCH": "Aesculus hippocastanum",
        "BAUMBEZEICHNUNG_DEUTSCH": "Gemeine Roßkastanie",
        "BAUMTYP": "Laub",
        "BEMERKUNG": null,
        "PFLANZJAHR": null,
        "ENTNAHMEJAHR": null,
        "BAUMPATENSCHAFT": null,
        "ALTERSKLASSIZIERUNG": "mittel",
        "OBJECTID": 1205
      },
      "geometry": {
        "type": "Point",
        "coordinates": [
          15.403548558260049,
          47.077126694432785
        ]
      }
    },
    {
      "type": "Feature",
      "properties": {
        "NUMMER": 18218,
        "BAUMBEZEICHNUNG_BOTANISCH": "Platanus x acerifolia",
        "BAUMBEZEICHNUNG_DEUTSCH": "Platane",
        "BAUMTYP": "Laub",
        "BEMERKUNG": null,
        "PFLANZJAHR": null,
        "ENTNAHMEJAHR": null,
        "BAUMPATENSCHAFT": null,
        "ALTERSKLASSIZIERUNG": "mittel",
        "OBJECTID": 1414
      },
      "geometry": {
        "type": "Point",
        "coordinates": [
          15.40734173109386,
          47.07590488486971
        ]
      }
    }
  ]
}