{
  "type": "FeatureCollection",
  "features": [
    {
      "type": "Feature",
      "properties": {
        "nummer": 18226,
        "objectid": 446,
        "baumbezeichnung_deutsch": "Säulenpappel",
        "baumbezeichnung_botanisch": "Populus nigra 'Italica'",
        "baumtyp": "Laub",
        "bemerkung": null,
        "pflanzjahr": null,
        "entnahmejahr": null,
        "baumpatenschaft": null,
        "altersklassifizierung": "mittel"
      },
      "geometry": {
        "type": "Point",
        "coordinates": [
          15.407605506406664,
          47.07495829990396
        ]
      }
    },
    {
      "type": "Feature",
      "properties": {
        "nummer": 14202,
        "objectid": 1205,
        "baumbezeichnung_deutsch": "Gemeine Roßkastanie",
        "baumbezeichnung_botanisch": "Aesculus hippocastanum",
        "baumtyp": "Laub",
        "bemerkung": null,
        "pflanzjahr": null,
        "entnahmejahr": null,
        "baumpatenschaft": null,
        "altersklassifizierung": "mittel"
      },
      "geometry": {
        "type": "Point",
        "coordinates": [
          15.403548558260049,
          47.077126694432785
        ]
      }
    },
    {
      "type": "Feature",
      "properties": {
        "nummer": 18218,
        "objectid": 1414,
        "baumbezeichnung_deutsch": "Platane",
        "baumbezeichnung_botanisch": "Platanus x acerifolia",
        "baumtyp": "Laub",
        "bemerkung": null,
        "pflanzjahr": null,
        "entnahmejahr": null,
        "baumpatenschaft": null,
        "altersklassifizierung": "mittel"
      },
      "geometry": {
        "type": "Point",
        "coordinates": [
          15.40734173109386,
          47.07590488486971
        ]
      }
    }
  ]
}