{"type":"FeatureCollection","features":[{"type":"Feature","properties":{"nummer":17611,"baumbezeichnung_botanisch":"Acer negundo","baumbezeichnung_deutsch":"Eschenahorn","baumtyp":"Laub","bemerkung":null,"pflanzjahr":null,"entnahmejahr":null,"marker-size":"small","marker-symbol":"park2","marker-color":"#A3DDAD"},"geometry":{"type":"Point","coordinates":[15.3983992783652,47.07044989648087],"bbox":[15.3983992783652,47.07044989648087,15.3983992783652,47.07044989648087]}},{"type":"Feature","properties":{"nummer":17612,"baumbezeichnung_botanisch":"Acer pseudoplatanus","baumbezeichnung_deutsch":"Bergahorn","baumtyp":"Laub","bemerkung":null,"pflanzjahr":null,"entnahmejahr":null,"marker-size":"small","marker-symbol":"park2","marker-color":"#A3DDAD"},"geometry":{"type":"Point","coordinates":[15.39829364290757,47.07048486789562],"bbox":[15.39829364290757,47.07048486789562,15.39829364290757,47.07048486789562]}},{"type":"Feature","properties":{"nummer":22614,"baumbezeichnung_botanisch":"Acer pseudoplatanus","baumbezeichnung_deutsch":"Bergahorn","baumtyp":"Laub","bemerkung":null,"pflanzjahr":null,"entnahmejahr":null,"marker-size":"small","marker-symbol":"park2","marker-color":"#A3DDAD"},"geometry":{"type":"Point","coordinates":[15.39818852142102,47.07051905185379],"bbox":[15.39818852142102,47.07051905185379,15.39818852142102,47.07051905185379]}},{"type":"Feature","properties":{"nummer":15234,"baumbezeichnung_botanisch":"Acer negundo","baumbezeichnung_deutsch":"Eschenahorn","baumtyp":"Laub","bemerkung":null,"pflanzjahr":null,"entnahmejahr":null,"marker-size":"small","marker-symbol":"park2","marker-color":"#A3DDAD"},"geometry":{"type":"Point","coordinates":[15.39798395543661,47.07058574792415],"bbox":[15.39798395543661,47.07058574792415,15.39798395543661,47.07058574792415]}},{"type":"Feature","properties":{"nummer":25428,"baumbezeichnung_botanisch":"Acer negundo","baumbezeichnung_deutsch":"Eschenahorn","baumtyp":"Laub","bemerkung":null,"pflanzjahr":null,"entnahmejahr":null,"marker-size":"small","marker-symbol":"park2","marker-color":"#A3DDAD"},"geometry":{"type":"Point","coordinates":[15.39778103324922,47.07065177347063],"bbox":[15.39778103324922,47.07065177347063,15.39778103324922,47.07065177347063]}},{"type":"Feature","properties":{"nummer":17613,"baumbezeichnung_botanisch":"Acer pseudoplatanus","baumbezeichnung_deutsch":"Bergahorn","baumtyp":"Laub","bemerkung":null,"pflanzjahr":null,"entnahmejahr":null,"marker-size":"small","marker-symbol":"park2","marker-color":"#A3DDAD"},"geometry":{"type":"Point","coordinates":[15.39741946218063,47.07077040591845],"bbox":[15.39741946218063,47.07077040591845,15.39741946218063,47.07077040591845]}},{"type":"Feature","properties":{"nummer":17614,"baumbezeichnung_botanisch":"Acer platanoides","baumbezeichnung_deutsch":"Spitzahorn","baumtyp":"Laub","bemerkung":null,"pflanzjahr":"2011","entnahmejahr":null,"marker-size":"small","marker-symbol":"park2","marker-color":"#A3DDAD"},"geometry":{"type":"Point","coordinates":[15.39767890155373,47.07068660212104],"bbox":[15.39767890155373,47.07068660212104,15.39767890155373,47.07068660212104]}},{"type":"Feature","properties":{"nummer":7751,"baumbezeichnung_botanisch":"Acer platanoides","baumbezeichnung_deutsch":"Spitzahorn","baumtyp":"Laub","bemerkung":null,"pflanzjahr":"2011","entnahmejahr":null,"marker-size":"small","marker-symbol":"park2","marker-color":"#A3DDAD"},"geometry":{"type":"Point","coordinates":[15.39788200037018,47.07061877918288],"bbox":[15.39788200037018,47.07061877918288,15.39788200037018,47.07061877918288]}},{"type":"Feature","properties":{"nummer":12581,"baumbezeichnung_botanisch":"Acer platanoides","baumbezeichnung_deutsch":"Spitzahorn","baumtyp":"Laub","bemerkung":null,"pflanzjahr":"2011","entnahmejahr":null,"marker-size":"small","marker-symbol":"park2","marker-color":"#A3DDAD"},"geometry":{"type":"Point","coordinates":[15.39808231927104,47.07055328982892],"bbox":[15.39808231927104,47.07055328982892,15.39808231927104,47.07055328982892]}}]}