{"type":"FeatureCollection","features":[{"type":"Feature","properties":{"nummer":2566,"baumbezeichnung_botanisch":"Cercis canadensis","baumbezeichnung_deutsch":"Kanadischer Judasbaum","baumtyp":"Laub","bemerkung":null,"pflanzjahr":"2005","entnahmejahr":null,"marker-size":"small","marker-symbol":"park2","marker-color":"#A3DDAD"},"geometry":{"type":"Point","coordinates":[15.39849210076909,47.06050652043391],"bbox":[15.39849210076909,47.06050652043391,15.39849210076909,47.06050652043391]}},{"type":"Feature","properties":{"nummer":20778,"baumbezeichnung_botanisch":"Aesculus hippocastanum","baumbezeichnung_deutsch":"Gemeine Roßkastanie","baumtyp":"Laub","bemerkung":null,"pflanzjahr":null,"entnahmejahr":null,"marker-size":"small","marker-symbol":"park2","marker-color":"#A3DDAD"},"geometry":{"type":"Point","coordinates":[15.39758271687355,47.06054823801725],"bbox":[15.39758271687355,47.06054823801725,15.39758271687355,47.06054823801725]}},{"type":"Feature","properties":{"nummer":26154,"baumbezeichnung_botanisch":"Aesculus hippocastanum","baumbezeichnung_deutsch":"Gemeine Roßkastanie","baumtyp":"Laub","bemerkung":null,"pflanzjahr":null,"entnahmejahr":null,"marker-size":"small","marker-symbol":"park2","marker-color":"#A3DDAD"},"geometry":{"type":"Point","coordinates":[15.39773060542235,47.06054070676704],"bbox":[15.39773060542235,47.06054070676704,15.39773060542235,47.06054070676704]}},{"type":"Feature","properties":{"nummer":6316,"baumbezeichnung_botanisch":"Aesculus hippocastanum","baumbezeichnung_deutsch":"Gemeine Roßkastanie","baumtyp":"Laub","bemerkung":null,"pflanzjahr":null,"entnahmejahr":null,"marker-size":"small","marker-symbol":"park2","marker-color":"#A3DDAD"},"geometry":{"type":"Point","coordinates":[15.39784834237747,47.0605358786745],"bbox":[15.39784834237747,47.0605358786745,15.39784834237747,47.0605358786745]}},{"type":"Feature","properties":{"nummer":17816,"baumbezeichnung_botanisch":"Aesculus hippocastanum","baumbezeichnung_deutsch":"Gemeine Roßkastanie","baumtyp":"Laub","bemerkung":null,"pflanzjahr":null,"entnahmejahr":null,"marker-size":"small","marker-symbol":"park2","marker-color":"#A3DDAD"},"geometry":{"type":"Point","coordinates":[15.3979756200826,47.06052894281179],"bbox":[15.3979756200826,47.06052894281179,15.3979756200826,47.06052894281179]}},{"type":"Feature","properties":{"nummer":9445,"baumbezeichnung_botanisch":"Aesculus hippocastanum","baumbezeichnung_deutsch":"Gemeine Roßkastanie","baumtyp":"Laub","bemerkung":null,"pflanzjahr":null,"entnahmejahr":null,"marker-size":"small","marker-symbol":"park2","marker-color":"#A3DDAD"},"geometry":{"type":"Point","coordinates":[15.39810758866108,47.06052323258786],"bbox":[15.39810758866108,47.06052323258786,15.39810758866108,47.06052323258786]}},{"type":"Feature","properties":{"nummer":7853,"baumbezeichnung_botanisch":"Aesculus hippocastanum","baumbezeichnung_deutsch":"Gemeine Roßkastanie","baumtyp":"Laub","bemerkung":null,"pflanzjahr":null,"entnahmejahr":null,"marker-size":"small","marker-symbol":"park2","marker-color":"#A3DDAD"},"geometry":{"type":"Point","coordinates":[15.3982313254356,47.06051779660516],"bbox":[15.3982313254356,47.06051779660516,15.3982313254356,47.06051779660516]}},{"type":"Feature","properties":{"nummer":6716,"baumbezeichnung_botanisch":"Aesculus hippocastanum","baumbezeichnung_deutsch":"Gemeine Roßkastanie","baumtyp":"Laub","bemerkung":null,"pflanzjahr":null,"entnahmejahr":null,"marker-size":"small","marker-symbol":"park2","marker-color":"#A3DDAD"},"geometry":{"type":"Point","coordinates":[15.3983610761082,47.06051095252943],"bbox":[15.3983610761082,47.06051095252943,15.3983610761082,47.06051095252943]}}]}