{"type":"FeatureCollection","features":[{"type":"Feature","properties":{"nummer":27717,"baumbezeichnung_botanisch":"Fraxinus excelsior","baumbezeichnung_deutsch":"Esche","baumtyp":"Laub","bemerkung":null,"pflanzjahr":null,"entnahmejahr":null,"marker-size":"small","marker-symbol":"park2","marker-color":"#A3DDAD"},"geometry":{"type":"Point","coordinates":[15.39840941099473,47.02353403939392],"bbox":[15.39840941099473,47.02353403939392,15.39840941099473,47.02353403939392]}},{"type":"Feature","properties":{"nummer":28984,"baumbezeichnung_botanisch":"Fraxinus excelsior","baumbezeichnung_deutsch":"Esche","baumtyp":"Laub","bemerkung":null,"pflanzjahr":null,"entnahmejahr":null,"marker-size":"small","marker-symbol":"park2","marker-color":"#A3DDAD"},"geometry":{"type":"Point","coordinates":[15.3984852056974,47.02351309597224],"bbox":[15.3984852056974,47.02351309597224,15.3984852056974,47.02351309597224]}},{"type":"Feature","properties":{"nummer":28983,"baumbezeichnung_botanisch":"Fraxinus excelsior","baumbezeichnung_deutsch":"Esche","baumtyp":"Laub","bemerkung":null,"pflanzjahr":null,"entnahmejahr":null,"marker-size":"small","marker-symbol":"park2","marker-color":"#A3DDAD"},"geometry":{"type":"Point","coordinates":[15.39855752365099,47.02349441060438],"bbox":[15.39855752365099,47.02349441060438,15.39855752365099,47.02349441060438]}}]}