{"type":"FeatureCollection","features":[{"type":"Feature","properties":{"nummer":26267,"baumbezeichnung_botanisch":"Platanus x acerifolia","baumbezeichnung_deutsch":"Platane","baumtyp":"Laub","bemerkung":null,"pflanzjahr":"1987","entnahmejahr":null,"marker-size":"small","marker-symbol":"park2","marker-color":"#A3DDAD"},"geometry":{"type":"Point","coordinates":[15.4013181064014,47.07202465039846],"bbox":[15.4013181064014,47.07202465039846,15.4013181064014,47.07202465039846]}},{"type":"Feature","properties":{"nummer":21456,"baumbezeichnung_botanisch":"Platanus x acerifolia","baumbezeichnung_deutsch":"Platane","baumtyp":"Laub","bemerkung":null,"pflanzjahr":"1987","entnahmejahr":null,"marker-size":"small","marker-symbol":"park2","marker-color":"#A3DDAD"},"geometry":{"type":"Point","coordinates":[15.40133197563137,47.07212747862278],"bbox":[15.40133197563137,47.07212747862278,15.40133197563137,47.07212747862278]}},{"type":"Feature","properties":{"nummer":6533,"baumbezeichnung_botanisch":"Platanus x acerifolia","baumbezeichnung_deutsch":"Platane","baumtyp":"Laub","bemerkung":null,"pflanzjahr":"1987","entnahmejahr":null,"marker-size":"small","marker-symbol":"park2","marker-color":"#A3DDAD"},"geometry":{"type":"Point","coordinates":[15.40133980530281,47.07223160680753],"bbox":[15.40133980530281,47.07223160680753,15.40133980530281,47.07223160680753]}},{"type":"Feature","properties":{"nummer":22950,"baumbezeichnung_botanisch":"Platanus x acerifolia","baumbezeichnung_deutsch":"Platane","baumtyp":"Laub","bemerkung":null,"pflanzjahr":"1987","entnahmejahr":null,"marker-size":"small","marker-symbol":"park2","marker-color":"#A3DDAD"},"geometry":{"type":"Point","coordinates":[15.40135326563678,47.0723337300702],"bbox":[15.40135326563678,47.0723337300702,15.40135326563678,47.0723337300702]}},{"type":"Feature","properties":{"nummer":26070,"baumbezeichnung_botanisch":"Platanus x acerifolia","baumbezeichnung_deutsch":"Platane","baumtyp":"Laub","bemerkung":null,"pflanzjahr":"1987","entnahmejahr":null,"marker-size":"small","marker-symbol":"park2","marker-color":"#A3DDAD"},"geometry":{"type":"Point","coordinates":[15.40136355808518,47.07243932656326],"bbox":[15.40136355808518,47.07243932656326,15.40136355808518,47.07243932656326]}},{"type":"Feature","properties":{"nummer":23864,"baumbezeichnung_botanisch":"Platanus x acerifolia","baumbezeichnung_deutsch":"Platane","baumtyp":"Laub","bemerkung":null,"pflanzjahr":"1987","entnahmejahr":null,"marker-size":"small","marker-symbol":"park2","marker-color":"#A3DDAD"},"geometry":{"type":"Point","coordinates":[15.4013852548221,47.07264341349549],"bbox":[15.4013852548221,47.07264341349549,15.4013852548221,47.07264341349549]}},{"type":"Feature","properties":{"nummer":48546,"baumbezeichnung_botanisch":"Liriodendron tulipifera","baumbezeichnung_deutsch":"Tulpenbaum","baumtyp":"Laub","bemerkung":null,"pflanzjahr":"2012","entnahmejahr":null,"marker-size":"small","marker-symbol":"park2","marker-color":"#A3DDAD"},"geometry":{"type":"Point","coordinates":[15.40140160312633,47.07278398376849],"bbox":[15.40140160312633,47.07278398376849,15.40140160312633,47.07278398376849]}},{"type":"Feature","properties":{"nummer":48547,"baumbezeichnung_botanisch":"Liriodendron tulipifera","baumbezeichnung_deutsch":"Tulpenbaum","baumtyp":"Laub","bemerkung":null,"pflanzjahr":"2012","entnahmejahr":null,"marker-size":"small","marker-symbol":"park2","marker-color":"#A3DDAD"},"geometry":{"type":"Point","coordinates":[15.40140910321421,47.07285306345519],"bbox":[15.40140910321421,47.07285306345519,15.40140910321421,47.07285306345519]}}]}