{"type":"FeatureCollection","features":[{"type":"Feature","properties":{"nummer":6314,"baumbezeichnung_botanisch":"Aesculus hippocastanum","baumbezeichnung_deutsch":"Gemeine Roßkastanie","baumtyp":"Laub","bemerkung":null,"pflanzjahr":"2002","entnahmejahr":null,"marker-size":"small","marker-symbol":"park2","marker-color":"#A3DDAD"},"geometry":{"type":"Point","coordinates":[15.40099397242213,47.04061085287842],"bbox":[15.40099397242213,47.04061085287842,15.40099397242213,47.04061085287842]}},{"type":"Feature","properties":{"nummer":26331,"baumbezeichnung_botanisch":"Aesculus hippocastanum","baumbezeichnung_deutsch":"Gemeine Roßkastanie","baumtyp":"Laub","bemerkung":null,"pflanzjahr":"1996","entnahmejahr":null,"marker-size":"small","marker-symbol":"park2","marker-color":"#A3DDAD"},"geometry":{"type":"Point","coordinates":[15.40098375519884,47.0405810269903],"bbox":[15.40098375519884,47.0405810269903,15.40098375519884,47.0405810269903]}},{"type":"Feature","properties":{"nummer":5305,"baumbezeichnung_botanisch":"Aesculus hippocastanum","baumbezeichnung_deutsch":"Gemeine Roßkastanie","baumtyp":"Laub","bemerkung":null,"pflanzjahr":"1996","entnahmejahr":null,"marker-size":"small","marker-symbol":"park2","marker-color":"#A3DDAD"},"geometry":{"type":"Point","coordinates":[15.40094641914668,47.04060750421493],"bbox":[15.40094641914668,47.04060750421493,15.40094641914668,47.04060750421493]}},{"type":"Feature","properties":{"nummer":12369,"baumbezeichnung_botanisch":"Aesculus hippocastanum","baumbezeichnung_deutsch":"Gemeine Roßkastanie","baumtyp":"Laub","bemerkung":null,"pflanzjahr":null,"entnahmejahr":null,"marker-size":"small","marker-symbol":"park2","marker-color":"#A3DDAD"},"geometry":{"type":"Point","coordinates":[15.40096118112277,47.04055406048623],"bbox":[15.40096118112277,47.04055406048623,15.40096118112277,47.04055406048623]}},{"type":"Feature","properties":{"nummer":17210,"baumbezeichnung_botanisch":"Aesculus hippocastanum","baumbezeichnung_deutsch":"Gemeine Roßkastanie","baumtyp":"Laub","bemerkung":null,"pflanzjahr":null,"entnahmejahr":null,"marker-size":"small","marker-symbol":"park2","marker-color":"#A3DDAD"},"geometry":{"type":"Point","coordinates":[15.40092591216686,47.04055245825043],"bbox":[15.40092591216686,47.04055245825043,15.40092591216686,47.04055245825043]}},{"type":"Feature","properties":{"nummer":17281,"baumbezeichnung_botanisch":"Aesculus hippocastanum","baumbezeichnung_deutsch":"Gemeine Roßkastanie","baumtyp":"Laub","bemerkung":null,"pflanzjahr":null,"entnahmejahr":null,"marker-size":"small","marker-symbol":"park2","marker-color":"#A3DDAD"},"geometry":{"type":"Point","coordinates":[15.40091886401413,47.04057929617002],"bbox":[15.40091886401413,47.04057929617002,15.40091886401413,47.04057929617002]}}]}