{
  "type": "FeatureCollection",
  "features": [
    {
      "type": "Feature",
      "properties": {
        "NUMMER": 29365,
        "BAUMBEZEICHNUNG_BOTANISCH": "Quercus robur 'Fastigiata'",
        "BAUMBEZEICHNUNG_DEUTSCH": "Säulenstieleiche",
        "BAUMTYP": "Laub",
        "BEMERKUNG": null,
        "PFLANZJAHR": "2009",
        "ENTNAHMEJAHR": null,
        "BAUMPATENSCHAFT": null,
        "ALTERSKLASSIZIERUNG": "jung",
        "OBJECTID": 311
      },
      "geometry": {
        "type": "Point",
        "coordinates": [
          15.4246489875299,
          47.055277052801564
        ]
      }
    },
    {
      "type": "Feature",
      "properties": {
        "NUMMER": 29367,
        "BAUMBEZEICHNUNG_BOTANISCH": "Ulmus x hollandica 'Wredei'",
        "BAUMBEZEICHNUNG_DEUTSCH": "Goldulme",
        "BAUMTYP": "Laub",
        "BEMERKUNG": null,
        "PFLANZJAHR": "2009",
        "ENTNAHMEJAHR": null,
        "BAUMPATENSCHAFT": null,
        "ALTERSKLASSIZIERUNG": "jung",
        "OBJECTID": 313
      },
      "geometry": {
        "type": "Point",
        "coordinates": [
          15.424598759853268,
          47.05516527510969
        ]
      }
    },
    {
      "type": "Feature",
      "properties": {
        "NUMMER": 13681,
        "BAUMBEZEICHNUNG_BOTANISCH": "Juglans regia",
        "BAUMBEZEICHNUNG_DEUTSCH": "Walnuß",
        "BAUMTYP": "Laub",
        "BEMERKUNG": null,
        "PFLANZJAHR": null,
        "ENTNAHMEJAHR": null,
        "BAUMPATENSCHAFT": null,
        "ALTERSKLASSIZIERUNG": "jung",
        "OBJECTID": 914
      },
      "geometry": {
        "type": "Point",
        "coordinates": [
          15.420201272922714,
          47.05794385717722
        ]
      }
    },
    {
      "type": "Feature",
      "properties": {
        "NUMMER": 13713,
        "BAUMBEZEICHNUNG_BOTANISCH": "Acer pseudoplatanus",
        "BAUMBEZEICHNUNG_DEUTSCH": "Bergahorn",
        "BAUMTYP": "Laub",
        "BEMERKUNG": null,
        "PFLANZJAHR": null,
        "ENTNAHMEJAHR": null,
        "BAUMPATENSCHAFT": null,
        "ALTERSKLASSIZIERUNG": "mittel",
        "OBJECTID": 916
      },
      "geometry": {
        "type": "Point",
        "coordinates": [
          15.422952503619499,
          47.0561411864357
        ]
      }
    },
    {
      "type": "Feature",
      "properties": {
        "NUMMER": 13711,
        "BAUMBEZEICHNUNG_BOTANISCH": "Acer pseudoplatanus",
        "BAUMBEZEICHNUNG_DEUTSCH": "Bergahorn",
        "BAUMTYP": "Laub",
        "BEMERKUNG": null,
        "PFLANZJAHR": null,
        "ENTNAHMEJAHR": null,
        "BAUMPATENSCHAFT": null,
        "ALTERSKLASSIZIERUNG": "mittel",
        "OBJECTID": 985
      },
      "geometry": {
        "type": "Point",
        "coordinates": [
          15.42281372195388,
          47.05618213170431
        ]
      }
    },
    {
      "type": "Feature",
      "properties": {
        "NUMMER": 13702,
        "BAUMBEZEICHNUNG_BOTANISCH": "Acer pseudoplatanus",
        "BAUMBEZEICHNUNG_DEUTSCH": "Bergahorn",
        "BAUMTYP": "Laub",
        "BEMERKUNG": null,
        "PFLANZJAHR": null,
        "ENTNAHMEJAHR": null,
        "BAUMPATENSCHAFT": null,
        "ALTERSKLASSIZIERUNG": "mittel",
        "OBJECTID": 997
      },
      "geometry": {
        "type": "Point",
        "coordinates": [
          15.421944231616475,
          47.05655994948854
        ]
      }
    }
  ]
}