{
  "type": "FeatureCollection",
  "features": [
    {
      "type": "Feature",
      "properties": {
        "nummer": 29365,
        "objectid": 311,
        "baumbezeichnung_deutsch": "Säulenstieleiche",
        "baumbezeichnung_botanisch": "Quercus robur 'Fastigiata'",
        "baumtyp": "Laub",
        "bemerkung": null,
        "pflanzjahr": "2009",
        "entnahmejahr": null,
        "baumpatenschaft": null,
        "altersklassifizierung": "jung"
      },
      "geometry": {
        "type": "Point",
        "coordinates": [
          15.4246489875299,
          47.055277052801564
        ]
      }
    },
    {
      "type": "Feature",
      "properties": {
        "nummer": 29367,
        "objectid": 313,
        "baumbezeichnung_deutsch": "Goldulme",
        "baumbezeichnung_botanisch": "Ulmus x hollandica 'Wredei'",
        "baumtyp": "Laub",
        "bemerkung": null,
        "pflanzjahr": "2009",
        "entnahmejahr": null,
        "baumpatenschaft": null,
        "altersklassifizierung": "jung"
      },
      "geometry": {
        "type": "Point",
        "coordinates": [
          15.424598759853268,
          47.05516527510969
        ]
      }
    },
    {
      "type": "Feature",
      "properties": {
        "nummer": 13681,
        "objectid": 914,
        "baumbezeichnung_deutsch": "Walnuß",
        "baumbezeichnung_botanisch": "Juglans regia",
        "baumtyp": "Laub",
        "bemerkung": null,
        "pflanzjahr": null,
        "entnahmejahr": null,
        "baumpatenschaft": null,
        "altersklassifizierung": "jung"
      },
      "geometry": {
        "type": "Point",
        "coordinates": [
          15.420201272922714,
          47.05794385717722
        ]
      }
    },
    {
      "type": "Feature",
      "properties": {
        "nummer": 13713,
        "objectid": 916,
        "baumbezeichnung_deutsch": "Bergahorn",
        "baumbezeichnung_botanisch": "Acer pseudoplatanus",
        "baumtyp": "Laub",
        "bemerkung": null,
        "pflanzjahr": null,
        "entnahmejahr": null,
        "baumpatenschaft": null,
        "altersklassifizierung": "mittel"
      },
      "geometry": {
        "type": "Point",
        "coordinates": [
          15.422952503619499,
          47.0561411864357
        ]
      }
    },
    {
      "type": "Feature",
      "properties": {
        "nummer": 13711,
        "objectid": 985,
        "baumbezeichnung_deutsch": "Bergahorn",
        "baumbezeichnung_botanisch": "Acer pseudoplatanus",
        "baumtyp": "Laub",
        "bemerkung": null,
        "pflanzjahr": null,
        "entnahmejahr": null,
        "baumpatenschaft": null,
        "altersklassifizierung": "mittel"
      },
      "geometry": {
        "type": "Point",
        "coordinates": [
          15.42281372195388,
          47.05618213170431
        ]
      }
    },
    {
      "type": "Feature",
      "properties": {
        "nummer": 13702,
        "objectid": 997,
        "baumbezeichnung_deutsch": "Bergahorn",
        "baumbezeichnung_botanisch": "Acer pseudoplatanus",
        "baumtyp": "Laub",
        "bemerkung": null,
        "pflanzjahr": null,
        "entnahmejahr": null,
        "baumpatenschaft": null,
        "altersklassifizierung": "mittel"
      },
      "geometry": {
        "type": "Point",
        "coordinates": [
          15.421944231616475,
          47.05655994948854
        ]
      }
    }
  ]
}