{"type":"FeatureCollection","features":[{"type":"Feature","properties":{"nummer":26718,"baumbezeichnung_botanisch":"Sophora japonica","baumbezeichnung_deutsch":"Schnurbaum","baumtyp":"Laub","bemerkung":null,"pflanzjahr":null,"entnahmejahr":null,"marker-size":"small","marker-symbol":"park2","marker-color":"#A3DDAD"},"geometry":{"type":"Point","coordinates":[15.39707840825031,47.07948502396263],"bbox":[15.39707840825031,47.07948502396263,15.39707840825031,47.07948502396263]}},{"type":"Feature","properties":{"nummer":6265,"baumbezeichnung_botanisch":"Sophora japonica","baumbezeichnung_deutsch":"Schnurbaum","baumtyp":"Laub","bemerkung":null,"pflanzjahr":null,"entnahmejahr":null,"marker-size":"small","marker-symbol":"park2","marker-color":"#A3DDAD"},"geometry":{"type":"Point","coordinates":[15.39715448419042,47.07953717161303],"bbox":[15.39715448419042,47.07953717161303,15.39715448419042,47.07953717161303]}},{"type":"Feature","properties":{"nummer":28762,"baumbezeichnung_botanisch":"Sophora japonica","baumbezeichnung_deutsch":"Schnurbaum","baumtyp":"Laub","bemerkung":null,"pflanzjahr":null,"entnahmejahr":null,"marker-size":"small","marker-symbol":"park2","marker-color":"#A3DDAD"},"geometry":{"type":"Point","coordinates":[15.39725319295718,47.07956999442785],"bbox":[15.39725319295718,47.07956999442785,15.39725319295718,47.07956999442785]}},{"type":"Feature","properties":{"nummer":19639,"baumbezeichnung_botanisch":"Quercus robur","baumbezeichnung_deutsch":"Stieleiche","baumtyp":"Laub","bemerkung":null,"pflanzjahr":"1908","entnahmejahr":null,"marker-size":"small","marker-symbol":"park2","marker-color":"#A3DDAD"},"geometry":{"type":"Point","coordinates":[15.39597356659573,47.07994435104143],"bbox":[15.39597356659573,47.07994435104143,15.39597356659573,47.07994435104143]}},{"type":"Feature","properties":{"nummer":1600,"baumbezeichnung_botanisch":"Aesculus hippocastanum","baumbezeichnung_deutsch":"Gemeine Roßkastanie","baumtyp":"Laub","bemerkung":null,"pflanzjahr":null,"entnahmejahr":null,"marker-size":"small","marker-symbol":"park2","marker-color":"#A3DDAD"},"geometry":{"type":"Point","coordinates":[15.39607674420738,47.07998063868317],"bbox":[15.39607674420738,47.07998063868317,15.39607674420738,47.07998063868317]}},{"type":"Feature","properties":{"nummer":9200,"baumbezeichnung_botanisch":"Aesculus hippocastanum","baumbezeichnung_deutsch":"Gemeine Roßkastanie","baumtyp":"Laub","bemerkung":null,"pflanzjahr":null,"entnahmejahr":null,"marker-size":"small","marker-symbol":"park2","marker-color":"#A3DDAD"},"geometry":{"type":"Point","coordinates":[15.39615712183695,47.08003974851918],"bbox":[15.39615712183695,47.08003974851918,15.39615712183695,47.08003974851918]}},{"type":"Feature","properties":{"nummer":5470,"baumbezeichnung_botanisch":"Abies balsamea","baumbezeichnung_deutsch":"Balsamtanne","baumtyp":"Nadel","bemerkung":null,"pflanzjahr":null,"entnahmejahr":null,"marker-size":"small","marker-symbol":"park","marker-color":"#3BB451"},"geometry":{"type":"Point","coordinates":[15.39623854892509,47.08007214251283],"bbox":[15.39623854892509,47.08007214251283,15.39623854892509,47.08007214251283]}},{"type":"Feature","properties":{"nummer":6773,"baumbezeichnung_botanisch":"Abies balsamea","baumbezeichnung_deutsch":"Balsamtanne","baumtyp":"Nadel","bemerkung":null,"pflanzjahr":null,"entnahmejahr":null,"marker-size":"small","marker-symbol":"park","marker-color":"#3BB451"},"geometry":{"type":"Point","coordinates":[15.39627095936025,47.08012431914838],"bbox":[15.39627095936025,47.08012431914838,15.39627095936025,47.08012431914838]}},{"type":"Feature","properties":{"nummer":7744,"baumbezeichnung_botanisch":"Abies balsamea","baumbezeichnung_deutsch":"Balsamtanne","baumtyp":"Nadel","bemerkung":null,"pflanzjahr":null,"entnahmejahr":null,"marker-size":"small","marker-symbol":"park","marker-color":"#3BB451"},"geometry":{"type":"Point","coordinates":[15.39623228499271,47.08010335801903],"bbox":[15.39623228499271,47.08010335801903,15.39623228499271,47.08010335801903]}},{"type":"Feature","properties":{"nummer":8020,"baumbezeichnung_botanisch":"Aesculus hippocastanum","baumbezeichnung_deutsch":"Gemeine Roßkastanie","baumtyp":"Laub","bemerkung":null,"pflanzjahr":null,"entnahmejahr":null,"marker-size":"small","marker-symbol":"park2","marker-color":"#A3DDAD"},"geometry":{"type":"Point","coordinates":[15.39617453388036,47.08010936677716],"bbox":[15.39617453388036,47.08010936677716,15.39617453388036,47.08010936677716]}},{"type":"Feature","properties":{"nummer":27855,"baumbezeichnung_botanisch":"Aesculus hippocastanum","baumbezeichnung_deutsch":"Gemeine Roßkastanie","baumtyp":"Laub","bemerkung":null,"pflanzjahr":null,"entnahmejahr":null,"marker-size":"small","marker-symbol":"park2","marker-color":"#A3DDAD"},"geometry":{"type":"Point","coordinates":[15.39598106021223,47.08012242530182],"bbox":[15.39598106021223,47.08012242530182,15.39598106021223,47.08012242530182]}}]}