{"type":"FeatureCollection","features":[{"type":"Feature","properties":{"nummer":10598,"baumbezeichnung_botanisch":"Prunus serrulata 'Shirofugen'","baumbezeichnung_deutsch":"Japanische Blütenkirsche","baumtyp":"Laub","bemerkung":null,"pflanzjahr":"2004","entnahmejahr":null,"marker-size":"small","marker-symbol":"park2","marker-color":"#A3DDAD"},"geometry":{"type":"Point","coordinates":[15.39706124508533,47.06691922923881],"bbox":[15.39706124508533,47.06691922923881,15.39706124508533,47.06691922923881]}},{"type":"Feature","properties":{"nummer":9158,"baumbezeichnung_botanisch":"Prunus serrulata 'Shirofugen'","baumbezeichnung_deutsch":"Japanische Blütenkirsche","baumtyp":"Laub","bemerkung":null,"pflanzjahr":"2009","entnahmejahr":null,"marker-size":"small","marker-symbol":"park2","marker-color":"#A3DDAD"},"geometry":{"type":"Point","coordinates":[15.39675854685736,47.06695154864542],"bbox":[15.39675854685736,47.06695154864542,15.39675854685736,47.06695154864542]}},{"type":"Feature","properties":{"nummer":27395,"baumbezeichnung_botanisch":"Prunus serrulata 'Shirofugen'","baumbezeichnung_deutsch":"Japanische Blütenkirsche","baumtyp":"Laub","bemerkung":null,"pflanzjahr":"2005","entnahmejahr":null,"marker-size":"small","marker-symbol":"park2","marker-color":"#A3DDAD"},"geometry":{"type":"Point","coordinates":[15.39696188013435,47.06692958628111],"bbox":[15.39696188013435,47.06692958628111,15.39696188013435,47.06692958628111]}},{"type":"Feature","properties":{"nummer":1787,"baumbezeichnung_botanisch":"Acer negundo","baumbezeichnung_deutsch":"Eschenahorn","baumtyp":"Laub","bemerkung":null,"pflanzjahr":null,"entnahmejahr":null,"marker-size":"small","marker-symbol":"park2","marker-color":"#A3DDAD"},"geometry":{"type":"Point","coordinates":[15.39722522266065,47.06690061366948],"bbox":[15.39722522266065,47.06690061366948,15.39722522266065,47.06690061366948]}},{"type":"Feature","properties":{"nummer":17705,"baumbezeichnung_botanisch":"Acer negundo","baumbezeichnung_deutsch":"Eschenahorn","baumtyp":"Laub","bemerkung":null,"pflanzjahr":null,"entnahmejahr":null,"marker-size":"small","marker-symbol":"park2","marker-color":"#A3DDAD"},"geometry":{"type":"Point","coordinates":[15.39614130743331,47.0670203155463],"bbox":[15.39614130743331,47.0670203155463,15.39614130743331,47.0670203155463]}},{"type":"Feature","properties":{"nummer":21941,"baumbezeichnung_botanisch":"Acer negundo","baumbezeichnung_deutsch":"Eschenahorn","baumtyp":"Laub","bemerkung":null,"pflanzjahr":null,"entnahmejahr":null,"marker-size":"small","marker-symbol":"park2","marker-color":"#A3DDAD"},"geometry":{"type":"Point","coordinates":[15.39601498084072,47.06703440829666],"bbox":[15.39601498084072,47.06703440829666,15.39601498084072,47.06703440829666]}},{"type":"Feature","properties":{"nummer":1862,"baumbezeichnung_botanisch":"Prunus serrulata 'Shirofugen'","baumbezeichnung_deutsch":"Japanische Blütenkirsche","baumtyp":"Laub","bemerkung":null,"pflanzjahr":"2011","entnahmejahr":null,"marker-size":"small","marker-symbol":"park2","marker-color":"#A3DDAD"},"geometry":{"type":"Point","coordinates":[15.3968600521649,47.06694075957989],"bbox":[15.3968600521649,47.06694075957989,15.3968600521649,47.06694075957989]}},{"type":"Feature","properties":{"nummer":28870,"baumbezeichnung_botanisch":"Prunus serrulata 'Shirofugen'","baumbezeichnung_deutsch":"Japanische Blütenkirsche","baumtyp":"Laub","bemerkung":null,"pflanzjahr":"2011","entnahmejahr":null,"marker-size":"small","marker-symbol":"park2","marker-color":"#A3DDAD"},"geometry":{"type":"Point","coordinates":[15.39665468782375,47.06696367657203],"bbox":[15.39665468782375,47.06696367657203,15.39665468782375,47.06696367657203]}},{"type":"Feature","properties":{"nummer":20341,"baumbezeichnung_botanisch":"Prunus serrulata 'Shirofugen'","baumbezeichnung_deutsch":"Japanische Blütenkirsche","baumtyp":"Laub","bemerkung":null,"pflanzjahr":"2011","entnahmejahr":null,"marker-size":"small","marker-symbol":"park2","marker-color":"#A3DDAD"},"geometry":{"type":"Point","coordinates":[15.39654131960011,47.06697529461715],"bbox":[15.39654131960011,47.06697529461715,15.39654131960011,47.06697529461715]}}]}