{"type":"FeatureCollection","features":[{"type":"Feature","properties":{"nummer":6248,"baumbezeichnung_botanisch":"Tilia platyphyllos","baumbezeichnung_deutsch":"Sommerlinde","baumtyp":"Laub","bemerkung":null,"pflanzjahr":"2000","entnahmejahr":null,"marker-size":"small","marker-symbol":"park2","marker-color":"#A3DDAD"},"geometry":{"type":"Point","coordinates":[15.3972485891777,47.02529222267991],"bbox":[15.3972485891777,47.02529222267991,15.3972485891777,47.02529222267991]}},{"type":"Feature","properties":{"nummer":10391,"baumbezeichnung_botanisch":"Populus nigra 'Italica'","baumbezeichnung_deutsch":"Säulenpappel","baumtyp":"Laub","bemerkung":null,"pflanzjahr":"1989","entnahmejahr":null,"marker-size":"small","marker-symbol":"park2","marker-color":"#A3DDAD"},"geometry":{"type":"Point","coordinates":[15.39726788553452,47.02544750349336],"bbox":[15.39726788553452,47.02544750349336,15.39726788553452,47.02544750349336]}},{"type":"Feature","properties":{"nummer":909,"baumbezeichnung_botanisch":"Populus nigra 'Italica'","baumbezeichnung_deutsch":"Säulenpappel","baumtyp":"Laub","bemerkung":null,"pflanzjahr":"1989","entnahmejahr":null,"marker-size":"small","marker-symbol":"park2","marker-color":"#A3DDAD"},"geometry":{"type":"Point","coordinates":[15.39728342566804,47.02560702530624],"bbox":[15.39728342566804,47.02560702530624,15.39728342566804,47.02560702530624]}},{"type":"Feature","properties":{"nummer":5230,"baumbezeichnung_botanisch":"Tilia cordata","baumbezeichnung_deutsch":"Winterlinde","baumtyp":"Laub","bemerkung":null,"pflanzjahr":"1989","entnahmejahr":null,"marker-size":"small","marker-symbol":"park2","marker-color":"#A3DDAD"},"geometry":{"type":"Point","coordinates":[15.39728418771363,47.02576153796777],"bbox":[15.39728418771363,47.02576153796777,15.39728418771363,47.02576153796777]}},{"type":"Feature","properties":{"nummer":12097,"baumbezeichnung_botanisch":"Tilia cordata","baumbezeichnung_deutsch":"Winterlinde","baumtyp":"Laub","bemerkung":null,"pflanzjahr":"1989","entnahmejahr":null,"marker-size":"small","marker-symbol":"park2","marker-color":"#A3DDAD"},"geometry":{"type":"Point","coordinates":[15.3973093700039,47.02588889474755],"bbox":[15.3973093700039,47.02588889474755,15.3973093700039,47.02588889474755]}},{"type":"Feature","properties":{"nummer":18502,"baumbezeichnung_botanisch":"Tilia cordata","baumbezeichnung_deutsch":"Winterlinde","baumtyp":"Laub","bemerkung":null,"pflanzjahr":"1989","entnahmejahr":null,"marker-size":"small","marker-symbol":"park2","marker-color":"#A3DDAD"},"geometry":{"type":"Point","coordinates":[15.39732440832435,47.02605004055357],"bbox":[15.39732440832435,47.02605004055357,15.39732440832435,47.02605004055357]}}]}