{
  "type": "FeatureCollection",
  "features": [
    {
      "type": "Feature",
      "id": 1618,
      "properties": {
        "nummer": 30111,
        "objectid": 1618,
        "baumbezeichnung_deutsch": "Spitzahorn",
        "baumbezeichnung_botanisch": "Acer platanoides",
        "baumtyp": "Laub",
        "bemerkung": null,
        "pflanzjahr": "2011",
        "entnahmejahr": null,
        "baumpatenschaft": null,
        "altersklassifizierung": "jung"
      },
      "geometry": {
        "type": "Point",
        "coordinates": [
          15.38430565787112,
          47.059427189397674
        ]
      }
    },
    {
      "type": "Feature",
      "id": 1619,
      "properties": {
        "nummer": 30110,
        "objectid": 1619,
        "baumbezeichnung_deutsch": "Spitzahorn",
        "baumbezeichnung_botanisch": "Acer platanoides",
        "baumtyp": "Laub",
        "bemerkung": null,
        "pflanzjahr": "2011",
        "entnahmejahr": null,
        "baumpatenschaft": null,
        "altersklassifizierung": "jung"
      },
      "geometry": {
        "type": "Point",
        "coordinates": [
          15.384367172168002,
          47.05938877355195
        ]
      }
    },
    {
      "type": "Feature",
      "id": 1620,
      "properties": {
        "nummer": 30112,
        "objectid": 1620,
        "baumbezeichnung_deutsch": "Spitzahorn",
        "baumbezeichnung_botanisch": "Acer platanoides",
        "baumtyp": "Laub",
        "bemerkung": null,
        "pflanzjahr": "2011",
        "entnahmejahr": null,
        "baumpatenschaft": null,
        "altersklassifizierung": "jung"
      },
      "geometry": {
        "type": "Point",
        "coordinates": [
          15.38416542944604,
          47.05952249062839
        ]
      }
    },
    {
      "type": "Feature",
      "id": 1621,
      "properties": {
        "nummer": 30113,
        "objectid": 1621,
        "baumbezeichnung_deutsch": "Spitzahorn",
        "baumbezeichnung_botanisch": "Acer platanoides",
        "baumtyp": "Laub",
        "bemerkung": null,
        "pflanzjahr": "2011",
        "entnahmejahr": null,
        "baumpatenschaft": null,
        "altersklassifizierung": "jung"
      },
      "geometry": {
        "type": "Point",
        "coordinates": [
          15.384098301138678,
          47.05956318492272
        ]
      }
    }
  ]
}