{
  "type": "FeatureCollection",
  "features": [
    {
      "type": "Feature",
      "properties": {
        "nummer": 30111,
        "baumbezeichnung_botanisch": "Acer platanoides",
        "baumbezeichnung_deutsch": "Spitzahorn",
        "baumtyp": "Laub",
        "altersklassifizierung": "jung",
        "bemerkung": null,
        "pflanzjahr": "2011",
        "entnahmejahr": null,
        "baumpatenschaft": null,
        "objectid": 1618
      },
      "geometry": {
        "type": "Point",
        "coordinates": [
          15.38431123366428,
          47.05942711622198
        ],
        "bbox": [
          15.38431123366428,
          47.05942711622198,
          15.38431123366428,
          47.05942711622198
        ]
      }
    },
    {
      "type": "Feature",
      "properties": {
        "nummer": 30110,
        "baumbezeichnung_botanisch": "Acer platanoides",
        "baumbezeichnung_deutsch": "Spitzahorn",
        "baumtyp": "Laub",
        "altersklassifizierung": "jung",
        "bemerkung": null,
        "pflanzjahr": "2011",
        "entnahmejahr": null,
        "baumpatenschaft": null,
        "objectid": 1619
      },
      "geometry": {
        "type": "Point",
        "coordinates": [
          15.384372748312932,
          47.05938870023416
        ],
        "bbox": [
          15.384372748312932,
          47.05938870023416,
          15.384372748312932,
          47.05938870023416
        ]
      }
    },
    {
      "type": "Feature",
      "properties": {
        "nummer": 30112,
        "baumbezeichnung_botanisch": "Acer platanoides",
        "baumbezeichnung_deutsch": "Spitzahorn",
        "baumtyp": "Laub",
        "altersklassifizierung": "jung",
        "bemerkung": null,
        "pflanzjahr": "2011",
        "entnahmejahr": null,
        "baumpatenschaft": null,
        "objectid": 1620
      },
      "geometry": {
        "type": "Point",
        "coordinates": [
          15.384171004425909,
          47.05952241781365
        ],
        "bbox": [
          15.384171004425909,
          47.05952241781365,
          15.384171004425909,
          47.05952241781365
        ]
      }
    },
    {
      "type": "Feature",
      "properties": {
        "nummer": 30113,
        "baumbezeichnung_botanisch": "Acer platanoides",
        "baumbezeichnung_deutsch": "Spitzahorn",
        "baumtyp": "Laub",
        "altersklassifizierung": "jung",
        "bemerkung": null,
        "pflanzjahr": "2011",
        "entnahmejahr": null,
        "baumpatenschaft": null,
        "objectid": 1621
      },
      "geometry": {
        "type": "Point",
        "coordinates": [
          15.384103875736482,
          47.059563112257145
        ],
        "bbox": [
          15.384103875736482,
          47.059563112257145,
          15.384103875736482,
          47.059563112257145
        ]
      }
    }
  ]
}