{"type":"FeatureCollection","features":[{"type":"Feature","properties":{"nummer":24649,"baumbezeichnung_botanisch":"Sophora japonica","baumbezeichnung_deutsch":"Schnurbaum","baumtyp":"Laub","bemerkung":null,"pflanzjahr":null,"entnahmejahr":null,"marker-size":"small","marker-symbol":"park2","marker-color":"#A3DDAD"},"geometry":{"type":"Point","coordinates":[15.42754493696621,47.09022120738738],"bbox":[15.42754493696621,47.09022120738738,15.42754493696621,47.09022120738738]}},{"type":"Feature","properties":{"nummer":10447,"baumbezeichnung_botanisch":"Acer platanoides","baumbezeichnung_deutsch":"Spitzahorn","baumtyp":"Laub","bemerkung":null,"pflanzjahr":null,"entnahmejahr":null,"marker-size":"small","marker-symbol":"park2","marker-color":"#A3DDAD"},"geometry":{"type":"Point","coordinates":[15.42749005825828,47.09029531047949],"bbox":[15.42749005825828,47.09029531047949,15.42749005825828,47.09029531047949]}},{"type":"Feature","properties":{"nummer":14135,"baumbezeichnung_botanisch":"Acer platanoides","baumbezeichnung_deutsch":"Spitzahorn","baumtyp":"Laub","bemerkung":null,"pflanzjahr":null,"entnahmejahr":null,"marker-size":"small","marker-symbol":"park2","marker-color":"#A3DDAD"},"geometry":{"type":"Point","coordinates":[15.4274310163697,47.09037366216143],"bbox":[15.4274310163697,47.09037366216143,15.4274310163697,47.09037366216143]}},{"type":"Feature","properties":{"nummer":23130,"baumbezeichnung_botanisch":"Sophora japonica","baumbezeichnung_deutsch":"Schnurbaum","baumtyp":"Laub","bemerkung":null,"pflanzjahr":"2010","entnahmejahr":null,"marker-size":"small","marker-symbol":"park2","marker-color":"#A3DDAD"},"geometry":{"type":"Point","coordinates":[15.42737982786126,47.09044736991265],"bbox":[15.42737982786126,47.09044736991265,15.42737982786126,47.09044736991265]}}]}