{"type":"FeatureCollection","features":[{"type":"Feature","properties":{"nummer":8555,"baumbezeichnung_botanisch":"Acer platanoides","baumbezeichnung_deutsch":"Spitzahorn","baumtyp":"Laub","bemerkung":null,"pflanzjahr":null,"entnahmejahr":null,"marker-size":"small","marker-symbol":"park2","marker-color":"#A3DDAD"},"geometry":{"type":"Point","coordinates":[15.42671838936847,47.08760742780587],"bbox":[15.42671838936847,47.08760742780587,15.42671838936847,47.08760742780587]}},{"type":"Feature","properties":{"nummer":12533,"baumbezeichnung_botanisch":"Fraxinus excelsior","baumbezeichnung_deutsch":"Esche","baumtyp":"Laub","bemerkung":null,"pflanzjahr":null,"entnahmejahr":null,"marker-size":"small","marker-symbol":"park2","marker-color":"#A3DDAD"},"geometry":{"type":"Point","coordinates":[15.42678033789917,47.08756608905604],"bbox":[15.42678033789917,47.08756608905604,15.42678033789917,47.08756608905604]}},{"type":"Feature","properties":{"nummer":31973,"baumbezeichnung_botanisch":"Fraxinus excelsior","baumbezeichnung_deutsch":"Esche","baumtyp":"Laub","bemerkung":null,"pflanzjahr":null,"entnahmejahr":null,"marker-size":"small","marker-symbol":"park2","marker-color":"#A3DDAD"},"geometry":{"type":"Point","coordinates":[15.42674568849708,47.08758726805652],"bbox":[15.42674568849708,47.08758726805652,15.42674568849708,47.08758726805652]}},{"type":"Feature","properties":{"nummer":14063,"baumbezeichnung_botanisch":"Fraxinus excelsior","baumbezeichnung_deutsch":"Esche","baumtyp":"Laub","bemerkung":null,"pflanzjahr":null,"entnahmejahr":null,"marker-size":"small","marker-symbol":"park2","marker-color":"#A3DDAD"},"geometry":{"type":"Point","coordinates":[15.42737974288883,47.08722101532448],"bbox":[15.42737974288883,47.08722101532448,15.42737974288883,47.08722101532448]}},{"type":"Feature","properties":{"nummer":20209,"baumbezeichnung_botanisch":"Acer platanoides 'Cleveland'","baumbezeichnung_deutsch":"Spitzahorn","baumtyp":"Laub","bemerkung":null,"pflanzjahr":"2012","entnahmejahr":null,"marker-size":"small","marker-symbol":"park2","marker-color":"#A3DDAD"},"geometry":{"type":"Point","coordinates":[15.42636743243319,47.08700565960501],"bbox":[15.42636743243319,47.08700565960501,15.42636743243319,47.08700565960501]}},{"type":"Feature","properties":{"nummer":56869,"baumbezeichnung_botanisch":"Acer platanoides 'Cleveland'","baumbezeichnung_deutsch":"Spitzahorn","baumtyp":"Laub","bemerkung":null,"pflanzjahr":"2012","entnahmejahr":null,"marker-size":"small","marker-symbol":"park2","marker-color":"#A3DDAD"},"geometry":{"type":"Point","coordinates":[15.42730641429486,47.08711307278082],"bbox":[15.42730641429486,47.08711307278082,15.42730641429486,47.08711307278082]}}]}