{"type":"FeatureCollection","features":[{"type":"Feature","properties":{"nummer":26437,"baumbezeichnung_botanisch":"Celtis australis","baumbezeichnung_deutsch":"Zürgel Baum","baumtyp":"Laub","bemerkung":null,"pflanzjahr":"2002","entnahmejahr":null,"marker-size":"small","marker-symbol":"park2","marker-color":"#A3DDAD"},"geometry":{"type":"Point","coordinates":[15.45313518091329,47.05700156690038],"bbox":[15.45313518091329,47.05700156690038,15.45313518091329,47.05700156690038]}},{"type":"Feature","properties":{"nummer":16243,"baumbezeichnung_botanisch":"Celtis australis","baumbezeichnung_deutsch":"Zürgel Baum","baumtyp":"Laub","bemerkung":null,"pflanzjahr":"2002","entnahmejahr":null,"marker-size":"small","marker-symbol":"park2","marker-color":"#A3DDAD"},"geometry":{"type":"Point","coordinates":[15.45332790150433,47.05663691760159],"bbox":[15.45332790150433,47.05663691760159,15.45332790150433,47.05663691760159]}},{"type":"Feature","properties":{"nummer":24637,"baumbezeichnung_botanisch":"Celtis australis","baumbezeichnung_deutsch":"Zürgel Baum","baumtyp":"Laub","bemerkung":null,"pflanzjahr":"2002","entnahmejahr":null,"marker-size":"small","marker-symbol":"park2","marker-color":"#A3DDAD"},"geometry":{"type":"Point","coordinates":[15.45340383400177,47.05646275673295],"bbox":[15.45340383400177,47.05646275673295,15.45340383400177,47.05646275673295]}}]}