{"type":"FeatureCollection","features":[{"type":"Feature","properties":{"nummer":4161,"baumbezeichnung_botanisch":"Aesculus hippocastanum","baumbezeichnung_deutsch":"Gemeine Roßkastanie","baumtyp":"Laub","bemerkung":null,"pflanzjahr":null,"entnahmejahr":null,"marker-size":"small","marker-symbol":"park2","marker-color":"#A3DDAD"},"geometry":{"type":"Point","coordinates":[15.45332094634432,47.0361461845605],"bbox":[15.45332094634432,47.0361461845605,15.45332094634432,47.0361461845605]}}]}