{
  "type": "FeatureCollection",
  "features": [
    {
      "type": "Feature",
      "properties": {
        "nummer": 23028,
        "baumbezeichnung_botanisch": "Aesculus hippocastanum",
        "baumbezeichnung_deutsch": "Gemeine Roßkastanie",
        "baumtyp": "Laub",
        "altersklassifizierung": "alt",
        "bemerkung": null,
        "pflanzjahr": null,
        "entnahmejahr": null,
        "baumpatenschaft": null,
        "objectid": 15118
      },
      "geometry": {
        "type": "Point",
        "coordinates": [
          15.45332094634432,
          47.0361461845605
        ]
      }
    }
  ]
}