{"type":"FeatureCollection","features":[{"type":"Feature","properties":{"nummer":18865,"baumbezeichnung_botanisch":"Tilia cordata","baumbezeichnung_deutsch":"Winterlinde","baumtyp":"Laub","bemerkung":null,"pflanzjahr":"1985","entnahmejahr":null,"marker-size":"small","marker-symbol":"park2","marker-color":"#A3DDAD"},"geometry":{"type":"Point","coordinates":[15.45621871496558,47.06045464464408],"bbox":[15.45621871496558,47.06045464464408,15.45621871496558,47.06045464464408]}},{"type":"Feature","properties":{"nummer":23455,"baumbezeichnung_botanisch":"Tilia cordata","baumbezeichnung_deutsch":"Winterlinde","baumtyp":"Laub","bemerkung":null,"pflanzjahr":"1985","entnahmejahr":null,"marker-size":"small","marker-symbol":"park2","marker-color":"#A3DDAD"},"geometry":{"type":"Point","coordinates":[15.45613380859859,47.06042570889133],"bbox":[15.45613380859859,47.06042570889133,15.45613380859859,47.06042570889133]}},{"type":"Feature","properties":{"nummer":16417,"baumbezeichnung_botanisch":"Tilia cordata","baumbezeichnung_deutsch":"Winterlinde","baumtyp":"Laub","bemerkung":null,"pflanzjahr":"1985","entnahmejahr":null,"marker-size":"small","marker-symbol":"park2","marker-color":"#A3DDAD"},"geometry":{"type":"Point","coordinates":[15.45592078959777,47.06035856126577],"bbox":[15.45592078959777,47.06035856126577,15.45592078959777,47.06035856126577]}},{"type":"Feature","properties":{"nummer":12678,"baumbezeichnung_botanisch":"Tilia cordata","baumbezeichnung_deutsch":"Winterlinde","baumtyp":"Laub","bemerkung":null,"pflanzjahr":"1985","entnahmejahr":null,"marker-size":"small","marker-symbol":"park2","marker-color":"#A3DDAD"},"geometry":{"type":"Point","coordinates":[15.45558642707913,47.06025505661954],"bbox":[15.45558642707913,47.06025505661954,15.45558642707913,47.06025505661954]}},{"type":"Feature","properties":{"nummer":14739,"baumbezeichnung_botanisch":"Tilia cordata","baumbezeichnung_deutsch":"Winterlinde","baumtyp":"Laub","bemerkung":null,"pflanzjahr":"1985","entnahmejahr":null,"marker-size":"small","marker-symbol":"park2","marker-color":"#A3DDAD"},"geometry":{"type":"Point","coordinates":[15.45544644567517,47.06021062374804],"bbox":[15.45544644567517,47.06021062374804,15.45544644567517,47.06021062374804]}},{"type":"Feature","properties":{"nummer":3759,"baumbezeichnung_botanisch":"Tilia cordata","baumbezeichnung_deutsch":"Winterlinde","baumtyp":"Laub","bemerkung":null,"pflanzjahr":"1985","entnahmejahr":null,"marker-size":"small","marker-symbol":"park2","marker-color":"#A3DDAD"},"geometry":{"type":"Point","coordinates":[15.4552911213993,47.06016269052852],"bbox":[15.4552911213993,47.06016269052852,15.4552911213993,47.06016269052852]}},{"type":"Feature","properties":{"nummer":25520,"baumbezeichnung_botanisch":"Tilia cordata","baumbezeichnung_deutsch":"Winterlinde","baumtyp":"Laub","bemerkung":null,"pflanzjahr":"1985","entnahmejahr":null,"marker-size":"small","marker-symbol":"park2","marker-color":"#A3DDAD"},"geometry":{"type":"Point","coordinates":[15.45513624817638,47.06011376211106],"bbox":[15.45513624817638,47.06011376211106,15.45513624817638,47.06011376211106]}},{"type":"Feature","properties":{"nummer":15678,"baumbezeichnung_botanisch":"Tilia cordata","baumbezeichnung_deutsch":"Winterlinde","baumtyp":"Laub","bemerkung":null,"pflanzjahr":"2009","entnahmejahr":null,"marker-size":"small","marker-symbol":"park2","marker-color":"#A3DDAD"},"geometry":{"type":"Point","coordinates":[15.4557289967942,47.06029899649788],"bbox":[15.4557289967942,47.06029899649788,15.4557289967942,47.06029899649788]}}]}