{"type":"FeatureCollection","features":[{"type":"Feature","properties":{"nummer":26064,"baumbezeichnung_botanisch":"Sophora japonica","baumbezeichnung_deutsch":"Schnurbaum","baumtyp":"Laub","bemerkung":null,"pflanzjahr":null,"entnahmejahr":null,"marker-size":"small","marker-symbol":"park2","marker-color":"#A3DDAD"},"geometry":{"type":"Point","coordinates":[15.45629454836138,47.03794781839442],"bbox":[15.45629454836138,47.03794781839442,15.45629454836138,47.03794781839442]}},{"type":"Feature","properties":{"nummer":23373,"baumbezeichnung_botanisch":"Fraxinus excelsior 'Diversifolia'","baumbezeichnung_deutsch":"Einblättrige Esche","baumtyp":"Laub","bemerkung":null,"pflanzjahr":"2005","entnahmejahr":null,"marker-size":"small","marker-symbol":"park2","marker-color":"#A3DDAD"},"geometry":{"type":"Point","coordinates":[15.45633354568023,47.03789277903539],"bbox":[15.45633354568023,47.03789277903539,15.45633354568023,47.03789277903539]}},{"type":"Feature","properties":{"nummer":1360,"baumbezeichnung_botanisch":"Quercus sp.","baumbezeichnung_deutsch":"Eiche","baumtyp":"Laub","bemerkung":null,"pflanzjahr":null,"entnahmejahr":null,"marker-size":"small","marker-symbol":"park2","marker-color":"#A3DDAD"},"geometry":{"type":"Point","coordinates":[15.45616712384705,47.0381681943127],"bbox":[15.45616712384705,47.0381681943127,15.45616712384705,47.0381681943127]}},{"type":"Feature","properties":{"nummer":5379,"baumbezeichnung_botanisch":"Quercus sp.","baumbezeichnung_deutsch":"Eiche","baumtyp":"Laub","bemerkung":null,"pflanzjahr":null,"entnahmejahr":null,"marker-size":"small","marker-symbol":"park2","marker-color":"#A3DDAD"},"geometry":{"type":"Point","coordinates":[15.45618226354115,47.03811622790308],"bbox":[15.45618226354115,47.03811622790308,15.45618226354115,47.03811622790308]}}]}