{"type":"FeatureCollection","features":[{"type":"Feature","properties":{"nummer":45040,"baumbezeichnung_botanisch":"Quercus cerris","baumbezeichnung_deutsch":"Zerr - Eiche","baumtyp":"Laub","bemerkung":null,"pflanzjahr":"2011","entnahmejahr":null,"marker-size":"small","marker-symbol":"park2","marker-color":"#A3DDAD"},"geometry":{"type":"Point","coordinates":[15.42809236973615,47.07834325842291],"bbox":[15.42809236973615,47.07834325842291,15.42809236973615,47.07834325842291]}}]}