{"type":"FeatureCollection","features":[{"type":"Feature","properties":{"nummer":34275,"baumbezeichnung_botanisch":"Acer platanoides","baumbezeichnung_deutsch":"Spitzahorn","baumtyp":"Laub","bemerkung":null,"pflanzjahr":null,"entnahmejahr":null,"marker-size":"small","marker-symbol":"park2","marker-color":"#A3DDAD"},"geometry":{"type":"Point","coordinates":[15.42785192896078,47.0300892408798],"bbox":[15.42785192896078,47.0300892408798,15.42785192896078,47.0300892408798]}},{"type":"Feature","properties":{"nummer":34276,"baumbezeichnung_botanisch":"Acer platanoides","baumbezeichnung_deutsch":"Spitzahorn","baumtyp":"Laub","bemerkung":null,"pflanzjahr":null,"entnahmejahr":null,"marker-size":"small","marker-symbol":"park2","marker-color":"#A3DDAD"},"geometry":{"type":"Point","coordinates":[15.4282698625238,47.02997236650979],"bbox":[15.4282698625238,47.02997236650979,15.4282698625238,47.02997236650979]}},{"type":"Feature","properties":{"nummer":34277,"baumbezeichnung_botanisch":"Acer platanoides","baumbezeichnung_deutsch":"Spitzahorn","baumtyp":"Laub","bemerkung":null,"pflanzjahr":null,"entnahmejahr":null,"marker-size":"small","marker-symbol":"park2","marker-color":"#A3DDAD"},"geometry":{"type":"Point","coordinates":[15.42843076377856,47.02992604245742],"bbox":[15.42843076377856,47.02992604245742,15.42843076377856,47.02992604245742]}},{"type":"Feature","properties":{"nummer":34278,"baumbezeichnung_botanisch":"Acer platanoides","baumbezeichnung_deutsch":"Spitzahorn","baumtyp":"Laub","bemerkung":null,"pflanzjahr":null,"entnahmejahr":null,"marker-size":"small","marker-symbol":"park2","marker-color":"#A3DDAD"},"geometry":{"type":"Point","coordinates":[15.42856131523688,47.02992469807798],"bbox":[15.42856131523688,47.02992469807798,15.42856131523688,47.02992469807798]}},{"type":"Feature","properties":{"nummer":34279,"baumbezeichnung_botanisch":"Acer platanoides","baumbezeichnung_deutsch":"Spitzahorn","baumtyp":"Laub","bemerkung":null,"pflanzjahr":null,"entnahmejahr":null,"marker-size":"small","marker-symbol":"park2","marker-color":"#A3DDAD"},"geometry":{"type":"Point","coordinates":[15.42869644206601,47.02996146810548],"bbox":[15.42869644206601,47.02996146810548,15.42869644206601,47.02996146810548]}},{"type":"Feature","properties":{"nummer":34283,"baumbezeichnung_botanisch":"Acer platanoides","baumbezeichnung_deutsch":"Spitzahorn","baumtyp":"Laub","bemerkung":null,"pflanzjahr":null,"entnahmejahr":null,"marker-size":"small","marker-symbol":"park2","marker-color":"#A3DDAD"},"geometry":{"type":"Point","coordinates":[15.42801138770391,47.02992271719093],"bbox":[15.42801138770391,47.02992271719093,15.42801138770391,47.02992271719093]}},{"type":"Feature","properties":{"nummer":34294,"baumbezeichnung_botanisch":"Koelreuteria paniculata","baumbezeichnung_deutsch":"Blasenbaum","baumtyp":"Laub","bemerkung":null,"pflanzjahr":null,"entnahmejahr":null,"marker-size":"small","marker-symbol":"park2","marker-color":"#A3DDAD"},"geometry":{"type":"Point","coordinates":[15.42825534060038,47.03052083535359],"bbox":[15.42825534060038,47.03052083535359,15.42825534060038,47.03052083535359]}},{"type":"Feature","properties":{"nummer":34295,"baumbezeichnung_botanisch":"Koelreuteria paniculata","baumbezeichnung_deutsch":"Blasenbaum","baumtyp":"Laub","bemerkung":null,"pflanzjahr":null,"entnahmejahr":null,"marker-size":"small","marker-symbol":"park2","marker-color":"#A3DDAD"},"geometry":{"type":"Point","coordinates":[15.42841181341045,47.0305304053974],"bbox":[15.42841181341045,47.0305304053974,15.42841181341045,47.0305304053974]}},{"type":"Feature","properties":{"nummer":34296,"baumbezeichnung_botanisch":"Koelreuteria paniculata","baumbezeichnung_deutsch":"Blasenbaum","baumtyp":"Laub","bemerkung":null,"pflanzjahr":null,"entnahmejahr":null,"marker-size":"small","marker-symbol":"park2","marker-color":"#A3DDAD"},"geometry":{"type":"Point","coordinates":[15.42805848631606,47.03022415769975],"bbox":[15.42805848631606,47.03022415769975,15.42805848631606,47.03022415769975]}},{"type":"Feature","properties":{"nummer":34297,"baumbezeichnung_botanisch":"Koelreuteria paniculata","baumbezeichnung_deutsch":"Blasenbaum","baumtyp":"Laub","bemerkung":null,"pflanzjahr":null,"entnahmejahr":null,"marker-size":"small","marker-symbol":"park2","marker-color":"#A3DDAD"},"geometry":{"type":"Point","coordinates":[15.42857172606055,47.03013183829935],"bbox":[15.42857172606055,47.03013183829935,15.42857172606055,47.03013183829935]}},{"type":"Feature","properties":{"nummer":34298,"baumbezeichnung_botanisch":"Quercus palustris","baumbezeichnung_deutsch":"Sumpf - Eiche","baumtyp":"Laub","bemerkung":null,"pflanzjahr":null,"entnahmejahr":null,"marker-size":"small","marker-symbol":"park2","marker-color":"#A3DDAD"},"geometry":{"type":"Point","coordinates":[15.42796000738342,47.03028406608946],"bbox":[15.42796000738342,47.03028406608946,15.42796000738342,47.03028406608946]}}]}