{
  "type": "FeatureCollection",
  "features": [
    {
      "type": "Feature",
      "properties": {
        "Naturdenkmal": true,
        "Naturdenkmal_Eigentum": "privat",
        "nummer": "Naturdenkmal-108",
        "objectid": "Naturdenkmal-38",
        "baumbezeichnung_deutsch": "Linde",
        "baumbezeichnung_botanisch": null
      },
      "geometry": {
        "type": "Point",
        "coordinates": [
          15.492104693859469,
          47.10755954605627
        ]
      }
    }
  ]
}