{"type":"FeatureCollection","features":[{"type":"Feature","properties":{"nummer":32307,"baumbezeichnung_botanisch":"Flächenkartierung","baumbezeichnung_deutsch":"Flächenkartierung","baumtyp":"Flächenkartierung","bemerkung":null,"pflanzjahr":null,"entnahmejahr":null,"marker-size":"small","marker-symbol":"","marker-color":null},"geometry":{"type":"Point","coordinates":[15.49262956608416,47.10913988543828],"bbox":[15.49262956608416,47.10913988543828,15.49262956608416,47.10913988543828]}}]}