{"type":"FeatureCollection","features":[{"type":"Feature","properties":{"nummer":27176,"baumbezeichnung_botanisch":"Flächenkartierung","baumbezeichnung_deutsch":"Flächenkartierung","baumtyp":"Flächenkartierung","altersklassifizierung":"jung","bemerkung":null,"pflanzjahr":null,"entnahmejahr":null,"baumpatenschaft":null,"objectid":9902},"geometry":{"type":"Point","coordinates":[15.49262956608416,47.10913988543828],"bbox":[15.49262956608416,47.10913988543828,15.49262956608416,47.10913988543828]}}]}