{"type":"FeatureCollection","features":[{"type":"Feature","properties":{"nummer":36002,"baumbezeichnung_botanisch":"Betula pendula","baumbezeichnung_deutsch":"Sandbirke, Weißbirke","baumtyp":"Laub","bemerkung":null,"pflanzjahr":null,"entnahmejahr":null,"marker-size":"small","marker-symbol":"park2","marker-color":"#A3DDAD"},"geometry":{"type":"Point","coordinates":[15.498456164011,47.07501958189437],"bbox":[15.498456164011,47.07501958189437,15.498456164011,47.07501958189437]}},{"type":"Feature","properties":{"nummer":36003,"baumbezeichnung_botanisch":"Betula pendula","baumbezeichnung_deutsch":"Sandbirke, Weißbirke","baumtyp":"Laub","bemerkung":null,"pflanzjahr":null,"entnahmejahr":null,"marker-size":"small","marker-symbol":"park2","marker-color":"#A3DDAD"},"geometry":{"type":"Point","coordinates":[15.49855381205682,47.07499219640961],"bbox":[15.49855381205682,47.07499219640961,15.49855381205682,47.07499219640961]}},{"type":"Feature","properties":{"nummer":21344,"baumbezeichnung_botanisch":"Betula pendula","baumbezeichnung_deutsch":"Sandbirke, Weißbirke","baumtyp":"Laub","bemerkung":null,"pflanzjahr":null,"entnahmejahr":null,"marker-size":"small","marker-symbol":"park2","marker-color":"#A3DDAD"},"geometry":{"type":"Point","coordinates":[15.49792466262029,47.07481516384544],"bbox":[15.49792466262029,47.07481516384544,15.49792466262029,47.07481516384544]}}]}