{"type":"FeatureCollection","features":[{"type":"Feature","properties":{"nummer":29159,"baumbezeichnung_botanisch":"Tilia tomentosa","baumbezeichnung_deutsch":"Silberlinde","baumtyp":"Laub","bemerkung":null,"pflanzjahr":"2006","entnahmejahr":null,"marker-size":"small","marker-symbol":"park2","marker-color":"#A3DDAD"},"geometry":{"type":"Point","coordinates":[15.39569698208348,47.05792828289819],"bbox":[15.39569698208348,47.05792828289819,15.39569698208348,47.05792828289819]}}]}