{
  "type": "FeatureCollection",
  "features": [
    {
      "type": "Feature",
      "properties": {
        "Naturdenkmal": true,
        "Naturdenkmal_Eigentum": "privat",
        "nummer": "Naturdenkmal-13",
        "objectid": "Naturdenkmal-63",
        "baumbezeichnung_deutsch": "Mädchenhaarbaum",
        "baumbezeichnung_botanisch": "Ginkgo biloba"
      },
      "geometry": {
        "type": "Point",
        "coordinates": [
          15.448408204719627,
          47.07423166491191
        ]
      }
    },
    {
      "type": "Feature",
      "properties": {
        "Naturdenkmal": true,
        "Naturdenkmal_Eigentum": "privat",
        "nummer": "Naturdenkmal-28",
        "objectid": "Naturdenkmal-70",
        "baumbezeichnung_deutsch": "Platane",
        "baumbezeichnung_botanisch": "Platanus x hispanica"
      },
      "geometry": {
        "type": "Point",
        "coordinates": [
          15.450012673691342,
          47.07491976869011
        ]
      }
    }
  ]
}