{"type":"FeatureCollection","features":[{"type":"Feature","properties":{"nummer":24761,"baumbezeichnung_botanisch":"Platanus x acerifolia","baumbezeichnung_deutsch":"Platane","baumtyp":"Laub","altersklassifizierung":"jung","bemerkung":null,"pflanzjahr":"2005","entnahmejahr":null,"baumpatenschaft":null,"objectid":27089},"geometry":{"type":"Point","coordinates":[15.45127028329389,47.05040491100139],"bbox":[15.45127028329389,47.05040491100139,15.45127028329389,47.05040491100139]}},{"type":"Feature","properties":{"nummer":24762,"baumbezeichnung_botanisch":"Platanus x acerifolia","baumbezeichnung_deutsch":"Platane","baumtyp":"Laub","altersklassifizierung":"jung","bemerkung":null,"pflanzjahr":"2005","entnahmejahr":null,"baumpatenschaft":null,"objectid":27090},"geometry":{"type":"Point","coordinates":[15.451425040926768,47.05020618929557],"bbox":[15.451425040926768,47.05020618929557,15.451425040926768,47.05020618929557]}},{"type":"Feature","properties":{"nummer":24763,"baumbezeichnung_botanisch":"Platanus x acerifolia","baumbezeichnung_deutsch":"Platane","baumtyp":"Laub","altersklassifizierung":"jung","bemerkung":null,"pflanzjahr":"2005","entnahmejahr":null,"baumpatenschaft":null,"objectid":27091},"geometry":{"type":"Point","coordinates":[15.45158519720302,47.04999680038528],"bbox":[15.45158519720302,47.04999680038528,15.45158519720302,47.04999680038528]}},{"type":"Feature","properties":{"nummer":24764,"baumbezeichnung_botanisch":"Platanus x acerifolia","baumbezeichnung_deutsch":"Platane","baumtyp":"Laub","altersklassifizierung":"jung","bemerkung":null,"pflanzjahr":"2005","entnahmejahr":null,"baumpatenschaft":null,"objectid":27092},"geometry":{"type":"Point","coordinates":[15.451725928138645,47.04980392018289],"bbox":[15.451725928138645,47.04980392018289,15.451725928138645,47.04980392018289]}},{"type":"Feature","properties":{"nummer":24765,"baumbezeichnung_botanisch":"Platanus x acerifolia","baumbezeichnung_deutsch":"Platane","baumtyp":"Laub","altersklassifizierung":"jung","bemerkung":null,"pflanzjahr":"2005","entnahmejahr":null,"baumpatenschaft":null,"objectid":27093},"geometry":{"type":"Point","coordinates":[15.45188426113764,47.04959927607959],"bbox":[15.45188426113764,47.04959927607959,15.45188426113764,47.04959927607959]}},{"type":"Feature","properties":{"nummer":24766,"baumbezeichnung_botanisch":"Platanus x acerifolia","baumbezeichnung_deutsch":"Platane","baumtyp":"Laub","altersklassifizierung":"jung","bemerkung":null,"pflanzjahr":"2005","entnahmejahr":null,"baumpatenschaft":null,"objectid":27094},"geometry":{"type":"Point","coordinates":[15.452030487923539,47.04938977806453],"bbox":[15.452030487923539,47.04938977806453,15.452030487923539,47.04938977806453]}},{"type":"Feature","properties":{"nummer":24767,"baumbezeichnung_botanisch":"Platanus x acerifolia","baumbezeichnung_deutsch":"Platane","baumtyp":"Laub","altersklassifizierung":"jung","bemerkung":null,"pflanzjahr":"2005","entnahmejahr":null,"baumpatenschaft":null,"objectid":27095},"geometry":{"type":"Point","coordinates":[15.452185318387322,47.049186296545436],"bbox":[15.452185318387322,47.049186296545436,15.452185318387322,47.049186296545436]}}]}