{"type":"FeatureCollection","features":[{"type":"Feature","properties":{"nummer":2961,"baumbezeichnung_botanisch":"Carpinus betulus","baumbezeichnung_deutsch":"Hain - oder Weißbuche","baumtyp":"Laub","bemerkung":null,"pflanzjahr":null,"entnahmejahr":null,"marker-size":"small","marker-symbol":"park2","marker-color":"#A3DDAD"},"geometry":{"type":"Point","coordinates":[15.43784037014378,47.09328766268256],"bbox":[15.43784037014378,47.09328766268256,15.43784037014378,47.09328766268256]}},{"type":"Feature","properties":{"nummer":29380,"baumbezeichnung_botanisch":"Carpinus betulus","baumbezeichnung_deutsch":"Hain - oder Weißbuche","baumtyp":"Laub","bemerkung":null,"pflanzjahr":null,"entnahmejahr":null,"marker-size":"small","marker-symbol":"park2","marker-color":"#A3DDAD"},"geometry":{"type":"Point","coordinates":[15.43801908765739,47.09340375133468],"bbox":[15.43801908765739,47.09340375133468,15.43801908765739,47.09340375133468]}}]}