{"type":"FeatureCollection","features":[{"type":"Feature","properties":{"nummer":25500,"baumbezeichnung_botanisch":"Fraxinus excelsior","baumbezeichnung_deutsch":"Esche","baumtyp":"Laub","bemerkung":null,"pflanzjahr":null,"entnahmejahr":null,"marker-size":"small","marker-symbol":"park2","marker-color":"#A3DDAD"},"geometry":{"type":"Point","coordinates":[15.43726544159726,47.08357811522138],"bbox":[15.43726544159726,47.08357811522138,15.43726544159726,47.08357811522138]}}]}