{"type":"FeatureCollection","features":[{"type":"Feature","properties":{"nummer":15851,"baumbezeichnung_botanisch":"Juglans regia","baumbezeichnung_deutsch":"Walnuß","baumtyp":"Laub","bemerkung":null,"pflanzjahr":null,"entnahmejahr":null,"marker-size":"small","marker-symbol":"park2","marker-color":"#A3DDAD"},"geometry":{"type":"Point","coordinates":[15.40828866371762,47.09269985125588],"bbox":[15.40828866371762,47.09269985125588,15.40828866371762,47.09269985125588]}},{"type":"Feature","properties":{"nummer":17547,"baumbezeichnung_botanisch":"Juglans regia","baumbezeichnung_deutsch":"Walnuß","baumtyp":"Laub","bemerkung":null,"pflanzjahr":null,"entnahmejahr":null,"marker-size":"small","marker-symbol":"park2","marker-color":"#A3DDAD"},"geometry":{"type":"Point","coordinates":[15.40831306259903,47.0926176865267],"bbox":[15.40831306259903,47.0926176865267,15.40831306259903,47.0926176865267]}},{"type":"Feature","properties":{"nummer":55280,"baumbezeichnung_botanisch":"Acer pseudoplatanus","baumbezeichnung_deutsch":"Bergahorn","baumtyp":"Laub","bemerkung":null,"pflanzjahr":null,"entnahmejahr":null,"marker-size":"small","marker-symbol":"park2","marker-color":"#A3DDAD"},"geometry":{"type":"Point","coordinates":[15.40676017487126,47.09264052937814],"bbox":[15.40676017487126,47.09264052937814,15.40676017487126,47.09264052937814]}},{"type":"Feature","properties":{"nummer":55281,"baumbezeichnung_botanisch":"Acer pseudoplatanus","baumbezeichnung_deutsch":"Bergahorn","baumtyp":"Laub","bemerkung":null,"pflanzjahr":null,"entnahmejahr":null,"marker-size":"small","marker-symbol":"park2","marker-color":"#A3DDAD"},"geometry":{"type":"Point","coordinates":[15.40651658875347,47.09292057551649],"bbox":[15.40651658875347,47.09292057551649,15.40651658875347,47.09292057551649]}},{"type":"Feature","properties":{"nummer":55587,"baumbezeichnung_botanisch":"Acer platanoides","baumbezeichnung_deutsch":"Spitzahorn","baumtyp":"Laub","bemerkung":null,"pflanzjahr":null,"entnahmejahr":null,"marker-size":"small","marker-symbol":"park2","marker-color":"#A3DDAD"},"geometry":{"type":"Point","coordinates":[15.40579508008877,47.09380908488812],"bbox":[15.40579508008877,47.09380908488812,15.40579508008877,47.09380908488812]}},{"type":"Feature","properties":{"nummer":55588,"baumbezeichnung_botanisch":"Acer platanoides","baumbezeichnung_deutsch":"Spitzahorn","baumtyp":"Laub","bemerkung":null,"pflanzjahr":null,"entnahmejahr":null,"marker-size":"small","marker-symbol":"park2","marker-color":"#A3DDAD"},"geometry":{"type":"Point","coordinates":[15.40571848537697,47.09390485103064],"bbox":[15.40571848537697,47.09390485103064,15.40571848537697,47.09390485103064]}},{"type":"Feature","properties":{"nummer":55589,"baumbezeichnung_botanisch":"Acer platanoides","baumbezeichnung_deutsch":"Spitzahorn","baumtyp":"Laub","bemerkung":null,"pflanzjahr":null,"entnahmejahr":null,"marker-size":"small","marker-symbol":"park2","marker-color":"#A3DDAD"},"geometry":{"type":"Point","coordinates":[15.40564197462109,47.09399585761587],"bbox":[15.40564197462109,47.09399585761587,15.40564197462109,47.09399585761587]}}]}