{
  "type": "FeatureCollection",
  "features": [
    {
      "type": "Feature",
      "properties": {
        "nummer": 15183,
        "objectid": 1131,
        "baumbezeichnung_deutsch": "Schnurbaum",
        "baumbezeichnung_botanisch": "Sophora japonica",
        "baumtyp": "Laub",
        "bemerkung": null,
        "pflanzjahr": null,
        "entnahmejahr": null,
        "baumpatenschaft": null,
        "altersklassifizierung": "alt"
      },
      "geometry": {
        "type": "Point",
        "coordinates": [
          15.40631606277507,
          47.06819994753391
        ]
      }
    },
    {
      "type": "Feature",
      "properties": {
        "nummer": 15170,
        "objectid": 1625,
        "baumbezeichnung_deutsch": "Schnurbaum",
        "baumbezeichnung_botanisch": "Sophora japonica",
        "baumtyp": "Laub",
        "bemerkung": null,
        "pflanzjahr": null,
        "entnahmejahr": null,
        "baumpatenschaft": null,
        "altersklassifizierung": "mittel"
      },
      "geometry": {
        "type": "Point",
        "coordinates": [
          15.40754814882516,
          47.068177123745016
        ]
      }
    }
  ]
}