{
  "type": "FeatureCollection",
  "features": [
    {
      "type": "Feature",
      "properties": {
        "NUMMER": 15183,
        "BAUMBEZEICHNUNG_BOTANISCH": "Sophora japonica",
        "BAUMBEZEICHNUNG_DEUTSCH": "Schnurbaum",
        "BAUMTYP": "Laub",
        "BEMERKUNG": null,
        "PFLANZJAHR": null,
        "ENTNAHMEJAHR": null,
        "BAUMPATENSCHAFT": null,
        "ALTERSKLASSIZIERUNG": "alt",
        "OBJECTID": 1131
      },
      "geometry": {
        "type": "Point",
        "coordinates": [
          15.40631606277507,
          47.06819994753391
        ]
      }
    },
    {
      "type": "Feature",
      "properties": {
        "NUMMER": 15170,
        "BAUMBEZEICHNUNG_BOTANISCH": "Sophora japonica",
        "BAUMBEZEICHNUNG_DEUTSCH": "Schnurbaum",
        "BAUMTYP": "Laub",
        "BEMERKUNG": null,
        "PFLANZJAHR": null,
        "ENTNAHMEJAHR": null,
        "BAUMPATENSCHAFT": null,
        "ALTERSKLASSIZIERUNG": "mittel",
        "OBJECTID": 1625
      },
      "geometry": {
        "type": "Point",
        "coordinates": [
          15.40754814882516,
          47.068177123745016
        ]
      }
    }
  ]
}