{"type":"FeatureCollection","features":[{"type":"Feature","properties":{"nummer":2537,"baumbezeichnung_botanisch":"Tilia cordata","baumbezeichnung_deutsch":"Winterlinde","baumtyp":"Laub","bemerkung":null,"pflanzjahr":"2009","entnahmejahr":null,"marker-size":"small","marker-symbol":"park2","marker-color":"#A3DDAD"},"geometry":{"type":"Point","coordinates":[15.40722553203247,47.05316463095954],"bbox":[15.40722553203247,47.05316463095954,15.40722553203247,47.05316463095954]}},{"type":"Feature","properties":{"nummer":20620,"baumbezeichnung_botanisch":"Tilia cordata","baumbezeichnung_deutsch":"Winterlinde","baumtyp":"Laub","bemerkung":null,"pflanzjahr":"1991","entnahmejahr":null,"marker-size":"small","marker-symbol":"park2","marker-color":"#A3DDAD"},"geometry":{"type":"Point","coordinates":[15.40670163024089,47.0530056727385],"bbox":[15.40670163024089,47.0530056727385,15.40670163024089,47.0530056727385]}},{"type":"Feature","properties":{"nummer":6634,"baumbezeichnung_botanisch":"Tilia cordata","baumbezeichnung_deutsch":"Winterlinde","baumtyp":"Laub","bemerkung":null,"pflanzjahr":"1991","entnahmejahr":null,"marker-size":"small","marker-symbol":"park2","marker-color":"#A3DDAD"},"geometry":{"type":"Point","coordinates":[15.40571173020227,47.05282557514037],"bbox":[15.40571173020227,47.05282557514037,15.40571173020227,47.05282557514037]}}]}