{
  "type": "FeatureCollection",
  "features": [
    {
      "type": "Feature",
      "properties": {
        "nummer": 31747,
        "baumbezeichnung_botanisch": "Ulmus 'Regal'",
        "baumbezeichnung_deutsch": "Resista-Ulme",
        "baumtyp": "Laub",
        "altersklassifizierung": "jung",
        "bemerkung": null,
        "pflanzjahr": "2014",
        "entnahmejahr": null,
        "baumpatenschaft": null,
        "objectid": 30978
      },
      "geometry": {
        "type": "Point",
        "coordinates": [
          15.408288558914858,
          47.056967604683045
        ],
        "bbox": [
          15.408288558914858,
          47.056967604683045,
          15.408288558914858,
          47.056967604683045
        ]
      }
    }
  ]
}