{"type":"FeatureCollection","features":[{"type":"Feature","properties":{"nummer":15840,"baumbezeichnung_botanisch":"Picea abies","baumbezeichnung_deutsch":"Rotfichte","baumtyp":"Nadel","bemerkung":null,"pflanzjahr":null,"entnahmejahr":null,"marker-size":"small","marker-symbol":"park","marker-color":"#3BB451"},"geometry":{"type":"Point","coordinates":[15.40600781932564,47.07194869477818],"bbox":[15.40600781932564,47.07194869477818,15.40600781932564,47.07194869477818]}},{"type":"Feature","properties":{"nummer":13396,"baumbezeichnung_botanisch":"Picea abies","baumbezeichnung_deutsch":"Rotfichte","baumtyp":"Nadel","bemerkung":null,"pflanzjahr":null,"entnahmejahr":null,"marker-size":"small","marker-symbol":"park","marker-color":"#3BB451"},"geometry":{"type":"Point","coordinates":[15.40607009930261,47.07197299983566],"bbox":[15.40607009930261,47.07197299983566,15.40607009930261,47.07197299983566]}},{"type":"Feature","properties":{"nummer":14404,"baumbezeichnung_botanisch":"Abies nordmanniana","baumbezeichnung_deutsch":"Nordmannstanne","baumtyp":"Nadel","bemerkung":null,"pflanzjahr":null,"entnahmejahr":null,"marker-size":"small","marker-symbol":"park","marker-color":"#3BB451"},"geometry":{"type":"Point","coordinates":[15.40612611670096,47.07195679585753],"bbox":[15.40612611670096,47.07195679585753,15.40612611670096,47.07195679585753]}},{"type":"Feature","properties":{"nummer":39561,"baumbezeichnung_botanisch":"Juglans regia","baumbezeichnung_deutsch":"Walnuß","baumtyp":"Laub","bemerkung":null,"pflanzjahr":null,"entnahmejahr":null,"marker-size":"small","marker-symbol":"park2","marker-color":"#A3DDAD"},"geometry":{"type":"Point","coordinates":[15.40581642964688,47.07196027475483],"bbox":[15.40581642964688,47.07196027475483,15.40581642964688,47.07196027475483]}},{"type":"Feature","properties":{"nummer":39562,"baumbezeichnung_botanisch":"Picea abies","baumbezeichnung_deutsch":"Rotfichte","baumtyp":"Nadel","bemerkung":null,"pflanzjahr":null,"entnahmejahr":null,"marker-size":"small","marker-symbol":"park","marker-color":"#3BB451"},"geometry":{"type":"Point","coordinates":[15.40617712994484,47.07196320446442],"bbox":[15.40617712994484,47.07196320446442,15.40617712994484,47.07196320446442]}},{"type":"Feature","properties":{"nummer":39564,"baumbezeichnung_botanisch":"Picea abies","baumbezeichnung_deutsch":"Rotfichte","baumtyp":"Nadel","bemerkung":null,"pflanzjahr":null,"entnahmejahr":null,"marker-size":"small","marker-symbol":"park","marker-color":"#3BB451"},"geometry":{"type":"Point","coordinates":[15.40617011372831,47.07199083079473],"bbox":[15.40617011372831,47.07199083079473,15.40617011372831,47.07199083079473]}}]}