{"type":"FeatureCollection","features":[{"type":"Feature","properties":{"nummer":24685,"baumbezeichnung_botanisch":"Aesculus hippocastanum","baumbezeichnung_deutsch":"Gemeine Roßkastanie","baumtyp":"Laub","bemerkung":null,"pflanzjahr":null,"entnahmejahr":null,"marker-size":"small","marker-symbol":"park2","marker-color":"#A3DDAD"},"geometry":{"type":"Point","coordinates":[15.40561108711883,47.0645924240704],"bbox":[15.40561108711883,47.0645924240704,15.40561108711883,47.0645924240704]}},{"type":"Feature","properties":{"nummer":5494,"baumbezeichnung_botanisch":"Aesculus hippocastanum","baumbezeichnung_deutsch":"Gemeine Roßkastanie","baumtyp":"Laub","bemerkung":null,"pflanzjahr":null,"entnahmejahr":null,"marker-size":"small","marker-symbol":"park2","marker-color":"#A3DDAD"},"geometry":{"type":"Point","coordinates":[15.40572220743534,47.06460601545764],"bbox":[15.40572220743534,47.06460601545764,15.40572220743534,47.06460601545764]}},{"type":"Feature","properties":{"nummer":8414,"baumbezeichnung_botanisch":"Aesculus hippocastanum","baumbezeichnung_deutsch":"Gemeine Roßkastanie","baumtyp":"Laub","bemerkung":null,"pflanzjahr":null,"entnahmejahr":null,"marker-size":"small","marker-symbol":"park2","marker-color":"#A3DDAD"},"geometry":{"type":"Point","coordinates":[15.40571624610762,47.06465582690225],"bbox":[15.40571624610762,47.06465582690225,15.40571624610762,47.06465582690225]}},{"type":"Feature","properties":{"nummer":17837,"baumbezeichnung_botanisch":"Aesculus hippocastanum","baumbezeichnung_deutsch":"Gemeine Roßkastanie","baumtyp":"Laub","bemerkung":null,"pflanzjahr":null,"entnahmejahr":null,"marker-size":"small","marker-symbol":"park2","marker-color":"#A3DDAD"},"geometry":{"type":"Point","coordinates":[15.40561475281924,47.06465266350739],"bbox":[15.40561475281924,47.06465266350739,15.40561475281924,47.06465266350739]}}]}