{"type":"FeatureCollection","features":[{"type":"Feature","properties":{"nummer":11067,"baumbezeichnung_botanisch":"Tilia cordata","baumbezeichnung_deutsch":"Winterlinde","baumtyp":"Laub","bemerkung":null,"pflanzjahr":null,"entnahmejahr":null,"marker-size":"small","marker-symbol":"park2","marker-color":"#A3DDAD"},"geometry":{"type":"Point","coordinates":[15.40690424434466,47.05887474417037],"bbox":[15.40690424434466,47.05887474417037,15.40690424434466,47.05887474417037]}},{"type":"Feature","properties":{"nummer":18334,"baumbezeichnung_botanisch":"Tilia cordata","baumbezeichnung_deutsch":"Winterlinde","baumtyp":"Laub","bemerkung":null,"pflanzjahr":null,"entnahmejahr":null,"marker-size":"small","marker-symbol":"park2","marker-color":"#A3DDAD"},"geometry":{"type":"Point","coordinates":[15.40678791128819,47.05888615040426],"bbox":[15.40678791128819,47.05888615040426,15.40678791128819,47.05888615040426]}}]}