{"type":"FeatureCollection","features":[{"type":"Feature","properties":{"nummer":24147,"baumbezeichnung_botanisch":"Quercus robur","baumbezeichnung_deutsch":"Stieleiche","baumtyp":"Laub","bemerkung":null,"pflanzjahr":null,"entnahmejahr":null,"marker-size":"small","marker-symbol":"park2","marker-color":"#A3DDAD"},"geometry":{"type":"Point","coordinates":[15.46806123859611,47.09632389494112],"bbox":[15.46806123859611,47.09632389494112,15.46806123859611,47.09632389494112]}},{"type":"Feature","properties":{"nummer":24145,"baumbezeichnung_botanisch":"Quercus robur","baumbezeichnung_deutsch":"Stieleiche","baumtyp":"Laub","bemerkung":null,"pflanzjahr":null,"entnahmejahr":null,"marker-size":"small","marker-symbol":"park2","marker-color":"#A3DDAD"},"geometry":{"type":"Point","coordinates":[15.46810301713293,47.09634092979958],"bbox":[15.46810301713293,47.09634092979958,15.46810301713293,47.09634092979958]}}]}