{
  "type": "FeatureCollection",
  "features": [
    {
      "type": "Feature",
      "properties": {
        "nummer": 6275,
        "baumbezeichnung_botanisch": "Tilia cordata",
        "baumbezeichnung_deutsch": "Winterlinde",
        "baumtyp": "Laub",
        "altersklassifizierung": "jung",
        "bemerkung": null,
        "pflanzjahr": null,
        "entnahmejahr": null,
        "baumpatenschaft": null,
        "objectid": 5834
      },
      "geometry": {
        "type": "Point",
        "coordinates": [
          15.457442253708894,
          47.06680320835877
        ],
        "bbox": [
          15.457442253708894,
          47.06680320835877,
          15.457442253708894,
          47.06680320835877
        ]
      }
    }
  ]
}