{
  "type": "FeatureCollection",
  "features": [
    {
      "type": "Feature",
      "id": 576,
      "properties": {
        "nummer": 10125,
        "objectid": 576,
        "baumbezeichnung_deutsch": "Gemeine Roßkastanie",
        "baumbezeichnung_botanisch": "Aesculus hippocastanum",
        "baumtyp": "Laub",
        "bemerkung": null,
        "pflanzjahr": null,
        "entnahmejahr": null,
        "baumpatenschaft": null,
        "altersklassifizierung": "mittel"
      },
      "geometry": {
        "type": "Point",
        "coordinates": [
          15.45594756338159,
          47.0738884504596
        ]
      }
    }
  ]
}