{
  "type": "FeatureCollection",
  "features": [
    {
      "type": "Feature",
      "properties": {
        "nummer": 16884,
        "objectid": 1029,
        "baumbezeichnung_deutsch": "Vogelkirsche",
        "baumbezeichnung_botanisch": "Prunus avium",
        "baumtyp": "Laub",
        "bemerkung": null,
        "pflanzjahr": null,
        "entnahmejahr": null,
        "baumpatenschaft": null,
        "altersklassifizierung": "mittel"
      },
      "geometry": {
        "type": "Point",
        "coordinates": [
          15.455770522097868,
          47.05865332781879
        ]
      }
    }
  ]
}