{
  "type": "FeatureCollection",
  "features": [
    {
      "type": "Feature",
      "properties": {
        "NUMMER": 16884,
        "BAUMBEZEICHNUNG_BOTANISCH": "Prunus avium",
        "BAUMBEZEICHNUNG_DEUTSCH": "Vogelkirsche",
        "BAUMTYP": "Laub",
        "BEMERKUNG": null,
        "PFLANZJAHR": null,
        "ENTNAHMEJAHR": null,
        "BAUMPATENSCHAFT": null,
        "ALTERSKLASSIZIERUNG": "mittel",
        "OBJECTID": 1029
      },
      "geometry": {
        "type": "Point",
        "coordinates": [
          15.455770522097868,
          47.05865332781879
        ]
      }
    }
  ]
}