{"type":"FeatureCollection","features":[{"type":"Feature","properties":{"nummer":22555,"baumbezeichnung_botanisch":"Sophora japonica","baumbezeichnung_deutsch":"Schnurbaum","baumtyp":"Laub","bemerkung":null,"pflanzjahr":null,"entnahmejahr":null,"marker-size":"small","marker-symbol":"park2","marker-color":"#A3DDAD"},"geometry":{"type":"Point","coordinates":[15.45641432159032,47.03790316566155],"bbox":[15.45641432159032,47.03790316566155,15.45641432159032,47.03790316566155]}},{"type":"Feature","properties":{"nummer":26064,"baumbezeichnung_botanisch":"Sophora japonica","baumbezeichnung_deutsch":"Schnurbaum","baumtyp":"Laub","bemerkung":null,"pflanzjahr":null,"entnahmejahr":null,"marker-size":"small","marker-symbol":"park2","marker-color":"#A3DDAD"},"geometry":{"type":"Point","coordinates":[15.45629454836138,47.03794781839442],"bbox":[15.45629454836138,47.03794781839442,15.45629454836138,47.03794781839442]}},{"type":"Feature","properties":{"nummer":14631,"baumbezeichnung_botanisch":"Tilia cordata","baumbezeichnung_deutsch":"Winterlinde","baumtyp":"Laub","bemerkung":null,"pflanzjahr":null,"entnahmejahr":null,"marker-size":"small","marker-symbol":"park2","marker-color":"#A3DDAD"},"geometry":{"type":"Point","coordinates":[15.45668548494646,47.03798681292434],"bbox":[15.45668548494646,47.03798681292434,15.45668548494646,47.03798681292434]}},{"type":"Feature","properties":{"nummer":20486,"baumbezeichnung_botanisch":"Tilia cordata","baumbezeichnung_deutsch":"Winterlinde","baumtyp":"Laub","bemerkung":null,"pflanzjahr":null,"entnahmejahr":null,"marker-size":"small","marker-symbol":"park2","marker-color":"#A3DDAD"},"geometry":{"type":"Point","coordinates":[15.45668419110263,47.03805754076135],"bbox":[15.45668419110263,47.03805754076135,15.45668419110263,47.03805754076135]}},{"type":"Feature","properties":{"nummer":4162,"baumbezeichnung_botanisch":"Tilia cordata","baumbezeichnung_deutsch":"Winterlinde","baumtyp":"Laub","bemerkung":null,"pflanzjahr":null,"entnahmejahr":null,"marker-size":"small","marker-symbol":"park2","marker-color":"#A3DDAD"},"geometry":{"type":"Point","coordinates":[15.45668109237852,47.03813000878753],"bbox":[15.45668109237852,47.03813000878753,15.45668109237852,47.03813000878753]}},{"type":"Feature","properties":{"nummer":23050,"baumbezeichnung_botanisch":"Tilia cordata","baumbezeichnung_deutsch":"Winterlinde","baumtyp":"Laub","bemerkung":null,"pflanzjahr":null,"entnahmejahr":null,"marker-size":"small","marker-symbol":"park2","marker-color":"#A3DDAD"},"geometry":{"type":"Point","coordinates":[15.45667630465929,47.03820517137739],"bbox":[15.45667630465929,47.03820517137739,15.45667630465929,47.03820517137739]}},{"type":"Feature","properties":{"nummer":23373,"baumbezeichnung_botanisch":"Fraxinus excelsior 'Diversifolia'","baumbezeichnung_deutsch":"Einblättrige Esche","baumtyp":"Laub","bemerkung":null,"pflanzjahr":"2005","entnahmejahr":null,"marker-size":"small","marker-symbol":"park2","marker-color":"#A3DDAD"},"geometry":{"type":"Point","coordinates":[15.45633354568023,47.03789277903539],"bbox":[15.45633354568023,47.03789277903539,15.45633354568023,47.03789277903539]}},{"type":"Feature","properties":{"nummer":1360,"baumbezeichnung_botanisch":"Quercus sp.","baumbezeichnung_deutsch":"Eiche","baumtyp":"Laub","bemerkung":null,"pflanzjahr":null,"entnahmejahr":null,"marker-size":"small","marker-symbol":"park2","marker-color":"#A3DDAD"},"geometry":{"type":"Point","coordinates":[15.45616712384705,47.0381681943127],"bbox":[15.45616712384705,47.0381681943127,15.45616712384705,47.0381681943127]}},{"type":"Feature","properties":{"nummer":5379,"baumbezeichnung_botanisch":"Quercus sp.","baumbezeichnung_deutsch":"Eiche","baumtyp":"Laub","bemerkung":null,"pflanzjahr":null,"entnahmejahr":null,"marker-size":"small","marker-symbol":"park2","marker-color":"#A3DDAD"},"geometry":{"type":"Point","coordinates":[15.45618226354115,47.03811622790308],"bbox":[15.45618226354115,47.03811622790308,15.45618226354115,47.03811622790308]}},{"type":"Feature","properties":{"nummer":7961,"baumbezeichnung_botanisch":"Quercus sp.","baumbezeichnung_deutsch":"Eiche","baumtyp":"Laub","bemerkung":null,"pflanzjahr":null,"entnahmejahr":null,"marker-size":"small","marker-symbol":"park2","marker-color":"#A3DDAD"},"geometry":{"type":"Point","coordinates":[15.45656977528533,47.03829498726105],"bbox":[15.45656977528533,47.03829498726105,15.45656977528533,47.03829498726105]}}]}