{"type":"FeatureCollection","features":[{"type":"Feature","properties":{"nummer":23384,"baumbezeichnung_botanisch":"Quercus sp.","baumbezeichnung_deutsch":"Eiche","baumtyp":"Laub","altersklassifizierung":"jung","bemerkung":null,"pflanzjahr":null,"entnahmejahr":null,"baumpatenschaft":null,"objectid":2073},"geometry":{"type":"Point","coordinates":[15.456167123847047,47.038168194312696],"bbox":[15.456167123847047,47.038168194312696,15.456167123847047,47.038168194312696]}},{"type":"Feature","properties":{"nummer":5919,"baumbezeichnung_botanisch":"Sophora japonica","baumbezeichnung_deutsch":"Schnurbaum","baumtyp":"Laub","altersklassifizierung":"alt","bemerkung":null,"pflanzjahr":null,"entnahmejahr":null,"baumpatenschaft":null,"objectid":4016},"geometry":{"type":"Point","coordinates":[15.456414321590323,47.037903165661554],"bbox":[15.456414321590323,47.037903165661554,15.456414321590323,47.037903165661554]}},{"type":"Feature","properties":{"nummer":24589,"baumbezeichnung_botanisch":"Fraxinus excelsior 'Diversifolia'","baumbezeichnung_deutsch":"Einblättrige Esche","baumtyp":"Laub","altersklassifizierung":"jung","bemerkung":null,"pflanzjahr":"2005","entnahmejahr":null,"baumpatenschaft":null,"objectid":4381},"geometry":{"type":"Point","coordinates":[15.456333545680229,47.03789277903539],"bbox":[15.456333545680229,47.03789277903539,15.456333545680229,47.03789277903539]}},{"type":"Feature","properties":{"nummer":5920,"baumbezeichnung_botanisch":"Sophora japonica","baumbezeichnung_deutsch":"Schnurbaum","baumtyp":"Laub","altersklassifizierung":"alt","bemerkung":null,"pflanzjahr":null,"entnahmejahr":null,"baumpatenschaft":null,"objectid":12033},"geometry":{"type":"Point","coordinates":[15.456294548361383,47.03794781839442],"bbox":[15.456294548361383,47.03794781839442,15.456294548361383,47.03794781839442]}},{"type":"Feature","properties":{"nummer":5924,"baumbezeichnung_botanisch":"Tilia cordata","baumbezeichnung_deutsch":"Winterlinde","baumtyp":"Laub","altersklassifizierung":"alt","bemerkung":null,"pflanzjahr":null,"entnahmejahr":null,"baumpatenschaft":null,"objectid":12308},"geometry":{"type":"Point","coordinates":[15.456676304659293,47.038205171377385],"bbox":[15.456676304659293,47.038205171377385,15.456676304659293,47.038205171377385]}},{"type":"Feature","properties":{"nummer":5921,"baumbezeichnung_botanisch":"Tilia cordata","baumbezeichnung_deutsch":"Winterlinde","baumtyp":"Laub","altersklassifizierung":"mittel","bemerkung":null,"pflanzjahr":null,"entnahmejahr":null,"baumpatenschaft":null,"objectid":16683},"geometry":{"type":"Point","coordinates":[15.456685484946464,47.03798681292434],"bbox":[15.456685484946464,47.03798681292434,15.456685484946464,47.03798681292434]}},{"type":"Feature","properties":{"nummer":5923,"baumbezeichnung_botanisch":"Tilia cordata","baumbezeichnung_deutsch":"Winterlinde","baumtyp":"Laub","altersklassifizierung":"mittel","bemerkung":null,"pflanzjahr":null,"entnahmejahr":null,"baumpatenschaft":null,"objectid":15119},"geometry":{"type":"Point","coordinates":[15.456681092378515,47.038130008787526],"bbox":[15.456681092378515,47.038130008787526,15.456681092378515,47.038130008787526]}},{"type":"Feature","properties":{"nummer":23386,"baumbezeichnung_botanisch":"Quercus sp.","baumbezeichnung_deutsch":"Eiche","baumtyp":"Laub","altersklassifizierung":"jung","bemerkung":null,"pflanzjahr":null,"entnahmejahr":null,"baumpatenschaft":null,"objectid":14474},"geometry":{"type":"Point","coordinates":[15.456569775285327,47.038294987261054],"bbox":[15.456569775285327,47.038294987261054,15.456569775285327,47.038294987261054]}},{"type":"Feature","properties":{"nummer":23385,"baumbezeichnung_botanisch":"Quercus sp.","baumbezeichnung_deutsch":"Eiche","baumtyp":"Laub","altersklassifizierung":"jung","bemerkung":null,"pflanzjahr":null,"entnahmejahr":null,"baumpatenschaft":null,"objectid":13028},"geometry":{"type":"Point","coordinates":[15.45618226354115,47.038116227903075],"bbox":[15.45618226354115,47.038116227903075,15.45618226354115,47.038116227903075]}},{"type":"Feature","properties":{"nummer":5922,"baumbezeichnung_botanisch":"Tilia cordata","baumbezeichnung_deutsch":"Winterlinde","baumtyp":"Laub","altersklassifizierung":"mittel","bemerkung":null,"pflanzjahr":null,"entnahmejahr":null,"baumpatenschaft":null,"objectid":25747},"geometry":{"type":"Point","coordinates":[15.45668419110263,47.03805754076135],"bbox":[15.45668419110263,47.03805754076135,15.45668419110263,47.03805754076135]}}]}