{"type":"FeatureCollection","features":[{"type":"Feature","properties":{"nummer":26734,"baumbezeichnung_botanisch":"Tilia sp.","baumbezeichnung_deutsch":"Linde","baumtyp":"Laub","bemerkung":null,"pflanzjahr":null,"entnahmejahr":null,"marker-size":"small","marker-symbol":"park2","marker-color":"#A3DDAD"},"geometry":{"type":"Point","coordinates":[15.40855642262775,47.08221229238973],"bbox":[15.40855642262775,47.08221229238973,15.40855642262775,47.08221229238973]}},{"type":"Feature","properties":{"nummer":10369,"baumbezeichnung_botanisch":"Tilia sp.","baumbezeichnung_deutsch":"Linde","baumtyp":"Laub","bemerkung":null,"pflanzjahr":null,"entnahmejahr":null,"marker-size":"small","marker-symbol":"park2","marker-color":"#A3DDAD"},"geometry":{"type":"Point","coordinates":[15.40851023395925,47.08228626259962],"bbox":[15.40851023395925,47.08228626259962,15.40851023395925,47.08228626259962]}},{"type":"Feature","properties":{"nummer":16449,"baumbezeichnung_botanisch":"Tilia sp.","baumbezeichnung_deutsch":"Linde","baumtyp":"Laub","bemerkung":null,"pflanzjahr":null,"entnahmejahr":null,"marker-size":"small","marker-symbol":"park2","marker-color":"#A3DDAD"},"geometry":{"type":"Point","coordinates":[15.40837667726573,47.08225450747673],"bbox":[15.40837667726573,47.08225450747673,15.40837667726573,47.08225450747673]}}]}