{
  "type": "FeatureCollection",
  "features": [
    {
      "type": "Feature",
      "properties": {
        "nummer": 17376,
        "objectid": 640,
        "baumbezeichnung_deutsch": "Eschenahorn",
        "baumbezeichnung_botanisch": "Acer negundo",
        "baumtyp": "Laub",
        "bemerkung": null,
        "pflanzjahr": null,
        "entnahmejahr": null,
        "baumpatenschaft": null,
        "altersklassifizierung": "mittel"
      },
      "geometry": {
        "type": "Point",
        "coordinates": [
          15.410403620116464,
          47.04855219069898
        ]
      }
    }
  ]
}