{
  "type": "FeatureCollection",
  "features": [
    {
      "type": "Feature",
      "properties": {
        "NUMMER": 17376,
        "BAUMBEZEICHNUNG_BOTANISCH": "Acer negundo",
        "BAUMBEZEICHNUNG_DEUTSCH": "Eschenahorn",
        "BAUMTYP": "Laub",
        "BEMERKUNG": null,
        "PFLANZJAHR": null,
        "ENTNAHMEJAHR": null,
        "BAUMPATENSCHAFT": null,
        "ALTERSKLASSIZIERUNG": "mittel",
        "OBJECTID": 640
      },
      "geometry": {
        "type": "Point",
        "coordinates": [
          15.410403620116464,
          47.04855219069898
        ]
      }
    }
  ]
}