{
  "type": "FeatureCollection",
  "features": [
    {
      "type": "Feature",
      "properties": {
        "nummer": 31800,
        "objectid": 1120,
        "baumbezeichnung_deutsch": "Gelbe Pavie",
        "baumbezeichnung_botanisch": "Aesculus flava",
        "baumtyp": "Laub",
        "bemerkung": null,
        "pflanzjahr": "2014",
        "entnahmejahr": null,
        "baumpatenschaft": null,
        "altersklassifizierung": "jung"
      },
      "geometry": {
        "type": "Point",
        "coordinates": [
          15.412259806933333,
          47.039951442568864
        ]
      }
    }
  ]
}