{"type":"FeatureCollection","features":[{"type":"Feature","properties":{"nummer":2101,"baumbezeichnung_botanisch":"Fagus sylvatica","baumbezeichnung_deutsch":"Rotbuche","baumtyp":"Laub","bemerkung":null,"pflanzjahr":null,"entnahmejahr":null,"marker-size":"small","marker-symbol":"park2","marker-color":"#A3DDAD"},"geometry":{"type":"Point","coordinates":[15.45772956183212,47.0685545983804],"bbox":[15.45772956183212,47.0685545983804,15.45772956183212,47.0685545983804]}}]}