{"type":"FeatureCollection","features":[{"type":"Feature","properties":{"nummer":2181,"baumbezeichnung_botanisch":"Tilia cordata","baumbezeichnung_deutsch":"Winterlinde","baumtyp":"Laub","bemerkung":null,"pflanzjahr":null,"entnahmejahr":null,"marker-size":"small","marker-symbol":"park2","marker-color":"#A3DDAD"},"geometry":{"type":"Point","coordinates":[15.45744225370889,47.06680320835877],"bbox":[15.45744225370889,47.06680320835877,15.45744225370889,47.06680320835877]}}]}