{"type":"FeatureCollection","features":[{"type":"Feature","properties":{"nummer":10667,"baumbezeichnung_botanisch":"Tilia cordata","baumbezeichnung_deutsch":"Winterlinde","baumtyp":"Laub","bemerkung":null,"pflanzjahr":"1985","entnahmejahr":null,"marker-size":"small","marker-symbol":"park2","marker-color":"#A3DDAD"},"geometry":{"type":"Point","coordinates":[15.45769312896494,47.06091785146892],"bbox":[15.45769312896494,47.06091785146892,15.45769312896494,47.06091785146892]}},{"type":"Feature","properties":{"nummer":4869,"baumbezeichnung_botanisch":"Tilia cordata","baumbezeichnung_deutsch":"Winterlinde","baumtyp":"Laub","bemerkung":null,"pflanzjahr":"1985","entnahmejahr":null,"marker-size":"small","marker-symbol":"park2","marker-color":"#A3DDAD"},"geometry":{"type":"Point","coordinates":[15.45748037042704,47.06084935498932],"bbox":[15.45748037042704,47.06084935498932,15.45748037042704,47.06084935498932]}},{"type":"Feature","properties":{"nummer":20214,"baumbezeichnung_botanisch":"Tilia cordata 'Erecta'","baumbezeichnung_deutsch":"Winterlinde Erecta","baumtyp":"Laub","bemerkung":null,"pflanzjahr":"1996","entnahmejahr":null,"marker-size":"small","marker-symbol":"park2","marker-color":"#A3DDAD"},"geometry":{"type":"Point","coordinates":[15.45735068701459,47.06080935260115],"bbox":[15.45735068701459,47.06080935260115,15.45735068701459,47.06080935260115]}}]}