{"type":"FeatureCollection","features":[{"type":"Feature","properties":{"nummer":3216,"baumbezeichnung_botanisch":"Tilia sp.","baumbezeichnung_deutsch":"Linde","baumtyp":"Laub","bemerkung":null,"pflanzjahr":"1987","entnahmejahr":null,"marker-size":"small","marker-symbol":"park2","marker-color":"#A3DDAD"},"geometry":{"type":"Point","coordinates":[15.41976059001717,47.07471292004305],"bbox":[15.41976059001717,47.07471292004305,15.41976059001717,47.07471292004305]}},{"type":"Feature","properties":{"nummer":10086,"baumbezeichnung_botanisch":"Tilia sp.","baumbezeichnung_deutsch":"Linde","baumtyp":"Laub","bemerkung":null,"pflanzjahr":"1987","entnahmejahr":null,"marker-size":"small","marker-symbol":"park2","marker-color":"#A3DDAD"},"geometry":{"type":"Point","coordinates":[15.41942976454852,47.07465000519522],"bbox":[15.41942976454852,47.07465000519522,15.41942976454852,47.07465000519522]}}]}