{"type":"FeatureCollection","features":[{"type":"Feature","properties":{"nummer":9865,"baumbezeichnung_botanisch":"Tilia cordata","baumbezeichnung_deutsch":"Winterlinde","baumtyp":"Laub","bemerkung":null,"pflanzjahr":null,"entnahmejahr":null,"marker-size":"small","marker-symbol":"park2","marker-color":"#A3DDAD"},"geometry":{"type":"Point","coordinates":[15.43104879761464,47.08759502310802],"bbox":[15.43104879761464,47.08759502310802,15.43104879761464,47.08759502310802]}}]}