{"type":"FeatureCollection","features":[{"type":"Feature","properties":{"nummer":22438,"baumbezeichnung_botanisch":"Aesculus hippocastanum","baumbezeichnung_deutsch":"Gemeine Roßkastanie","baumtyp":"Laub","bemerkung":null,"pflanzjahr":null,"entnahmejahr":null,"marker-size":"small","marker-symbol":"park2","marker-color":"#A3DDAD"},"geometry":{"type":"Point","coordinates":[15.43163951512615,47.07900280119739],"bbox":[15.43163951512615,47.07900280119739,15.43163951512615,47.07900280119739]}},{"type":"Feature","properties":{"nummer":22863,"baumbezeichnung_botanisch":"Aesculus hippocastanum","baumbezeichnung_deutsch":"Gemeine Roßkastanie","baumtyp":"Laub","bemerkung":null,"pflanzjahr":null,"entnahmejahr":null,"marker-size":"small","marker-symbol":"park2","marker-color":"#A3DDAD"},"geometry":{"type":"Point","coordinates":[15.43160298612284,47.07906981387046],"bbox":[15.43160298612284,47.07906981387046,15.43160298612284,47.07906981387046]}},{"type":"Feature","properties":{"nummer":21632,"baumbezeichnung_botanisch":"Aesculus hippocastanum","baumbezeichnung_deutsch":"Gemeine Roßkastanie","baumtyp":"Laub","bemerkung":null,"pflanzjahr":null,"entnahmejahr":null,"marker-size":"small","marker-symbol":"park2","marker-color":"#A3DDAD"},"geometry":{"type":"Point","coordinates":[15.43156745354471,47.07913240882228],"bbox":[15.43156745354471,47.07913240882228,15.43156745354471,47.07913240882228]}},{"type":"Feature","properties":{"nummer":15928,"baumbezeichnung_botanisch":"Aesculus hippocastanum","baumbezeichnung_deutsch":"Gemeine Roßkastanie","baumtyp":"Laub","bemerkung":null,"pflanzjahr":null,"entnahmejahr":null,"marker-size":"small","marker-symbol":"park2","marker-color":"#A3DDAD"},"geometry":{"type":"Point","coordinates":[15.43152925226409,47.07918462934475],"bbox":[15.43152925226409,47.07918462934475,15.43152925226409,47.07918462934475]}},{"type":"Feature","properties":{"nummer":17118,"baumbezeichnung_botanisch":"Aesculus hippocastanum","baumbezeichnung_deutsch":"Gemeine Roßkastanie","baumtyp":"Laub","bemerkung":null,"pflanzjahr":null,"entnahmejahr":null,"marker-size":"small","marker-symbol":"park2","marker-color":"#A3DDAD"},"geometry":{"type":"Point","coordinates":[15.43150305493508,47.07922080750461],"bbox":[15.43150305493508,47.07922080750461,15.43150305493508,47.07922080750461]}}]}