{"type":"FeatureCollection","features":[{"type":"Feature","properties":{"nummer":27467,"baumbezeichnung_botanisch":"Gleditsia triacanthos 'Inermis'","baumbezeichnung_deutsch":"dornenloser Christusdorn","baumtyp":"Laub","bemerkung":null,"pflanzjahr":"2007","entnahmejahr":null,"marker-size":"small","marker-symbol":"park2","marker-color":"#A3DDAD"},"geometry":{"type":"Point","coordinates":[15.43162252962577,47.06546295041353],"bbox":[15.43162252962577,47.06546295041353,15.43162252962577,47.06546295041353]}}]}