{"type":"FeatureCollection","features":[{"type":"Feature","properties":{"nummer":6498,"baumbezeichnung_botanisch":"Fraxinus excelsior 'Globosum'","baumbezeichnung_deutsch":"Kugelesche","baumtyp":"Laub","bemerkung":null,"pflanzjahr":null,"entnahmejahr":null,"marker-size":"small","marker-symbol":"park2","marker-color":"#A3DDAD"},"geometry":{"type":"Point","coordinates":[15.43057404060659,47.05794611424008],"bbox":[15.43057404060659,47.05794611424008,15.43057404060659,47.05794611424008]}},{"type":"Feature","properties":{"nummer":21732,"baumbezeichnung_botanisch":"Fraxinus excelsior 'Globosum'","baumbezeichnung_deutsch":"Kugelesche","baumtyp":"Laub","bemerkung":null,"pflanzjahr":null,"entnahmejahr":null,"marker-size":"small","marker-symbol":"park2","marker-color":"#A3DDAD"},"geometry":{"type":"Point","coordinates":[15.43056466936497,47.05788514411638],"bbox":[15.43056466936497,47.05788514411638,15.43056466936497,47.05788514411638]}},{"type":"Feature","properties":{"nummer":26390,"baumbezeichnung_botanisch":"Fraxinus excelsior 'Globosum'","baumbezeichnung_deutsch":"Kugelesche","baumtyp":"Laub","bemerkung":null,"pflanzjahr":null,"entnahmejahr":null,"marker-size":"small","marker-symbol":"park2","marker-color":"#A3DDAD"},"geometry":{"type":"Point","coordinates":[15.43054055723162,47.05778944332246],"bbox":[15.43054055723162,47.05778944332246,15.43054055723162,47.05778944332246]}},{"type":"Feature","properties":{"nummer":4852,"baumbezeichnung_botanisch":"Fraxinus excelsior 'Globosum'","baumbezeichnung_deutsch":"Kugelesche","baumtyp":"Laub","bemerkung":null,"pflanzjahr":null,"entnahmejahr":null,"marker-size":"small","marker-symbol":"park2","marker-color":"#A3DDAD"},"geometry":{"type":"Point","coordinates":[15.43052617034659,47.05772805483465],"bbox":[15.43052617034659,47.05772805483465,15.43052617034659,47.05772805483465]}},{"type":"Feature","properties":{"nummer":12663,"baumbezeichnung_botanisch":"Fraxinus excelsior 'Globosum'","baumbezeichnung_deutsch":"Kugelesche","baumtyp":"Laub","bemerkung":null,"pflanzjahr":"2011","entnahmejahr":null,"marker-size":"small","marker-symbol":"park2","marker-color":"#A3DDAD"},"geometry":{"type":"Point","coordinates":[15.43051228929704,47.05766711110528],"bbox":[15.43051228929704,47.05766711110528,15.43051228929704,47.05766711110528]}}]}