{"type":"FeatureCollection","features":[{"type":"Feature","properties":{"nummer":32955,"baumbezeichnung_botanisch":"Gleditsia triacanthos 'Inermis'","baumbezeichnung_deutsch":"dornenloser Christusdorn","baumtyp":"Laub","bemerkung":null,"pflanzjahr":"2009","entnahmejahr":null,"marker-size":"small","marker-symbol":"park2","marker-color":"#A3DDAD"},"geometry":{"type":"Point","coordinates":[15.43333412537936,47.09917419921278],"bbox":[15.43333412537936,47.09917419921278,15.43333412537936,47.09917419921278]}},{"type":"Feature","properties":{"nummer":32946,"baumbezeichnung_botanisch":"Gleditsia triacanthos 'Inermis'","baumbezeichnung_deutsch":"dornenloser Christusdorn","baumtyp":"Laub","bemerkung":null,"pflanzjahr":"2009","entnahmejahr":null,"marker-size":"small","marker-symbol":"park2","marker-color":"#A3DDAD"},"geometry":{"type":"Point","coordinates":[15.43325363669995,47.09928801500173],"bbox":[15.43325363669995,47.09928801500173,15.43325363669995,47.09928801500173]}}]}