{"type":"FeatureCollection","features":[{"type":"Feature","properties":{"nummer":16529,"baumbezeichnung_botanisch":"Pseudotsuga menziesii","baumbezeichnung_deutsch":"Küsten - Douglasie, Grüne Douglasie","baumtyp":"Nadel","bemerkung":null,"pflanzjahr":null,"entnahmejahr":null,"marker-size":"small","marker-symbol":"park","marker-color":"#3BB451"},"geometry":{"type":"Point","coordinates":[15.43441361047657,47.05424793770324],"bbox":[15.43441361047657,47.05424793770324,15.43441361047657,47.05424793770324]}}]}