{"type":"FeatureCollection","features":[{"type":"Feature","properties":{"nummer":29255,"baumbezeichnung_botanisch":"Acer pseudoplatanus","baumbezeichnung_deutsch":"Bergahorn","baumtyp":"Laub","bemerkung":null,"pflanzjahr":null,"entnahmejahr":null,"marker-size":"small","marker-symbol":"park2","marker-color":"#A3DDAD"},"geometry":{"type":"Point","coordinates":[15.43318938793362,47.05882454474293],"bbox":[15.43318938793362,47.05882454474293,15.43318938793362,47.05882454474293]}},{"type":"Feature","properties":{"nummer":26579,"baumbezeichnung_botanisch":"Acer pseudoplatanus","baumbezeichnung_deutsch":"Bergahorn","baumtyp":"Laub","bemerkung":null,"pflanzjahr":null,"entnahmejahr":null,"marker-size":"small","marker-symbol":"park2","marker-color":"#A3DDAD"},"geometry":{"type":"Point","coordinates":[15.43306493988438,47.05881354283874],"bbox":[15.43306493988438,47.05881354283874,15.43306493988438,47.05881354283874]}}]}