{
  "type": "FeatureCollection",
  "features": [
    {
      "type": "Feature",
      "properties": {
        "Naturdenkmal": true,
        "Naturdenkmal_Eigentum": "öffentlich",
        "nummer": "Naturdenkmal-88",
        "objectid": "Naturdenkmal-94",
        "baumbezeichnung_deutsch": "Roßkastanie",
        "baumbezeichnung_botanisch": "Aesculus hippocastanum"
      },
      "geometry": {
        "type": "Point",
        "coordinates": [
          15.462289627523992,
          47.065854122054915
        ]
      }
    }
  ]
}