{
  "type": "FeatureCollection",
  "features": [
    {
      "type": "Feature",
      "properties": {
        "nummer": 8777,
        "objectid": 1013,
        "baumbezeichnung_deutsch": "Spitzahorn",
        "baumbezeichnung_botanisch": "Acer platanoides",
        "baumtyp": "Laub",
        "bemerkung": null,
        "pflanzjahr": "1986",
        "entnahmejahr": null,
        "baumpatenschaft": null,
        "altersklassifizierung": "jung"
      },
      "geometry": {
        "type": "Point",
        "coordinates": [
          15.462617622145713,
          47.0569295760565
        ]
      }
    }
  ]
}