{
  "type": "FeatureCollection",
  "features": [
    {
      "type": "Feature",
      "properties": {
        "NUMMER": 19953,
        "BAUMBEZEICHNUNG_BOTANISCH": "Robinia pseudoacacia 'Umbraculifera'",
        "BAUMBEZEICHNUNG_DEUTSCH": "Kugelakazie",
        "BAUMTYP": "Laub",
        "BEMERKUNG": null,
        "PFLANZJAHR": "1996",
        "ENTNAHMEJAHR": null,
        "BAUMPATENSCHAFT": null,
        "ALTERSKLASSIZIERUNG": "jung",
        "OBJECTID": 568
      },
      "geometry": {
        "type": "Point",
        "coordinates": [
          15.42855816126678,
          47.07684032333891
        ]
      }
    }
  ]
}