{
  "type": "FeatureCollection",
  "features": [
    {
      "type": "Feature",
      "id": 1085,
      "properties": {
        "nummer": 27584,
        "objectid": 1085,
        "baumbezeichnung_deutsch": "Walnuß",
        "baumbezeichnung_botanisch": "Juglans regia",
        "baumtyp": "Laub",
        "bemerkung": null,
        "pflanzjahr": "2007",
        "entnahmejahr": null,
        "baumpatenschaft": null,
        "altersklassifizierung": "jung"
      },
      "geometry": {
        "type": "Point",
        "coordinates": [
          15.430160517284861,
          47.07009465132202
        ]
      }
    }
  ]
}