{
  "type": "FeatureCollection",
  "features": [
    {
      "type": "Feature",
      "properties": {
        "NUMMER": 27584,
        "BAUMBEZEICHNUNG_BOTANISCH": "Juglans regia",
        "BAUMBEZEICHNUNG_DEUTSCH": "Walnuß",
        "BAUMTYP": "Laub",
        "BEMERKUNG": null,
        "PFLANZJAHR": "2007",
        "ENTNAHMEJAHR": null,
        "BAUMPATENSCHAFT": null,
        "ALTERSKLASSIZIERUNG": "jung",
        "OBJECTID": 1085
      },
      "geometry": {
        "type": "Point",
        "coordinates": [
          15.430160517284861,
          47.07009465132202
        ]
      }
    }
  ]
}