{"type":"FeatureCollection","features":[{"type":"Feature","properties":{"nummer":16885,"baumbezeichnung_botanisch":"Tilia cordata","baumbezeichnung_deutsch":"Winterlinde","baumtyp":"Laub","bemerkung":null,"pflanzjahr":null,"entnahmejahr":null,"marker-size":"small","marker-symbol":"park2","marker-color":"#A3DDAD"},"geometry":{"type":"Point","coordinates":[15.42803898085673,47.06199832434691],"bbox":[15.42803898085673,47.06199832434691,15.42803898085673,47.06199832434691]}},{"type":"Feature","properties":{"nummer":17019,"baumbezeichnung_botanisch":"Tilia cordata","baumbezeichnung_deutsch":"Winterlinde","baumtyp":"Laub","bemerkung":null,"pflanzjahr":null,"entnahmejahr":null,"marker-size":"small","marker-symbol":"park2","marker-color":"#A3DDAD"},"geometry":{"type":"Point","coordinates":[15.42797060093422,47.0620670417013],"bbox":[15.42797060093422,47.0620670417013,15.42797060093422,47.0620670417013]}},{"type":"Feature","properties":{"nummer":17022,"baumbezeichnung_botanisch":"Tilia cordata","baumbezeichnung_deutsch":"Winterlinde","baumtyp":"Laub","bemerkung":null,"pflanzjahr":null,"entnahmejahr":null,"marker-size":"small","marker-symbol":"park2","marker-color":"#A3DDAD"},"geometry":{"type":"Point","coordinates":[15.42793996788734,47.06213479277385],"bbox":[15.42793996788734,47.06213479277385,15.42793996788734,47.06213479277385]}},{"type":"Feature","properties":{"nummer":17231,"baumbezeichnung_botanisch":"Populus nigra","baumbezeichnung_deutsch":"Schwarzpappel","baumtyp":"Laub","bemerkung":null,"pflanzjahr":null,"entnahmejahr":null,"marker-size":"small","marker-symbol":"park2","marker-color":"#A3DDAD"},"geometry":{"type":"Point","coordinates":[15.42789180772429,47.06214952079335],"bbox":[15.42789180772429,47.06214952079335,15.42789180772429,47.06214952079335]}},{"type":"Feature","properties":{"nummer":17233,"baumbezeichnung_botanisch":"Prunus avium","baumbezeichnung_deutsch":"Vogelkirsche","baumtyp":"Laub","bemerkung":null,"pflanzjahr":null,"entnahmejahr":null,"marker-size":"small","marker-symbol":"park2","marker-color":"#A3DDAD"},"geometry":{"type":"Point","coordinates":[15.42789467908734,47.06219739213917],"bbox":[15.42789467908734,47.06219739213917,15.42789467908734,47.06219739213917]}},{"type":"Feature","properties":{"nummer":16626,"baumbezeichnung_botanisch":"Prunus 'Frucht'","baumbezeichnung_deutsch":"Fruchtkirsche","baumtyp":"Laub","bemerkung":null,"pflanzjahr":null,"entnahmejahr":null,"marker-size":"small","marker-symbol":"park2","marker-color":"#A3DDAD"},"geometry":{"type":"Point","coordinates":[15.42784354418547,47.06233524225647],"bbox":[15.42784354418547,47.06233524225647,15.42784354418547,47.06233524225647]}}]}