{
  "type": "FeatureCollection",
  "features": [
    {
      "type": "Feature",
      "properties": {
        "nummer": 19953,
        "objectid": 568,
        "baumbezeichnung_deutsch": "Kugelakazie",
        "baumbezeichnung_botanisch": "Robinia pseudoacacia 'Umbraculifera'",
        "baumtyp": "Laub",
        "bemerkung": null,
        "pflanzjahr": "1996",
        "entnahmejahr": null,
        "baumpatenschaft": null,
        "altersklassifizierung": "jung"
      },
      "geometry": {
        "type": "Point",
        "coordinates": [
          15.42855816126678,
          47.07684032333891
        ]
      }
    }
  ]
}