{
  "type": "FeatureCollection",
  "features": [
    {
      "type": "Feature",
      "properties": {
        "nummer": 21098,
        "objectid": 740,
        "baumbezeichnung_deutsch": "Kugelakazie",
        "baumbezeichnung_botanisch": "Robinia pseudoacacia 'Umbraculifera'",
        "baumtyp": "Laub",
        "bemerkung": null,
        "pflanzjahr": null,
        "entnahmejahr": null,
        "baumpatenschaft": null,
        "altersklassifizierung": "jung"
      },
      "geometry": {
        "type": "Point",
        "coordinates": [
          15.428815855716234,
          47.0578953131487
        ]
      }
    },
    {
      "type": "Feature",
      "properties": {
        "nummer": 21109,
        "objectid": 1261,
        "baumbezeichnung_deutsch": "Japanische Blütenkirsche",
        "baumbezeichnung_botanisch": "Prunus serrulata 'Kanzan'",
        "baumtyp": "Laub",
        "bemerkung": null,
        "pflanzjahr": null,
        "entnahmejahr": null,
        "baumpatenschaft": null,
        "altersklassifizierung": "mittel"
      },
      "geometry": {
        "type": "Point",
        "coordinates": [
          15.42850273186245,
          47.0578366883481
        ]
      }
    }
  ]
}