{
  "type": "FeatureCollection",
  "features": [
    {
      "type": "Feature",
      "properties": {
        "NUMMER": 21098,
        "BAUMBEZEICHNUNG_BOTANISCH": "Robinia pseudoacacia 'Umbraculifera'",
        "BAUMBEZEICHNUNG_DEUTSCH": "Kugelakazie",
        "BAUMTYP": "Laub",
        "BEMERKUNG": null,
        "PFLANZJAHR": null,
        "ENTNAHMEJAHR": null,
        "BAUMPATENSCHAFT": null,
        "ALTERSKLASSIZIERUNG": "jung",
        "OBJECTID": 740
      },
      "geometry": {
        "type": "Point",
        "coordinates": [
          15.428815855716234,
          47.0578953131487
        ]
      }
    },
    {
      "type": "Feature",
      "properties": {
        "NUMMER": 21109,
        "BAUMBEZEICHNUNG_BOTANISCH": "Prunus serrulata 'Kanzan'",
        "BAUMBEZEICHNUNG_DEUTSCH": "Japanische Blütenkirsche",
        "BAUMTYP": "Laub",
        "BEMERKUNG": null,
        "PFLANZJAHR": null,
        "ENTNAHMEJAHR": null,
        "BAUMPATENSCHAFT": null,
        "ALTERSKLASSIZIERUNG": "mittel",
        "OBJECTID": 1261
      },
      "geometry": {
        "type": "Point",
        "coordinates": [
          15.42850273186245,
          47.0578366883481
        ]
      }
    }
  ]
}