{"type":"FeatureCollection","features":[{"type":"Feature","properties":{"nummer":5197,"baumbezeichnung_botanisch":"Fraxinus ornus","baumbezeichnung_deutsch":"Blumenesche","baumtyp":"Laub","bemerkung":null,"pflanzjahr":"2010","entnahmejahr":null,"marker-size":"small","marker-symbol":"park2","marker-color":"#A3DDAD"},"geometry":{"type":"Point","coordinates":[15.47798485520112,47.05016481377166],"bbox":[15.47798485520112,47.05016481377166,15.47798485520112,47.05016481377166]}},{"type":"Feature","properties":{"nummer":415,"baumbezeichnung_botanisch":"Fraxinus ornus","baumbezeichnung_deutsch":"Blumenesche","baumtyp":"Laub","bemerkung":null,"pflanzjahr":"2010","entnahmejahr":null,"marker-size":"small","marker-symbol":"park2","marker-color":"#A3DDAD"},"geometry":{"type":"Point","coordinates":[15.47774860800414,47.05003754681033],"bbox":[15.47774860800414,47.05003754681033,15.47774860800414,47.05003754681033]}},{"type":"Feature","properties":{"nummer":6813,"baumbezeichnung_botanisch":"Fraxinus ornus","baumbezeichnung_deutsch":"Blumenesche","baumtyp":"Laub","bemerkung":null,"pflanzjahr":"2010","entnahmejahr":null,"marker-size":"small","marker-symbol":"park2","marker-color":"#A3DDAD"},"geometry":{"type":"Point","coordinates":[15.47726964003558,47.0498426472635],"bbox":[15.47726964003558,47.0498426472635,15.47726964003558,47.0498426472635]}},{"type":"Feature","properties":{"nummer":25439,"baumbezeichnung_botanisch":"Fraxinus ornus","baumbezeichnung_deutsch":"Blumenesche","baumtyp":"Laub","bemerkung":null,"pflanzjahr":"2010","entnahmejahr":null,"marker-size":"small","marker-symbol":"park2","marker-color":"#A3DDAD"},"geometry":{"type":"Point","coordinates":[15.47705093969822,47.04974269910023],"bbox":[15.47705093969822,47.04974269910023,15.47705093969822,47.04974269910023]}},{"type":"Feature","properties":{"nummer":379,"baumbezeichnung_botanisch":"Fraxinus ornus","baumbezeichnung_deutsch":"Blumenesche","baumtyp":"Laub","bemerkung":null,"pflanzjahr":"2010","entnahmejahr":null,"marker-size":"small","marker-symbol":"park2","marker-color":"#A3DDAD"},"geometry":{"type":"Point","coordinates":[15.47682871486012,47.04964739793162],"bbox":[15.47682871486012,47.04964739793162,15.47682871486012,47.04964739793162]}},{"type":"Feature","properties":{"nummer":18046,"baumbezeichnung_botanisch":"Fraxinus ornus","baumbezeichnung_deutsch":"Blumenesche","baumtyp":"Laub","bemerkung":null,"pflanzjahr":"2010","entnahmejahr":null,"marker-size":"small","marker-symbol":"park2","marker-color":"#A3DDAD"},"geometry":{"type":"Point","coordinates":[15.4766200875798,47.0495584401053],"bbox":[15.4766200875798,47.0495584401053,15.4766200875798,47.0495584401053]}},{"type":"Feature","properties":{"nummer":10301,"baumbezeichnung_botanisch":"Fraxinus ornus","baumbezeichnung_deutsch":"Blumenesche","baumtyp":"Laub","bemerkung":null,"pflanzjahr":"2010","entnahmejahr":null,"marker-size":"small","marker-symbol":"park2","marker-color":"#A3DDAD"},"geometry":{"type":"Point","coordinates":[15.47639349879959,47.04945062010781],"bbox":[15.47639349879959,47.04945062010781,15.47639349879959,47.04945062010781]}},{"type":"Feature","properties":{"nummer":6053,"baumbezeichnung_botanisch":"Fraxinus ornus","baumbezeichnung_deutsch":"Blumenesche","baumtyp":"Laub","bemerkung":null,"pflanzjahr":"2010","entnahmejahr":null,"marker-size":"small","marker-symbol":"park2","marker-color":"#A3DDAD"},"geometry":{"type":"Point","coordinates":[15.47617127635646,47.04935531767405],"bbox":[15.47617127635646,47.04935531767405,15.47617127635646,47.04935531767405]}}]}