{
  "type": "FeatureCollection",
  "features": [
    {
      "type": "Feature",
      "properties": {
        "nummer": 15446,
        "objectid": 1349,
        "baumbezeichnung_deutsch": "Esche",
        "baumbezeichnung_botanisch": "Fraxinus excelsior",
        "baumtyp": "Laub",
        "bemerkung": null,
        "pflanzjahr": null,
        "entnahmejahr": null,
        "baumpatenschaft": null,
        "altersklassifizierung": "alt"
      },
      "geometry": {
        "type": "Point",
        "coordinates": [
          15.430807141863147,
          47.070097344087415
        ]
      }
    }
  ]
}