{
  "type": "FeatureCollection",
  "features": [
    {
      "type": "Feature",
      "properties": {
        "NUMMER": 15446,
        "BAUMBEZEICHNUNG_BOTANISCH": "Fraxinus excelsior",
        "BAUMBEZEICHNUNG_DEUTSCH": "Esche",
        "BAUMTYP": "Laub",
        "BEMERKUNG": null,
        "PFLANZJAHR": null,
        "ENTNAHMEJAHR": null,
        "BAUMPATENSCHAFT": null,
        "ALTERSKLASSIZIERUNG": "alt",
        "OBJECTID": 1349
      },
      "geometry": {
        "type": "Point",
        "coordinates": [
          15.430807141863147,
          47.070097344087415
        ]
      }
    }
  ]
}