{
  "type": "FeatureCollection",
  "features": [
    {
      "type": "Feature",
      "properties": {
        "nummer": 10908,
        "baumbezeichnung_botanisch": "Tilia x europaea",
        "baumbezeichnung_deutsch": "Holländische Linde",
        "baumtyp": "Laub",
        "altersklassifizierung": "mittel",
        "bemerkung": null,
        "pflanzjahr": "1986",
        "entnahmejahr": null,
        "baumpatenschaft": null,
        "objectid": 25096
      },
      "geometry": {
        "type": "Point",
        "coordinates": [
          15.431990041213675,
          47.067186537911816
        ]
      }
    }
  ]
}