{
  "type": "FeatureCollection",
  "features": [
    {
      "type": "Feature",
      "properties": {
        "NUMMER": 10957,
        "BAUMBEZEICHNUNG_BOTANISCH": "Platanus x acerifolia",
        "BAUMBEZEICHNUNG_DEUTSCH": "Platane",
        "BAUMTYP": "Laub",
        "BEMERKUNG": null,
        "PFLANZJAHR": "1984",
        "ENTNAHMEJAHR": null,
        "BAUMPATENSCHAFT": "Grazer Wechselseitige Versicherung",
        "ALTERSKLASSIZIERUNG": "mittel",
        "OBJECTID": 979
      },
      "geometry": {
        "type": "Point",
        "coordinates": [
          15.431585585856167,
          47.05388735125558
        ]
      }
    }
  ]
}