{"type":"FeatureCollection","features":[{"type":"Feature","properties":{"nummer":10957,"baumbezeichnung_botanisch":"Platanus x acerifolia","baumbezeichnung_deutsch":"Platane","baumtyp":"Laub","altersklassifizierung":"mittel","bemerkung":null,"pflanzjahr":"1984","entnahmejahr":null,"baumpatenschaft":"Grazer Wechselseitige Versicherung","objectid":979},"geometry":{"type":"Point","coordinates":[15.431591396654747,47.053887283974454],"bbox":[15.431591396654747,47.053887283974454,15.431591396654747,47.053887283974454]}},{"type":"Feature","properties":{"nummer":21793,"baumbezeichnung_botanisch":"Platanus x acerifolia","baumbezeichnung_deutsch":"Platane","baumtyp":"Laub","altersklassifizierung":"jung","bemerkung":null,"pflanzjahr":"1999","entnahmejahr":null,"baumpatenschaft":"Erste Allgemeine Versicherungs-AG","objectid":5203},"geometry":{"type":"Point","coordinates":[15.431755235413137,47.0538979239711],"bbox":[15.431755235413137,47.0538979239711,15.431755235413137,47.0538979239711]}},{"type":"Feature","properties":{"nummer":10959,"baumbezeichnung_botanisch":"Platanus x acerifolia","baumbezeichnung_deutsch":"Platane","baumtyp":"Laub","altersklassifizierung":"mittel","bemerkung":null,"pflanzjahr":"1984","entnahmejahr":null,"baumpatenschaft":"Dir. Ferdinand Ackerl, Wiener Allianz Versicherungs-AG","objectid":10768},"geometry":{"type":"Point","coordinates":[15.431144681668481,47.053864747752286],"bbox":[15.431144681668481,47.053864747752286,15.431144681668481,47.053864747752286]}},{"type":"Feature","properties":{"nummer":21792,"baumbezeichnung_botanisch":"Platanus x acerifolia","baumbezeichnung_deutsch":"Platane","baumtyp":"Laub","altersklassifizierung":"jung","bemerkung":null,"pflanzjahr":null,"entnahmejahr":null,"baumpatenschaft":null,"objectid":9001},"geometry":{"type":"Point","coordinates":[15.430450649862467,47.05382741796435],"bbox":[15.430450649862467,47.05382741796435,15.430450649862467,47.05382741796435]}},{"type":"Feature","properties":{"nummer":10962,"baumbezeichnung_botanisch":"Platanus x acerifolia","baumbezeichnung_deutsch":"Platane","baumtyp":"Laub","altersklassifizierung":"jung","bemerkung":null,"pflanzjahr":"1984","entnahmejahr":null,"baumpatenschaft":null,"objectid":14186},"geometry":{"type":"Point","coordinates":[15.430613841794282,47.05383581469416],"bbox":[15.430613841794282,47.05383581469416,15.430613841794282,47.05383581469416]}},{"type":"Feature","properties":{"nummer":10961,"baumbezeichnung_botanisch":"Platanus x acerifolia","baumbezeichnung_deutsch":"Platane","baumtyp":"Laub","altersklassifizierung":"mittel","bemerkung":null,"pflanzjahr":"1984","entnahmejahr":null,"baumpatenschaft":null,"objectid":15034},"geometry":{"type":"Point","coordinates":[15.430790828664895,47.05384566952473],"bbox":[15.430790828664895,47.05384566952473,15.430790828664895,47.05384566952473]}},{"type":"Feature","properties":{"nummer":10960,"baumbezeichnung_botanisch":"Platanus x acerifolia","baumbezeichnung_deutsch":"Platane","baumtyp":"Laub","altersklassifizierung":"mittel","bemerkung":null,"pflanzjahr":"1984","entnahmejahr":null,"baumpatenschaft":null,"objectid":24016},"geometry":{"type":"Point","coordinates":[15.430949950327262,47.05385349388809],"bbox":[15.430949950327262,47.05385349388809,15.430949950327262,47.05385349388809]}},{"type":"Feature","properties":{"nummer":10963,"baumbezeichnung_botanisch":"Ailanthus altissima","baumbezeichnung_deutsch":"Götterbaum","baumtyp":"Laub","altersklassifizierung":"mittel","bemerkung":null,"pflanzjahr":null,"entnahmejahr":null,"baumpatenschaft":null,"objectid":19331},"geometry":{"type":"Point","coordinates":[15.430541889809938,47.05384891827989],"bbox":[15.430541889809938,47.05384891827989,15.430541889809938,47.05384891827989]}},{"type":"Feature","properties":{"nummer":15508,"baumbezeichnung_botanisch":"Fraxinus excelsior 'Globosum'","baumbezeichnung_deutsch":"Kugelesche","baumtyp":"Laub","altersklassifizierung":"mittel","bemerkung":null,"pflanzjahr":null,"entnahmejahr":null,"baumpatenschaft":null,"objectid":19747},"geometry":{"type":"Point","coordinates":[15.432379175056093,47.053480797169335],"bbox":[15.432379175056093,47.053480797169335,15.432379175056093,47.053480797169335]}},{"type":"Feature","properties":{"nummer":10958,"baumbezeichnung_botanisch":"Platanus x acerifolia","baumbezeichnung_deutsch":"Platane","baumtyp":"Laub","altersklassifizierung":"mittel","bemerkung":null,"pflanzjahr":"1984","entnahmejahr":null,"baumpatenschaft":"Konsul Kurt Brühl","objectid":25856},"geometry":{"type":"Point","coordinates":[15.431370343055198,47.053875975816254],"bbox":[15.431370343055198,47.053875975816254,15.431370343055198,47.053875975816254]}}]}