{
  "type": "FeatureCollection",
  "features": [
    {
      "type": "Feature",
      "properties": {
        "nummer": 12791,
        "baumbezeichnung_botanisch": "Platanus x acerifolia",
        "baumbezeichnung_deutsch": "Platane",
        "baumtyp": "Laub",
        "altersklassifizierung": "mittel",
        "bemerkung": null,
        "pflanzjahr": null,
        "entnahmejahr": null,
        "baumpatenschaft": null,
        "objectid": 4144
      },
      "geometry": {
        "type": "Point",
        "coordinates": [
          15.430824532599296,
          47.04580560709235
        ]
      }
    },
    {
      "type": "Feature",
      "properties": {
        "nummer": 12786,
        "baumbezeichnung_botanisch": "Platanus x acerifolia",
        "baumbezeichnung_deutsch": "Platane",
        "baumtyp": "Laub",
        "altersklassifizierung": "mittel",
        "bemerkung": null,
        "pflanzjahr": null,
        "entnahmejahr": null,
        "baumpatenschaft": null,
        "objectid": 5481
      },
      "geometry": {
        "type": "Point",
        "coordinates": [
          15.432199376877852,
          47.045965049945494
        ]
      }
    },
    {
      "type": "Feature",
      "properties": {
        "nummer": 12785,
        "baumbezeichnung_botanisch": "Platanus x acerifolia",
        "baumbezeichnung_deutsch": "Platane",
        "baumtyp": "Laub",
        "altersklassifizierung": "mittel",
        "bemerkung": null,
        "pflanzjahr": null,
        "entnahmejahr": null,
        "baumpatenschaft": null,
        "objectid": 16881
      },
      "geometry": {
        "type": "Point",
        "coordinates": [
          15.432442109281778,
          47.0459944720283
        ]
      }
    },
    {
      "type": "Feature",
      "properties": {
        "nummer": 12788,
        "baumbezeichnung_botanisch": "Platanus x acerifolia",
        "baumbezeichnung_deutsch": "Platane",
        "baumtyp": "Laub",
        "altersklassifizierung": "mittel",
        "bemerkung": null,
        "pflanzjahr": null,
        "entnahmejahr": null,
        "baumpatenschaft": null,
        "objectid": 18531
      },
      "geometry": {
        "type": "Point",
        "coordinates": [
          15.431558306755575,
          47.045893585485956
        ]
      }
    },
    {
      "type": "Feature",
      "properties": {
        "nummer": 12787,
        "baumbezeichnung_botanisch": "Platanus x acerifolia",
        "baumbezeichnung_deutsch": "Platane",
        "baumtyp": "Laub",
        "altersklassifizierung": "mittel",
        "bemerkung": null,
        "pflanzjahr": null,
        "entnahmejahr": null,
        "baumpatenschaft": null,
        "objectid": 18399
      },
      "geometry": {
        "type": "Point",
        "coordinates": [
          15.43183949332714,
          47.04592432996267
        ]
      }
    },
    {
      "type": "Feature",
      "properties": {
        "nummer": 15510,
        "baumbezeichnung_botanisch": "Aesculus hippocastanum",
        "baumbezeichnung_deutsch": "Gemeine Roßkastanie",
        "baumtyp": "Laub",
        "altersklassifizierung": "mittel",
        "bemerkung": null,
        "pflanzjahr": null,
        "entnahmejahr": null,
        "baumpatenschaft": null,
        "objectid": 13255
      },
      "geometry": {
        "type": "Point",
        "coordinates": [
          15.432945778297341,
          47.04582765435952
        ]
      }
    },
    {
      "type": "Feature",
      "properties": {
        "nummer": 12789,
        "baumbezeichnung_botanisch": "Platanus x acerifolia",
        "baumbezeichnung_deutsch": "Platane",
        "baumtyp": "Laub",
        "altersklassifizierung": "mittel",
        "bemerkung": null,
        "pflanzjahr": null,
        "entnahmejahr": null,
        "baumpatenschaft": null,
        "objectid": 23235
      },
      "geometry": {
        "type": "Point",
        "coordinates": [
          15.431311839237395,
          47.04586416709517
        ]
      }
    },
    {
      "type": "Feature",
      "properties": {
        "nummer": 12790,
        "baumbezeichnung_botanisch": "Platanus x acerifolia",
        "baumbezeichnung_deutsch": "Platane",
        "baumtyp": "Laub",
        "altersklassifizierung": "mittel",
        "bemerkung": null,
        "pflanzjahr": null,
        "entnahmejahr": null,
        "baumpatenschaft": null,
        "objectid": 21861
      },
      "geometry": {
        "type": "Point",
        "coordinates": [
          15.431068423381793,
          47.045834844254436
        ]
      }
    }
  ]
}