{
  "type": "FeatureCollection",
  "features": [
    {
      "type": "Feature",
      "properties": {
        "nummer": 10957,
        "objectid": 979,
        "baumbezeichnung_deutsch": "Platane",
        "baumbezeichnung_botanisch": "Platanus x acerifolia",
        "baumtyp": "Laub",
        "bemerkung": null,
        "pflanzjahr": "1984",
        "entnahmejahr": null,
        "baumpatenschaft": "Grazer Wechselseitige Versicherung",
        "altersklassifizierung": "mittel"
      },
      "geometry": {
        "type": "Point",
        "coordinates": [
          15.431585585856167,
          47.05388735125558
        ]
      }
    }
  ]
}