{"type":"FeatureCollection","features":[{"type":"Feature","properties":{"nummer":25858,"baumbezeichnung_botanisch":"Acer platanoides","baumbezeichnung_deutsch":"Spitzahorn","baumtyp":"Laub","bemerkung":null,"pflanzjahr":"1986","entnahmejahr":null,"marker-size":"small","marker-symbol":"park2","marker-color":"#A3DDAD"},"geometry":{"type":"Point","coordinates":[15.46614548627038,47.05842293606019],"bbox":[15.46614548627038,47.05842293606019,15.46614548627038,47.05842293606019]}},{"type":"Feature","properties":{"nummer":3832,"baumbezeichnung_botanisch":"Acer platanoides","baumbezeichnung_deutsch":"Spitzahorn","baumtyp":"Laub","bemerkung":null,"pflanzjahr":"1986","entnahmejahr":null,"marker-size":"small","marker-symbol":"park2","marker-color":"#A3DDAD"},"geometry":{"type":"Point","coordinates":[15.46642614281389,47.05855061263178],"bbox":[15.46642614281389,47.05855061263178,15.46642614281389,47.05855061263178]}},{"type":"Feature","properties":{"nummer":3831,"baumbezeichnung_botanisch":"Acer platanoides","baumbezeichnung_deutsch":"Spitzahorn","baumtyp":"Laub","bemerkung":null,"pflanzjahr":"1986","entnahmejahr":null,"marker-size":"small","marker-symbol":"park2","marker-color":"#A3DDAD"},"geometry":{"type":"Point","coordinates":[15.46656973925565,47.05861424609993],"bbox":[15.46656973925565,47.05861424609993,15.46656973925565,47.05861424609993]}}]}