{
  "type": "FeatureCollection",
  "features": [
    {
      "type": "Feature",
      "id": 626,
      "properties": {
        "nummer": 18318,
        "objectid": 626,
        "baumbezeichnung_deutsch": "Esche",
        "baumbezeichnung_botanisch": "Fraxinus excelsior",
        "baumtyp": "Laub",
        "bemerkung": null,
        "pflanzjahr": null,
        "entnahmejahr": null,
        "baumpatenschaft": null,
        "altersklassifizierung": "mittel"
      },
      "geometry": {
        "type": "Point",
        "coordinates": [
          15.398807240008974,
          47.041794307596284
        ]
      }
    },
    {
      "type": "Feature",
      "id": 644,
      "properties": {
        "nummer": 18344,
        "objectid": 644,
        "baumbezeichnung_deutsch": "Bergahorn",
        "baumbezeichnung_botanisch": "Acer pseudoplatanus",
        "baumtyp": "Laub",
        "bemerkung": null,
        "pflanzjahr": "1984",
        "entnahmejahr": null,
        "baumpatenschaft": "Grazer Wechselseitige Versicherung",
        "altersklassifizierung": "mittel"
      },
      "geometry": {
        "type": "Point",
        "coordinates": [
          15.402424635812455,
          47.04021884498225
        ]
      }
    }
  ]
}