{
  "type": "FeatureCollection",
  "features": [
    {
      "type": "Feature",
      "properties": {
        "NUMMER": 18318,
        "BAUMBEZEICHNUNG_BOTANISCH": "Fraxinus excelsior",
        "BAUMBEZEICHNUNG_DEUTSCH": "Esche",
        "BAUMTYP": "Laub",
        "BEMERKUNG": null,
        "PFLANZJAHR": null,
        "ENTNAHMEJAHR": null,
        "BAUMPATENSCHAFT": null,
        "ALTERSKLASSIZIERUNG": "mittel",
        "OBJECTID": 626
      },
      "geometry": {
        "type": "Point",
        "coordinates": [
          15.398807240008974,
          47.041794307596284
        ]
      }
    },
    {
      "type": "Feature",
      "properties": {
        "NUMMER": 18344,
        "BAUMBEZEICHNUNG_BOTANISCH": "Acer pseudoplatanus",
        "BAUMBEZEICHNUNG_DEUTSCH": "Bergahorn",
        "BAUMTYP": "Laub",
        "BEMERKUNG": null,
        "PFLANZJAHR": "1984",
        "ENTNAHMEJAHR": null,
        "BAUMPATENSCHAFT": "Grazer Wechselseitige Versicherung",
        "ALTERSKLASSIZIERUNG": "mittel",
        "OBJECTID": 644
      },
      "geometry": {
        "type": "Point",
        "coordinates": [
          15.402424635812455,
          47.04021884498225
        ]
      }
    }
  ]
}