{"type":"FeatureCollection","features":[{"type":"Feature","properties":{"nummer":25009,"baumbezeichnung_botanisch":"Acer platanoides","baumbezeichnung_deutsch":"Spitzahorn","baumtyp":"Laub","bemerkung":null,"pflanzjahr":null,"entnahmejahr":null,"marker-size":"small","marker-symbol":"park2","marker-color":"#A3DDAD"},"geometry":{"type":"Point","coordinates":[15.38641617707047,47.04523904975886],"bbox":[15.38641617707047,47.04523904975886,15.38641617707047,47.04523904975886]}},{"type":"Feature","properties":{"nummer":17156,"baumbezeichnung_botanisch":"Acer pseudoplatanus","baumbezeichnung_deutsch":"Bergahorn","baumtyp":"Laub","bemerkung":null,"pflanzjahr":null,"entnahmejahr":null,"marker-size":"small","marker-symbol":"park2","marker-color":"#A3DDAD"},"geometry":{"type":"Point","coordinates":[15.38640649524901,47.04516916716703],"bbox":[15.38640649524901,47.04516916716703,15.38640649524901,47.04516916716703]}},{"type":"Feature","properties":{"nummer":23715,"baumbezeichnung_botanisch":"Acer pseudoplatanus","baumbezeichnung_deutsch":"Bergahorn","baumtyp":"Laub","bemerkung":null,"pflanzjahr":null,"entnahmejahr":null,"marker-size":"small","marker-symbol":"park2","marker-color":"#A3DDAD"},"geometry":{"type":"Point","coordinates":[15.38639840511328,47.04509857816378],"bbox":[15.38639840511328,47.04509857816378,15.38639840511328,47.04509857816378]}},{"type":"Feature","properties":{"nummer":6084,"baumbezeichnung_botanisch":"Acer pseudoplatanus","baumbezeichnung_deutsch":"Bergahorn","baumtyp":"Laub","bemerkung":null,"pflanzjahr":null,"entnahmejahr":null,"marker-size":"small","marker-symbol":"park2","marker-color":"#A3DDAD"},"geometry":{"type":"Point","coordinates":[15.38636816665213,47.04496459929906],"bbox":[15.38636816665213,47.04496459929906,15.38636816665213,47.04496459929906]}}]}