{
  "type": "FeatureCollection",
  "features": [
    {
      "type": "Feature",
      "properties": {
        "nummer": 21024,
        "objectid": 828,
        "baumbezeichnung_deutsch": "Spitzahorn",
        "baumbezeichnung_botanisch": "Acer platanoides",
        "baumtyp": "Laub",
        "bemerkung": null,
        "pflanzjahr": "1984",
        "entnahmejahr": null,
        "baumpatenschaft": null,
        "altersklassifizierung": "mittel"
      },
      "geometry": {
        "type": "Point",
        "coordinates": [
          15.401862187145554,
          47.07618653240515
        ]
      }
    }
  ]
}