{
  "type": "FeatureCollection",
  "features": [
    {
      "type": "Feature",
      "id": 1374,
      "properties": {
        "nummer": 19759,
        "objectid": 1374,
        "baumbezeichnung_deutsch": "Sommerlinde",
        "baumbezeichnung_botanisch": "Tilia platyphyllos",
        "baumtyp": "Laub",
        "bemerkung": null,
        "pflanzjahr": "1995",
        "entnahmejahr": null,
        "baumpatenschaft": null,
        "altersklassifizierung": "jung"
      },
      "geometry": {
        "type": "Point",
        "coordinates": [
          15.400454741435816,
          47.06726974909965
        ]
      }
    }
  ]
}