{"type":"FeatureCollection","features":[{"type":"Feature","properties":{"nummer":27814,"baumbezeichnung_botanisch":"Populus nigra 'Italica'","baumbezeichnung_deutsch":"Säulenpappel","baumtyp":"Laub","bemerkung":null,"pflanzjahr":null,"entnahmejahr":null,"marker-size":"small","marker-symbol":"park2","marker-color":"#A3DDAD"},"geometry":{"type":"Point","coordinates":[15.40025040566499,47.06638578330775],"bbox":[15.40025040566499,47.06638578330775,15.40025040566499,47.06638578330775]}},{"type":"Feature","properties":{"nummer":16005,"baumbezeichnung_botanisch":"Tilia platyphyllos","baumbezeichnung_deutsch":"Sommerlinde","baumtyp":"Laub","bemerkung":null,"pflanzjahr":"1995","entnahmejahr":null,"marker-size":"small","marker-symbol":"park2","marker-color":"#A3DDAD"},"geometry":{"type":"Point","coordinates":[15.40084339634635,47.06727761283749],"bbox":[15.40084339634635,47.06727761283749,15.40084339634635,47.06727761283749]}},{"type":"Feature","properties":{"nummer":10194,"baumbezeichnung_botanisch":"Tilia platyphyllos","baumbezeichnung_deutsch":"Sommerlinde","baumtyp":"Laub","bemerkung":null,"pflanzjahr":"1995","entnahmejahr":null,"marker-size":"small","marker-symbol":"park2","marker-color":"#A3DDAD"},"geometry":{"type":"Point","coordinates":[15.40065885557468,47.06727372536744],"bbox":[15.40065885557468,47.06727372536744,15.40065885557468,47.06727372536744]}},{"type":"Feature","properties":{"nummer":4,"baumbezeichnung_botanisch":"Tilia platyphyllos","baumbezeichnung_deutsch":"Sommerlinde","baumtyp":"Laub","bemerkung":null,"pflanzjahr":"1995","entnahmejahr":null,"marker-size":"small","marker-symbol":"park2","marker-color":"#A3DDAD"},"geometry":{"type":"Point","coordinates":[15.40046038317937,47.06726972466867],"bbox":[15.40046038317937,47.06726972466867,15.40046038317937,47.06726972466867]}}]}