{
  "type": "FeatureCollection",
  "features": [
    {
      "type": "Feature",
      "properties": {
        "NUMMER": 21024,
        "BAUMBEZEICHNUNG_BOTANISCH": "Acer platanoides",
        "BAUMBEZEICHNUNG_DEUTSCH": "Spitzahorn",
        "BAUMTYP": "Laub",
        "BEMERKUNG": null,
        "PFLANZJAHR": "1984",
        "ENTNAHMEJAHR": null,
        "BAUMPATENSCHAFT": null,
        "ALTERSKLASSIZIERUNG": "mittel",
        "OBJECTID": 828
      },
      "geometry": {
        "type": "Point",
        "coordinates": [
          15.401862187145554,
          47.07618653240515
        ]
      }
    }
  ]
}