{
  "type": "FeatureCollection",
  "features": [
    {
      "type": "Feature",
      "properties": {
        "NUMMER": 19759,
        "BAUMBEZEICHNUNG_BOTANISCH": "Tilia platyphyllos",
        "BAUMBEZEICHNUNG_DEUTSCH": "Sommerlinde",
        "BAUMTYP": "Laub",
        "BEMERKUNG": null,
        "PFLANZJAHR": "1995",
        "ENTNAHMEJAHR": null,
        "BAUMPATENSCHAFT": null,
        "ALTERSKLASSIZIERUNG": "jung",
        "OBJECTID": 1374
      },
      "geometry": {
        "type": "Point",
        "coordinates": [
          15.400454741435816,
          47.06726974909965
        ]
      }
    }
  ]
}