{"type":"FeatureCollection","features":[{"type":"Feature","properties":{"nummer":17487,"baumbezeichnung_botanisch":"Acer pseudoplatanus","baumbezeichnung_deutsch":"Bergahorn","baumtyp":"Laub","bemerkung":null,"pflanzjahr":"1984","entnahmejahr":null,"marker-size":"small","marker-symbol":"park2","marker-color":"#A3DDAD"},"geometry":{"type":"Point","coordinates":[15.40225212944658,47.04018305733784],"bbox":[15.40225212944658,47.04018305733784,15.40225212944658,47.04018305733784]}},{"type":"Feature","properties":{"nummer":4681,"baumbezeichnung_botanisch":"Acer pseudoplatanus 'Purpurascens'","baumbezeichnung_deutsch":"Rotlaubiger Bergahorn","baumtyp":"Laub","bemerkung":null,"pflanzjahr":"1984","entnahmejahr":null,"marker-size":"small","marker-symbol":"park2","marker-color":"#A3DDAD"},"geometry":{"type":"Point","coordinates":[15.40245586111332,47.04012022353379],"bbox":[15.40245586111332,47.04012022353379,15.40245586111332,47.04012022353379]}},{"type":"Feature","properties":{"nummer":8627,"baumbezeichnung_botanisch":"Acer pseudoplatanus","baumbezeichnung_deutsch":"Bergahorn","baumtyp":"Laub","bemerkung":null,"pflanzjahr":"1984","entnahmejahr":null,"marker-size":"small","marker-symbol":"park2","marker-color":"#A3DDAD"},"geometry":{"type":"Point","coordinates":[15.4027208241516,47.04003962837086],"bbox":[15.4027208241516,47.04003962837086,15.4027208241516,47.04003962837086]}}]}