{
  "type": "FeatureCollection",
  "features": [
    {
      "type": "Feature",
      "properties": {
        "NUMMER": 24183,
        "BAUMBEZEICHNUNG_BOTANISCH": "Prunus serrulata",
        "BAUMBEZEICHNUNG_DEUTSCH": "Japanische Kirsche",
        "BAUMTYP": "Laub",
        "BEMERKUNG": null,
        "PFLANZJAHR": null,
        "ENTNAHMEJAHR": null,
        "BAUMPATENSCHAFT": "Fa. Kastner & Öhler",
        "ALTERSKLASSIZIERUNG": "jung",
        "OBJECTID": 15
      },
      "geometry": {
        "type": "Point",
        "coordinates": [
          15.393794311040057,
          47.06782460963561
        ]
      }
    },
    {
      "type": "Feature",
      "properties": {
        "NUMMER": 15145,
        "BAUMBEZEICHNUNG_BOTANISCH": "Acer pseudoplatanus",
        "BAUMBEZEICHNUNG_DEUTSCH": "Bergahorn",
        "BAUMTYP": "Laub",
        "BEMERKUNG": null,
        "PFLANZJAHR": null,
        "ENTNAHMEJAHR": null,
        "BAUMPATENSCHAFT": null,
        "ALTERSKLASSIZIERUNG": "mittel",
        "OBJECTID": 441
      },
      "geometry": {
        "type": "Point",
        "coordinates": [
          15.393627978735724,
          47.06729552761153
        ]
      }
    },
    {
      "type": "Feature",
      "properties": {
        "NUMMER": 23926,
        "BAUMBEZEICHNUNG_BOTANISCH": "Sorbus aria 'Lutescens'",
        "BAUMBEZEICHNUNG_DEUTSCH": "Gelblaubige Mehlbeere",
        "BAUMTYP": "Laub",
        "BEMERKUNG": null,
        "PFLANZJAHR": "2003",
        "ENTNAHMEJAHR": null,
        "BAUMPATENSCHAFT": "Fa. Kastner & Öhler",
        "ALTERSKLASSIZIERUNG": "jung",
        "OBJECTID": 750
      },
      "geometry": {
        "type": "Point",
        "coordinates": [
          15.393787411554447,
          47.06749228428635
        ]
      }
    }
  ]
}