{
  "type": "FeatureCollection",
  "features": [
    {
      "type": "Feature",
      "properties": {
        "nummer": 24183,
        "objectid": 15,
        "baumbezeichnung_deutsch": "Japanische Kirsche",
        "baumbezeichnung_botanisch": "Prunus serrulata",
        "baumtyp": "Laub",
        "bemerkung": null,
        "pflanzjahr": null,
        "entnahmejahr": null,
        "baumpatenschaft": "Fa. Kastner & Öhler",
        "altersklassifizierung": "jung"
      },
      "geometry": {
        "type": "Point",
        "coordinates": [
          15.393794311040057,
          47.06782460963561
        ]
      }
    },
    {
      "type": "Feature",
      "properties": {
        "nummer": 15145,
        "objectid": 441,
        "baumbezeichnung_deutsch": "Bergahorn",
        "baumbezeichnung_botanisch": "Acer pseudoplatanus",
        "baumtyp": "Laub",
        "bemerkung": null,
        "pflanzjahr": null,
        "entnahmejahr": null,
        "baumpatenschaft": null,
        "altersklassifizierung": "mittel"
      },
      "geometry": {
        "type": "Point",
        "coordinates": [
          15.393627978735724,
          47.06729552761153
        ]
      }
    },
    {
      "type": "Feature",
      "properties": {
        "nummer": 23926,
        "objectid": 750,
        "baumbezeichnung_deutsch": "Gelblaubige Mehlbeere",
        "baumbezeichnung_botanisch": "Sorbus aria 'Lutescens'",
        "baumtyp": "Laub",
        "bemerkung": null,
        "pflanzjahr": "2003",
        "entnahmejahr": null,
        "baumpatenschaft": "Fa. Kastner & Öhler",
        "altersklassifizierung": "jung"
      },
      "geometry": {
        "type": "Point",
        "coordinates": [
          15.393787411554447,
          47.06749228428635
        ]
      }
    }
  ]
}