{
  "type": "FeatureCollection",
  "features": [
    {
      "type": "Feature",
      "properties": {
        "NUMMER": 17183,
        "BAUMBEZEICHNUNG_BOTANISCH": "Sophora japonica",
        "BAUMBEZEICHNUNG_DEUTSCH": "Schnurbaum",
        "BAUMTYP": "Laub",
        "BEMERKUNG": null,
        "PFLANZJAHR": null,
        "ENTNAHMEJAHR": null,
        "BAUMPATENSCHAFT": null,
        "ALTERSKLASSIZIERUNG": "mittel",
        "OBJECTID": 1418
      },
      "geometry": {
        "type": "Point",
        "coordinates": [
          15.392254643587766,
          47.04860382478059
        ]
      }
    },
    {
      "type": "Feature",
      "properties": {
        "Naturdenkmal": true,
        "Naturdenkmal_Eigentum": "öffentlich",
        "nummer": "Naturdenkmal-121",
        "objectid": "Naturdenkmal-52",
        "baumbezeichnung_deutsch": "Platane",
        "baumbezeichnung_botanisch": "Platanus x hispanica"
      },
      "geometry": {
        "type": "Point",
        "coordinates": [
          15.394576137349635,
          47.04890688212
        ]
      }
    }
  ]
}