{"type":"FeatureCollection","features":[{"type":"Feature","properties":{"nummer":24903,"baumbezeichnung_botanisch":"Aesculus hippocastanum","baumbezeichnung_deutsch":"Gemeine Roßkastanie","baumtyp":"Laub","bemerkung":null,"pflanzjahr":null,"entnahmejahr":null,"marker-size":"small","marker-symbol":"park2","marker-color":"#A3DDAD"},"geometry":{"type":"Point","coordinates":[15.45067417644121,47.08101042668179],"bbox":[15.45067417644121,47.08101042668179,15.45067417644121,47.08101042668179]}},{"type":"Feature","properties":{"nummer":3483,"baumbezeichnung_botanisch":"Aesculus hippocastanum","baumbezeichnung_deutsch":"Gemeine Roßkastanie","baumtyp":"Laub","bemerkung":null,"pflanzjahr":null,"entnahmejahr":null,"marker-size":"small","marker-symbol":"park2","marker-color":"#A3DDAD"},"geometry":{"type":"Point","coordinates":[15.45054477097884,47.08121720146879],"bbox":[15.45054477097884,47.08121720146879,15.45054477097884,47.08121720146879]}},{"type":"Feature","properties":{"nummer":23388,"baumbezeichnung_botanisch":"Aesculus hippocastanum","baumbezeichnung_deutsch":"Gemeine Roßkastanie","baumtyp":"Laub","bemerkung":null,"pflanzjahr":null,"entnahmejahr":null,"marker-size":"small","marker-symbol":"park2","marker-color":"#A3DDAD"},"geometry":{"type":"Point","coordinates":[15.45052624986771,47.08129284263769],"bbox":[15.45052624986771,47.08129284263769,15.45052624986771,47.08129284263769]}},{"type":"Feature","properties":{"nummer":4115,"baumbezeichnung_botanisch":"Castanea sativa","baumbezeichnung_deutsch":"Eßkastanie","baumtyp":"Laub","bemerkung":null,"pflanzjahr":null,"entnahmejahr":null,"marker-size":"small","marker-symbol":"park2","marker-color":"#A3DDAD"},"geometry":{"type":"Point","coordinates":[15.45133589651856,47.08133724634084],"bbox":[15.45133589651856,47.08133724634084,15.45133589651856,47.08133724634084]}},{"type":"Feature","properties":{"nummer":18376,"baumbezeichnung_botanisch":"Acer platanoides","baumbezeichnung_deutsch":"Spitzahorn","baumtyp":"Laub","bemerkung":null,"pflanzjahr":null,"entnahmejahr":null,"marker-size":"small","marker-symbol":"park2","marker-color":"#A3DDAD"},"geometry":{"type":"Point","coordinates":[15.45108003058213,47.08125440708993],"bbox":[15.45108003058213,47.08125440708993,15.45108003058213,47.08125440708993]}},{"type":"Feature","properties":{"nummer":18374,"baumbezeichnung_botanisch":"Salix matsudana 'Tortuosa'","baumbezeichnung_deutsch":"Korkenzieherweide","baumtyp":"Laub","bemerkung":null,"pflanzjahr":null,"entnahmejahr":null,"marker-size":"small","marker-symbol":"park2","marker-color":"#A3DDAD"},"geometry":{"type":"Point","coordinates":[15.4512342582648,47.08127277860438],"bbox":[15.4512342582648,47.08127277860438,15.4512342582648,47.08127277860438]}},{"type":"Feature","properties":{"nummer":10652,"baumbezeichnung_botanisch":"Aesculus hippocastanum","baumbezeichnung_deutsch":"Gemeine Roßkastanie","baumtyp":"Laub","bemerkung":null,"pflanzjahr":"2007","entnahmejahr":null,"marker-size":"small","marker-symbol":"park2","marker-color":"#A3DDAD"},"geometry":{"type":"Point","coordinates":[15.45061464725443,47.08107787920013],"bbox":[15.45061464725443,47.08107787920013,15.45061464725443,47.08107787920013]}},{"type":"Feature","properties":{"nummer":19692,"baumbezeichnung_botanisch":"Aesculus hippocastanum","baumbezeichnung_deutsch":"Gemeine Roßkastanie","baumtyp":"Laub","bemerkung":null,"pflanzjahr":"1997","entnahmejahr":null,"marker-size":"small","marker-symbol":"park2","marker-color":"#A3DDAD"},"geometry":{"type":"Point","coordinates":[15.4505841242289,47.0811532359804],"bbox":[15.4505841242289,47.0811532359804,15.4505841242289,47.0811532359804]}}]}