{
  "type": "FeatureCollection",
  "features": [
    {
      "type": "Feature",
      "properties": {
        "nummer": 7261,
        "objectid": 1,
        "baumbezeichnung_deutsch": "Gemeine Roßkastanie",
        "baumbezeichnung_botanisch": "Aesculus hippocastanum",
        "baumtyp": "Laub",
        "bemerkung": null,
        "pflanzjahr": null,
        "entnahmejahr": null,
        "baumpatenschaft": null,
        "altersklassifizierung": "mittel"
      },
      "geometry": {
        "type": "Point",
        "coordinates": [
          15.450843795974695,
          47.08367731386206
        ]
      }
    },
    {
      "type": "Feature",
      "properties": {
        "nummer": 7267,
        "objectid": 517,
        "baumbezeichnung_deutsch": "Hain - oder Weißbuche",
        "baumbezeichnung_botanisch": "Carpinus betulus",
        "baumtyp": "Laub",
        "bemerkung": null,
        "pflanzjahr": null,
        "entnahmejahr": null,
        "baumpatenschaft": null,
        "altersklassifizierung": "alt"
      },
      "geometry": {
        "type": "Point",
        "coordinates": [
          15.450989315997539,
          47.08353279201454
        ]
      }
    },
    {
      "type": "Feature",
      "properties": {
        "nummer": 3852,
        "objectid": 1327,
        "baumbezeichnung_deutsch": "Hain - oder Weißbuche",
        "baumbezeichnung_botanisch": "Carpinus betulus",
        "baumtyp": "Laub",
        "bemerkung": null,
        "pflanzjahr": null,
        "entnahmejahr": null,
        "baumpatenschaft": null,
        "altersklassifizierung": "jung"
      },
      "geometry": {
        "type": "Point",
        "coordinates": [
          15.450568302756707,
          47.08468171037076
        ]
      }
    },
    {
      "type": "Feature",
      "properties": {
        "nummer": 27378,
        "objectid": 1078,
        "baumbezeichnung_deutsch": "Hain - oder Weißbuche",
        "baumbezeichnung_botanisch": "Carpinus betulus",
        "baumtyp": "Laub",
        "bemerkung": null,
        "pflanzjahr": "2007",
        "entnahmejahr": null,
        "baumpatenschaft": null,
        "altersklassifizierung": "jung"
      },
      "geometry": {
        "type": "Point",
        "coordinates": [
          15.449955407505112,
          47.084218995279855
        ]
      }
    },
    {
      "type": "Feature",
      "properties": {
        "nummer": 27379,
        "objectid": 1087,
        "baumbezeichnung_deutsch": "Hain - oder Weißbuche",
        "baumbezeichnung_botanisch": "Carpinus betulus",
        "baumtyp": "Laub",
        "bemerkung": null,
        "pflanzjahr": "2007",
        "entnahmejahr": null,
        "baumpatenschaft": null,
        "altersklassifizierung": "jung"
      },
      "geometry": {
        "type": "Point",
        "coordinates": [
          15.449935976092906,
          47.08419656515015
        ]
      }
    },
    {
      "type": "Feature",
      "properties": {
        "nummer": 7226,
        "objectid": 1095,
        "baumbezeichnung_deutsch": "Winterlinde",
        "baumbezeichnung_botanisch": "Tilia cordata",
        "baumtyp": "Laub",
        "bemerkung": null,
        "pflanzjahr": null,
        "entnahmejahr": null,
        "baumpatenschaft": null,
        "altersklassifizierung": "mittel"
      },
      "geometry": {
        "type": "Point",
        "coordinates": [
          15.45028726743225,
          47.08429949273214
        ]
      }
    },
    {
      "type": "Feature",
      "properties": {
        "nummer": 7234,
        "objectid": 1098,
        "baumbezeichnung_deutsch": "Hain - oder Weißbuche",
        "baumbezeichnung_botanisch": "Carpinus betulus",
        "baumtyp": "Laub",
        "bemerkung": null,
        "pflanzjahr": null,
        "entnahmejahr": null,
        "baumpatenschaft": null,
        "altersklassifizierung": "alt"
      },
      "geometry": {
        "type": "Point",
        "coordinates": [
          15.450259516371553,
          47.08421149023482
        ]
      }
    },
    {
      "type": "Feature",
      "properties": {
        "nummer": 7232,
        "objectid": 1099,
        "baumbezeichnung_deutsch": "Winterlinde",
        "baumbezeichnung_botanisch": "Tilia cordata",
        "baumtyp": "Laub",
        "bemerkung": null,
        "pflanzjahr": null,
        "entnahmejahr": null,
        "baumpatenschaft": null,
        "altersklassifizierung": "alt"
      },
      "geometry": {
        "type": "Point",
        "coordinates": [
          15.45022082239682,
          47.08425508486789
        ]
      }
    }
  ]
}