{
  "type": "FeatureCollection",
  "features": [
    {
      "type": "Feature",
      "properties": {
        "nummer": 27527,
        "baumbezeichnung_botanisch": "Aesculus hippocastanum",
        "baumbezeichnung_deutsch": "Gemeine Roßkastanie",
        "baumtyp": "Laub",
        "altersklassifizierung": "jung",
        "bemerkung": null,
        "pflanzjahr": "2007",
        "entnahmejahr": null,
        "baumpatenschaft": null,
        "objectid": 969
      },
      "geometry": {
        "type": "Point",
        "coordinates": [
          15.45061464725443,
          47.08107787920013
        ]
      }
    },
    {
      "type": "Feature",
      "properties": {
        "nummer": 3784,
        "baumbezeichnung_botanisch": "Aesculus hippocastanum",
        "baumbezeichnung_deutsch": "Gemeine Roßkastanie",
        "baumtyp": "Laub",
        "altersklassifizierung": "mittel",
        "bemerkung": null,
        "pflanzjahr": null,
        "entnahmejahr": null,
        "baumpatenschaft": null,
        "objectid": 4396
      },
      "geometry": {
        "type": "Point",
        "coordinates": [
          15.450526249867709,
          47.081292842637694
        ]
      }
    },
    {
      "type": "Feature",
      "properties": {
        "nummer": 3783,
        "baumbezeichnung_botanisch": "Aesculus hippocastanum",
        "baumbezeichnung_deutsch": "Gemeine Roßkastanie",
        "baumtyp": "Laub",
        "altersklassifizierung": "mittel",
        "bemerkung": null,
        "pflanzjahr": null,
        "entnahmejahr": "2014",
        "baumpatenschaft": null,
        "objectid": 5791
      },
      "geometry": {
        "type": "Point",
        "coordinates": [
          15.45054477097884,
          47.08121720146879
        ]
      }
    },
    {
      "type": "Feature",
      "properties": {
        "nummer": 3780,
        "baumbezeichnung_botanisch": "Aesculus hippocastanum",
        "baumbezeichnung_deutsch": "Gemeine Roßkastanie",
        "baumtyp": "Laub",
        "altersklassifizierung": "mittel",
        "bemerkung": null,
        "pflanzjahr": null,
        "entnahmejahr": null,
        "baumpatenschaft": null,
        "objectid": 11475
      },
      "geometry": {
        "type": "Point",
        "coordinates": [
          15.450674176441206,
          47.081010426681786
        ]
      }
    },
    {
      "type": "Feature",
      "properties": {
        "nummer": 20187,
        "baumbezeichnung_botanisch": "Aesculus hippocastanum",
        "baumbezeichnung_deutsch": "Gemeine Roßkastanie",
        "baumtyp": "Laub",
        "altersklassifizierung": "jung",
        "bemerkung": null,
        "pflanzjahr": "1997",
        "entnahmejahr": null,
        "baumpatenschaft": null,
        "objectid": 20643
      },
      "geometry": {
        "type": "Point",
        "coordinates": [
          15.4505841242289,
          47.0811532359804
        ]
      }
    },
    {
      "type": "Feature",
      "properties": {
        "nummer": 7992,
        "baumbezeichnung_botanisch": "Castanea sativa",
        "baumbezeichnung_deutsch": "Eßkastanie",
        "baumtyp": "Laub",
        "altersklassifizierung": "mittel",
        "bemerkung": null,
        "pflanzjahr": null,
        "entnahmejahr": null,
        "baumpatenschaft": null,
        "objectid": 29250
      },
      "geometry": {
        "type": "Point",
        "coordinates": [
          15.45133589651856,
          47.081337246340844
        ]
      }
    },
    {
      "type": "Feature",
      "properties": {
        "nummer": 24303,
        "baumbezeichnung_botanisch": "Salix matsudana 'Tortuosa'",
        "baumbezeichnung_deutsch": "Korkenzieherweide",
        "baumtyp": "Laub",
        "altersklassifizierung": "jung",
        "bemerkung": null,
        "pflanzjahr": null,
        "entnahmejahr": null,
        "baumpatenschaft": null,
        "objectid": 25993
      },
      "geometry": {
        "type": "Point",
        "coordinates": [
          15.4512342582648,
          47.08127277860438
        ]
      }
    },
    {
      "type": "Feature",
      "properties": {
        "nummer": 24302,
        "baumbezeichnung_botanisch": "Acer platanoides",
        "baumbezeichnung_deutsch": "Spitzahorn",
        "baumtyp": "Laub",
        "altersklassifizierung": "jung",
        "bemerkung": null,
        "pflanzjahr": null,
        "entnahmejahr": null,
        "baumpatenschaft": null,
        "objectid": 25994
      },
      "geometry": {
        "type": "Point",
        "coordinates": [
          15.451080030582128,
          47.08125440708993
        ]
      }
    }
  ]
}