{
  "type": "FeatureCollection",
  "features": [
    {
      "type": "Feature",
      "properties": {
        "NUMMER": 27527,
        "BAUMBEZEICHNUNG_BOTANISCH": "Aesculus hippocastanum",
        "BAUMBEZEICHNUNG_DEUTSCH": "Gemeine Roßkastanie",
        "BAUMTYP": "Laub",
        "BEMERKUNG": null,
        "PFLANZJAHR": "2007",
        "ENTNAHMEJAHR": null,
        "BAUMPATENSCHAFT": null,
        "ALTERSKLASSIZIERUNG": "jung",
        "OBJECTID": 969
      },
      "geometry": {
        "type": "Point",
        "coordinates": [
          15.450608785089612,
          47.08107780296547
        ]
      }
    }
  ]
}