{
  "type": "FeatureCollection",
  "features": [
    {
      "type": "Feature",
      "properties": {
        "NUMMER": 7261,
        "BAUMBEZEICHNUNG_BOTANISCH": "Aesculus hippocastanum",
        "BAUMBEZEICHNUNG_DEUTSCH": "Gemeine Roßkastanie",
        "BAUMTYP": "Laub",
        "BEMERKUNG": null,
        "PFLANZJAHR": null,
        "ENTNAHMEJAHR": null,
        "BAUMPATENSCHAFT": null,
        "ALTERSKLASSIZIERUNG": "mittel",
        "OBJECTID": 1
      },
      "geometry": {
        "type": "Point",
        "coordinates": [
          15.450843795974695,
          47.08367731386206
        ]
      }
    },
    {
      "type": "Feature",
      "properties": {
        "NUMMER": 7267,
        "BAUMBEZEICHNUNG_BOTANISCH": "Carpinus betulus",
        "BAUMBEZEICHNUNG_DEUTSCH": "Hain - oder Weißbuche",
        "BAUMTYP": "Laub",
        "BEMERKUNG": null,
        "PFLANZJAHR": null,
        "ENTNAHMEJAHR": null,
        "BAUMPATENSCHAFT": null,
        "ALTERSKLASSIZIERUNG": "alt",
        "OBJECTID": 517
      },
      "geometry": {
        "type": "Point",
        "coordinates": [
          15.450989315997539,
          47.08353279201454
        ]
      }
    },
    {
      "type": "Feature",
      "properties": {
        "NUMMER": 3852,
        "BAUMBEZEICHNUNG_BOTANISCH": "Carpinus betulus",
        "BAUMBEZEICHNUNG_DEUTSCH": "Hain - oder Weißbuche",
        "BAUMTYP": "Laub",
        "BEMERKUNG": null,
        "PFLANZJAHR": null,
        "ENTNAHMEJAHR": null,
        "BAUMPATENSCHAFT": null,
        "ALTERSKLASSIZIERUNG": "jung",
        "OBJECTID": 1327
      },
      "geometry": {
        "type": "Point",
        "coordinates": [
          15.450568302756707,
          47.08468171037076
        ]
      }
    },
    {
      "type": "Feature",
      "properties": {
        "NUMMER": 27378,
        "BAUMBEZEICHNUNG_BOTANISCH": "Carpinus betulus",
        "BAUMBEZEICHNUNG_DEUTSCH": "Hain - oder Weißbuche",
        "BAUMTYP": "Laub",
        "BEMERKUNG": null,
        "PFLANZJAHR": "2007",
        "ENTNAHMEJAHR": null,
        "BAUMPATENSCHAFT": null,
        "ALTERSKLASSIZIERUNG": "jung",
        "OBJECTID": 1078
      },
      "geometry": {
        "type": "Point",
        "coordinates": [
          15.449955407505112,
          47.084218995279855
        ]
      }
    },
    {
      "type": "Feature",
      "properties": {
        "NUMMER": 27379,
        "BAUMBEZEICHNUNG_BOTANISCH": "Carpinus betulus",
        "BAUMBEZEICHNUNG_DEUTSCH": "Hain - oder Weißbuche",
        "BAUMTYP": "Laub",
        "BEMERKUNG": null,
        "PFLANZJAHR": "2007",
        "ENTNAHMEJAHR": null,
        "BAUMPATENSCHAFT": null,
        "ALTERSKLASSIZIERUNG": "jung",
        "OBJECTID": 1087
      },
      "geometry": {
        "type": "Point",
        "coordinates": [
          15.449935976092906,
          47.08419656515015
        ]
      }
    },
    {
      "type": "Feature",
      "properties": {
        "NUMMER": 7226,
        "BAUMBEZEICHNUNG_BOTANISCH": "Tilia cordata",
        "BAUMBEZEICHNUNG_DEUTSCH": "Winterlinde",
        "BAUMTYP": "Laub",
        "BEMERKUNG": null,
        "PFLANZJAHR": null,
        "ENTNAHMEJAHR": null,
        "BAUMPATENSCHAFT": null,
        "ALTERSKLASSIZIERUNG": "mittel",
        "OBJECTID": 1095
      },
      "geometry": {
        "type": "Point",
        "coordinates": [
          15.45028726743225,
          47.08429949273214
        ]
      }
    },
    {
      "type": "Feature",
      "properties": {
        "NUMMER": 7234,
        "BAUMBEZEICHNUNG_BOTANISCH": "Carpinus betulus",
        "BAUMBEZEICHNUNG_DEUTSCH": "Hain - oder Weißbuche",
        "BAUMTYP": "Laub",
        "BEMERKUNG": null,
        "PFLANZJAHR": null,
        "ENTNAHMEJAHR": null,
        "BAUMPATENSCHAFT": null,
        "ALTERSKLASSIZIERUNG": "alt",
        "OBJECTID": 1098
      },
      "geometry": {
        "type": "Point",
        "coordinates": [
          15.450259516371553,
          47.08421149023482
        ]
      }
    },
    {
      "type": "Feature",
      "properties": {
        "NUMMER": 7232,
        "BAUMBEZEICHNUNG_BOTANISCH": "Tilia cordata",
        "BAUMBEZEICHNUNG_DEUTSCH": "Winterlinde",
        "BAUMTYP": "Laub",
        "BEMERKUNG": null,
        "PFLANZJAHR": null,
        "ENTNAHMEJAHR": null,
        "BAUMPATENSCHAFT": null,
        "ALTERSKLASSIZIERUNG": "alt",
        "OBJECTID": 1099
      },
      "geometry": {
        "type": "Point",
        "coordinates": [
          15.45022082239682,
          47.08425508486789
        ]
      }
    }
  ]
}