{
  "type": "FeatureCollection",
  "features": [
    {
      "type": "Feature",
      "properties": {
        "nummer": 27527,
        "objectid": 969,
        "baumbezeichnung_deutsch": "Gemeine Roßkastanie",
        "baumbezeichnung_botanisch": "Aesculus hippocastanum",
        "baumtyp": "Laub",
        "bemerkung": null,
        "pflanzjahr": "2007",
        "entnahmejahr": null,
        "baumpatenschaft": null,
        "altersklassifizierung": "jung"
      },
      "geometry": {
        "type": "Point",
        "coordinates": [
          15.450608785089612,
          47.08107780296547
        ]
      }
    }
  ]
}