{
  "type": "FeatureCollection",
  "features": [
    {
      "type": "Feature",
      "properties": {
        "NUMMER": 23585,
        "BAUMBEZEICHNUNG_BOTANISCH": "Celtis australis",
        "BAUMBEZEICHNUNG_DEUTSCH": "Zürgel Baum",
        "BAUMTYP": "Laub",
        "BEMERKUNG": null,
        "PFLANZJAHR": "2002",
        "ENTNAHMEJAHR": null,
        "BAUMPATENSCHAFT": null,
        "ALTERSKLASSIZIERUNG": "jung",
        "OBJECTID": 308
      },
      "geometry": {
        "type": "Point",
        "coordinates": [
          15.452266970039954,
          47.05879041282901
        ]
      }
    }
  ]
}