{
  "type": "FeatureCollection",
  "features": [
    {
      "type": "Feature",
      "id": 308,
      "properties": {
        "nummer": 23585,
        "objectid": 308,
        "baumbezeichnung_deutsch": "Zürgel Baum",
        "baumbezeichnung_botanisch": "Celtis australis",
        "baumtyp": "Laub",
        "bemerkung": null,
        "pflanzjahr": "2002",
        "entnahmejahr": null,
        "baumpatenschaft": null,
        "altersklassifizierung": "jung"
      },
      "geometry": {
        "type": "Point",
        "coordinates": [
          15.452266970039954,
          47.05879041282901
        ]
      }
    }
  ]
}