{
  "type": "FeatureCollection",
  "features": [
    {
      "type": "Feature",
      "properties": {
        "nummer": 23584,
        "baumbezeichnung_botanisch": "Celtis australis",
        "baumbezeichnung_deutsch": "Zürgel Baum",
        "baumtyp": "Laub",
        "altersklassifizierung": "jung",
        "bemerkung": null,
        "pflanzjahr": "2002",
        "entnahmejahr": null,
        "baumpatenschaft": null,
        "objectid": 26158
      },
      "geometry": {
        "type": "Point",
        "coordinates": [
          15.452231628554022,
          47.05887242771412
        ],
        "bbox": [
          15.452231628554022,
          47.05887242771412,
          15.452231628554022,
          47.05887242771412
        ]
      }
    }
  ]
}