{"type":"FeatureCollection","features":[{"type":"Feature","properties":{"nummer":24766,"baumbezeichnung_botanisch":"Platanus x acerifolia","baumbezeichnung_deutsch":"Platane","baumtyp":"Laub","altersklassifizierung":"jung","bemerkung":null,"pflanzjahr":"2005","entnahmejahr":null,"baumpatenschaft":null,"objectid":27094},"geometry":{"type":"Point","coordinates":[15.452030487923539,47.04938977806453],"bbox":[15.452030487923539,47.04938977806453,15.452030487923539,47.04938977806453]}},{"type":"Feature","properties":{"nummer":24767,"baumbezeichnung_botanisch":"Platanus x acerifolia","baumbezeichnung_deutsch":"Platane","baumtyp":"Laub","altersklassifizierung":"jung","bemerkung":null,"pflanzjahr":"2005","entnahmejahr":null,"baumpatenschaft":null,"objectid":27095},"geometry":{"type":"Point","coordinates":[15.452185318387322,47.049186296545436],"bbox":[15.452185318387322,47.049186296545436,15.452185318387322,47.049186296545436]}}]}