{"type":"FeatureCollection","features":[{"type":"Feature","properties":{"nummer":27872,"baumbezeichnung_botanisch":"Platanus x acerifolia","baumbezeichnung_deutsch":"Platane","baumtyp":"Laub","bemerkung":null,"pflanzjahr":"2005","entnahmejahr":null,"marker-size":"small","marker-symbol":"park2","marker-color":"#A3DDAD"},"geometry":{"type":"Point","coordinates":[15.45203048792354,47.04938977806453],"bbox":[15.45203048792354,47.04938977806453,15.45203048792354,47.04938977806453]}},{"type":"Feature","properties":{"nummer":27944,"baumbezeichnung_botanisch":"Platanus x acerifolia","baumbezeichnung_deutsch":"Platane","baumtyp":"Laub","bemerkung":null,"pflanzjahr":"2005","entnahmejahr":null,"marker-size":"small","marker-symbol":"park2","marker-color":"#A3DDAD"},"geometry":{"type":"Point","coordinates":[15.45218531838732,47.04918629654544],"bbox":[15.45218531838732,47.04918629654544,15.45218531838732,47.04918629654544]}}]}