{
  "type": "FeatureCollection",
  "features": [
    {
      "type": "Feature",
      "properties": {
        "nummer": 29030,
        "baumbezeichnung_botanisch": "Aesculus hippocastanum",
        "baumbezeichnung_deutsch": "Gemeine Roßkastanie",
        "baumtyp": "Laub",
        "altersklassifizierung": "jung",
        "bemerkung": null,
        "pflanzjahr": "2008",
        "entnahmejahr": null,
        "baumpatenschaft": null,
        "objectid": 17024
      },
      "geometry": {
        "type": "Point",
        "coordinates": [
          15.451068165823626,
          47.032341229568615
        ]
      }
    },
    {
      "type": "Feature",
      "properties": {
        "nummer": 9765,
        "baumbezeichnung_botanisch": "Aesculus hippocastanum",
        "baumbezeichnung_deutsch": "Gemeine Roßkastanie",
        "baumtyp": "Laub",
        "altersklassifizierung": "jung",
        "bemerkung": null,
        "pflanzjahr": null,
        "entnahmejahr": null,
        "baumpatenschaft": null,
        "objectid": 17209
      },
      "geometry": {
        "type": "Point",
        "coordinates": [
          15.451165232831096,
          47.03222334278581
        ]
      }
    },
    {
      "type": "Feature",
      "properties": {
        "nummer": 9770,
        "baumbezeichnung_botanisch": "Aesculus hippocastanum",
        "baumbezeichnung_deutsch": "Gemeine Roßkastanie",
        "baumtyp": "Laub",
        "altersklassifizierung": "mittel",
        "bemerkung": null,
        "pflanzjahr": null,
        "entnahmejahr": null,
        "baumpatenschaft": null,
        "objectid": 14189
      },
      "geometry": {
        "type": "Point",
        "coordinates": [
          15.450912826625641,
          47.032513383278655
        ]
      }
    },
    {
      "type": "Feature",
      "properties": {
        "nummer": 9769,
        "baumbezeichnung_botanisch": "Aesculus hippocastanum",
        "baumbezeichnung_deutsch": "Gemeine Roßkastanie",
        "baumtyp": "Laub",
        "altersklassifizierung": "mittel",
        "bemerkung": null,
        "pflanzjahr": null,
        "entnahmejahr": null,
        "baumpatenschaft": null,
        "objectid": 23486
      },
      "geometry": {
        "type": "Point",
        "coordinates": [
          15.450962572009912,
          47.03245759403732
        ]
      }
    },
    {
      "type": "Feature",
      "properties": {
        "nummer": 9766,
        "baumbezeichnung_botanisch": "Aesculus hippocastanum",
        "baumbezeichnung_deutsch": "Gemeine Roßkastanie",
        "baumtyp": "Laub",
        "altersklassifizierung": "jung",
        "bemerkung": null,
        "pflanzjahr": null,
        "entnahmejahr": null,
        "baumpatenschaft": null,
        "objectid": 23494
      },
      "geometry": {
        "type": "Point",
        "coordinates": [
          15.45111823372613,
          47.03227944118789
        ]
      }
    },
    {
      "type": "Feature",
      "properties": {
        "nummer": 27814,
        "baumbezeichnung_botanisch": "Aesculus hippocastanum",
        "baumbezeichnung_deutsch": "Gemeine Roßkastanie",
        "baumtyp": "Laub",
        "altersklassifizierung": "jung",
        "bemerkung": null,
        "pflanzjahr": null,
        "entnahmejahr": null,
        "baumpatenschaft": null,
        "objectid": 27959
      },
      "geometry": {
        "type": "Point",
        "coordinates": [
          15.451018860409267,
          47.032395089200165
        ]
      }
    },
    {
      "type": "Feature",
      "properties": {
        "nummer": 9745,
        "baumbezeichnung_botanisch": "Aesculus hippocastanum",
        "baumbezeichnung_deutsch": "Gemeine Roßkastanie",
        "baumtyp": "Laub",
        "altersklassifizierung": "mittel",
        "bemerkung": null,
        "pflanzjahr": null,
        "entnahmejahr": null,
        "baumpatenschaft": null,
        "objectid": 26366
      },
      "geometry": {
        "type": "Point",
        "coordinates": [
          15.451828125864145,
          47.030866111786146
        ]
      }
    }
  ]
}