{"type":"FeatureCollection","features":[{"type":"Feature","properties":{"nummer":13134,"baumbezeichnung_botanisch":"Betula pendula","baumbezeichnung_deutsch":"Sandbirke, Weißbirke","baumtyp":"Laub","bemerkung":null,"pflanzjahr":null,"entnahmejahr":null,"marker-size":"small","marker-symbol":"park2","marker-color":"#A3DDAD"},"geometry":{"type":"Point","coordinates":[15.43929689556145,47.06591915748783],"bbox":[15.43929689556145,47.06591915748783,15.43929689556145,47.06591915748783]}},{"type":"Feature","properties":{"nummer":13629,"baumbezeichnung_botanisch":"Betula pendula","baumbezeichnung_deutsch":"Sandbirke, Weißbirke","baumtyp":"Laub","bemerkung":null,"pflanzjahr":null,"entnahmejahr":null,"marker-size":"small","marker-symbol":"park2","marker-color":"#A3DDAD"},"geometry":{"type":"Point","coordinates":[15.43920391012087,47.06585039029525],"bbox":[15.43920391012087,47.06585039029525,15.43920391012087,47.06585039029525]}},{"type":"Feature","properties":{"nummer":7122,"baumbezeichnung_botanisch":"Betula pendula","baumbezeichnung_deutsch":"Sandbirke, Weißbirke","baumtyp":"Laub","bemerkung":null,"pflanzjahr":null,"entnahmejahr":null,"marker-size":"small","marker-symbol":"park2","marker-color":"#A3DDAD"},"geometry":{"type":"Point","coordinates":[15.43915962271979,47.06583325855451],"bbox":[15.43915962271979,47.06583325855451,15.43915962271979,47.06583325855451]}},{"type":"Feature","properties":{"nummer":28145,"baumbezeichnung_botanisch":"Betula pendula","baumbezeichnung_deutsch":"Sandbirke, Weißbirke","baumtyp":"Laub","bemerkung":null,"pflanzjahr":null,"entnahmejahr":null,"marker-size":"small","marker-symbol":"park2","marker-color":"#A3DDAD"},"geometry":{"type":"Point","coordinates":[15.43909088013893,47.06581351555047],"bbox":[15.43909088013893,47.06581351555047,15.43909088013893,47.06581351555047]}},{"type":"Feature","properties":{"nummer":15937,"baumbezeichnung_botanisch":"Betula pendula","baumbezeichnung_deutsch":"Sandbirke, Weißbirke","baumtyp":"Laub","bemerkung":null,"pflanzjahr":null,"entnahmejahr":null,"marker-size":"small","marker-symbol":"park2","marker-color":"#A3DDAD"},"geometry":{"type":"Point","coordinates":[15.43895077034017,47.06581512545493],"bbox":[15.43895077034017,47.06581512545493,15.43895077034017,47.06581512545493]}}]}