{"type":"FeatureCollection","features":[{"type":"Feature","properties":{"nummer":8202,"baumbezeichnung_botanisch":"Acer pseudoplatanus","baumbezeichnung_deutsch":"Bergahorn","baumtyp":"Laub","bemerkung":null,"pflanzjahr":null,"entnahmejahr":null,"marker-size":"small","marker-symbol":"park2","marker-color":"#A3DDAD"},"geometry":{"type":"Point","coordinates":[15.40285159733437,47.07294177702079],"bbox":[15.40285159733437,47.07294177702079,15.40285159733437,47.07294177702079]}},{"type":"Feature","properties":{"nummer":21591,"baumbezeichnung_botanisch":"Acer pseudoplatanus","baumbezeichnung_deutsch":"Bergahorn","baumtyp":"Laub","bemerkung":null,"pflanzjahr":null,"entnahmejahr":null,"marker-size":"small","marker-symbol":"park2","marker-color":"#A3DDAD"},"geometry":{"type":"Point","coordinates":[15.40293845079319,47.072940496904],"bbox":[15.40293845079319,47.072940496904,15.40293845079319,47.072940496904]}},{"type":"Feature","properties":{"nummer":45355,"baumbezeichnung_botanisch":"Koelreuteria paniculata 'Fastigiata'","baumbezeichnung_deutsch":"Säulenblasenbaum","baumtyp":"Laub","bemerkung":null,"pflanzjahr":"2011","entnahmejahr":null,"marker-size":"small","marker-symbol":"park2","marker-color":"#A3DDAD"},"geometry":{"type":"Point","coordinates":[15.40378717738477,47.07302494682381],"bbox":[15.40378717738477,47.07302494682381,15.40378717738477,47.07302494682381]}},{"type":"Feature","properties":{"nummer":45356,"baumbezeichnung_botanisch":"Koelreuteria paniculata 'Fastigiata'","baumbezeichnung_deutsch":"Säulenblasenbaum","baumtyp":"Laub","bemerkung":null,"pflanzjahr":"2011","entnahmejahr":null,"marker-size":"small","marker-symbol":"park2","marker-color":"#A3DDAD"},"geometry":{"type":"Point","coordinates":[15.40347383422827,47.07303469248827],"bbox":[15.40347383422827,47.07303469248827,15.40347383422827,47.07303469248827]}},{"type":"Feature","properties":{"nummer":45357,"baumbezeichnung_botanisch":"Koelreuteria paniculata 'Fastigiata'","baumbezeichnung_deutsch":"Säulenblasenbaum","baumtyp":"Laub","bemerkung":null,"pflanzjahr":"2011","entnahmejahr":null,"marker-size":"small","marker-symbol":"park2","marker-color":"#A3DDAD"},"geometry":{"type":"Point","coordinates":[15.40315689185112,47.07304440707284],"bbox":[15.40315689185112,47.07304440707284,15.40315689185112,47.07304440707284]}},{"type":"Feature","properties":{"nummer":45358,"baumbezeichnung_botanisch":"Koelreuteria paniculata","baumbezeichnung_deutsch":"Blasenbaum","baumtyp":"Laub","bemerkung":null,"pflanzjahr":"2011","entnahmejahr":null,"marker-size":"small","marker-symbol":"park2","marker-color":"#A3DDAD"},"geometry":{"type":"Point","coordinates":[15.40406191482369,47.07295832403525],"bbox":[15.40406191482369,47.07295832403525,15.40406191482369,47.07295832403525]}}]}