{"type":"FeatureCollection","features":[{"type":"Feature","properties":{"Naturdenkmal":true,"Naturdenkmal_Eigentum":"öffentlich","nummer":"Naturdenkmal-2","objectid":"Naturdenkmal-40","baumbezeichnung_deutsch":"Platane","baumbezeichnung_botanisch":"Platanus x hispanica"},"geometry":{"type":"Point","coordinates":[15.391015018268304,47.07482706831641],"bbox":[15.391015018268304,47.07482706831641,15.391015018268304,47.07482706831641]}},{"type":"Feature","properties":{"Naturdenkmal":true,"Naturdenkmal_Eigentum":"öffentlich","nummer":"Naturdenkmal-4","objectid":"Naturdenkmal-59","baumbezeichnung_deutsch":"Platane","baumbezeichnung_botanisch":"Platanus x hispanica"},"geometry":{"type":"Point","coordinates":[15.391012496114872,47.07508533443349],"bbox":[15.391012496114872,47.07508533443349,15.391012496114872,47.07508533443349]}},{"type":"Feature","properties":{"Naturdenkmal":true,"Naturdenkmal_Eigentum":"privat","nummer":"Naturdenkmal-51","objectid":"Naturdenkmal-81","baumbezeichnung_deutsch":"Platane","baumbezeichnung_botanisch":"Platanus x hispanica"},"geometry":{"type":"Point","coordinates":[15.391005757505626,47.07662935395685],"bbox":[15.391005757505626,47.07662935395685,15.391005757505626,47.07662935395685]}},{"type":"Feature","properties":{"Naturdenkmal":true,"Naturdenkmal_Eigentum":"öffentlich","nummer":"Naturdenkmal-6","objectid":"Naturdenkmal-2","baumbezeichnung_deutsch":"Platane","baumbezeichnung_botanisch":"Platanus x hispanica"},"geometry":{"type":"Point","coordinates":[15.391450320125575,47.07483601484121],"bbox":[15.391450320125575,47.07483601484121,15.391450320125575,47.07483601484121]}},{"type":"Feature","properties":{"Naturdenkmal":true,"Naturdenkmal_Eigentum":"öffentlich","nummer":"Naturdenkmal-3","objectid":"Naturdenkmal-13","baumbezeichnung_deutsch":"Platane","baumbezeichnung_botanisch":"Platanus x hispanica"},"geometry":{"type":"Point","coordinates":[15.390916546770109,47.074938184239564],"bbox":[15.390916546770109,47.074938184239564,15.390916546770109,47.074938184239564]}},{"type":"Feature","properties":{"Naturdenkmal":true,"Naturdenkmal_Eigentum":"öffentlich","nummer":"Naturdenkmal-5","objectid":"Naturdenkmal-99","baumbezeichnung_deutsch":"Platane","baumbezeichnung_botanisch":"Platanus x hispanica"},"geometry":{"type":"Point","coordinates":[15.391162218023762,47.074974055768074],"bbox":[15.391162218023762,47.074974055768074,15.391162218023762,47.074974055768074]}}]}