{
  "type": "FeatureCollection",
  "features": [
    {
      "type": "Feature",
      "properties": {
        "nummer": 27436,
        "baumbezeichnung_botanisch": "Quercus robur",
        "baumbezeichnung_deutsch": "Stieleiche",
        "baumtyp": "Laub",
        "altersklassifizierung": "alt",
        "bemerkung": null,
        "pflanzjahr": null,
        "entnahmejahr": null,
        "baumpatenschaft": null,
        "objectid": 13167
      },
      "geometry": {
        "type": "Point",
        "coordinates": [
          15.388388726878171,
          47.025084587384974
        ]
      }
    },
    {
      "type": "Feature",
      "properties": {
        "nummer": 27437,
        "baumbezeichnung_botanisch": "Quercus robur",
        "baumbezeichnung_deutsch": "Stieleiche",
        "baumtyp": "Laub",
        "altersklassifizierung": "alt",
        "bemerkung": null,
        "pflanzjahr": null,
        "entnahmejahr": null,
        "baumpatenschaft": null,
        "objectid": 25637
      },
      "geometry": {
        "type": "Point",
        "coordinates": [
          15.387853747286039,
          47.02515050299513
        ]
      }
    }
  ]
}