{"type":"FeatureCollection","features":[{"type":"Feature","properties":{"nummer":11946,"baumbezeichnung_botanisch":"Robinia pseudoacacia","baumbezeichnung_deutsch":"Scheinakazie","baumtyp":"Laub","bemerkung":null,"pflanzjahr":null,"entnahmejahr":null,"marker-size":"small","marker-symbol":"park2","marker-color":"#A3DDAD"},"geometry":{"type":"Point","coordinates":[15.42373990290134,47.0917918543804],"bbox":[15.42373990290134,47.0917918543804,15.42373990290134,47.0917918543804]}},{"type":"Feature","properties":{"nummer":15757,"baumbezeichnung_botanisch":"Ailanthus altissima","baumbezeichnung_deutsch":"Götterbaum","baumtyp":"Laub","bemerkung":null,"pflanzjahr":null,"entnahmejahr":null,"marker-size":"small","marker-symbol":"park2","marker-color":"#A3DDAD"},"geometry":{"type":"Point","coordinates":[15.42368916141149,47.09184471887532],"bbox":[15.42368916141149,47.09184471887532,15.42368916141149,47.09184471887532]}},{"type":"Feature","properties":{"nummer":2939,"baumbezeichnung_botanisch":"Robinia pseudoacacia","baumbezeichnung_deutsch":"Scheinakazie","baumtyp":"Laub","bemerkung":null,"pflanzjahr":null,"entnahmejahr":null,"marker-size":"small","marker-symbol":"park2","marker-color":"#A3DDAD"},"geometry":{"type":"Point","coordinates":[15.42357882408867,47.09191285883906],"bbox":[15.42357882408867,47.09191285883906,15.42357882408867,47.09191285883906]}},{"type":"Feature","properties":{"nummer":2936,"baumbezeichnung_botanisch":"Robinia pseudoacacia","baumbezeichnung_deutsch":"Scheinakazie","baumtyp":"Laub","bemerkung":null,"pflanzjahr":null,"entnahmejahr":null,"marker-size":"small","marker-symbol":"park2","marker-color":"#A3DDAD"},"geometry":{"type":"Point","coordinates":[15.42350373496101,47.09197079135043],"bbox":[15.42350373496101,47.09197079135043,15.42350373496101,47.09197079135043]}},{"type":"Feature","properties":{"nummer":8537,"baumbezeichnung_botanisch":"Koelreuteria paniculata","baumbezeichnung_deutsch":"Blasenbaum","baumtyp":"Laub","bemerkung":null,"pflanzjahr":"1996","entnahmejahr":null,"marker-size":"small","marker-symbol":"park2","marker-color":"#A3DDAD"},"geometry":{"type":"Point","coordinates":[15.42389313313489,47.09166842147398],"bbox":[15.42389313313489,47.09166842147398,15.42389313313489,47.09166842147398]}},{"type":"Feature","properties":{"nummer":8140,"baumbezeichnung_botanisch":"Koelreuteria paniculata","baumbezeichnung_deutsch":"Blasenbaum","baumtyp":"Laub","bemerkung":null,"pflanzjahr":"1996","entnahmejahr":null,"marker-size":"small","marker-symbol":"park2","marker-color":"#A3DDAD"},"geometry":{"type":"Point","coordinates":[15.42381497002724,47.09173209554005],"bbox":[15.42381497002724,47.09173209554005,15.42381497002724,47.09173209554005]}}]}