{"type":"FeatureCollection","features":[{"type":"Feature","properties":{"nummer":1097,"baumbezeichnung_botanisch":"Salix alba 'Tristis'","baumbezeichnung_deutsch":"Trauerweide","baumtyp":"Laub","bemerkung":null,"pflanzjahr":null,"entnahmejahr":null,"marker-size":"small","marker-symbol":"park2","marker-color":"#A3DDAD"},"geometry":{"type":"Point","coordinates":[15.42451865414708,47.08510458087245],"bbox":[15.42451865414708,47.08510458087245,15.42451865414708,47.08510458087245]}},{"type":"Feature","properties":{"nummer":10851,"baumbezeichnung_botanisch":"Salix alba 'Tristis'","baumbezeichnung_deutsch":"Trauerweide","baumtyp":"Laub","bemerkung":null,"pflanzjahr":null,"entnahmejahr":null,"marker-size":"small","marker-symbol":"park2","marker-color":"#A3DDAD"},"geometry":{"type":"Point","coordinates":[15.42446885861756,47.08515159300604],"bbox":[15.42446885861756,47.08515159300604,15.42446885861756,47.08515159300604]}},{"type":"Feature","properties":{"nummer":6694,"baumbezeichnung_botanisch":"Salix alba 'Tristis'","baumbezeichnung_deutsch":"Trauerweide","baumtyp":"Laub","bemerkung":null,"pflanzjahr":null,"entnahmejahr":null,"marker-size":"small","marker-symbol":"park2","marker-color":"#A3DDAD"},"geometry":{"type":"Point","coordinates":[15.42442722680607,47.08519867010962],"bbox":[15.42442722680607,47.08519867010962,15.42442722680607,47.08519867010962]}},{"type":"Feature","properties":{"nummer":26056,"baumbezeichnung_botanisch":"Salix alba 'Tristis'","baumbezeichnung_deutsch":"Trauerweide","baumtyp":"Laub","bemerkung":null,"pflanzjahr":null,"entnahmejahr":null,"marker-size":"small","marker-symbol":"park2","marker-color":"#A3DDAD"},"geometry":{"type":"Point","coordinates":[15.42438967681202,47.0852457805942],"bbox":[15.42438967681202,47.0852457805942,15.42438967681202,47.0852457805942]}}]}