{"type":"FeatureCollection","features":[{"type":"Feature","properties":{"nummer":24868,"baumbezeichnung_botanisch":"Aesculus hippocastanum","baumbezeichnung_deutsch":"Gemeine Roßkastanie","baumtyp":"Laub","bemerkung":null,"pflanzjahr":null,"entnahmejahr":null,"marker-size":"small","marker-symbol":"park2","marker-color":"#A3DDAD"},"geometry":{"type":"Point","coordinates":[15.46228754576731,47.06587493071454],"bbox":[15.46228754576731,47.06587493071454,15.46228754576731,47.06587493071454]}}]}