{
  "type": "FeatureCollection",
  "features": [
    {
      "type": "Feature",
      "properties": {
        "nummer": 6163,
        "objectid": 1138,
        "baumbezeichnung_deutsch": "Gemeine Roßkastanie",
        "baumbezeichnung_botanisch": "Aesculus hippocastanum",
        "baumtyp": "Laub",
        "bemerkung": null,
        "pflanzjahr": "1985",
        "entnahmejahr": null,
        "baumpatenschaft": null,
        "altersklassifizierung": "jung"
      },
      "geometry": {
        "type": "Point",
        "coordinates": [
          15.45987455084774,
          47.061119055051144
        ]
      }
    }
  ]
}