{"type":"FeatureCollection","features":[{"type":"Feature","properties":{"nummer":23036,"baumbezeichnung_botanisch":"Acer pseudoplatanus","baumbezeichnung_deutsch":"Bergahorn","baumtyp":"Laub","bemerkung":null,"pflanzjahr":null,"entnahmejahr":null,"marker-size":"small","marker-symbol":"park2","marker-color":"#A3DDAD"},"geometry":{"type":"Point","coordinates":[15.47034589970747,47.0430143821247],"bbox":[15.47034589970747,47.0430143821247,15.47034589970747,47.0430143821247]}},{"type":"Feature","properties":{"nummer":16338,"baumbezeichnung_botanisch":"Acer pseudoplatanus","baumbezeichnung_deutsch":"Bergahorn","baumtyp":"Laub","bemerkung":null,"pflanzjahr":null,"entnahmejahr":null,"marker-size":"small","marker-symbol":"park2","marker-color":"#A3DDAD"},"geometry":{"type":"Point","coordinates":[15.47050393917499,47.04309453797659],"bbox":[15.47050393917499,47.04309453797659,15.47050393917499,47.04309453797659]}},{"type":"Feature","properties":{"nummer":10299,"baumbezeichnung_botanisch":"Acer pseudoplatanus","baumbezeichnung_deutsch":"Bergahorn","baumtyp":"Laub","bemerkung":null,"pflanzjahr":null,"entnahmejahr":null,"marker-size":"small","marker-symbol":"park2","marker-color":"#A3DDAD"},"geometry":{"type":"Point","coordinates":[15.47062557657288,47.04314458612667],"bbox":[15.47062557657288,47.04314458612667,15.47062557657288,47.04314458612667]}}]}