{"type":"FeatureCollection","features":[{"type":"Feature","properties":{"nummer":29466,"baumbezeichnung_botanisch":"Aesculus flava","baumbezeichnung_deutsch":"Gelbe Pavie","baumtyp":"Laub","altersklassifizierung":"jung","bemerkung":null,"pflanzjahr":"2009","entnahmejahr":null,"baumpatenschaft":null,"objectid":8296},"geometry":{"type":"Point","coordinates":[15.433130649844683,47.04200663101795],"bbox":[15.433130649844683,47.04200663101795,15.433130649844683,47.04200663101795]}}]}