{
  "type": "FeatureCollection",
  "features": [
    {
      "type": "Feature",
      "properties": {
        "nummer": 14945,
        "baumbezeichnung_botanisch": "Tilia cordata",
        "baumbezeichnung_deutsch": "Winterlinde",
        "baumtyp": "Laub",
        "altersklassifizierung": "alt",
        "bemerkung": null,
        "pflanzjahr": null,
        "entnahmejahr": null,
        "baumpatenschaft": null,
        "objectid": 6209
      },
      "geometry": {
        "type": "Point",
        "coordinates": [
          15.388943453837488,
          47.067669838348365
        ],
        "bbox": [
          15.388943453837488,
          47.067669838348365,
          15.388943453837488,
          47.067669838348365
        ]
      }
    },
    {
      "type": "Feature",
      "properties": {
        "nummer": 14946,
        "baumbezeichnung_botanisch": "Tilia cordata",
        "baumbezeichnung_deutsch": "Winterlinde",
        "baumtyp": "Laub",
        "altersklassifizierung": "alt",
        "bemerkung": null,
        "pflanzjahr": null,
        "entnahmejahr": null,
        "baumpatenschaft": null,
        "objectid": 17143
      },
      "geometry": {
        "type": "Point",
        "coordinates": [
          15.38877008151928,
          47.067606895667076
        ],
        "bbox": [
          15.38877008151928,
          47.067606895667076,
          15.38877008151928,
          47.067606895667076
        ]
      }
    },
    {
      "type": "Feature",
      "properties": {
        "nummer": 30997,
        "baumbezeichnung_botanisch": "Tilia cordata",
        "baumbezeichnung_deutsch": "Winterlinde",
        "baumtyp": "Laub",
        "altersklassifizierung": "jung",
        "bemerkung": null,
        "pflanzjahr": "2012",
        "entnahmejahr": null,
        "baumpatenschaft": null,
        "objectid": 26814
      },
      "geometry": {
        "type": "Point",
        "coordinates": [
          15.388597340501631,
          47.06754549610889
        ],
        "bbox": [
          15.388597340501631,
          47.06754549610889,
          15.388597340501631,
          47.06754549610889
        ]
      }
    }
  ]
}