{"type":"FeatureCollection","features":[{"type":"Feature","properties":{"nummer":2289,"baumbezeichnung_botanisch":"Tilia cordata","baumbezeichnung_deutsch":"Winterlinde","baumtyp":"Laub","bemerkung":null,"pflanzjahr":null,"entnahmejahr":null,"marker-size":"small","marker-symbol":"park2","marker-color":"#A3DDAD"},"geometry":{"type":"Point","coordinates":[15.38894345383749,47.06766983834837],"bbox":[15.38894345383749,47.06766983834837,15.38894345383749,47.06766983834837]}},{"type":"Feature","properties":{"nummer":25240,"baumbezeichnung_botanisch":"Tilia cordata","baumbezeichnung_deutsch":"Winterlinde","baumtyp":"Laub","bemerkung":null,"pflanzjahr":null,"entnahmejahr":null,"marker-size":"small","marker-symbol":"park2","marker-color":"#A3DDAD"},"geometry":{"type":"Point","coordinates":[15.38877008151928,47.06760689566708],"bbox":[15.38877008151928,47.06760689566708,15.38877008151928,47.06760689566708]}},{"type":"Feature","properties":{"nummer":26089,"baumbezeichnung_botanisch":"Tilia cordata","baumbezeichnung_deutsch":"Winterlinde","baumtyp":"Laub","bemerkung":null,"pflanzjahr":"2012","entnahmejahr":null,"marker-size":"small","marker-symbol":"park2","marker-color":"#A3DDAD"},"geometry":{"type":"Point","coordinates":[15.38859734050163,47.06754549610889],"bbox":[15.38859734050163,47.06754549610889,15.38859734050163,47.06754549610889]}}]}