{
  "type": "FeatureCollection",
  "features": [
    {
      "type": "Feature",
      "properties": {
        "Naturdenkmal": true,
        "Naturdenkmal_Eigentum": "privat",
        "nummer": "Naturdenkmal-115",
        "objectid": "Naturdenkmal-125",
        "baumbezeichnung_deutsch": "2 Weihrauchzedern",
        "baumbezeichnung_botanisch": "Calocedrus decurrens"
      },
      "geometry": {
        "type": "Point",
        "coordinates": [
          15.388772806348822,
          47.05389596096654
        ]
      }
    }
  ]
}