{"type":"FeatureCollection","features":[{"type":"Feature","properties":{"nummer":15620,"baumbezeichnung_botanisch":"Prunus serrulata 'Amanogawa'","baumbezeichnung_deutsch":"Japanische Säulenkirsche","baumtyp":"Laub","bemerkung":null,"pflanzjahr":"2003","entnahmejahr":null,"marker-size":"small","marker-symbol":"park2","marker-color":"#A3DDAD"},"geometry":{"type":"Point","coordinates":[15.4401734930331,47.07498773441836],"bbox":[15.4401734930331,47.07498773441836,15.4401734930331,47.07498773441836]}},{"type":"Feature","properties":{"nummer":14262,"baumbezeichnung_botanisch":"Prunus serrulata 'Amanogawa'","baumbezeichnung_deutsch":"Japanische Säulenkirsche","baumtyp":"Laub","bemerkung":null,"pflanzjahr":"2003","entnahmejahr":null,"marker-size":"small","marker-symbol":"park2","marker-color":"#A3DDAD"},"geometry":{"type":"Point","coordinates":[15.44019084449376,47.07507576204587],"bbox":[15.44019084449376,47.07507576204587,15.44019084449376,47.07507576204587]}},{"type":"Feature","properties":{"nummer":13738,"baumbezeichnung_botanisch":"Tilia cordata","baumbezeichnung_deutsch":"Winterlinde","baumtyp":"Laub","bemerkung":null,"pflanzjahr":null,"entnahmejahr":null,"marker-size":"small","marker-symbol":"park2","marker-color":"#A3DDAD"},"geometry":{"type":"Point","coordinates":[15.44010467969619,47.0748096996004],"bbox":[15.44010467969619,47.0748096996004,15.44010467969619,47.0748096996004]}},{"type":"Feature","properties":{"nummer":23489,"baumbezeichnung_botanisch":"Prunus serrulata 'Amanogawa'","baumbezeichnung_deutsch":"Japanische Säulenkirsche","baumtyp":"Laub","bemerkung":null,"pflanzjahr":"2012","entnahmejahr":null,"marker-size":"small","marker-symbol":"park2","marker-color":"#A3DDAD"},"geometry":{"type":"Point","coordinates":[15.44017912071722,47.07502636466425],"bbox":[15.44017912071722,47.07502636466425,15.44017912071722,47.07502636466425]}}]}