{"type":"FeatureCollection","features":[{"type":"Feature","properties":{"nummer":22799,"baumbezeichnung_botanisch":"Acer campestre 'Elsrijk'","baumbezeichnung_deutsch":"Schmalkroniger Feldahorn","baumtyp":"Laub","bemerkung":null,"pflanzjahr":"2006","entnahmejahr":null,"marker-size":"small","marker-symbol":"park2","marker-color":"#A3DDAD"},"geometry":{"type":"Point","coordinates":[15.44117477582214,47.07298844340055],"bbox":[15.44117477582214,47.07298844340055,15.44117477582214,47.07298844340055]}},{"type":"Feature","properties":{"nummer":27799,"baumbezeichnung_botanisch":"Acer campestre 'Elsrijk'","baumbezeichnung_deutsch":"Schmalkroniger Feldahorn","baumtyp":"Laub","bemerkung":null,"pflanzjahr":"2006","entnahmejahr":null,"marker-size":"small","marker-symbol":"park2","marker-color":"#A3DDAD"},"geometry":{"type":"Point","coordinates":[15.44092918921791,47.07300794117273],"bbox":[15.44092918921791,47.07300794117273,15.44092918921791,47.07300794117273]}},{"type":"Feature","properties":{"nummer":27800,"baumbezeichnung_botanisch":"Acer campestre 'Elsrijk'","baumbezeichnung_deutsch":"Schmalkroniger Feldahorn","baumtyp":"Laub","bemerkung":null,"pflanzjahr":"2006","entnahmejahr":null,"marker-size":"small","marker-symbol":"park2","marker-color":"#A3DDAD"},"geometry":{"type":"Point","coordinates":[15.44089726610607,47.07293210049715],"bbox":[15.44089726610607,47.07293210049715,15.44089726610607,47.07293210049715]}}]}