{
  "type": "FeatureCollection",
  "features": [
    {
      "type": "Feature",
      "properties": {
        "NUMMER": 11731,
        "BAUMBEZEICHNUNG_BOTANISCH": "Tilia platyphyllos",
        "BAUMBEZEICHNUNG_DEUTSCH": "Sommerlinde",
        "BAUMTYP": "Laub",
        "BEMERKUNG": null,
        "PFLANZJAHR": null,
        "ENTNAHMEJAHR": null,
        "BAUMPATENSCHAFT": null,
        "ALTERSKLASSIZIERUNG": "jung",
        "OBJECTID": 498
      },
      "geometry": {
        "type": "Point",
        "coordinates": [
          15.434179782657695,
          47.05617840245495
        ]
      }
    },
    {
      "type": "Feature",
      "properties": {
        "NUMMER": 11737,
        "BAUMBEZEICHNUNG_BOTANISCH": "Tilia americana",
        "BAUMBEZEICHNUNG_DEUTSCH": "Amerikanische Linde",
        "BAUMTYP": "Laub",
        "BEMERKUNG": null,
        "PFLANZJAHR": null,
        "ENTNAHMEJAHR": null,
        "BAUMPATENSCHAFT": null,
        "ALTERSKLASSIZIERUNG": "jung",
        "OBJECTID": 1241
      },
      "geometry": {
        "type": "Point",
        "coordinates": [
          15.433861031676827,
          47.056940101174646
        ]
      }
    }
  ]
}