{
  "type": "FeatureCollection",
  "features": [
    {
      "type": "Feature",
      "id": 108,
      "properties": {
        "nummer": 30141,
        "objectid": 108,
        "baumbezeichnung_deutsch": "Kugelsandkirsche",
        "baumbezeichnung_botanisch": "Prunus fruticosa 'Globosum'",
        "baumtyp": "Laub",
        "bemerkung": null,
        "pflanzjahr": "2011",
        "entnahmejahr": null,
        "baumpatenschaft": null,
        "altersklassifizierung": "jung"
      },
      "geometry": {
        "type": "Point",
        "coordinates": [
          15.434284016971064,
          47.06801206013999
        ]
      }
    },
    {
      "type": "Feature",
      "id": 727,
      "properties": {
        "nummer": 3434,
        "objectid": 727,
        "baumbezeichnung_deutsch": "Hängehainbuche",
        "baumbezeichnung_botanisch": "Carpinus betulus 'Pendula'",
        "baumtyp": "Laub",
        "bemerkung": null,
        "pflanzjahr": null,
        "entnahmejahr": null,
        "baumpatenschaft": null,
        "altersklassifizierung": "alt"
      },
      "geometry": {
        "type": "Point",
        "coordinates": [
          15.435766537964131,
          47.06691101589065
        ]
      }
    },
    {
      "type": "Feature",
      "id": 1345,
      "properties": {
        "nummer": 21819,
        "objectid": 1345,
        "baumbezeichnung_deutsch": "Feldahorn",
        "baumbezeichnung_botanisch": "Acer campestre",
        "baumtyp": "Laub",
        "bemerkung": null,
        "pflanzjahr": "1999",
        "entnahmejahr": null,
        "baumpatenschaft": null,
        "altersklassifizierung": "jung"
      },
      "geometry": {
        "type": "Point",
        "coordinates": [
          15.434565606096701,
          47.06843891296712
        ]
      }
    },
    {
      "type": "Feature",
      "id": 1346,
      "properties": {
        "nummer": 21823,
        "objectid": 1346,
        "baumbezeichnung_deutsch": "Feldahorn",
        "baumbezeichnung_botanisch": "Acer campestre",
        "baumtyp": "Laub",
        "bemerkung": null,
        "pflanzjahr": "1999",
        "entnahmejahr": null,
        "baumpatenschaft": null,
        "altersklassifizierung": "jung"
      },
      "geometry": {
        "type": "Point",
        "coordinates": [
          15.4345451313186,
          47.068219957913
        ]
      }
    },
    {
      "type": "Feature",
      "id": 1347,
      "properties": {
        "nummer": 21824,
        "objectid": 1347,
        "baumbezeichnung_deutsch": "Feldahorn",
        "baumbezeichnung_botanisch": "Acer campestre",
        "baumtyp": "Laub",
        "bemerkung": null,
        "pflanzjahr": "1999",
        "entnahmejahr": null,
        "baumpatenschaft": null,
        "altersklassifizierung": "jung"
      },
      "geometry": {
        "type": "Point",
        "coordinates": [
          15.434537912966086,
          47.06811050414842
        ]
      }
    },
    {
      "type": "Feature",
      "id": 1349,
      "properties": {
        "nummer": 15446,
        "objectid": 1349,
        "baumbezeichnung_deutsch": "Esche",
        "baumbezeichnung_botanisch": "Fraxinus excelsior",
        "baumtyp": "Laub",
        "bemerkung": null,
        "pflanzjahr": null,
        "entnahmejahr": null,
        "baumpatenschaft": null,
        "altersklassifizierung": "alt"
      },
      "geometry": {
        "type": "Point",
        "coordinates": [
          15.430807141863147,
          47.070097344087415
        ]
      }
    },
    {
      "type": "Feature",
      "id": 1585,
      "properties": {
        "nummer": 21833,
        "objectid": 1585,
        "baumbezeichnung_deutsch": "Feldahorn",
        "baumbezeichnung_botanisch": "Acer campestre",
        "baumtyp": "Laub",
        "bemerkung": null,
        "pflanzjahr": "1999",
        "entnahmejahr": null,
        "baumpatenschaft": null,
        "altersklassifizierung": "jung"
      },
      "geometry": {
        "type": "Point",
        "coordinates": [
          15.434475583539813,
          47.067507298065365
        ]
      }
    }
  ]
}