{
  "type": "FeatureCollection",
  "features": [
    {
      "type": "Feature",
      "id": 498,
      "properties": {
        "nummer": 11731,
        "objectid": 498,
        "baumbezeichnung_deutsch": "Sommerlinde",
        "baumbezeichnung_botanisch": "Tilia platyphyllos",
        "baumtyp": "Laub",
        "bemerkung": null,
        "pflanzjahr": null,
        "entnahmejahr": null,
        "baumpatenschaft": null,
        "altersklassifizierung": "jung"
      },
      "geometry": {
        "type": "Point",
        "coordinates": [
          15.434179782657695,
          47.05617840245495
        ]
      }
    },
    {
      "type": "Feature",
      "id": 1241,
      "properties": {
        "nummer": 11737,
        "objectid": 1241,
        "baumbezeichnung_deutsch": "Amerikanische Linde",
        "baumbezeichnung_botanisch": "Tilia americana",
        "baumtyp": "Laub",
        "bemerkung": null,
        "pflanzjahr": null,
        "entnahmejahr": null,
        "baumpatenschaft": null,
        "altersklassifizierung": "jung"
      },
      "geometry": {
        "type": "Point",
        "coordinates": [
          15.433861031676827,
          47.056940101174646
        ]
      }
    }
  ]
}