{
  "type": "FeatureCollection",
  "features": [
    {
      "type": "Feature",
      "properties": {
        "NUMMER": 419,
        "BAUMBEZEICHNUNG_BOTANISCH": "Acer pseudoplatanus",
        "BAUMBEZEICHNUNG_DEUTSCH": "Bergahorn",
        "BAUMTYP": "Laub",
        "BEMERKUNG": null,
        "PFLANZJAHR": null,
        "ENTNAHMEJAHR": null,
        "BAUMPATENSCHAFT": null,
        "ALTERSKLASSIZIERUNG": "mittel",
        "OBJECTID": 377
      },
      "geometry": {
        "type": "Point",
        "coordinates": [
          15.43540973231593,
          47.05980026569626
        ]
      }
    },
    {
      "type": "Feature",
      "properties": {
        "NUMMER": 11228,
        "BAUMBEZEICHNUNG_BOTANISCH": "Prunus serrulata 'Kanzan'",
        "BAUMBEZEICHNUNG_DEUTSCH": "Japanische Blütenkirsche",
        "BAUMTYP": "Laub",
        "BEMERKUNG": null,
        "PFLANZJAHR": null,
        "ENTNAHMEJAHR": null,
        "BAUMPATENSCHAFT": null,
        "ALTERSKLASSIZIERUNG": "jung",
        "OBJECTID": 998
      },
      "geometry": {
        "type": "Point",
        "coordinates": [
          15.433066073815645,
          47.05896957512822
        ]
      }
    },
    {
      "type": "Feature",
      "properties": {
        "NUMMER": 203,
        "BAUMBEZEICHNUNG_BOTANISCH": "Acer pseudoplatanus",
        "BAUMBEZEICHNUNG_DEUTSCH": "Bergahorn",
        "BAUMTYP": "Laub",
        "BEMERKUNG": null,
        "PFLANZJAHR": null,
        "ENTNAHMEJAHR": null,
        "BAUMPATENSCHAFT": null,
        "ALTERSKLASSIZIERUNG": "mittel",
        "OBJECTID": 1197
      },
      "geometry": {
        "type": "Point",
        "coordinates": [
          15.435689849584069,
          47.06143974384461
        ]
      }
    },
    {
      "type": "Feature",
      "properties": {
        "NUMMER": 205,
        "BAUMBEZEICHNUNG_BOTANISCH": "Acer pseudoplatanus",
        "BAUMBEZEICHNUNG_DEUTSCH": "Bergahorn",
        "BAUMTYP": "Laub",
        "BEMERKUNG": null,
        "PFLANZJAHR": null,
        "ENTNAHMEJAHR": null,
        "BAUMPATENSCHAFT": null,
        "ALTERSKLASSIZIERUNG": "mittel",
        "OBJECTID": 1125
      },
      "geometry": {
        "type": "Point",
        "coordinates": [
          15.435736766708374,
          47.061304224292925
        ]
      }
    },
    {
      "type": "Feature",
      "properties": {
        "NUMMER": 11225,
        "BAUMBEZEICHNUNG_BOTANISCH": "Prunus serrulata 'Kanzan'",
        "BAUMBEZEICHNUNG_DEUTSCH": "Japanische Blütenkirsche",
        "BAUMTYP": "Laub",
        "BEMERKUNG": null,
        "PFLANZJAHR": null,
        "ENTNAHMEJAHR": null,
        "BAUMPATENSCHAFT": null,
        "ALTERSKLASSIZIERUNG": "jung",
        "OBJECTID": 1136
      },
      "geometry": {
        "type": "Point",
        "coordinates": [
          15.4327138462704,
          47.05894583861781
        ]
      }
    }
  ]
}