{
  "type": "FeatureCollection",
  "features": [
    {
      "type": "Feature",
      "id": 377,
      "properties": {
        "nummer": 419,
        "objectid": 377,
        "baumbezeichnung_deutsch": "Bergahorn",
        "baumbezeichnung_botanisch": "Acer pseudoplatanus",
        "baumtyp": "Laub",
        "bemerkung": null,
        "pflanzjahr": null,
        "entnahmejahr": null,
        "baumpatenschaft": null,
        "altersklassifizierung": "mittel"
      },
      "geometry": {
        "type": "Point",
        "coordinates": [
          15.43540973231593,
          47.05980026569626
        ]
      }
    },
    {
      "type": "Feature",
      "id": 998,
      "properties": {
        "nummer": 11228,
        "objectid": 998,
        "baumbezeichnung_deutsch": "Japanische Blütenkirsche",
        "baumbezeichnung_botanisch": "Prunus serrulata 'Kanzan'",
        "baumtyp": "Laub",
        "bemerkung": null,
        "pflanzjahr": null,
        "entnahmejahr": null,
        "baumpatenschaft": null,
        "altersklassifizierung": "jung"
      },
      "geometry": {
        "type": "Point",
        "coordinates": [
          15.433066073815645,
          47.05896957512822
        ]
      }
    },
    {
      "type": "Feature",
      "id": 1125,
      "properties": {
        "nummer": 205,
        "objectid": 1125,
        "baumbezeichnung_deutsch": "Bergahorn",
        "baumbezeichnung_botanisch": "Acer pseudoplatanus",
        "baumtyp": "Laub",
        "bemerkung": null,
        "pflanzjahr": null,
        "entnahmejahr": null,
        "baumpatenschaft": null,
        "altersklassifizierung": "mittel"
      },
      "geometry": {
        "type": "Point",
        "coordinates": [
          15.435736766708374,
          47.061304224292925
        ]
      }
    },
    {
      "type": "Feature",
      "id": 1136,
      "properties": {
        "nummer": 11225,
        "objectid": 1136,
        "baumbezeichnung_deutsch": "Japanische Blütenkirsche",
        "baumbezeichnung_botanisch": "Prunus serrulata 'Kanzan'",
        "baumtyp": "Laub",
        "bemerkung": null,
        "pflanzjahr": null,
        "entnahmejahr": null,
        "baumpatenschaft": null,
        "altersklassifizierung": "jung"
      },
      "geometry": {
        "type": "Point",
        "coordinates": [
          15.4327138462704,
          47.05894583861781
        ]
      }
    },
    {
      "type": "Feature",
      "id": 1197,
      "properties": {
        "nummer": 203,
        "objectid": 1197,
        "baumbezeichnung_deutsch": "Bergahorn",
        "baumbezeichnung_botanisch": "Acer pseudoplatanus",
        "baumtyp": "Laub",
        "bemerkung": null,
        "pflanzjahr": null,
        "entnahmejahr": null,
        "baumpatenschaft": null,
        "altersklassifizierung": "mittel"
      },
      "geometry": {
        "type": "Point",
        "coordinates": [
          15.435689849584069,
          47.06143974384461
        ]
      }
    }
  ]
}