{"type":"FeatureCollection","features":[{"type":"Feature","properties":{"nummer":24031,"baumbezeichnung_botanisch":"Tilia tomentosa","baumbezeichnung_deutsch":"Silberlinde","baumtyp":"Laub","bemerkung":null,"pflanzjahr":"1984","entnahmejahr":null,"marker-size":"small","marker-symbol":"park2","marker-color":"#A3DDAD"},"geometry":{"type":"Point","coordinates":[15.44219387952788,47.07027779558946],"bbox":[15.44219387952788,47.07027779558946,15.44219387952788,47.07027779558946]}},{"type":"Feature","properties":{"nummer":5050,"baumbezeichnung_botanisch":"Tilia tomentosa","baumbezeichnung_deutsch":"Silberlinde","baumtyp":"Laub","bemerkung":null,"pflanzjahr":"1998","entnahmejahr":null,"marker-size":"small","marker-symbol":"park2","marker-color":"#A3DDAD"},"geometry":{"type":"Point","coordinates":[15.4422825758202,47.07019275571349],"bbox":[15.4422825758202,47.07019275571349,15.4422825758202,47.07019275571349]}}]}