{
  "type": "FeatureCollection",
  "features": [
    {
      "type": "Feature",
      "id": 1299,
      "properties": {
        "nummer": 16151,
        "objectid": 1299,
        "baumbezeichnung_deutsch": "Rotbuche",
        "baumbezeichnung_botanisch": "Fagus sylvatica",
        "baumtyp": "Laub",
        "bemerkung": null,
        "pflanzjahr": null,
        "entnahmejahr": null,
        "baumpatenschaft": null,
        "altersklassifizierung": "mittel"
      },
      "geometry": {
        "type": "Point",
        "coordinates": [
          15.42279618453065,
          47.0881299756585
        ]
      }
    },
    {
      "type": "Feature",
      "id": 1300,
      "properties": {
        "nummer": 16152,
        "objectid": 1300,
        "baumbezeichnung_deutsch": "Sandbirke, Weißbirke",
        "baumbezeichnung_botanisch": "Betula pendula",
        "baumtyp": "Laub",
        "bemerkung": null,
        "pflanzjahr": null,
        "entnahmejahr": null,
        "baumpatenschaft": null,
        "altersklassifizierung": "mittel"
      },
      "geometry": {
        "type": "Point",
        "coordinates": [
          15.422726727385033,
          47.088185933895076
        ]
      }
    }
  ]
}