{"type":"FeatureCollection","features":[{"type":"Feature","properties":{"nummer":11583,"baumbezeichnung_botanisch":"Prunus cerasifera 'Nigra'","baumbezeichnung_deutsch":"Echte Blutpflaume","baumtyp":"Laub","bemerkung":null,"pflanzjahr":"2005","entnahmejahr":null,"marker-size":"small","marker-symbol":"park2","marker-color":"#A3DDAD"},"geometry":{"type":"Point","coordinates":[15.44928071952333,47.06889817951026],"bbox":[15.44928071952333,47.06889817951026,15.44928071952333,47.06889817951026]}},{"type":"Feature","properties":{"nummer":1068,"baumbezeichnung_botanisch":"Prunus cerasifera 'Nigra'","baumbezeichnung_deutsch":"Echte Blutpflaume","baumtyp":"Laub","bemerkung":null,"pflanzjahr":"2005","entnahmejahr":null,"marker-size":"small","marker-symbol":"park2","marker-color":"#A3DDAD"},"geometry":{"type":"Point","coordinates":[15.44932802160956,47.06889527071036],"bbox":[15.44932802160956,47.06889527071036,15.44932802160956,47.06889527071036]}},{"type":"Feature","properties":{"nummer":14307,"baumbezeichnung_botanisch":"Prunus cerasifera 'Nigra'","baumbezeichnung_deutsch":"Echte Blutpflaume","baumtyp":"Laub","bemerkung":null,"pflanzjahr":"2005","entnahmejahr":null,"marker-size":"small","marker-symbol":"park2","marker-color":"#A3DDAD"},"geometry":{"type":"Point","coordinates":[15.44929464250537,47.06888194235037],"bbox":[15.44929464250537,47.06888194235037,15.44929464250537,47.06888194235037]}},{"type":"Feature","properties":{"nummer":18736,"baumbezeichnung_botanisch":"Prunus cerasifera 'Nigra'","baumbezeichnung_deutsch":"Echte Blutpflaume","baumtyp":"Laub","bemerkung":null,"pflanzjahr":"2005","entnahmejahr":null,"marker-size":"small","marker-symbol":"park2","marker-color":"#A3DDAD"},"geometry":{"type":"Point","coordinates":[15.4493229567987,47.0688702809001],"bbox":[15.4493229567987,47.0688702809001,15.4493229567987,47.0688702809001]}}]}