{"type":"FeatureCollection","features":[{"type":"Feature","properties":{"nummer":13768,"baumbezeichnung_botanisch":"Platanus x acerifolia","baumbezeichnung_deutsch":"Platane","baumtyp":"Laub","bemerkung":null,"pflanzjahr":null,"entnahmejahr":null,"marker-size":"small","marker-symbol":"park2","marker-color":"#A3DDAD"},"geometry":{"type":"Point","coordinates":[15.44816477842284,47.05497830789793],"bbox":[15.44816477842284,47.05497830789793,15.44816477842284,47.05497830789793]}},{"type":"Feature","properties":{"nummer":25564,"baumbezeichnung_botanisch":"Platanus x acerifolia","baumbezeichnung_deutsch":"Platane","baumtyp":"Laub","bemerkung":null,"pflanzjahr":"2000","entnahmejahr":null,"marker-size":"small","marker-symbol":"park2","marker-color":"#A3DDAD"},"geometry":{"type":"Point","coordinates":[15.44826198562894,47.05484782291556],"bbox":[15.44826198562894,47.05484782291556,15.44826198562894,47.05484782291556]}},{"type":"Feature","properties":{"nummer":22190,"baumbezeichnung_botanisch":"Platanus x acerifolia","baumbezeichnung_deutsch":"Platane","baumtyp":"Laub","bemerkung":null,"pflanzjahr":"2002","entnahmejahr":null,"marker-size":"small","marker-symbol":"park2","marker-color":"#A3DDAD"},"geometry":{"type":"Point","coordinates":[15.44849141700472,47.05453479955187],"bbox":[15.44849141700472,47.05453479955187,15.44849141700472,47.05453479955187]}},{"type":"Feature","properties":{"nummer":17035,"baumbezeichnung_botanisch":"Platanus x acerifolia","baumbezeichnung_deutsch":"Platane","baumtyp":"Laub","bemerkung":null,"pflanzjahr":"2002","entnahmejahr":null,"marker-size":"small","marker-symbol":"park2","marker-color":"#A3DDAD"},"geometry":{"type":"Point","coordinates":[15.44837986912241,47.0546919790021],"bbox":[15.44837986912241,47.0546919790021,15.44837986912241,47.0546919790021]}}]}