{"type":"FeatureCollection","features":[{"type":"Feature","properties":{"nummer":25775,"baumbezeichnung_botanisch":"Acer platanoides 'Olmstedt'","baumbezeichnung_deutsch":"Spitzahorn","baumtyp":"Laub","bemerkung":null,"pflanzjahr":"1991","entnahmejahr":null,"marker-size":"small","marker-symbol":"park2","marker-color":"#A3DDAD"},"geometry":{"type":"Point","coordinates":[15.44267056510027,47.06978699250965],"bbox":[15.44267056510027,47.06978699250965,15.44267056510027,47.06978699250965]}},{"type":"Feature","properties":{"nummer":23410,"baumbezeichnung_botanisch":"Acer platanoides","baumbezeichnung_deutsch":"Spitzahorn","baumtyp":"Laub","bemerkung":null,"pflanzjahr":"1991","entnahmejahr":null,"marker-size":"small","marker-symbol":"park2","marker-color":"#A3DDAD"},"geometry":{"type":"Point","coordinates":[15.44275726340798,47.06983716889555],"bbox":[15.44275726340798,47.06983716889555,15.44275726340798,47.06983716889555]}},{"type":"Feature","properties":{"nummer":26359,"baumbezeichnung_botanisch":"Acer platanoides","baumbezeichnung_deutsch":"Spitzahorn","baumtyp":"Laub","bemerkung":null,"pflanzjahr":"1991","entnahmejahr":null,"marker-size":"small","marker-symbol":"park2","marker-color":"#A3DDAD"},"geometry":{"type":"Point","coordinates":[15.44283813717395,47.06988610343323],"bbox":[15.44283813717395,47.06988610343323,15.44283813717395,47.06988610343323]}},{"type":"Feature","properties":{"nummer":12708,"baumbezeichnung_botanisch":"Tilia platyphyllos","baumbezeichnung_deutsch":"Sommerlinde","baumtyp":"Laub","bemerkung":null,"pflanzjahr":"1991","entnahmejahr":null,"marker-size":"small","marker-symbol":"park2","marker-color":"#A3DDAD"},"geometry":{"type":"Point","coordinates":[15.4430548495375,47.06998169347934],"bbox":[15.4430548495375,47.06998169347934,15.4430548495375,47.06998169347934]}}]}