{"type":"FeatureCollection","features":[{"type":"Feature","properties":{"nummer":24371,"baumbezeichnung_botanisch":"Acer platanoides","baumbezeichnung_deutsch":"Spitzahorn","baumtyp":"Laub","bemerkung":null,"pflanzjahr":"1985","entnahmejahr":null,"marker-size":"small","marker-symbol":"park2","marker-color":"#A3DDAD"},"geometry":{"type":"Point","coordinates":[15.44268658777409,47.06392284486565],"bbox":[15.44268658777409,47.06392284486565,15.44268658777409,47.06392284486565]}},{"type":"Feature","properties":{"nummer":3698,"baumbezeichnung_botanisch":"Acer platanoides","baumbezeichnung_deutsch":"Spitzahorn","baumtyp":"Laub","bemerkung":null,"pflanzjahr":"1985","entnahmejahr":null,"marker-size":"small","marker-symbol":"park2","marker-color":"#A3DDAD"},"geometry":{"type":"Point","coordinates":[15.4427454880325,47.06380990314391],"bbox":[15.4427454880325,47.06380990314391,15.4427454880325,47.06380990314391]}}]}