{"type":"FeatureCollection","features":[{"type":"Feature","properties":{"nummer":14909,"baumbezeichnung_botanisch":"Aesculus hippocastanum","baumbezeichnung_deutsch":"Gemeine Roßkastanie","baumtyp":"Laub","bemerkung":null,"pflanzjahr":null,"entnahmejahr":null,"marker-size":"small","marker-symbol":"park2","marker-color":"#A3DDAD"},"geometry":{"type":"Point","coordinates":[15.44357474233878,47.05260747265108],"bbox":[15.44357474233878,47.05260747265108,15.44357474233878,47.05260747265108]}}]}