{
  "type": "FeatureCollection",
  "features": [
    {
      "type": "Feature",
      "properties": {
        "nummer": 15861,
        "objectid": 602,
        "baumbezeichnung_deutsch": "Schwarzerle",
        "baumbezeichnung_botanisch": "Alnus glutinosa",
        "baumtyp": "Laub",
        "bemerkung": null,
        "pflanzjahr": null,
        "entnahmejahr": null,
        "baumpatenschaft": null,
        "altersklassifizierung": "mittel"
      },
      "geometry": {
        "type": "Point",
        "coordinates": [
          15.445152388973215,
          47.1039548279924
        ]
      }
    }
  ]
}