{
  "type": "FeatureCollection",
  "features": [
    {
      "type": "Feature",
      "properties": {
        "NUMMER": 2393,
        "BAUMBEZEICHNUNG_BOTANISCH": "Picea abies",
        "BAUMBEZEICHNUNG_DEUTSCH": "Rotfichte",
        "BAUMTYP": "Nadel",
        "BEMERKUNG": null,
        "PFLANZJAHR": null,
        "ENTNAHMEJAHR": null,
        "BAUMPATENSCHAFT": null,
        "ALTERSKLASSIZIERUNG": "mittel",
        "OBJECTID": 59
      },
      "geometry": {
        "type": "Point",
        "coordinates": [
          15.444145340718352,
          47.07679280140203
        ]
      }
    },
    {
      "type": "Feature",
      "properties": {
        "NUMMER": 10623,
        "BAUMBEZEICHNUNG_BOTANISCH": "Acer platanoides 'Globosum'",
        "BAUMBEZEICHNUNG_DEUTSCH": "Kugelahorn",
        "BAUMTYP": "Laub",
        "BEMERKUNG": null,
        "PFLANZJAHR": "1989",
        "ENTNAHMEJAHR": null,
        "BAUMPATENSCHAFT": null,
        "ALTERSKLASSIZIERUNG": "jung",
        "OBJECTID": 1393
      },
      "geometry": {
        "type": "Point",
        "coordinates": [
          15.445728944590918,
          47.07733378035664
        ]
      }
    },
    {
      "type": "Feature",
      "properties": {
        "NUMMER": 2288,
        "BAUMBEZEICHNUNG_BOTANISCH": "Chamaecyparis pisifera 'Squarrosa'",
        "BAUMBEZEICHNUNG_DEUTSCH": "Silber Sawarascheinzypresse",
        "BAUMTYP": "Nadel",
        "BEMERKUNG": null,
        "PFLANZJAHR": null,
        "ENTNAHMEJAHR": null,
        "BAUMPATENSCHAFT": null,
        "ALTERSKLASSIZIERUNG": "mittel",
        "OBJECTID": 1123
      },
      "geometry": {
        "type": "Point",
        "coordinates": [
          15.444857520580058,
          47.07573925465556
        ]
      }
    }
  ]
}