{
  "type": "FeatureCollection",
  "features": [
    {
      "type": "Feature",
      "id": 59,
      "properties": {
        "nummer": 2393,
        "objectid": 59,
        "baumbezeichnung_deutsch": "Rotfichte",
        "baumbezeichnung_botanisch": "Picea abies",
        "baumtyp": "Nadel",
        "bemerkung": null,
        "pflanzjahr": null,
        "entnahmejahr": null,
        "baumpatenschaft": null,
        "altersklassifizierung": "mittel"
      },
      "geometry": {
        "type": "Point",
        "coordinates": [
          15.444145340718352,
          47.07679280140203
        ]
      }
    },
    {
      "type": "Feature",
      "id": 1123,
      "properties": {
        "nummer": 2288,
        "objectid": 1123,
        "baumbezeichnung_deutsch": "Silber Sawarascheinzypresse",
        "baumbezeichnung_botanisch": "Chamaecyparis pisifera 'Squarrosa'",
        "baumtyp": "Nadel",
        "bemerkung": null,
        "pflanzjahr": null,
        "entnahmejahr": null,
        "baumpatenschaft": null,
        "altersklassifizierung": "mittel"
      },
      "geometry": {
        "type": "Point",
        "coordinates": [
          15.444857520580058,
          47.07573925465556
        ]
      }
    },
    {
      "type": "Feature",
      "id": 1393,
      "properties": {
        "nummer": 10623,
        "objectid": 1393,
        "baumbezeichnung_deutsch": "Kugelahorn",
        "baumbezeichnung_botanisch": "Acer platanoides 'Globosum'",
        "baumtyp": "Laub",
        "bemerkung": null,
        "pflanzjahr": "1989",
        "entnahmejahr": null,
        "baumpatenschaft": null,
        "altersklassifizierung": "jung"
      },
      "geometry": {
        "type": "Point",
        "coordinates": [
          15.445728944590918,
          47.07733378035664
        ]
      }
    }
  ]
}