{
  "type": "FeatureCollection",
  "features": [
    {
      "type": "Feature",
      "properties": {
        "nummer": 6203,
        "baumbezeichnung_botanisch": "Acer pseudoplatanus",
        "baumbezeichnung_deutsch": "Bergahorn",
        "baumtyp": "Laub",
        "altersklassifizierung": "jung",
        "bemerkung": null,
        "pflanzjahr": null,
        "entnahmejahr": null,
        "baumpatenschaft": null,
        "objectid": 17755
      },
      "geometry": {
        "type": "Point",
        "coordinates": [
          15.44443316805252,
          47.04160487126267
        ]
      }
    },
    {
      "type": "Feature",
      "properties": {
        "nummer": 6206,
        "baumbezeichnung_botanisch": "Acer pseudoplatanus",
        "baumbezeichnung_deutsch": "Bergahorn",
        "baumtyp": "Laub",
        "altersklassifizierung": "jung",
        "bemerkung": null,
        "pflanzjahr": null,
        "entnahmejahr": null,
        "baumpatenschaft": null,
        "objectid": 15124
      },
      "geometry": {
        "type": "Point",
        "coordinates": [
          15.444382504984842,
          47.04184981904837
        ]
      }
    },
    {
      "type": "Feature",
      "properties": {
        "nummer": 6205,
        "baumbezeichnung_botanisch": "Acer pseudoplatanus",
        "baumbezeichnung_deutsch": "Bergahorn",
        "baumtyp": "Laub",
        "altersklassifizierung": "jung",
        "bemerkung": null,
        "pflanzjahr": null,
        "entnahmejahr": null,
        "baumpatenschaft": null,
        "objectid": 15125
      },
      "geometry": {
        "type": "Point",
        "coordinates": [
          15.444397819860935,
          47.0417772756107
        ]
      }
    },
    {
      "type": "Feature",
      "properties": {
        "nummer": 6204,
        "baumbezeichnung_botanisch": "Acer pseudoplatanus",
        "baumbezeichnung_deutsch": "Bergahorn",
        "baumtyp": "Laub",
        "altersklassifizierung": "jung",
        "bemerkung": null,
        "pflanzjahr": null,
        "entnahmejahr": null,
        "baumpatenschaft": null,
        "objectid": 22379
      },
      "geometry": {
        "type": "Point",
        "coordinates": [
          15.444422478683512,
          47.041658057215116
        ]
      }
    },
    {
      "type": "Feature",
      "properties": {
        "nummer": 6207,
        "baumbezeichnung_botanisch": "Acer pseudoplatanus",
        "baumbezeichnung_deutsch": "Bergahorn",
        "baumtyp": "Laub",
        "altersklassifizierung": "jung",
        "bemerkung": null,
        "pflanzjahr": null,
        "entnahmejahr": null,
        "baumpatenschaft": null,
        "objectid": 19810
      },
      "geometry": {
        "type": "Point",
        "coordinates": [
          15.444360505148525,
          47.04195870473892
        ]
      }
    },
    {
      "type": "Feature",
      "properties": {
        "nummer": 6202,
        "baumbezeichnung_botanisch": "Acer pseudoplatanus",
        "baumbezeichnung_deutsch": "Bergahorn",
        "baumtyp": "Laub",
        "altersklassifizierung": "jung",
        "bemerkung": null,
        "pflanzjahr": null,
        "entnahmejahr": null,
        "baumpatenschaft": null,
        "objectid": 28834
      },
      "geometry": {
        "type": "Point",
        "coordinates": [
          15.444443290545554,
          47.04155332700428
        ]
      }
    }
  ]
}