{
  "type": "FeatureCollection",
  "features": [
    {
      "type": "Feature",
      "properties": {
        "NUMMER": 18526,
        "BAUMBEZEICHNUNG_BOTANISCH": "Salix alba 'Tristis'",
        "BAUMBEZEICHNUNG_DEUTSCH": "Trauerweide",
        "BAUMTYP": "Laub",
        "BEMERKUNG": null,
        "PFLANZJAHR": null,
        "ENTNAHMEJAHR": null,
        "BAUMPATENSCHAFT": null,
        "ALTERSKLASSIZIERUNG": "jung",
        "OBJECTID": 512
      },
      "geometry": {
        "type": "Point",
        "coordinates": [
          15.461106359204765,
          47.08475700852075
        ]
      }
    },
    {
      "type": "Feature",
      "properties": {
        "Naturdenkmal": true,
        "Naturdenkmal_Eigentum": "öffentlich",
        "nummer": "Naturdenkmal-80",
        "objectid": "Naturdenkmal-91",
        "baumbezeichnung_deutsch": "Hemlocktanne",
        "baumbezeichnung_botanisch": null
      },
      "geometry": {
        "type": "Point",
        "coordinates": [
          15.462794735195017,
          47.08334697868862
        ]
      }
    }
  ]
}