{"type":"FeatureCollection","features":[{"type":"Feature","properties":{"nummer":14302,"baumbezeichnung_botanisch":"Juglans regia","baumbezeichnung_deutsch":"Walnuß","baumtyp":"Laub","bemerkung":null,"pflanzjahr":null,"entnahmejahr":null,"marker-size":"small","marker-symbol":"park2","marker-color":"#A3DDAD"},"geometry":{"type":"Point","coordinates":[15.46075104469656,47.08966812780124],"bbox":[15.46075104469656,47.08966812780124,15.46075104469656,47.08966812780124]}},{"type":"Feature","properties":{"nummer":28255,"baumbezeichnung_botanisch":"Salix sp.","baumbezeichnung_deutsch":"Weide","baumtyp":"Laub","bemerkung":null,"pflanzjahr":null,"entnahmejahr":"2011","marker-size":"small","marker-symbol":"park2","marker-color":"#B3B3B3"},"geometry":{"type":"Point","coordinates":[15.46216830664742,47.09068738633538],"bbox":[15.46216830664742,47.09068738633538,15.46216830664742,47.09068738633538]}}]}