{
  "type": "FeatureCollection",
  "features": [
    {
      "type": "Feature",
      "properties": {
        "nummer": 18526,
        "objectid": 512,
        "baumbezeichnung_deutsch": "Trauerweide",
        "baumbezeichnung_botanisch": "Salix alba 'Tristis'",
        "baumtyp": "Laub",
        "bemerkung": null,
        "pflanzjahr": null,
        "entnahmejahr": null,
        "baumpatenschaft": null,
        "altersklassifizierung": "jung"
      },
      "geometry": {
        "type": "Point",
        "coordinates": [
          15.461106359204765,
          47.08475700852075
        ]
      }
    },
    {
      "type": "Feature",
      "properties": {
        "Naturdenkmal": true,
        "Naturdenkmal_Eigentum": "öffentlich",
        "nummer": "Naturdenkmal-80",
        "objectid": "Naturdenkmal-91",
        "baumbezeichnung_deutsch": "Hemlocktanne",
        "baumbezeichnung_botanisch": null
      },
      "geometry": {
        "type": "Point",
        "coordinates": [
          15.462794735195017,
          47.08334697868862
        ]
      }
    }
  ]
}