{
  "type": "FeatureCollection",
  "features": [
    {
      "type": "Feature",
      "properties": {
        "nummer": 11213,
        "baumbezeichnung_botanisch": "Juglans regia",
        "baumbezeichnung_deutsch": "Walnuß",
        "baumtyp": "Laub",
        "altersklassifizierung": "alt",
        "bemerkung": null,
        "pflanzjahr": null,
        "entnahmejahr": null,
        "baumpatenschaft": null,
        "objectid": 20961
      },
      "geometry": {
        "type": "Point",
        "coordinates": [
          15.460751044696558,
          47.08966812780124
        ]
      }
    }
  ]
}