{
  "type": "FeatureCollection",
  "features": [
    {
      "type": "Feature",
      "properties": {
        "nummer": 30931,
        "baumbezeichnung_botanisch": "Flächenkartierung",
        "baumbezeichnung_deutsch": "Flächenkartierung",
        "baumtyp": "Flächenkartierung",
        "altersklassifizierung": "mittel",
        "bemerkung": null,
        "pflanzjahr": null,
        "entnahmejahr": null,
        "baumpatenschaft": null,
        "objectid": 28927
      },
      "geometry": {
        "type": "Point",
        "coordinates": [
          15.462512057666101,
          47.04362587861337
        ]
      }
    },
    {
      "type": "Feature",
      "properties": {
        "nummer": 30932,
        "baumbezeichnung_botanisch": "Flächenkartierung",
        "baumbezeichnung_deutsch": "Flächenkartierung",
        "baumtyp": "Flächenkartierung",
        "altersklassifizierung": "mittel",
        "bemerkung": null,
        "pflanzjahr": null,
        "entnahmejahr": null,
        "baumpatenschaft": null,
        "objectid": 28928
      },
      "geometry": {
        "type": "Point",
        "coordinates": [
          15.46249278680811,
          47.04373997063172
        ]
      }
    }
  ]
}