{"type":"FeatureCollection","features":[{"type":"Feature","properties":{"nummer":56250,"baumbezeichnung_botanisch":"Flächenkartierung","baumbezeichnung_deutsch":"Flächenkartierung","baumtyp":"Flächenkartierung","bemerkung":null,"pflanzjahr":null,"entnahmejahr":null,"marker-size":"small","marker-symbol":"","marker-color":null},"geometry":{"type":"Point","coordinates":[15.4625120576661,47.04362587861337],"bbox":[15.4625120576661,47.04362587861337,15.4625120576661,47.04362587861337]}},{"type":"Feature","properties":{"nummer":56251,"baumbezeichnung_botanisch":"Flächenkartierung","baumbezeichnung_deutsch":"Flächenkartierung","baumtyp":"Flächenkartierung","bemerkung":null,"pflanzjahr":null,"entnahmejahr":null,"marker-size":"small","marker-symbol":"","marker-color":null},"geometry":{"type":"Point","coordinates":[15.46249278680811,47.04373997063172],"bbox":[15.46249278680811,47.04373997063172,15.46249278680811,47.04373997063172]}}]}