{"type":"FeatureCollection","features":[{"type":"Feature","properties":{"nummer":21325,"baumbezeichnung_botanisch":"Fraxinus excelsior 'Globosum'","baumbezeichnung_deutsch":"Kugelesche","baumtyp":"Laub","bemerkung":null,"pflanzjahr":null,"entnahmejahr":null,"marker-size":"small","marker-symbol":"park2","marker-color":"#A3DDAD"},"geometry":{"type":"Point","coordinates":[15.46107680414235,47.076189311363],"bbox":[15.46107680414235,47.076189311363,15.46107680414235,47.076189311363]}},{"type":"Feature","properties":{"nummer":13745,"baumbezeichnung_botanisch":"Fraxinus excelsior 'Globosum'","baumbezeichnung_deutsch":"Kugelesche","baumtyp":"Laub","bemerkung":null,"pflanzjahr":null,"entnahmejahr":null,"marker-size":"small","marker-symbol":"park2","marker-color":"#A3DDAD"},"geometry":{"type":"Point","coordinates":[15.4610057930471,47.0761636724613],"bbox":[15.4610057930471,47.0761636724613,15.4610057930471,47.0761636724613]}},{"type":"Feature","properties":{"nummer":12995,"baumbezeichnung_botanisch":"Fraxinus excelsior 'Globosum'","baumbezeichnung_deutsch":"Kugelesche","baumtyp":"Laub","bemerkung":null,"pflanzjahr":null,"entnahmejahr":null,"marker-size":"small","marker-symbol":"park2","marker-color":"#A3DDAD"},"geometry":{"type":"Point","coordinates":[15.46093708365376,47.07613899558924],"bbox":[15.46093708365376,47.07613899558924,15.46093708365376,47.07613899558924]}},{"type":"Feature","properties":{"nummer":10957,"baumbezeichnung_botanisch":"Fraxinus excelsior 'Globosum'","baumbezeichnung_deutsch":"Kugelesche","baumtyp":"Laub","bemerkung":null,"pflanzjahr":null,"entnahmejahr":null,"marker-size":"small","marker-symbol":"park2","marker-color":"#A3DDAD"},"geometry":{"type":"Point","coordinates":[15.4608681861582,47.07611214042882],"bbox":[15.4608681861582,47.07611214042882,15.4608681861582,47.07611214042882]}},{"type":"Feature","properties":{"nummer":3647,"baumbezeichnung_botanisch":"Fraxinus excelsior 'Globosum'","baumbezeichnung_deutsch":"Kugelesche","baumtyp":"Laub","bemerkung":null,"pflanzjahr":null,"entnahmejahr":null,"marker-size":"small","marker-symbol":"park2","marker-color":"#A3DDAD"},"geometry":{"type":"Point","coordinates":[15.46074224858218,47.07606282926607],"bbox":[15.46074224858218,47.07606282926607,15.46074224858218,47.07606282926607]}},{"type":"Feature","properties":{"nummer":15538,"baumbezeichnung_botanisch":"Fraxinus excelsior 'Globosum'","baumbezeichnung_deutsch":"Kugelesche","baumtyp":"Laub","bemerkung":null,"pflanzjahr":null,"entnahmejahr":null,"marker-size":"small","marker-symbol":"park2","marker-color":"#A3DDAD"},"geometry":{"type":"Point","coordinates":[15.46067312133965,47.076037150587],"bbox":[15.46067312133965,47.076037150587,15.46067312133965,47.076037150587]}},{"type":"Feature","properties":{"nummer":24025,"baumbezeichnung_botanisch":"Robinia pseudoacacia","baumbezeichnung_deutsch":"Scheinakazie","baumtyp":"Laub","bemerkung":null,"pflanzjahr":null,"entnahmejahr":null,"marker-size":"small","marker-symbol":"park2","marker-color":"#A3DDAD"},"geometry":{"type":"Point","coordinates":[15.46060582374028,47.07600990272011],"bbox":[15.46060582374028,47.07600990272011,15.46060582374028,47.07600990272011]}},{"type":"Feature","properties":{"nummer":8677,"baumbezeichnung_botanisch":"Fraxinus excelsior 'Globosum'","baumbezeichnung_deutsch":"Kugelesche","baumtyp":"Laub","bemerkung":null,"pflanzjahr":null,"entnahmejahr":null,"marker-size":"small","marker-symbol":"park2","marker-color":"#A3DDAD"},"geometry":{"type":"Point","coordinates":[15.46053882588025,47.07598686680266],"bbox":[15.46053882588025,47.07598686680266,15.46053882588025,47.07598686680266]}}]}