{"type":"FeatureCollection","features":[{"type":"Feature","properties":{"nummer":27658,"baumbezeichnung_botanisch":"Ulmus glabra","baumbezeichnung_deutsch":"Bergulme","baumtyp":"Laub","altersklassifizierung":"mittel","bemerkung":null,"pflanzjahr":null,"entnahmejahr":null,"baumpatenschaft":null,"objectid":23677},"geometry":{"type":"Point","coordinates":[15.374513687020437,47.11127485202119],"bbox":[15.374513687020437,47.11127485202119,15.374513687020437,47.11127485202119]}}]}