{"type":"FeatureCollection","features":[{"type":"Feature","properties":{"nummer":8498,"baumbezeichnung_botanisch":"Ulmus glabra","baumbezeichnung_deutsch":"Bergulme","baumtyp":"Laub","bemerkung":null,"pflanzjahr":null,"entnahmejahr":null,"marker-size":"small","marker-symbol":"park2","marker-color":"#A3DDAD"},"geometry":{"type":"Point","coordinates":[15.37451368702044,47.11127485202119],"bbox":[15.37451368702044,47.11127485202119,15.37451368702044,47.11127485202119]}}]}