{"type":"FeatureCollection","features":[{"type":"Feature","properties":{"nummer":27653,"baumbezeichnung_botanisch":"Betula pendula","baumbezeichnung_deutsch":"Sandbirke, Weißbirke","baumtyp":"Laub","altersklassifizierung":"mittel","bemerkung":null,"pflanzjahr":null,"entnahmejahr":null,"baumpatenschaft":null,"objectid":1782},"geometry":{"type":"Point","coordinates":[15.37416003386682,47.11123309906049],"bbox":[15.37416003386682,47.11123309906049,15.37416003386682,47.11123309906049]}},{"type":"Feature","properties":{"nummer":27654,"baumbezeichnung_botanisch":"Betula pendula","baumbezeichnung_deutsch":"Sandbirke, Weißbirke","baumtyp":"Laub","altersklassifizierung":"mittel","bemerkung":null,"pflanzjahr":null,"entnahmejahr":null,"baumpatenschaft":null,"objectid":1786},"geometry":{"type":"Point","coordinates":[15.37416040021256,47.11121277064469],"bbox":[15.37416040021256,47.11121277064469,15.37416040021256,47.11121277064469]}},{"type":"Feature","properties":{"nummer":27656,"baumbezeichnung_botanisch":"Betula pendula","baumbezeichnung_deutsch":"Sandbirke, Weißbirke","baumtyp":"Laub","altersklassifizierung":"mittel","bemerkung":null,"pflanzjahr":null,"entnahmejahr":null,"baumpatenschaft":null,"objectid":1787},"geometry":{"type":"Point","coordinates":[15.37417246832038,47.1111857627523],"bbox":[15.37417246832038,47.1111857627523,15.37417246832038,47.1111857627523]}},{"type":"Feature","properties":{"nummer":27655,"baumbezeichnung_botanisch":"Betula pendula","baumbezeichnung_deutsch":"Sandbirke, Weißbirke","baumtyp":"Laub","altersklassifizierung":"mittel","bemerkung":null,"pflanzjahr":null,"entnahmejahr":null,"baumpatenschaft":null,"objectid":1789},"geometry":{"type":"Point","coordinates":[15.37416401472409,47.11119585794377],"bbox":[15.37416401472409,47.11119585794377,15.37416401472409,47.11119585794377]}},{"type":"Feature","properties":{"nummer":27657,"baumbezeichnung_botanisch":"Betula pendula","baumbezeichnung_deutsch":"Sandbirke, Weißbirke","baumtyp":"Laub","altersklassifizierung":"mittel","bemerkung":null,"pflanzjahr":null,"entnahmejahr":null,"baumpatenschaft":null,"objectid":1790},"geometry":{"type":"Point","coordinates":[15.374184232450613,47.111175695366164],"bbox":[15.374184232450613,47.111175695366164,15.374184232450613,47.111175695366164]}}]}