{
  "type": "FeatureCollection",
  "features": [
    {
      "type": "Feature",
      "properties": {
        "NUMMER": 6254,
        "BAUMBEZEICHNUNG_BOTANISCH": "Platanus x acerifolia",
        "BAUMBEZEICHNUNG_DEUTSCH": "Platane",
        "BAUMTYP": "Laub",
        "BEMERKUNG": null,
        "PFLANZJAHR": null,
        "ENTNAHMEJAHR": null,
        "BAUMPATENSCHAFT": null,
        "ALTERSKLASSIZIERUNG": "alt",
        "OBJECTID": 779
      },
      "geometry": {
        "type": "Point",
        "coordinates": [
          15.3958003317158,
          47.07234060564999
        ]
      }
    }
  ]
}