{
  "type": "FeatureCollection",
  "features": [
    {
      "type": "Feature",
      "properties": {
        "NUMMER": 15911,
        "BAUMBEZEICHNUNG_BOTANISCH": "Acer platanoides",
        "BAUMBEZEICHNUNG_DEUTSCH": "Spitzahorn",
        "BAUMTYP": "Laub",
        "BEMERKUNG": null,
        "PFLANZJAHR": null,
        "ENTNAHMEJAHR": null,
        "BAUMPATENSCHAFT": null,
        "ALTERSKLASSIZIERUNG": "mittel",
        "OBJECTID": 403
      },
      "geometry": {
        "type": "Point",
        "coordinates": [
          15.396875623670613,
          47.06622952441149
        ]
      }
    },
    {
      "type": "Feature",
      "properties": {
        "NUMMER": 15915,
        "BAUMBEZEICHNUNG_BOTANISCH": "Acer negundo",
        "BAUMBEZEICHNUNG_DEUTSCH": "Eschenahorn",
        "BAUMTYP": "Laub",
        "BEMERKUNG": null,
        "PFLANZJAHR": null,
        "ENTNAHMEJAHR": null,
        "BAUMPATENSCHAFT": null,
        "ALTERSKLASSIZIERUNG": "mittel",
        "OBJECTID": 408
      },
      "geometry": {
        "type": "Point",
        "coordinates": [
          15.396269308146493,
          47.06629086181793
        ]
      }
    }
  ]
}