{
  "type": "FeatureCollection",
  "features": [
    {
      "type": "Feature",
      "properties": {
        "NUMMER": 12942,
        "BAUMBEZEICHNUNG_BOTANISCH": "Acer negundo",
        "BAUMBEZEICHNUNG_DEUTSCH": "Eschenahorn",
        "BAUMTYP": "Laub",
        "BEMERKUNG": null,
        "PFLANZJAHR": null,
        "ENTNAHMEJAHR": null,
        "BAUMPATENSCHAFT": null,
        "ALTERSKLASSIZIERUNG": "mittel",
        "OBJECTID": 623
      },
      "geometry": {
        "type": "Point",
        "coordinates": [
          15.394963234639546,
          47.06267902412128
        ]
      }
    }
  ]
}