{
  "type": "FeatureCollection",
  "features": [
    {
      "type": "Feature",
      "properties": {
        "nummer": 15911,
        "objectid": 403,
        "baumbezeichnung_deutsch": "Spitzahorn",
        "baumbezeichnung_botanisch": "Acer platanoides",
        "baumtyp": "Laub",
        "bemerkung": null,
        "pflanzjahr": null,
        "entnahmejahr": null,
        "baumpatenschaft": null,
        "altersklassifizierung": "mittel"
      },
      "geometry": {
        "type": "Point",
        "coordinates": [
          15.396875623670613,
          47.06622952441149
        ]
      }
    },
    {
      "type": "Feature",
      "properties": {
        "nummer": 15915,
        "objectid": 408,
        "baumbezeichnung_deutsch": "Eschenahorn",
        "baumbezeichnung_botanisch": "Acer negundo",
        "baumtyp": "Laub",
        "bemerkung": null,
        "pflanzjahr": null,
        "entnahmejahr": null,
        "baumpatenschaft": null,
        "altersklassifizierung": "mittel"
      },
      "geometry": {
        "type": "Point",
        "coordinates": [
          15.396269308146493,
          47.06629086181793
        ]
      }
    }
  ]
}