{
  "type": "FeatureCollection",
  "features": [
    {
      "type": "Feature",
      "id": 779,
      "properties": {
        "nummer": 6254,
        "objectid": 779,
        "baumbezeichnung_deutsch": "Platane",
        "baumbezeichnung_botanisch": "Platanus x acerifolia",
        "baumtyp": "Laub",
        "bemerkung": null,
        "pflanzjahr": null,
        "entnahmejahr": null,
        "baumpatenschaft": null,
        "altersklassifizierung": "alt"
      },
      "geometry": {
        "type": "Point",
        "coordinates": [
          15.3958003317158,
          47.07234060564999
        ]
      }
    }
  ]
}