{
  "type": "FeatureCollection",
  "features": [
    {
      "type": "Feature",
      "id": 623,
      "properties": {
        "nummer": 12942,
        "objectid": 623,
        "baumbezeichnung_deutsch": "Eschenahorn",
        "baumbezeichnung_botanisch": "Acer negundo",
        "baumtyp": "Laub",
        "bemerkung": null,
        "pflanzjahr": null,
        "entnahmejahr": null,
        "baumpatenschaft": null,
        "altersklassifizierung": "mittel"
      },
      "geometry": {
        "type": "Point",
        "coordinates": [
          15.394963234639546,
          47.06267902412128
        ]
      }
    }
  ]
}