{"type":"FeatureCollection","features":[{"type":"Feature","properties":{"nummer":29421,"baumbezeichnung_botanisch":"Fraxinus excelsior","baumbezeichnung_deutsch":"Esche","baumtyp":"Laub","altersklassifizierung":"mittel","bemerkung":null,"pflanzjahr":null,"entnahmejahr":null,"baumpatenschaft":null,"objectid":8475},"geometry":{"type":"Point","coordinates":[15.384947786504263,47.06312613301088],"bbox":[15.384947786504263,47.06312613301088,15.384947786504263,47.06312613301088]}}]}