{"type":"FeatureCollection","features":[{"type":"Feature","properties":{"nummer":32328,"baumbezeichnung_botanisch":"Fraxinus excelsior","baumbezeichnung_deutsch":"Esche","baumtyp":"Laub","bemerkung":null,"pflanzjahr":null,"entnahmejahr":null,"marker-size":"small","marker-symbol":"park2","marker-color":"#A3DDAD"},"geometry":{"type":"Point","coordinates":[15.38494778650426,47.06312613301088],"bbox":[15.38494778650426,47.06312613301088,15.38494778650426,47.06312613301088]}}]}