{"type":"FeatureCollection","features":[{"type":"Feature","properties":{"nummer":14902,"baumbezeichnung_botanisch":"Robinia pseudoacacia","baumbezeichnung_deutsch":"Scheinakazie","baumtyp":"Laub","bemerkung":null,"pflanzjahr":null,"entnahmejahr":null,"marker-size":"small","marker-symbol":"park2","marker-color":"#A3DDAD"},"geometry":{"type":"Point","coordinates":[15.38611866725766,47.04933593588316],"bbox":[15.38611866725766,47.04933593588316,15.38611866725766,47.04933593588316]}},{"type":"Feature","properties":{"nummer":20645,"baumbezeichnung_botanisch":"Prunus domestica","baumbezeichnung_deutsch":"Pflaume","baumtyp":"Laub","bemerkung":null,"pflanzjahr":null,"entnahmejahr":null,"marker-size":"small","marker-symbol":"park2","marker-color":"#A3DDAD"},"geometry":{"type":"Point","coordinates":[15.38609661311792,47.04942174639535],"bbox":[15.38609661311792,47.04942174639535,15.38609661311792,47.04942174639535]}},{"type":"Feature","properties":{"nummer":11435,"baumbezeichnung_botanisch":"Carpinus betulus","baumbezeichnung_deutsch":"Hain - oder Weißbuche","baumtyp":"Laub","bemerkung":null,"pflanzjahr":null,"entnahmejahr":null,"marker-size":"small","marker-symbol":"park2","marker-color":"#A3DDAD"},"geometry":{"type":"Point","coordinates":[15.38631172704206,47.04782401592066],"bbox":[15.38631172704206,47.04782401592066,15.38631172704206,47.04782401592066]}},{"type":"Feature","properties":{"nummer":2586,"baumbezeichnung_botanisch":"Carpinus betulus","baumbezeichnung_deutsch":"Hain - oder Weißbuche","baumtyp":"Laub","bemerkung":null,"pflanzjahr":null,"entnahmejahr":null,"marker-size":"small","marker-symbol":"park2","marker-color":"#A3DDAD"},"geometry":{"type":"Point","coordinates":[15.38620142836284,47.04787689188607],"bbox":[15.38620142836284,47.04787689188607,15.38620142836284,47.04787689188607]}},{"type":"Feature","properties":{"nummer":21055,"baumbezeichnung_botanisch":"Carpinus betulus","baumbezeichnung_deutsch":"Hain - oder Weißbuche","baumtyp":"Laub","bemerkung":null,"pflanzjahr":null,"entnahmejahr":null,"marker-size":"small","marker-symbol":"park2","marker-color":"#A3DDAD"},"geometry":{"type":"Point","coordinates":[15.38615448616385,47.04789692141814],"bbox":[15.38615448616385,47.04789692141814,15.38615448616385,47.04789692141814]}},{"type":"Feature","properties":{"nummer":2587,"baumbezeichnung_botanisch":"Carpinus betulus","baumbezeichnung_deutsch":"Hain - oder Weißbuche","baumtyp":"Laub","bemerkung":null,"pflanzjahr":null,"entnahmejahr":null,"marker-size":"small","marker-symbol":"park2","marker-color":"#A3DDAD"},"geometry":{"type":"Point","coordinates":[15.38613576714167,47.04790612106361],"bbox":[15.38613576714167,47.04790612106361,15.38613576714167,47.04790612106361]}}]}