{"type":"FeatureCollection","features":[{"type":"Feature","properties":{"nummer":24998,"baumbezeichnung_botanisch":"Robinia pseudoacacia","baumbezeichnung_deutsch":"Scheinakazie","baumtyp":"Laub","altersklassifizierung":"alt","bemerkung":null,"pflanzjahr":null,"entnahmejahr":null,"baumpatenschaft":null,"objectid":2985},"geometry":{"type":"Point","coordinates":[15.386118667257657,47.04933593588316],"bbox":[15.386118667257657,47.04933593588316,15.386118667257657,47.04933593588316]}},{"type":"Feature","properties":{"nummer":20035,"baumbezeichnung_botanisch":"Carpinus betulus","baumbezeichnung_deutsch":"Hain - oder Weißbuche","baumtyp":"Laub","altersklassifizierung":"mittel","bemerkung":null,"pflanzjahr":null,"entnahmejahr":null,"baumpatenschaft":null,"objectid":4663},"geometry":{"type":"Point","coordinates":[15.386311727042056,47.04782401592066],"bbox":[15.386311727042056,47.04782401592066,15.386311727042056,47.04782401592066]}},{"type":"Feature","properties":{"nummer":20037,"baumbezeichnung_botanisch":"Carpinus betulus","baumbezeichnung_deutsch":"Hain - oder Weißbuche","baumtyp":"Laub","altersklassifizierung":"mittel","bemerkung":null,"pflanzjahr":null,"entnahmejahr":null,"baumpatenschaft":null,"objectid":11208},"geometry":{"type":"Point","coordinates":[15.386154486163845,47.04789692141814],"bbox":[15.386154486163845,47.04789692141814,15.386154486163845,47.04789692141814]}},{"type":"Feature","properties":{"nummer":20036,"baumbezeichnung_botanisch":"Carpinus betulus","baumbezeichnung_deutsch":"Hain - oder Weißbuche","baumtyp":"Laub","altersklassifizierung":"mittel","bemerkung":null,"pflanzjahr":null,"entnahmejahr":null,"baumpatenschaft":null,"objectid":7023},"geometry":{"type":"Point","coordinates":[15.386201428362842,47.04787689188607],"bbox":[15.386201428362842,47.04787689188607,15.386201428362842,47.04787689188607]}},{"type":"Feature","properties":{"nummer":20038,"baumbezeichnung_botanisch":"Carpinus betulus","baumbezeichnung_deutsch":"Hain - oder Weißbuche","baumtyp":"Laub","altersklassifizierung":"mittel","bemerkung":null,"pflanzjahr":null,"entnahmejahr":null,"baumpatenschaft":null,"objectid":7024},"geometry":{"type":"Point","coordinates":[15.386135767141672,47.04790612106361],"bbox":[15.386135767141672,47.04790612106361,15.386135767141672,47.04790612106361]}},{"type":"Feature","properties":{"nummer":24999,"baumbezeichnung_botanisch":"Prunus domestica","baumbezeichnung_deutsch":"Pflaume","baumtyp":"Laub","altersklassifizierung":"alt","bemerkung":null,"pflanzjahr":null,"entnahmejahr":null,"baumpatenschaft":null,"objectid":26494},"geometry":{"type":"Point","coordinates":[15.386096613117916,47.04942174639535],"bbox":[15.386096613117916,47.04942174639535,15.386096613117916,47.04942174639535]}}]}