{"type":"FeatureCollection","features":[{"type":"Feature","properties":{"nummer":327,"baumbezeichnung_botanisch":"Sambucus nigra","baumbezeichnung_deutsch":"Schwarzer Hollunder","baumtyp":"Laub","bemerkung":null,"pflanzjahr":null,"entnahmejahr":null,"marker-size":"small","marker-symbol":"park2","marker-color":"#A3DDAD"},"geometry":{"type":"Point","coordinates":[15.41292737718919,47.08597574848713],"bbox":[15.41292737718919,47.08597574848713,15.41292737718919,47.08597574848713]}},{"type":"Feature","properties":{"nummer":15735,"baumbezeichnung_botanisch":"Robinia pseudoacacia","baumbezeichnung_deutsch":"Scheinakazie","baumtyp":"Laub","bemerkung":null,"pflanzjahr":null,"entnahmejahr":null,"marker-size":"small","marker-symbol":"park2","marker-color":"#A3DDAD"},"geometry":{"type":"Point","coordinates":[15.41305345901649,47.08582380539828],"bbox":[15.41305345901649,47.08582380539828,15.41305345901649,47.08582380539828]}}]}