{"type":"FeatureCollection","features":[{"type":"Feature","properties":{"nummer":17676,"baumbezeichnung_botanisch":"Aesculus hippocastanum","baumbezeichnung_deutsch":"Gemeine Roßkastanie","baumtyp":"Laub","bemerkung":null,"pflanzjahr":null,"entnahmejahr":null,"marker-size":"small","marker-symbol":"park2","marker-color":"#A3DDAD"},"geometry":{"type":"Point","coordinates":[15.41295713223142,47.07626076068235],"bbox":[15.41295713223142,47.07626076068235,15.41295713223142,47.07626076068235]}},{"type":"Feature","properties":{"nummer":23069,"baumbezeichnung_botanisch":"Aesculus hippocastanum","baumbezeichnung_deutsch":"Gemeine Roßkastanie","baumtyp":"Laub","bemerkung":null,"pflanzjahr":null,"entnahmejahr":null,"marker-size":"small","marker-symbol":"park2","marker-color":"#A3DDAD"},"geometry":{"type":"Point","coordinates":[15.41291651811391,47.07633053198951],"bbox":[15.41291651811391,47.07633053198951,15.41291651811391,47.07633053198951]}},{"type":"Feature","properties":{"nummer":10087,"baumbezeichnung_botanisch":"Aesculus hippocastanum","baumbezeichnung_deutsch":"Gemeine Roßkastanie","baumtyp":"Laub","bemerkung":null,"pflanzjahr":null,"entnahmejahr":null,"marker-size":"small","marker-symbol":"park2","marker-color":"#A3DDAD"},"geometry":{"type":"Point","coordinates":[15.41287927357225,47.07639731709291],"bbox":[15.41287927357225,47.07639731709291,15.41287927357225,47.07639731709291]}},{"type":"Feature","properties":{"nummer":28641,"baumbezeichnung_botanisch":"Aesculus hippocastanum","baumbezeichnung_deutsch":"Gemeine Roßkastanie","baumtyp":"Laub","bemerkung":null,"pflanzjahr":null,"entnahmejahr":null,"marker-size":"small","marker-symbol":"park2","marker-color":"#A3DDAD"},"geometry":{"type":"Point","coordinates":[15.41284852336393,47.07645096774458],"bbox":[15.41284852336393,47.07645096774458,15.41284852336393,47.07645096774458]}},{"type":"Feature","properties":{"nummer":10088,"baumbezeichnung_botanisch":"Aesculus hippocastanum","baumbezeichnung_deutsch":"Gemeine Roßkastanie","baumtyp":"Laub","bemerkung":null,"pflanzjahr":null,"entnahmejahr":null,"marker-size":"small","marker-symbol":"park2","marker-color":"#A3DDAD"},"geometry":{"type":"Point","coordinates":[15.41280984301797,47.07651777722861],"bbox":[15.41280984301797,47.07651777722861,15.41280984301797,47.07651777722861]}},{"type":"Feature","properties":{"nummer":7481,"baumbezeichnung_botanisch":"Aesculus hippocastanum","baumbezeichnung_deutsch":"Gemeine Roßkastanie","baumtyp":"Laub","bemerkung":null,"pflanzjahr":null,"entnahmejahr":null,"marker-size":"small","marker-symbol":"park2","marker-color":"#A3DDAD"},"geometry":{"type":"Point","coordinates":[15.41273210460773,47.07664809191274],"bbox":[15.41273210460773,47.07664809191274,15.41273210460773,47.07664809191274]}},{"type":"Feature","properties":{"nummer":4976,"baumbezeichnung_botanisch":"Aesculus hippocastanum","baumbezeichnung_deutsch":"Gemeine Roßkastanie","baumtyp":"Laub","bemerkung":null,"pflanzjahr":"1997","entnahmejahr":null,"marker-size":"small","marker-symbol":"park2","marker-color":"#A3DDAD"},"geometry":{"type":"Point","coordinates":[15.41277089179751,47.07657968219212],"bbox":[15.41277089179751,47.07657968219212,15.41277089179751,47.07657968219212]}}]}