{"type":"FeatureCollection","features":[{"type":"Feature","properties":{"nummer":15455,"baumbezeichnung_botanisch":"Prunus serrulata 'Kanzan'","baumbezeichnung_deutsch":"Japanische Blütenkirsche","baumtyp":"Laub","bemerkung":null,"pflanzjahr":"2003","entnahmejahr":null,"marker-size":"small","marker-symbol":"park2","marker-color":"#A3DDAD"},"geometry":{"type":"Point","coordinates":[15.3902062191212,47.06345836786765],"bbox":[15.3902062191212,47.06345836786765,15.3902062191212,47.06345836786765]}},{"type":"Feature","properties":{"nummer":4675,"baumbezeichnung_botanisch":"Prunus serrulata 'Kanzan'","baumbezeichnung_deutsch":"Japanische Blütenkirsche","baumtyp":"Laub","bemerkung":null,"pflanzjahr":"2007","entnahmejahr":null,"marker-size":"small","marker-symbol":"park2","marker-color":"#A3DDAD"},"geometry":{"type":"Point","coordinates":[15.38935506499324,47.06353371108617],"bbox":[15.38935506499324,47.06353371108617,15.38935506499324,47.06353371108617]}},{"type":"Feature","properties":{"nummer":15235,"baumbezeichnung_botanisch":"Prunus serrulata 'Kanzan'","baumbezeichnung_deutsch":"Japanische Blütenkirsche","baumtyp":"Laub","bemerkung":null,"pflanzjahr":"1987","entnahmejahr":null,"marker-size":"small","marker-symbol":"park2","marker-color":"#A3DDAD"},"geometry":{"type":"Point","coordinates":[15.39034674749615,47.06344548722905],"bbox":[15.39034674749615,47.06344548722905,15.39034674749615,47.06344548722905]}},{"type":"Feature","properties":{"nummer":22112,"baumbezeichnung_botanisch":"Prunus serrulata 'Kanzan'","baumbezeichnung_deutsch":"Japanische Blütenkirsche","baumtyp":"Laub","bemerkung":null,"pflanzjahr":"1987","entnahmejahr":null,"marker-size":"small","marker-symbol":"park2","marker-color":"#A3DDAD"},"geometry":{"type":"Point","coordinates":[15.39005281336069,47.0634714207937],"bbox":[15.39005281336069,47.0634714207937,15.39005281336069,47.0634714207937]}},{"type":"Feature","properties":{"nummer":4614,"baumbezeichnung_botanisch":"Prunus serrulata 'Kanzan'","baumbezeichnung_deutsch":"Japanische Blütenkirsche","baumtyp":"Laub","bemerkung":null,"pflanzjahr":"1987","entnahmejahr":null,"marker-size":"small","marker-symbol":"park2","marker-color":"#A3DDAD"},"geometry":{"type":"Point","coordinates":[15.38972744640669,47.0635001701583],"bbox":[15.38972744640669,47.0635001701583,15.38972744640669,47.0635001701583]}},{"type":"Feature","properties":{"nummer":15376,"baumbezeichnung_botanisch":"Prunus serrulata 'Kanzan'","baumbezeichnung_deutsch":"Japanische Blütenkirsche","baumtyp":"Laub","bemerkung":null,"pflanzjahr":"1987","entnahmejahr":null,"marker-size":"small","marker-symbol":"park2","marker-color":"#A3DDAD"},"geometry":{"type":"Point","coordinates":[15.38955078551907,47.06351661926591],"bbox":[15.38955078551907,47.06351661926591,15.38955078551907,47.06351661926591]}},{"type":"Feature","properties":{"nummer":18320,"baumbezeichnung_botanisch":"Prunus serrulata 'Kanzan'","baumbezeichnung_deutsch":"Japanische Blütenkirsche","baumtyp":"Laub","bemerkung":null,"pflanzjahr":"1987","entnahmejahr":null,"marker-size":"small","marker-symbol":"park2","marker-color":"#A3DDAD"},"geometry":{"type":"Point","coordinates":[15.38920308515481,47.06354575821565],"bbox":[15.38920308515481,47.06354575821565,15.38920308515481,47.06354575821565]}}]}