{"type":"FeatureCollection","features":[{"type":"Feature","properties":{"nummer":55271,"baumbezeichnung_botanisch":"Robinia pseudoacacia","baumbezeichnung_deutsch":"Scheinakazie","baumtyp":"Laub","bemerkung":null,"pflanzjahr":null,"entnahmejahr":null,"marker-size":"small","marker-symbol":"park2","marker-color":"#A3DDAD"},"geometry":{"type":"Point","coordinates":[15.41032970845017,47.08906143730049],"bbox":[15.41032970845017,47.08906143730049,15.41032970845017,47.08906143730049]}}]}