{"type":"FeatureCollection","features":[{"type":"Feature","properties":{"nummer":23148,"baumbezeichnung_botanisch":"Aesculus hippocastanum","baumbezeichnung_deutsch":"Gemeine Roßkastanie","baumtyp":"Laub","bemerkung":null,"pflanzjahr":null,"entnahmejahr":null,"marker-size":"small","marker-symbol":"park2","marker-color":"#A3DDAD"},"geometry":{"type":"Point","coordinates":[15.40973111671653,47.06604244609893],"bbox":[15.40973111671653,47.06604244609893,15.40973111671653,47.06604244609893]}}]}