{
  "type": "FeatureCollection",
  "features": [
    {
      "type": "Feature",
      "id": 422,
      "properties": {
        "nummer": 12013,
        "objectid": 422,
        "baumbezeichnung_deutsch": "Gemeine Roßkastanie",
        "baumbezeichnung_botanisch": "Aesculus hippocastanum",
        "baumtyp": "Laub",
        "bemerkung": null,
        "pflanzjahr": null,
        "entnahmejahr": null,
        "baumpatenschaft": null,
        "altersklassifizierung": "mittel"
      },
      "geometry": {
        "type": "Point",
        "coordinates": [
          15.416340948218854,
          47.078682305400484
        ]
      }
    },
    {
      "type": "Feature",
      "id": 1101,
      "properties": {
        "nummer": 27327,
        "objectid": 1101,
        "baumbezeichnung_deutsch": "Platane",
        "baumbezeichnung_botanisch": "Platanus x acerifolia",
        "baumtyp": "Laub",
        "bemerkung": null,
        "pflanzjahr": "2007",
        "entnahmejahr": null,
        "baumpatenschaft": null,
        "altersklassifizierung": "jung"
      },
      "geometry": {
        "type": "Point",
        "coordinates": [
          15.41650676029803,
          47.07826915984168
        ]
      }
    }
  ]
}