{
  "type": "FeatureCollection",
  "features": [
    {
      "type": "Feature",
      "properties": {
        "NUMMER": 12013,
        "BAUMBEZEICHNUNG_BOTANISCH": "Aesculus hippocastanum",
        "BAUMBEZEICHNUNG_DEUTSCH": "Gemeine Roßkastanie",
        "BAUMTYP": "Laub",
        "BEMERKUNG": null,
        "PFLANZJAHR": null,
        "ENTNAHMEJAHR": null,
        "BAUMPATENSCHAFT": null,
        "ALTERSKLASSIZIERUNG": "mittel",
        "OBJECTID": 422
      },
      "geometry": {
        "type": "Point",
        "coordinates": [
          15.416340948218854,
          47.078682305400484
        ]
      }
    },
    {
      "type": "Feature",
      "properties": {
        "NUMMER": 27327,
        "BAUMBEZEICHNUNG_BOTANISCH": "Platanus x acerifolia",
        "BAUMBEZEICHNUNG_DEUTSCH": "Platane",
        "BAUMTYP": "Laub",
        "BEMERKUNG": null,
        "PFLANZJAHR": "2007",
        "ENTNAHMEJAHR": null,
        "BAUMPATENSCHAFT": null,
        "ALTERSKLASSIZIERUNG": "jung",
        "OBJECTID": 1101
      },
      "geometry": {
        "type": "Point",
        "coordinates": [
          15.41650676029803,
          47.07826915984168
        ]
      }
    }
  ]
}