{
  "type": "FeatureCollection",
  "features": [
    {
      "type": "Feature",
      "properties": {
        "nummer": 16881,
        "baumbezeichnung_botanisch": "Alnus glutinosa",
        "baumbezeichnung_deutsch": "Schwarzerle",
        "baumtyp": "Laub",
        "altersklassifizierung": "alt",
        "bemerkung": null,
        "pflanzjahr": null,
        "entnahmejahr": null,
        "baumpatenschaft": null,
        "objectid": 25103
      },
      "geometry": {
        "type": "Point",
        "coordinates": [
          15.469979570279838,
          47.047137781298225
        ],
        "bbox": [
          15.469979570279838,
          47.047137781298225,
          15.469979570279838,
          47.047137781298225
        ]
      }
    }
  ]
}