{"type":"FeatureCollection","features":[{"type":"Feature","properties":{"nummer":10130,"baumbezeichnung_botanisch":"Alnus glutinosa","baumbezeichnung_deutsch":"Schwarzerle","baumtyp":"Laub","bemerkung":null,"pflanzjahr":null,"entnahmejahr":null,"marker-size":"small","marker-symbol":"park2","marker-color":"#A3DDAD"},"geometry":{"type":"Point","coordinates":[15.46997957027984,47.04713778129823],"bbox":[15.46997957027984,47.04713778129823,15.46997957027984,47.04713778129823]}}]}