{"type":"FeatureCollection","features":[{"type":"Feature","properties":{"nummer":27409,"baumbezeichnung_botanisch":"Carpinus betulus 'Fastigiata'","baumbezeichnung_deutsch":"Säulenhainbuche","baumtyp":"Laub","bemerkung":null,"pflanzjahr":null,"entnahmejahr":null,"marker-size":"small","marker-symbol":"park2","marker-color":"#A3DDAD"},"geometry":{"type":"Point","coordinates":[15.47063351218568,47.02186988714801],"bbox":[15.47063351218568,47.02186988714801,15.47063351218568,47.02186988714801]}},{"type":"Feature","properties":{"nummer":27411,"baumbezeichnung_botanisch":"Carpinus betulus 'Fastigiata'","baumbezeichnung_deutsch":"Säulenhainbuche","baumtyp":"Laub","bemerkung":null,"pflanzjahr":null,"entnahmejahr":null,"marker-size":"small","marker-symbol":"park2","marker-color":"#A3DDAD"},"geometry":{"type":"Point","coordinates":[15.47067438110965,47.02181613513917],"bbox":[15.47067438110965,47.02181613513917,15.47067438110965,47.02181613513917]}}]}