{
  "type": "FeatureCollection",
  "features": [
    {
      "type": "Feature",
      "properties": {
        "Naturdenkmal": true,
        "Naturdenkmal_Eigentum": "öffentlich",
        "nummer": "Naturdenkmal-69",
        "objectid": "Naturdenkmal-12",
        "baumbezeichnung_deutsch": "Edelkastanie",
        "baumbezeichnung_botanisch": "Castanea sativa"
      },
      "geometry": {
        "type": "Point",
        "coordinates": [
          15.498169024148893,
          47.06964112232859
        ]
      }
    }
  ]
}