{"type":"FeatureCollection","features":[{"type":"Feature","properties":{"nummer":55596,"baumbezeichnung_botanisch":"Fraxinus ornus","baumbezeichnung_deutsch":"Blumenesche","baumtyp":"Laub","bemerkung":null,"pflanzjahr":"2012","entnahmejahr":null,"marker-size":"small","marker-symbol":"park2","marker-color":"#A3DDAD"},"geometry":{"type":"Point","coordinates":[15.45163295901658,47.06073743443653],"bbox":[15.45163295901658,47.06073743443653,15.45163295901658,47.06073743443653]}},{"type":"Feature","properties":{"nummer":55597,"baumbezeichnung_botanisch":"Fraxinus ornus","baumbezeichnung_deutsch":"Blumenesche","baumtyp":"Laub","bemerkung":null,"pflanzjahr":"2012","entnahmejahr":null,"marker-size":"small","marker-symbol":"park2","marker-color":"#A3DDAD"},"geometry":{"type":"Point","coordinates":[15.4515006700024,47.06073403246009],"bbox":[15.4515006700024,47.06073403246009,15.4515006700024,47.06073403246009]}},{"type":"Feature","properties":{"nummer":55598,"baumbezeichnung_botanisch":"Fraxinus ornus","baumbezeichnung_deutsch":"Blumenesche","baumtyp":"Laub","bemerkung":null,"pflanzjahr":"2012","entnahmejahr":null,"marker-size":"small","marker-symbol":"park2","marker-color":"#A3DDAD"},"geometry":{"type":"Point","coordinates":[15.45132829513258,47.06073270071433],"bbox":[15.45132829513258,47.06073270071433,15.45132829513258,47.06073270071433]}},{"type":"Feature","properties":{"nummer":55599,"baumbezeichnung_botanisch":"Fraxinus ornus","baumbezeichnung_deutsch":"Blumenesche","baumtyp":"Laub","bemerkung":null,"pflanzjahr":"2012","entnahmejahr":null,"marker-size":"small","marker-symbol":"park2","marker-color":"#A3DDAD"},"geometry":{"type":"Point","coordinates":[15.45120293183792,47.06073173201089],"bbox":[15.45120293183792,47.06073173201089,15.45120293183792,47.06073173201089]}}]}