{"type":"FeatureCollection","features":[{"type":"Feature","properties":{"nummer":20570,"baumbezeichnung_botanisch":"Acer negundo","baumbezeichnung_deutsch":"Eschenahorn","baumtyp":"Laub","bemerkung":null,"pflanzjahr":null,"entnahmejahr":null,"marker-size":"small","marker-symbol":"park2","marker-color":"#A3DDAD"},"geometry":{"type":"Point","coordinates":[15.45128015167324,47.04690336640565],"bbox":[15.45128015167324,47.04690336640565,15.45128015167324,47.04690336640565]}},{"type":"Feature","properties":{"nummer":17760,"baumbezeichnung_botanisch":"Acer negundo","baumbezeichnung_deutsch":"Eschenahorn","baumtyp":"Laub","bemerkung":null,"pflanzjahr":null,"entnahmejahr":null,"marker-size":"small","marker-symbol":"park2","marker-color":"#A3DDAD"},"geometry":{"type":"Point","coordinates":[15.45112756027327,47.04691520762553],"bbox":[15.45112756027327,47.04691520762553,15.45112756027327,47.04691520762553]}},{"type":"Feature","properties":{"nummer":5380,"baumbezeichnung_botanisch":"Acer negundo","baumbezeichnung_deutsch":"Eschenahorn","baumtyp":"Laub","bemerkung":null,"pflanzjahr":null,"entnahmejahr":null,"marker-size":"small","marker-symbol":"park2","marker-color":"#A3DDAD"},"geometry":{"type":"Point","coordinates":[15.45098920069571,47.04693041488889],"bbox":[15.45098920069571,47.04693041488889,15.45098920069571,47.04693041488889]}},{"type":"Feature","properties":{"nummer":7962,"baumbezeichnung_botanisch":"Liquidambar styraciflua","baumbezeichnung_deutsch":"Amberbaum","baumtyp":"Laub","bemerkung":null,"pflanzjahr":"2011","entnahmejahr":null,"marker-size":"small","marker-symbol":"park2","marker-color":"#A3DDAD"},"geometry":{"type":"Point","coordinates":[15.45163669164177,47.04694192875085],"bbox":[15.45163669164177,47.04694192875085,15.45163669164177,47.04694192875085]}},{"type":"Feature","properties":{"nummer":19143,"baumbezeichnung_botanisch":"Liquidambar styraciflua","baumbezeichnung_deutsch":"Amberbaum","baumtyp":"Laub","bemerkung":null,"pflanzjahr":"2011","entnahmejahr":null,"marker-size":"small","marker-symbol":"park2","marker-color":"#A3DDAD"},"geometry":{"type":"Point","coordinates":[15.45146569835847,47.04691456604424],"bbox":[15.45146569835847,47.04691456604424,15.45146569835847,47.04691456604424]}}]}