{"type":"FeatureCollection","features":[{"type":"Feature","properties":{"nummer":22994,"baumbezeichnung_botanisch":"Aesculus hippocastanum","baumbezeichnung_deutsch":"Gemeine Roßkastanie","baumtyp":"Laub","bemerkung":null,"pflanzjahr":null,"entnahmejahr":"2012","marker-size":"small","marker-symbol":"park2","marker-color":"#B3B3B3"},"geometry":{"type":"Point","coordinates":[15.45204120459804,47.03037660391494],"bbox":[15.45204120459804,47.03037660391494,15.45204120459804,47.03037660391494]}},{"type":"Feature","properties":{"nummer":6590,"baumbezeichnung_botanisch":"Aesculus hippocastanum","baumbezeichnung_deutsch":"Gemeine Roßkastanie","baumtyp":"Laub","bemerkung":"Baum ist größtenteils abgestorben, Ersatzpflanzung geplant","pflanzjahr":null,"entnahmejahr":"2013","marker-size":"small","marker-symbol":"park2","marker-color":"#B3B3B3"},"geometry":{"type":"Point","coordinates":[15.45200925964319,47.03045085690784],"bbox":[15.45200925964319,47.03045085690784,15.45200925964319,47.03045085690784]}},{"type":"Feature","properties":{"nummer":8940,"baumbezeichnung_botanisch":"Acer negundo","baumbezeichnung_deutsch":"Eschenahorn","baumtyp":"Laub","bemerkung":null,"pflanzjahr":null,"entnahmejahr":null,"marker-size":"small","marker-symbol":"park2","marker-color":"#A3DDAD"},"geometry":{"type":"Point","coordinates":[15.45192318860212,47.03065911188384],"bbox":[15.45192318860212,47.03065911188384,15.45192318860212,47.03065911188384]}},{"type":"Feature","properties":{"nummer":4267,"baumbezeichnung_botanisch":"Aesculus hippocastanum","baumbezeichnung_deutsch":"Gemeine Roßkastanie","baumtyp":"Laub","bemerkung":null,"pflanzjahr":null,"entnahmejahr":null,"marker-size":"small","marker-symbol":"park2","marker-color":"#A3DDAD"},"geometry":{"type":"Point","coordinates":[15.45189096196885,47.0307296098883],"bbox":[15.45189096196885,47.0307296098883,15.45189096196885,47.0307296098883]}},{"type":"Feature","properties":{"nummer":24469,"baumbezeichnung_botanisch":"Aesculus hippocastanum","baumbezeichnung_deutsch":"Gemeine Roßkastanie","baumtyp":"Laub","bemerkung":null,"pflanzjahr":null,"entnahmejahr":null,"marker-size":"small","marker-symbol":"park2","marker-color":"#A3DDAD"},"geometry":{"type":"Point","coordinates":[15.45185953057708,47.03079265794346],"bbox":[15.45185953057708,47.03079265794346,15.45185953057708,47.03079265794346]}}]}