{
  "type": "FeatureCollection",
  "features": [
    {
      "type": "Feature",
      "properties": {
        "NUMMER": 16632,
        "BAUMBEZEICHNUNG_BOTANISCH": "Picea pungens",
        "BAUMBEZEICHNUNG_DEUTSCH": "Stechfichte",
        "BAUMTYP": "Nadel",
        "BEMERKUNG": null,
        "PFLANZJAHR": null,
        "ENTNAHMEJAHR": null,
        "BAUMPATENSCHAFT": null,
        "ALTERSKLASSIZIERUNG": "mittel",
        "OBJECTID": 1018
      },
      "geometry": {
        "type": "Point",
        "coordinates": [
          15.394409097786708,
          47.1006061782178
        ]
      }
    }
  ]
}