{"type":"FeatureCollection","features":[{"type":"Feature","properties":{"nummer":29585,"baumbezeichnung_botanisch":"Picea abies","baumbezeichnung_deutsch":"Rotfichte","baumtyp":"Nadel","bemerkung":null,"pflanzjahr":null,"entnahmejahr":"2012","marker-size":"small","marker-symbol":"park","marker-color":"#B3B3B3"},"geometry":{"type":"Point","coordinates":[15.46549545426674,47.05566399671742],"bbox":[15.46549545426674,47.05566399671742,15.46549545426674,47.05566399671742]}},{"type":"Feature","properties":{"nummer":29586,"baumbezeichnung_botanisch":"Picea abies","baumbezeichnung_deutsch":"Rotfichte","baumtyp":"Nadel","bemerkung":null,"pflanzjahr":null,"entnahmejahr":"2012","marker-size":"small","marker-symbol":"park","marker-color":"#B3B3B3"},"geometry":{"type":"Point","coordinates":[15.46546814670024,47.05565367859065],"bbox":[15.46546814670024,47.05565367859065,15.46546814670024,47.05565367859065]}},{"type":"Feature","properties":{"nummer":29588,"baumbezeichnung_botanisch":"Picea abies","baumbezeichnung_deutsch":"Rotfichte","baumtyp":"Nadel","bemerkung":null,"pflanzjahr":null,"entnahmejahr":"2012","marker-size":"small","marker-symbol":"park","marker-color":"#B3B3B3"},"geometry":{"type":"Point","coordinates":[15.46539453586994,47.05563145236377],"bbox":[15.46539453586994,47.05563145236377,15.46539453586994,47.05563145236377]}},{"type":"Feature","properties":{"nummer":29589,"baumbezeichnung_botanisch":"Picea abies","baumbezeichnung_deutsch":"Rotfichte","baumtyp":"Nadel","bemerkung":null,"pflanzjahr":null,"entnahmejahr":"2012","marker-size":"small","marker-symbol":"park","marker-color":"#B3B3B3"},"geometry":{"type":"Point","coordinates":[15.4653588225172,47.05561818106443],"bbox":[15.4653588225172,47.05561818106443,15.4653588225172,47.05561818106443]}},{"type":"Feature","properties":{"nummer":29590,"baumbezeichnung_botanisch":"Picea abies","baumbezeichnung_deutsch":"Rotfichte","baumtyp":"Nadel","bemerkung":null,"pflanzjahr":null,"entnahmejahr":"2012","marker-size":"small","marker-symbol":"park","marker-color":"#B3B3B3"},"geometry":{"type":"Point","coordinates":[15.46533151500079,47.05560786290529],"bbox":[15.46533151500079,47.05560786290529,15.46533151500079,47.05560786290529]}},{"type":"Feature","properties":{"nummer":29591,"baumbezeichnung_botanisch":"Picea abies","baumbezeichnung_deutsch":"Rotfichte","baumtyp":"Nadel","bemerkung":null,"pflanzjahr":null,"entnahmejahr":"2012","marker-size":"small","marker-symbol":"park","marker-color":"#B3B3B3"},"geometry":{"type":"Point","coordinates":[15.46529791392017,47.05559460674995],"bbox":[15.46529791392017,47.05559460674995,15.46529791392017,47.05559460674995]}}]}