{
  "type": "FeatureCollection",
  "features": [
    {
      "type": "Feature",
      "properties": {
        "NUMMER": 25284,
        "BAUMBEZEICHNUNG_BOTANISCH": "Fraxinus excelsior",
        "BAUMBEZEICHNUNG_DEUTSCH": "Esche",
        "BAUMTYP": "Laub",
        "BEMERKUNG": null,
        "PFLANZJAHR": null,
        "ENTNAHMEJAHR": null,
        "BAUMPATENSCHAFT": null,
        "ALTERSKLASSIZIERUNG": "mittel",
        "OBJECTID": 134
      },
      "geometry": {
        "type": "Point",
        "coordinates": [
          15.454841456278562,
          47.06211952724597
        ]
      }
    },
    {
      "type": "Feature",
      "properties": {
        "NUMMER": 24863,
        "BAUMBEZEICHNUNG_BOTANISCH": "Carpinus betulus 'Fastigiata'",
        "BAUMBEZEICHNUNG_DEUTSCH": "Säulenhainbuche",
        "BAUMTYP": "Laub",
        "BEMERKUNG": null,
        "PFLANZJAHR": "2005",
        "ENTNAHMEJAHR": null,
        "BAUMPATENSCHAFT": null,
        "ALTERSKLASSIZIERUNG": "jung",
        "OBJECTID": 799
      },
      "geometry": {
        "type": "Point",
        "coordinates": [
          15.453751079681759,
          47.062082972382456
        ]
      }
    },
    {
      "type": "Feature",
      "properties": {
        "NUMMER": 4857,
        "BAUMBEZEICHNUNG_BOTANISCH": "Fraxinus excelsior",
        "BAUMBEZEICHNUNG_DEUTSCH": "Esche",
        "BAUMTYP": "Laub",
        "BEMERKUNG": null,
        "PFLANZJAHR": null,
        "ENTNAHMEJAHR": null,
        "BAUMPATENSCHAFT": null,
        "ALTERSKLASSIZIERUNG": "jung",
        "OBJECTID": 800
      },
      "geometry": {
        "type": "Point",
        "coordinates": [
          15.45423887595039,
          47.06190619432743
        ]
      }
    },
    {
      "type": "Feature",
      "properties": {
        "NUMMER": 6197,
        "BAUMBEZEICHNUNG_BOTANISCH": "Tilia cordata",
        "BAUMBEZEICHNUNG_DEUTSCH": "Winterlinde",
        "BAUMTYP": "Laub",
        "BEMERKUNG": null,
        "PFLANZJAHR": "1985",
        "ENTNAHMEJAHR": null,
        "BAUMPATENSCHAFT": "Grazer Wechselseitige Versicherung",
        "ALTERSKLASSIZIERUNG": "jung",
        "OBJECTID": 887
      },
      "geometry": {
        "type": "Point",
        "coordinates": [
          15.453989397364962,
          47.05975685591236
        ]
      }
    },
    {
      "type": "Feature",
      "properties": {
        "NUMMER": 6177,
        "BAUMBEZEICHNUNG_BOTANISCH": "Tilia cordata",
        "BAUMBEZEICHNUNG_DEUTSCH": "Winterlinde",
        "BAUMTYP": "Laub",
        "BEMERKUNG": null,
        "PFLANZJAHR": "1985",
        "ENTNAHMEJAHR": null,
        "BAUMPATENSCHAFT": null,
        "ALTERSKLASSIZIERUNG": "jung",
        "OBJECTID": 1133
      },
      "geometry": {
        "type": "Point",
        "coordinates": [
          15.457687203254302,
          47.06091786711992
        ]
      }
    },
    {
      "type": "Feature",
      "properties": {
        "NUMMER": 6193,
        "BAUMBEZEICHNUNG_BOTANISCH": "Tilia cordata",
        "BAUMBEZEICHNUNG_DEUTSCH": "Winterlinde",
        "BAUMTYP": "Laub",
        "BEMERKUNG": null,
        "PFLANZJAHR": "1985",
        "ENTNAHMEJAHR": null,
        "BAUMPATENSCHAFT": "Siegfied Erne",
        "ALTERSKLASSIZIERUNG": "jung",
        "OBJECTID": 1141
      },
      "geometry": {
        "type": "Point",
        "coordinates": [
          15.454975554279264,
          47.060065602392754
        ]
      }
    }
  ]
}