{
  "type": "FeatureCollection",
  "features": [
    {
      "type": "Feature",
      "properties": {
        "nummer": 25284,
        "objectid": 134,
        "baumbezeichnung_deutsch": "Esche",
        "baumbezeichnung_botanisch": "Fraxinus excelsior",
        "baumtyp": "Laub",
        "bemerkung": null,
        "pflanzjahr": null,
        "entnahmejahr": null,
        "baumpatenschaft": null,
        "altersklassifizierung": "mittel"
      },
      "geometry": {
        "type": "Point",
        "coordinates": [
          15.454841456278562,
          47.06211952724597
        ]
      }
    },
    {
      "type": "Feature",
      "properties": {
        "nummer": 24863,
        "objectid": 799,
        "baumbezeichnung_deutsch": "Säulenhainbuche",
        "baumbezeichnung_botanisch": "Carpinus betulus 'Fastigiata'",
        "baumtyp": "Laub",
        "bemerkung": null,
        "pflanzjahr": "2005",
        "entnahmejahr": null,
        "baumpatenschaft": null,
        "altersklassifizierung": "jung"
      },
      "geometry": {
        "type": "Point",
        "coordinates": [
          15.453751079681759,
          47.062082972382456
        ]
      }
    },
    {
      "type": "Feature",
      "properties": {
        "nummer": 4857,
        "objectid": 800,
        "baumbezeichnung_deutsch": "Esche",
        "baumbezeichnung_botanisch": "Fraxinus excelsior",
        "baumtyp": "Laub",
        "bemerkung": null,
        "pflanzjahr": null,
        "entnahmejahr": null,
        "baumpatenschaft": null,
        "altersklassifizierung": "jung"
      },
      "geometry": {
        "type": "Point",
        "coordinates": [
          15.45423887595039,
          47.06190619432743
        ]
      }
    },
    {
      "type": "Feature",
      "properties": {
        "nummer": 6197,
        "objectid": 887,
        "baumbezeichnung_deutsch": "Winterlinde",
        "baumbezeichnung_botanisch": "Tilia cordata",
        "baumtyp": "Laub",
        "bemerkung": null,
        "pflanzjahr": "1985",
        "entnahmejahr": null,
        "baumpatenschaft": "Grazer Wechselseitige Versicherung",
        "altersklassifizierung": "jung"
      },
      "geometry": {
        "type": "Point",
        "coordinates": [
          15.453989397364962,
          47.05975685591236
        ]
      }
    },
    {
      "type": "Feature",
      "properties": {
        "nummer": 6177,
        "objectid": 1133,
        "baumbezeichnung_deutsch": "Winterlinde",
        "baumbezeichnung_botanisch": "Tilia cordata",
        "baumtyp": "Laub",
        "bemerkung": null,
        "pflanzjahr": "1985",
        "entnahmejahr": null,
        "baumpatenschaft": null,
        "altersklassifizierung": "jung"
      },
      "geometry": {
        "type": "Point",
        "coordinates": [
          15.457687203254302,
          47.06091786711992
        ]
      }
    },
    {
      "type": "Feature",
      "properties": {
        "nummer": 6193,
        "objectid": 1141,
        "baumbezeichnung_deutsch": "Winterlinde",
        "baumbezeichnung_botanisch": "Tilia cordata",
        "baumtyp": "Laub",
        "bemerkung": null,
        "pflanzjahr": "1985",
        "entnahmejahr": null,
        "baumpatenschaft": "Siegfied Erne",
        "altersklassifizierung": "jung"
      },
      "geometry": {
        "type": "Point",
        "coordinates": [
          15.454975554279264,
          47.060065602392754
        ]
      }
    }
  ]
}