{"type":"FeatureCollection","features":[{"type":"Feature","properties":{"nummer":22764,"baumbezeichnung_botanisch":"Tilia cordata","baumbezeichnung_deutsch":"Winterlinde","baumtyp":"Laub","bemerkung":null,"pflanzjahr":"2006","entnahmejahr":null,"marker-size":"small","marker-symbol":"park2","marker-color":"#A3DDAD"},"geometry":{"type":"Point","coordinates":[15.39104684936837,47.06842951090155],"bbox":[15.39104684936837,47.06842951090155,15.39104684936837,47.06842951090155]}},{"type":"Feature","properties":{"nummer":6169,"baumbezeichnung_botanisch":"Tilia cordata","baumbezeichnung_deutsch":"Winterlinde","baumtyp":"Laub","bemerkung":null,"pflanzjahr":"2007","entnahmejahr":null,"marker-size":"small","marker-symbol":"park2","marker-color":"#A3DDAD"},"geometry":{"type":"Point","coordinates":[15.39070080249885,47.06830145342163],"bbox":[15.39070080249885,47.06830145342163,15.39070080249885,47.06830145342163]}},{"type":"Feature","properties":{"nummer":23709,"baumbezeichnung_botanisch":"Tilia cordata","baumbezeichnung_deutsch":"Winterlinde","baumtyp":"Laub","bemerkung":null,"pflanzjahr":null,"entnahmejahr":null,"marker-size":"small","marker-symbol":"park2","marker-color":"#A3DDAD"},"geometry":{"type":"Point","coordinates":[15.39174069191761,47.06863579886072],"bbox":[15.39174069191761,47.06863579886072,15.39174069191761,47.06863579886072]}},{"type":"Feature","properties":{"nummer":23119,"baumbezeichnung_botanisch":"Tilia cordata","baumbezeichnung_deutsch":"Winterlinde","baumtyp":"Laub","bemerkung":null,"pflanzjahr":null,"entnahmejahr":null,"marker-size":"small","marker-symbol":"park2","marker-color":"#A3DDAD"},"geometry":{"type":"Point","coordinates":[15.39158032540705,47.06858970759663],"bbox":[15.39158032540705,47.06858970759663,15.39158032540705,47.06858970759663]}},{"type":"Feature","properties":{"nummer":1851,"baumbezeichnung_botanisch":"Tilia cordata","baumbezeichnung_deutsch":"Winterlinde","baumtyp":"Laub","bemerkung":null,"pflanzjahr":null,"entnahmejahr":null,"marker-size":"small","marker-symbol":"park2","marker-color":"#A3DDAD"},"geometry":{"type":"Point","coordinates":[15.39141512632737,47.06854070680195],"bbox":[15.39141512632737,47.06854070680195,15.39141512632737,47.06854070680195]}},{"type":"Feature","properties":{"nummer":6285,"baumbezeichnung_botanisch":"Tilia cordata","baumbezeichnung_deutsch":"Winterlinde","baumtyp":"Laub","bemerkung":null,"pflanzjahr":null,"entnahmejahr":null,"marker-size":"small","marker-symbol":"park2","marker-color":"#A3DDAD"},"geometry":{"type":"Point","coordinates":[15.39130963176199,47.06850955893422],"bbox":[15.39130963176199,47.06850955893422,15.39130963176199,47.06850955893422]}},{"type":"Feature","properties":{"nummer":18207,"baumbezeichnung_botanisch":"Tilia cordata","baumbezeichnung_deutsch":"Winterlinde","baumtyp":"Laub","bemerkung":null,"pflanzjahr":null,"entnahmejahr":null,"marker-size":"small","marker-symbol":"park2","marker-color":"#A3DDAD"},"geometry":{"type":"Point","coordinates":[15.39113520960999,47.06845654178233],"bbox":[15.39113520960999,47.06845654178233,15.39113520960999,47.06845654178233]}},{"type":"Feature","properties":{"nummer":1893,"baumbezeichnung_botanisch":"Tilia cordata","baumbezeichnung_deutsch":"Winterlinde","baumtyp":"Laub","bemerkung":null,"pflanzjahr":null,"entnahmejahr":null,"marker-size":"small","marker-symbol":"park2","marker-color":"#A3DDAD"},"geometry":{"type":"Point","coordinates":[15.39092816279582,47.06839023017487],"bbox":[15.39092816279582,47.06839023017487,15.39092816279582,47.06839023017487]}},{"type":"Feature","properties":{"nummer":10018,"baumbezeichnung_botanisch":"Tilia cordata","baumbezeichnung_deutsch":"Winterlinde","baumtyp":"Laub","bemerkung":null,"pflanzjahr":null,"entnahmejahr":null,"marker-size":"small","marker-symbol":"park2","marker-color":"#A3DDAD"},"geometry":{"type":"Point","coordinates":[15.39081418236137,47.0683498637858],"bbox":[15.39081418236137,47.0683498637858,15.39081418236137,47.0683498637858]}},{"type":"Feature","properties":{"nummer":19826,"baumbezeichnung_botanisch":"Tilia platyphyllos","baumbezeichnung_deutsch":"Sommerlinde","baumtyp":"Laub","bemerkung":null,"pflanzjahr":"1995","entnahmejahr":null,"marker-size":"small","marker-symbol":"park2","marker-color":"#A3DDAD"},"geometry":{"type":"Point","coordinates":[15.39121380721054,47.06848175598398],"bbox":[15.39121380721054,47.06848175598398,15.39121380721054,47.06848175598398]}}]}