{
  "type": "FeatureCollection",
  "features": [
    {
      "type": "Feature",
      "properties": {
        "nummer": 20350,
        "objectid": 458,
        "baumbezeichnung_deutsch": "Spitzahorn",
        "baumbezeichnung_botanisch": "Acer platanoides",
        "baumtyp": "Laub",
        "bemerkung": null,
        "pflanzjahr": "1998",
        "entnahmejahr": null,
        "baumpatenschaft": null,
        "altersklassifizierung": "jung"
      },
      "geometry": {
        "type": "Point",
        "coordinates": [
          15.44147103093101,
          47.0623278084677
        ]
      }
    },
    {
      "type": "Feature",
      "properties": {
        "nummer": 5052,
        "objectid": 1140,
        "baumbezeichnung_deutsch": "Spitzahorn",
        "baumbezeichnung_botanisch": "Acer platanoides",
        "baumtyp": "Laub",
        "bemerkung": null,
        "pflanzjahr": "1985",
        "entnahmejahr": null,
        "baumpatenschaft": "Daniela u. Michael Zekoll",
        "altersklassifizierung": "mittel"
      },
      "geometry": {
        "type": "Point",
        "coordinates": [
          15.44410754678939,
          47.06132443689573
        ]
      }
    }
  ]
}