{
  "type": "FeatureCollection",
  "features": [
    {
      "type": "Feature",
      "properties": {
        "NUMMER": 20350,
        "BAUMBEZEICHNUNG_BOTANISCH": "Acer platanoides",
        "BAUMBEZEICHNUNG_DEUTSCH": "Spitzahorn",
        "BAUMTYP": "Laub",
        "BEMERKUNG": null,
        "PFLANZJAHR": "1998",
        "ENTNAHMEJAHR": null,
        "BAUMPATENSCHAFT": null,
        "ALTERSKLASSIZIERUNG": "jung",
        "OBJECTID": 458
      },
      "geometry": {
        "type": "Point",
        "coordinates": [
          15.44147103093101,
          47.0623278084677
        ]
      }
    },
    {
      "type": "Feature",
      "properties": {
        "NUMMER": 5052,
        "BAUMBEZEICHNUNG_BOTANISCH": "Acer platanoides",
        "BAUMBEZEICHNUNG_DEUTSCH": "Spitzahorn",
        "BAUMTYP": "Laub",
        "BEMERKUNG": null,
        "PFLANZJAHR": "1985",
        "ENTNAHMEJAHR": null,
        "BAUMPATENSCHAFT": "Daniela u. Michael Zekoll",
        "ALTERSKLASSIZIERUNG": "mittel",
        "OBJECTID": 1140
      },
      "geometry": {
        "type": "Point",
        "coordinates": [
          15.44410754678939,
          47.06132443689573
        ]
      }
    }
  ]
}