{"type":"FeatureCollection","features":[{"type":"Feature","properties":{"nummer":2963,"baumbezeichnung_botanisch":"Pinus sylvestris","baumbezeichnung_deutsch":"Gemeine Kiefer","baumtyp":"Nadel","bemerkung":null,"pflanzjahr":null,"entnahmejahr":null,"marker-size":"small","marker-symbol":"park","marker-color":"#3BB451"},"geometry":{"type":"Point","coordinates":[15.4119337861929,47.09626049364838],"bbox":[15.4119337861929,47.09626049364838,15.4119337861929,47.09626049364838]}},{"type":"Feature","properties":{"nummer":17375,"baumbezeichnung_botanisch":"Pinus sylvestris","baumbezeichnung_deutsch":"Gemeine Kiefer","baumtyp":"Nadel","bemerkung":null,"pflanzjahr":null,"entnahmejahr":null,"marker-size":"small","marker-symbol":"park","marker-color":"#3BB451"},"geometry":{"type":"Point","coordinates":[15.41184859592252,47.09627628868315],"bbox":[15.41184859592252,47.09627628868315,15.41184859592252,47.09627628868315]}},{"type":"Feature","properties":{"nummer":13168,"baumbezeichnung_botanisch":"Chamaecyparis pisifera 'Aurea'","baumbezeichnung_deutsch":"Gelbe Sawarascheinzypresse","baumtyp":"Nadel","bemerkung":null,"pflanzjahr":null,"entnahmejahr":null,"marker-size":"small","marker-symbol":"park","marker-color":"#3BB451"},"geometry":{"type":"Point","coordinates":[15.41155672372245,47.0963017877094],"bbox":[15.41155672372245,47.0963017877094,15.41155672372245,47.0963017877094]}},{"type":"Feature","properties":{"nummer":10810,"baumbezeichnung_botanisch":"Chamaecyparis pisifera 'Aurea'","baumbezeichnung_deutsch":"Gelbe Sawarascheinzypresse","baumtyp":"Nadel","bemerkung":null,"pflanzjahr":null,"entnahmejahr":null,"marker-size":"small","marker-symbol":"park","marker-color":"#3BB451"},"geometry":{"type":"Point","coordinates":[15.41160327795317,47.0962958193271],"bbox":[15.41160327795317,47.0962958193271,15.41160327795317,47.0962958193271]}},{"type":"Feature","properties":{"nummer":89,"baumbezeichnung_botanisch":"Pinus sylvestris","baumbezeichnung_deutsch":"Gemeine Kiefer","baumtyp":"Nadel","bemerkung":null,"pflanzjahr":null,"entnahmejahr":null,"marker-size":"small","marker-symbol":"park","marker-color":"#3BB451"},"geometry":{"type":"Point","coordinates":[15.41174159343667,47.09626442409883],"bbox":[15.41174159343667,47.09626442409883,15.41174159343667,47.09626442409883]}},{"type":"Feature","properties":{"nummer":20958,"baumbezeichnung_botanisch":"Pinus sylvestris","baumbezeichnung_deutsch":"Gemeine Kiefer","baumtyp":"Nadel","bemerkung":null,"pflanzjahr":null,"entnahmejahr":null,"marker-size":"small","marker-symbol":"park","marker-color":"#3BB451"},"geometry":{"type":"Point","coordinates":[15.41177626247153,47.09623083483705],"bbox":[15.41177626247153,47.09623083483705,15.41177626247153,47.09623083483705]}},{"type":"Feature","properties":{"nummer":12791,"baumbezeichnung_botanisch":"Prunus serrulata 'Kanzan'","baumbezeichnung_deutsch":"Japanische Bl端tenkirsche","baumtyp":"Laub","bemerkung":null,"pflanzjahr":null,"entnahmejahr":null,"marker-size":"small","marker-symbol":"park2","marker-color":"#A3DDAD"},"geometry":{"type":"Point","coordinates":[15.41129106518391,47.09616790557121],"bbox":[15.41129106518391,47.09616790557121,15.41129106518391,47.09616790557121]}},{"type":"Feature","properties":{"nummer":6801,"baumbezeichnung_botanisch":"Prunus serrulata 'Kanzan'","baumbezeichnung_deutsch":"Japanische Bl端tenkirsche","baumtyp":"Laub","bemerkung":null,"pflanzjahr":null,"entnahmejahr":null,"marker-size":"small","marker-symbol":"park2","marker-color":"#A3DDAD"},"geometry":{"type":"Point","coordinates":[15.41122214318973,47.09618075340502],"bbox":[15.41122214318973,47.09618075340502,15.41122214318973,47.09618075340502]}},{"type":"Feature","properties":{"nummer":23320,"baumbezeichnung_botanisch":"Prunus serrulata 'Kanzan'","baumbezeichnung_deutsch":"Japanische Bl端tenkirsche","baumtyp":"Laub","bemerkung":null,"pflanzjahr":null,"entnahmejahr":null,"marker-size":"small","marker-symbol":"park2","marker-color":"#A3DDAD"},"geometry":{"type":"Point","coordinates":[15.41121122900964,47.09624433407808],"bbox":[15.41121122900964,47.09624433407808,15.41121122900964,47.09624433407808]}},{"type":"Feature","properties":{"nummer":6029,"baumbezeichnung_botanisch":"Prunus serrulata 'Kanzan'","baumbezeichnung_deutsch":"Japanische Bl端tenkirsche","baumtyp":"Laub","bemerkung":null,"pflanzjahr":null,"entnahmejahr":null,"marker-size":"small","marker-symbol":"park2","marker-color":"#A3DDAD"},"geometry":{"type":"Point","coordinates":[15.41113693679865,47.09628394645983],"bbox":[15.41113693679865,47.09628394645983,15.41113693679865,47.09628394645983]}}]}