{"type":"FeatureCollection","features":[{"type":"Feature","properties":{"nummer":19008,"baumbezeichnung_botanisch":"Prunus serrulata 'Hokusai'","baumbezeichnung_deutsch":"Japanische Kirsche","baumtyp":"Laub","bemerkung":null,"pflanzjahr":null,"entnahmejahr":null,"marker-size":"small","marker-symbol":"park2","marker-color":"#A3DDAD"},"geometry":{"type":"Point","coordinates":[15.46038071220079,47.08945984033524],"bbox":[15.46038071220079,47.08945984033524,15.46038071220079,47.08945984033524]}},{"type":"Feature","properties":{"nummer":11968,"baumbezeichnung_botanisch":"Prunus domestica","baumbezeichnung_deutsch":"Pflaume","baumtyp":"Laub","bemerkung":null,"pflanzjahr":null,"entnahmejahr":null,"marker-size":"small","marker-symbol":"park2","marker-color":"#A3DDAD"},"geometry":{"type":"Point","coordinates":[15.4604256946161,47.08950687765799],"bbox":[15.4604256946161,47.08950687765799,15.4604256946161,47.08950687765799]}}]}