{"type":"FeatureCollection","features":[{"type":"Feature","properties":{"nummer":9176,"baumbezeichnung_botanisch":"Corylus colurna","baumbezeichnung_deutsch":"Baumhasel","baumtyp":"Laub","bemerkung":null,"pflanzjahr":"1994","entnahmejahr":null,"marker-size":"small","marker-symbol":"park2","marker-color":"#A3DDAD"},"geometry":{"type":"Point","coordinates":[15.46042690952956,47.07852556535136],"bbox":[15.46042690952956,47.07852556535136,15.46042690952956,47.07852556535136]}},{"type":"Feature","properties":{"nummer":16222,"baumbezeichnung_botanisch":"Corylus colurna","baumbezeichnung_deutsch":"Baumhasel","baumtyp":"Laub","bemerkung":null,"pflanzjahr":"1994","entnahmejahr":null,"marker-size":"small","marker-symbol":"park2","marker-color":"#A3DDAD"},"geometry":{"type":"Point","coordinates":[15.46047006985476,47.07843140120674],"bbox":[15.46047006985476,47.07843140120674,15.46047006985476,47.07843140120674]}}]}