{"type":"FeatureCollection","features":[{"type":"Feature","properties":{"nummer":9723,"baumbezeichnung_botanisch":"Pyrus calleryana 'Chanticleer'","baumbezeichnung_deutsch":"Chinesische Wildbirne","baumtyp":"Laub","bemerkung":null,"pflanzjahr":"2001","entnahmejahr":null,"marker-size":"small","marker-symbol":"park2","marker-color":"#A3DDAD"},"geometry":{"type":"Point","coordinates":[15.43177218237284,47.06854481971099],"bbox":[15.43177218237284,47.06854481971099,15.43177218237284,47.06854481971099]}}]}