{"type":"FeatureCollection","features":[{"type":"Feature","properties":{"nummer":9495,"baumbezeichnung_botanisch":"Robinia pseudoacacia","baumbezeichnung_deutsch":"Scheinakazie","baumtyp":"Laub","bemerkung":null,"pflanzjahr":null,"entnahmejahr":null,"marker-size":"small","marker-symbol":"park2","marker-color":"#A3DDAD"},"geometry":{"type":"Point","coordinates":[15.43253672057997,47.07389243663751],"bbox":[15.43253672057997,47.07389243663751,15.43253672057997,47.07389243663751]}},{"type":"Feature","properties":{"nummer":23352,"baumbezeichnung_botanisch":"Aesculus hippocastanum","baumbezeichnung_deutsch":"Gemeine Roßkastanie","baumtyp":"Laub","bemerkung":null,"pflanzjahr":null,"entnahmejahr":null,"marker-size":"small","marker-symbol":"park2","marker-color":"#A3DDAD"},"geometry":{"type":"Point","coordinates":[15.43185460669771,47.07455241905775],"bbox":[15.43185460669771,47.07455241905775,15.43185460669771,47.07455241905775]}},{"type":"Feature","properties":{"nummer":10726,"baumbezeichnung_botanisch":"Aesculus hippocastanum","baumbezeichnung_deutsch":"Gemeine Roßkastanie","baumtyp":"Laub","bemerkung":null,"pflanzjahr":"1999","entnahmejahr":null,"marker-size":"small","marker-symbol":"park2","marker-color":"#A3DDAD"},"geometry":{"type":"Point","coordinates":[15.43168782328653,47.07468171061367],"bbox":[15.43168782328653,47.07468171061367,15.43168782328653,47.07468171061367]}},{"type":"Feature","properties":{"nummer":3308,"baumbezeichnung_botanisch":"Aesculus hippocastanum","baumbezeichnung_deutsch":"Gemeine Roßkastanie","baumtyp":"Laub","bemerkung":null,"pflanzjahr":"1999","entnahmejahr":null,"marker-size":"small","marker-symbol":"park2","marker-color":"#A3DDAD"},"geometry":{"type":"Point","coordinates":[15.4317387504145,47.07464132909242],"bbox":[15.4317387504145,47.07464132909242,15.4317387504145,47.07464132909242]}},{"type":"Feature","properties":{"nummer":23042,"baumbezeichnung_botanisch":"Aesculus hippocastanum","baumbezeichnung_deutsch":"Gemeine Roßkastanie","baumtyp":"Laub","bemerkung":null,"pflanzjahr":"1999","entnahmejahr":null,"marker-size":"small","marker-symbol":"park2","marker-color":"#A3DDAD"},"geometry":{"type":"Point","coordinates":[15.43179248172273,47.07459784839756],"bbox":[15.43179248172273,47.07459784839756,15.43179248172273,47.07459784839756]}}]}