{"type":"FeatureCollection","features":[{"type":"Feature","properties":{"nummer":23556,"baumbezeichnung_botanisch":"Prunus fruticosa 'Globosum'","baumbezeichnung_deutsch":"Kugelsandkirsche","baumtyp":"Laub","bemerkung":null,"pflanzjahr":"2007","entnahmejahr":null,"marker-size":"small","marker-symbol":"park2","marker-color":"#A3DDAD"},"geometry":{"type":"Point","coordinates":[15.43301788114396,47.070882544105],"bbox":[15.43301788114396,47.070882544105,15.43301788114396,47.070882544105]}},{"type":"Feature","properties":{"nummer":10729,"baumbezeichnung_botanisch":"Prunus fruticosa 'Globosum'","baumbezeichnung_deutsch":"Kugelsandkirsche","baumtyp":"Laub","bemerkung":null,"pflanzjahr":"2000","entnahmejahr":null,"marker-size":"small","marker-symbol":"park2","marker-color":"#A3DDAD"},"geometry":{"type":"Point","coordinates":[15.43290092576157,47.07089450267041],"bbox":[15.43290092576157,47.07089450267041,15.43290092576157,47.07089450267041]}},{"type":"Feature","properties":{"nummer":3309,"baumbezeichnung_botanisch":"Prunus fruticosa 'Globosum'","baumbezeichnung_deutsch":"Kugelsandkirsche","baumtyp":"Laub","bemerkung":null,"pflanzjahr":"2000","entnahmejahr":null,"marker-size":"small","marker-symbol":"park2","marker-color":"#A3DDAD"},"geometry":{"type":"Point","coordinates":[15.43275265941683,47.07091753894158],"bbox":[15.43275265941683,47.07091753894158,15.43275265941683,47.07091753894158]}},{"type":"Feature","properties":{"nummer":24918,"baumbezeichnung_botanisch":"Prunus fruticosa 'Globosum'","baumbezeichnung_deutsch":"Kugelsandkirsche","baumtyp":"Laub","bemerkung":null,"pflanzjahr":"2000","entnahmejahr":null,"marker-size":"small","marker-symbol":"park2","marker-color":"#A3DDAD"},"geometry":{"type":"Point","coordinates":[15.43263756873632,47.07094379615518],"bbox":[15.43263756873632,47.07094379615518,15.43263756873632,47.07094379615518]}}]}