{"type":"FeatureCollection","features":[{"type":"Feature","properties":{"nummer":2435,"baumbezeichnung_botanisch":"Platanus x acerifolia","baumbezeichnung_deutsch":"Platane","baumtyp":"Laub","bemerkung":null,"pflanzjahr":"1999","entnahmejahr":null,"marker-size":"small","marker-symbol":"park2","marker-color":"#A3DDAD"},"geometry":{"type":"Point","coordinates":[15.43175523541314,47.0538979239711],"bbox":[15.43175523541314,47.0538979239711,15.43175523541314,47.0538979239711]}},{"type":"Feature","properties":{"nummer":20336,"baumbezeichnung_botanisch":"Fraxinus excelsior 'Globosum'","baumbezeichnung_deutsch":"Kugelesche","baumtyp":"Laub","bemerkung":null,"pflanzjahr":null,"entnahmejahr":null,"marker-size":"small","marker-symbol":"park2","marker-color":"#A3DDAD"},"geometry":{"type":"Point","coordinates":[15.43237917505609,47.05348079716934],"bbox":[15.43237917505609,47.05348079716934,15.43237917505609,47.05348079716934]}}]}