{"type":"FeatureCollection","features":[{"type":"Feature","properties":{"nummer":34301,"baumbezeichnung_botanisch":"Liriodendron tulipifera 'Fastigiata'","baumbezeichnung_deutsch":"S채ulentulpenbaum","baumtyp":"Laub","bemerkung":null,"pflanzjahr":null,"entnahmejahr":null,"marker-size":"small","marker-symbol":"park2","marker-color":"#A3DDAD"},"geometry":{"type":"Point","coordinates":[15.43220074008567,47.02689089531418],"bbox":[15.43220074008567,47.02689089531418,15.43220074008567,47.02689089531418]}},{"type":"Feature","properties":{"nummer":34303,"baumbezeichnung_botanisch":"Liriodendron tulipifera 'Fastigiata'","baumbezeichnung_deutsch":"S채ulentulpenbaum","baumtyp":"Laub","bemerkung":null,"pflanzjahr":null,"entnahmejahr":null,"marker-size":"small","marker-symbol":"park2","marker-color":"#A3DDAD"},"geometry":{"type":"Point","coordinates":[15.43216785365559,47.02694422076186],"bbox":[15.43216785365559,47.02694422076186,15.43216785365559,47.02694422076186]}},{"type":"Feature","properties":{"nummer":34304,"baumbezeichnung_botanisch":"Liriodendron tulipifera 'Fastigiata'","baumbezeichnung_deutsch":"S채ulentulpenbaum","baumtyp":"Laub","bemerkung":null,"pflanzjahr":null,"entnahmejahr":null,"marker-size":"small","marker-symbol":"park2","marker-color":"#A3DDAD"},"geometry":{"type":"Point","coordinates":[15.43213956233612,47.02700961170572],"bbox":[15.43213956233612,47.02700961170572,15.43213956233612,47.02700961170572]}},{"type":"Feature","properties":{"nummer":34305,"baumbezeichnung_botanisch":"Liriodendron tulipifera 'Fastigiata'","baumbezeichnung_deutsch":"S채ulentulpenbaum","baumtyp":"Laub","bemerkung":null,"pflanzjahr":null,"entnahmejahr":null,"marker-size":"small","marker-symbol":"park2","marker-color":"#A3DDAD"},"geometry":{"type":"Point","coordinates":[15.43210987460255,47.02706296328871],"bbox":[15.43210987460255,47.02706296328871,15.43210987460255,47.02706296328871]}}]}