{"type":"FeatureCollection","features":[{"type":"Feature","properties":{"nummer":50152,"baumbezeichnung_botanisch":"Acer platanoides","baumbezeichnung_deutsch":"Spitzahorn","baumtyp":"Laub","bemerkung":null,"pflanzjahr":null,"entnahmejahr":null,"marker-size":"small","marker-symbol":"park2","marker-color":"#A3DDAD"},"geometry":{"type":"Point","coordinates":[15.43172509621274,47.03018751147985],"bbox":[15.43172509621274,47.03018751147985,15.43172509621274,47.03018751147985]}}]}