{"type":"FeatureCollection","features":[{"type":"Feature","properties":{"nummer":11435,"baumbezeichnung_botanisch":"Carpinus betulus","baumbezeichnung_deutsch":"Hain - oder Weißbuche","baumtyp":"Laub","bemerkung":null,"pflanzjahr":null,"entnahmejahr":null,"marker-size":"small","marker-symbol":"park2","marker-color":"#A3DDAD"},"geometry":{"type":"Point","coordinates":[15.38631172704206,47.04782401592066],"bbox":[15.38631172704206,47.04782401592066,15.38631172704206,47.04782401592066]}},{"type":"Feature","properties":{"nummer":2586,"baumbezeichnung_botanisch":"Carpinus betulus","baumbezeichnung_deutsch":"Hain - oder Weißbuche","baumtyp":"Laub","bemerkung":null,"pflanzjahr":null,"entnahmejahr":null,"marker-size":"small","marker-symbol":"park2","marker-color":"#A3DDAD"},"geometry":{"type":"Point","coordinates":[15.38620142836284,47.04787689188607],"bbox":[15.38620142836284,47.04787689188607,15.38620142836284,47.04787689188607]}},{"type":"Feature","properties":{"nummer":21055,"baumbezeichnung_botanisch":"Carpinus betulus","baumbezeichnung_deutsch":"Hain - oder Weißbuche","baumtyp":"Laub","bemerkung":null,"pflanzjahr":null,"entnahmejahr":null,"marker-size":"small","marker-symbol":"park2","marker-color":"#A3DDAD"},"geometry":{"type":"Point","coordinates":[15.38615448616385,47.04789692141814],"bbox":[15.38615448616385,47.04789692141814,15.38615448616385,47.04789692141814]}},{"type":"Feature","properties":{"nummer":2587,"baumbezeichnung_botanisch":"Carpinus betulus","baumbezeichnung_deutsch":"Hain - oder Weißbuche","baumtyp":"Laub","bemerkung":null,"pflanzjahr":null,"entnahmejahr":null,"marker-size":"small","marker-symbol":"park2","marker-color":"#A3DDAD"},"geometry":{"type":"Point","coordinates":[15.38613576714167,47.04790612106361],"bbox":[15.38613576714167,47.04790612106361,15.38613576714167,47.04790612106361]}}]}