{
  "type": "FeatureCollection",
  "features": [
    {
      "type": "Feature",
      "properties": {
        "NUMMER": 2750,
        "BAUMBEZEICHNUNG_BOTANISCH": "Acer pseudoplatanus",
        "BAUMBEZEICHNUNG_DEUTSCH": "Bergahorn",
        "BAUMTYP": "Laub",
        "BEMERKUNG": null,
        "PFLANZJAHR": null,
        "ENTNAHMEJAHR": null,
        "BAUMPATENSCHAFT": null,
        "ALTERSKLASSIZIERUNG": "alt",
        "OBJECTID": 62
      },
      "geometry": {
        "type": "Point",
        "coordinates": [
          15.44302517176249,
          47.07770165554533
        ]
      }
    },
    {
      "type": "Feature",
      "properties": {
        "NUMMER": 3525,
        "BAUMBEZEICHNUNG_BOTANISCH": "Tilia platyphyllos",
        "BAUMBEZEICHNUNG_DEUTSCH": "Sommerlinde",
        "BAUMTYP": "Laub",
        "BEMERKUNG": null,
        "PFLANZJAHR": null,
        "ENTNAHMEJAHR": null,
        "BAUMPATENSCHAFT": null,
        "ALTERSKLASSIZIERUNG": "jung",
        "OBJECTID": 435
      },
      "geometry": {
        "type": "Point",
        "coordinates": [
          15.442724255095406,
          47.078041660594494
        ]
      }
    },
    {
      "type": "Feature",
      "properties": {
        "NUMMER": 3601,
        "BAUMBEZEICHNUNG_BOTANISCH": "Aesculus hippocastanum",
        "BAUMBEZEICHNUNG_DEUTSCH": "Gemeine Roßkastanie",
        "BAUMTYP": "Laub",
        "BEMERKUNG": null,
        "PFLANZJAHR": null,
        "ENTNAHMEJAHR": null,
        "BAUMPATENSCHAFT": null,
        "ALTERSKLASSIZIERUNG": "alt",
        "OBJECTID": 680
      },
      "geometry": {
        "type": "Point",
        "coordinates": [
          15.44376030744484,
          47.07828107214894
        ]
      }
    },
    {
      "type": "Feature",
      "properties": {
        "NUMMER": 3610,
        "BAUMBEZEICHNUNG_BOTANISCH": "Aesculus hippocastanum",
        "BAUMBEZEICHNUNG_DEUTSCH": "Gemeine Roßkastanie",
        "BAUMTYP": "Laub",
        "BEMERKUNG": null,
        "PFLANZJAHR": null,
        "ENTNAHMEJAHR": null,
        "BAUMPATENSCHAFT": "Dipl.-Ing. Herta Zotter",
        "ALTERSKLASSIZIERUNG": "alt",
        "OBJECTID": 682
      },
      "geometry": {
        "type": "Point",
        "coordinates": [
          15.443640892092604,
          47.07815260822543
        ]
      }
    },
    {
      "type": "Feature",
      "properties": {
        "NUMMER": 2825,
        "BAUMBEZEICHNUNG_BOTANISCH": "Magnolia kobus",
        "BAUMBEZEICHNUNG_DEUTSCH": "Baummagnolie",
        "BAUMTYP": "Laub",
        "BEMERKUNG": null,
        "PFLANZJAHR": null,
        "ENTNAHMEJAHR": null,
        "BAUMPATENSCHAFT": null,
        "ALTERSKLASSIZIERUNG": "mittel",
        "OBJECTID": 1195
      },
      "geometry": {
        "type": "Point",
        "coordinates": [
          15.442118249584704,
          47.07798594427789
        ]
      }
    }
  ]
}