{"type":"FeatureCollection","features":[{"type":"Feature","properties":{"nummer":6468,"baumbezeichnung_botanisch":"Quercus sp.","baumbezeichnung_deutsch":"Eiche","baumtyp":"Laub","bemerkung":null,"pflanzjahr":null,"entnahmejahr":null,"marker-size":"small","marker-symbol":"park2","marker-color":"#A3DDAD"},"geometry":{"type":"Point","coordinates":[15.4528785626216,47.07637496180949],"bbox":[15.4528785626216,47.07637496180949,15.4528785626216,47.07637496180949]}}]}