{"type":"FeatureCollection","features":[{"type":"Feature","properties":{"nummer":4531,"baumbezeichnung_botanisch":"Acer platanoides","baumbezeichnung_deutsch":"Spitzahorn","baumtyp":"Laub","bemerkung":null,"pflanzjahr":null,"entnahmejahr":null,"marker-size":"small","marker-symbol":"park2","marker-color":"#A3DDAD"},"geometry":{"type":"Point","coordinates":[15.45340465498123,47.06196130290331],"bbox":[15.45340465498123,47.06196130290331,15.45340465498123,47.06196130290331]}}]}