{"type":"FeatureCollection","features":[{"type":"Feature","properties":{"nummer":21091,"baumbezeichnung_botanisch":"Acer pseudoplatanus","baumbezeichnung_deutsch":"Bergahorn","baumtyp":"Laub","bemerkung":null,"pflanzjahr":null,"entnahmejahr":null,"marker-size":"small","marker-symbol":"park2","marker-color":"#A3DDAD"},"geometry":{"type":"Point","coordinates":[15.4151693274676,47.08322616829317],"bbox":[15.4151693274676,47.08322616829317,15.4151693274676,47.08322616829317]}},{"type":"Feature","properties":{"nummer":23282,"baumbezeichnung_botanisch":"Acer pseudoplatanus","baumbezeichnung_deutsch":"Bergahorn","baumtyp":"Laub","bemerkung":null,"pflanzjahr":null,"entnahmejahr":null,"marker-size":"small","marker-symbol":"park2","marker-color":"#A3DDAD"},"geometry":{"type":"Point","coordinates":[15.41510834636413,47.08323399831738],"bbox":[15.41510834636413,47.08323399831738,15.41510834636413,47.08323399831738]}},{"type":"Feature","properties":{"nummer":23112,"baumbezeichnung_botanisch":"Acer pseudoplatanus","baumbezeichnung_deutsch":"Bergahorn","baumtyp":"Laub","bemerkung":null,"pflanzjahr":null,"entnahmejahr":null,"marker-size":"small","marker-symbol":"park2","marker-color":"#A3DDAD"},"geometry":{"type":"Point","coordinates":[15.41502513422648,47.08324279547568],"bbox":[15.41502513422648,47.08324279547568,15.41502513422648,47.08324279547568]}},{"type":"Feature","properties":{"nummer":33594,"baumbezeichnung_botanisch":"Acer pseudoplatanus","baumbezeichnung_deutsch":"Bergahorn","baumtyp":"Laub","bemerkung":null,"pflanzjahr":null,"entnahmejahr":null,"marker-size":"small","marker-symbol":"park2","marker-color":"#A3DDAD"},"geometry":{"type":"Point","coordinates":[15.41402763111339,47.08322616963076],"bbox":[15.41402763111339,47.08322616963076,15.41402763111339,47.08322616963076]}},{"type":"Feature","properties":{"nummer":33595,"baumbezeichnung_botanisch":"Acer pseudoplatanus","baumbezeichnung_deutsch":"Bergahorn","baumtyp":"Laub","bemerkung":null,"pflanzjahr":null,"entnahmejahr":null,"marker-size":"small","marker-symbol":"park2","marker-color":"#A3DDAD"},"geometry":{"type":"Point","coordinates":[15.41394169286577,47.08323504389691],"bbox":[15.41394169286577,47.08323504389691,15.41394169286577,47.08323504389691]}},{"type":"Feature","properties":{"nummer":33596,"baumbezeichnung_botanisch":"Acer pseudoplatanus","baumbezeichnung_deutsch":"Bergahorn","baumtyp":"Laub","bemerkung":null,"pflanzjahr":null,"entnahmejahr":null,"marker-size":"small","marker-symbol":"park2","marker-color":"#A3DDAD"},"geometry":{"type":"Point","coordinates":[15.41385571198012,47.08324631044571],"bbox":[15.41385571198012,47.08324631044571,15.41385571198012,47.08324631044571]}},{"type":"Feature","properties":{"nummer":57515,"baumbezeichnung_botanisch":"Fraxinus excelsior","baumbezeichnung_deutsch":"Esche","baumtyp":"Laub","bemerkung":null,"pflanzjahr":null,"entnahmejahr":null,"marker-size":"small","marker-symbol":"park2","marker-color":"#A3DDAD"},"geometry":{"type":"Point","coordinates":[15.41458250010954,47.0841027527693],"bbox":[15.41458250010954,47.0841027527693,15.41458250010954,47.0841027527693]}},{"type":"Feature","properties":{"nummer":57516,"baumbezeichnung_botanisch":"Flächenkartierung","baumbezeichnung_deutsch":"Flächenkartierung","baumtyp":"Flächenkartierung","bemerkung":null,"pflanzjahr":null,"entnahmejahr":null,"marker-size":"small","marker-symbol":"","marker-color":null},"geometry":{"type":"Point","coordinates":[15.41490890081207,47.08366270778458],"bbox":[15.41490890081207,47.08366270778458,15.41490890081207,47.08366270778458]}},{"type":"Feature","properties":{"nummer":57517,"baumbezeichnung_botanisch":"Carpinus betulus","baumbezeichnung_deutsch":"Hain - oder Weißbuche","baumtyp":"Laub","bemerkung":null,"pflanzjahr":null,"entnahmejahr":null,"marker-size":"small","marker-symbol":"park2","marker-color":"#A3DDAD"},"geometry":{"type":"Point","coordinates":[15.41486549890874,47.08355288046715],"bbox":[15.41486549890874,47.08355288046715,15.41486549890874,47.08355288046715]}},{"type":"Feature","properties":{"nummer":57518,"baumbezeichnung_botanisch":"Carpinus betulus","baumbezeichnung_deutsch":"Hain - oder Weißbuche","baumtyp":"Laub","bemerkung":null,"pflanzjahr":null,"entnahmejahr":null,"marker-size":"small","marker-symbol":"park2","marker-color":"#A3DDAD"},"geometry":{"type":"Point","coordinates":[15.41486947524301,47.08352435308697],"bbox":[15.41486947524301,47.08352435308697,15.41486947524301,47.08352435308697]}},{"type":"Feature","properties":{"nummer":57519,"baumbezeichnung_botanisch":"Prunus sp.","baumbezeichnung_deutsch":"Kirsche","baumtyp":"Laub","bemerkung":null,"pflanzjahr":null,"entnahmejahr":null,"marker-size":"small","marker-symbol":"park2","marker-color":"#A3DDAD"},"geometry":{"type":"Point","coordinates":[15.41482523238931,47.08346330828247],"bbox":[15.41482523238931,47.08346330828247,15.41482523238931,47.08346330828247]}}]}