{
  "type": "FeatureCollection",
  "features": [
    {
      "type": "Feature",
      "id": 538,
      "properties": {
        "nummer": 7938,
        "objectid": 538,
        "baumbezeichnung_deutsch": "Bergahorn",
        "baumbezeichnung_botanisch": "Acer pseudoplatanus",
        "baumtyp": "Laub",
        "bemerkung": null,
        "pflanzjahr": null,
        "entnahmejahr": null,
        "baumpatenschaft": null,
        "altersklassifizierung": "mittel"
      },
      "geometry": {
        "type": "Point",
        "coordinates": [
          15.436625434488501,
          47.08045842824414
        ]
      }
    },
    {
      "type": "Feature",
      "id": 968,
      "properties": {
        "nummer": 7933,
        "objectid": 968,
        "baumbezeichnung_deutsch": "Bergahorn",
        "baumbezeichnung_botanisch": "Acer pseudoplatanus",
        "baumtyp": "Laub",
        "bemerkung": null,
        "pflanzjahr": null,
        "entnahmejahr": null,
        "baumpatenschaft": null,
        "altersklassifizierung": "mittel"
      },
      "geometry": {
        "type": "Point",
        "coordinates": [
          15.437007132903316,
          47.08049689283873
        ]
      }
    },
    {
      "type": "Feature",
      "properties": {
        "Naturdenkmal": true,
        "Naturdenkmal_Eigentum": "privat",
        "nummer": "Naturdenkmal-104",
        "objectid": "Naturdenkmal-48",
        "baumbezeichnung_deutsch": "Platane",
        "baumbezeichnung_botanisch": "Platanus x hispanica"
      },
      "geometry": {
        "type": "Point",
        "coordinates": [
          15.436699855068705,
          47.08096470716296
        ]
      }
    }
  ]
}