{
  "type": "FeatureCollection",
  "features": [
    {
      "type": "Feature",
      "properties": {
        "NUMMER": 7938,
        "BAUMBEZEICHNUNG_BOTANISCH": "Acer pseudoplatanus",
        "BAUMBEZEICHNUNG_DEUTSCH": "Bergahorn",
        "BAUMTYP": "Laub",
        "BEMERKUNG": null,
        "PFLANZJAHR": null,
        "ENTNAHMEJAHR": null,
        "BAUMPATENSCHAFT": null,
        "ALTERSKLASSIZIERUNG": "mittel",
        "OBJECTID": 538
      },
      "geometry": {
        "type": "Point",
        "coordinates": [
          15.436625434488501,
          47.08045842824414
        ]
      }
    },
    {
      "type": "Feature",
      "properties": {
        "NUMMER": 7933,
        "BAUMBEZEICHNUNG_BOTANISCH": "Acer pseudoplatanus",
        "BAUMBEZEICHNUNG_DEUTSCH": "Bergahorn",
        "BAUMTYP": "Laub",
        "BEMERKUNG": null,
        "PFLANZJAHR": null,
        "ENTNAHMEJAHR": null,
        "BAUMPATENSCHAFT": null,
        "ALTERSKLASSIZIERUNG": "mittel",
        "OBJECTID": 968
      },
      "geometry": {
        "type": "Point",
        "coordinates": [
          15.437007132903316,
          47.08049689283873
        ]
      }
    },
    {
      "type": "Feature",
      "properties": {
        "Naturdenkmal": true,
        "Naturdenkmal_Eigentum": "privat",
        "nummer": "Naturdenkmal-104",
        "objectid": "Naturdenkmal-48",
        "baumbezeichnung_deutsch": "Platane",
        "baumbezeichnung_botanisch": "Platanus x hispanica"
      },
      "geometry": {
        "type": "Point",
        "coordinates": [
          15.436699855068705,
          47.08096470716296
        ]
      }
    }
  ]
}