{
  "type": "FeatureCollection",
  "features": [
    {
      "type": "Feature",
      "id": 272,
      "properties": {
        "nummer": 8035,
        "objectid": 272,
        "baumbezeichnung_deutsch": "Pflaume",
        "baumbezeichnung_botanisch": "Prunus domestica",
        "baumtyp": "Laub",
        "bemerkung": null,
        "pflanzjahr": null,
        "entnahmejahr": null,
        "baumpatenschaft": null,
        "altersklassifizierung": "jung"
      },
      "geometry": {
        "type": "Point",
        "coordinates": [
          15.472110782146563,
          47.03845573133983
        ]
      }
    }
  ]
}