{
  "type": "FeatureCollection",
  "features": [
    {
      "type": "Feature",
      "properties": {
        "NUMMER": 8035,
        "BAUMBEZEICHNUNG_BOTANISCH": "Prunus domestica",
        "BAUMBEZEICHNUNG_DEUTSCH": "Pflaume",
        "BAUMTYP": "Laub",
        "BEMERKUNG": null,
        "PFLANZJAHR": null,
        "ENTNAHMEJAHR": null,
        "BAUMPATENSCHAFT": null,
        "ALTERSKLASSIZIERUNG": "jung",
        "OBJECTID": 272
      },
      "geometry": {
        "type": "Point",
        "coordinates": [
          15.472110782146563,
          47.03845573133983
        ]
      }
    }
  ]
}