{
  "type": "FeatureCollection",
  "features": [
    {
      "type": "Feature",
      "properties": {
        "nummer": 8035,
        "baumbezeichnung_botanisch": "Prunus domestica",
        "baumbezeichnung_deutsch": "Pflaume",
        "baumtyp": "Laub",
        "altersklassifizierung": "jung",
        "bemerkung": null,
        "pflanzjahr": null,
        "entnahmejahr": null,
        "baumpatenschaft": null,
        "objectid": 272
      },
      "geometry": {
        "type": "Point",
        "coordinates": [
          15.472116809977898,
          47.03845561779099
        ],
        "bbox": [
          15.472116809977898,
          47.03845561779099,
          15.472116809977898,
          47.03845561779099
        ]
      }
    }
  ]
}