{"type":"FeatureCollection","features":[{"type":"Feature","properties":{"nummer":17835,"baumbezeichnung_botanisch":"Acer pseudoplatanus","baumbezeichnung_deutsch":"Bergahorn","baumtyp":"Laub","bemerkung":null,"pflanzjahr":null,"entnahmejahr":null,"marker-size":"small","marker-symbol":"park2","marker-color":"#A3DDAD"},"geometry":{"type":"Point","coordinates":[15.39932917494492,47.06572893451705],"bbox":[15.39932917494492,47.06572893451705,15.39932917494492,47.06572893451705]}},{"type":"Feature","properties":{"nummer":40210,"baumbezeichnung_botanisch":"Robinia pseudoacacia 'Umbraculifera'","baumbezeichnung_deutsch":"Kugelakazie","baumtyp":"Laub","bemerkung":null,"pflanzjahr":null,"entnahmejahr":null,"marker-size":"small","marker-symbol":"park2","marker-color":"#A3DDAD"},"geometry":{"type":"Point","coordinates":[15.39973368214303,47.06635107116082],"bbox":[15.39973368214303,47.06635107116082,15.39973368214303,47.06635107116082]}}]}