{
  "type": "FeatureCollection",
  "features": [
    {
      "type": "Feature",
      "properties": {
        "nummer": 22156,
        "objectid": 277,
        "baumbezeichnung_deutsch": "Stieleiche",
        "baumbezeichnung_botanisch": "Quercus robur",
        "baumtyp": "Laub",
        "bemerkung": null,
        "pflanzjahr": null,
        "entnahmejahr": null,
        "baumpatenschaft": null,
        "altersklassifizierung": "alt"
      },
      "geometry": {
        "type": "Point",
        "coordinates": [
          15.495994593834451,
          47.1050357838867
        ]
      }
    },
    {
      "type": "Feature",
      "properties": {
        "nummer": 22164,
        "objectid": 283,
        "baumbezeichnung_deutsch": "Bergahorn",
        "baumbezeichnung_botanisch": "Acer pseudoplatanus",
        "baumtyp": "Laub",
        "bemerkung": null,
        "pflanzjahr": null,
        "entnahmejahr": null,
        "baumpatenschaft": null,
        "altersklassifizierung": "mittel"
      },
      "geometry": {
        "type": "Point",
        "coordinates": [
          15.496112745001259,
          47.104938983797446
        ]
      }
    },
    {
      "type": "Feature",
      "properties": {
        "nummer": 22163,
        "objectid": 284,
        "baumbezeichnung_deutsch": "Bergahorn",
        "baumbezeichnung_botanisch": "Acer pseudoplatanus",
        "baumtyp": "Laub",
        "bemerkung": null,
        "pflanzjahr": null,
        "entnahmejahr": null,
        "baumpatenschaft": null,
        "altersklassifizierung": "mittel"
      },
      "geometry": {
        "type": "Point",
        "coordinates": [
          15.496073434057406,
          47.10498611075806
        ]
      }
    },
    {
      "type": "Feature",
      "properties": {
        "nummer": 22153,
        "objectid": 286,
        "baumbezeichnung_deutsch": "Rotbuche",
        "baumbezeichnung_botanisch": "Fagus sylvatica",
        "baumtyp": "Laub",
        "bemerkung": null,
        "pflanzjahr": null,
        "entnahmejahr": null,
        "baumpatenschaft": null,
        "altersklassifizierung": "alt"
      },
      "geometry": {
        "type": "Point",
        "coordinates": [
          15.495893181648691,
          47.1051057639672
        ]
      }
    },
    {
      "type": "Feature",
      "properties": {
        "nummer": 22170,
        "objectid": 288,
        "baumbezeichnung_deutsch": "Stieleiche",
        "baumbezeichnung_botanisch": "Quercus robur",
        "baumtyp": "Laub",
        "bemerkung": null,
        "pflanzjahr": null,
        "entnahmejahr": null,
        "baumpatenschaft": null,
        "altersklassifizierung": "mittel"
      },
      "geometry": {
        "type": "Point",
        "coordinates": [
          15.496078483779847,
          47.104845420337874
        ]
      }
    },
    {
      "type": "Feature",
      "properties": {
        "nummer": 22162,
        "objectid": 291,
        "baumbezeichnung_deutsch": "Bergahorn",
        "baumbezeichnung_botanisch": "Acer pseudoplatanus",
        "baumtyp": "Laub",
        "bemerkung": null,
        "pflanzjahr": null,
        "entnahmejahr": null,
        "baumpatenschaft": null,
        "altersklassifizierung": "mittel"
      },
      "geometry": {
        "type": "Point",
        "coordinates": [
          15.496031852517532,
          47.10500849293533
        ]
      }
    }
  ]
}