{
  "type": "FeatureCollection",
  "features": [
    {
      "type": "Feature",
      "properties": {
        "NUMMER": 22156,
        "BAUMBEZEICHNUNG_BOTANISCH": "Quercus robur",
        "BAUMBEZEICHNUNG_DEUTSCH": "Stieleiche",
        "BAUMTYP": "Laub",
        "BEMERKUNG": null,
        "PFLANZJAHR": null,
        "ENTNAHMEJAHR": null,
        "BAUMPATENSCHAFT": null,
        "ALTERSKLASSIZIERUNG": "alt",
        "OBJECTID": 277
      },
      "geometry": {
        "type": "Point",
        "coordinates": [
          15.495994593834451,
          47.1050357838867
        ]
      }
    },
    {
      "type": "Feature",
      "properties": {
        "NUMMER": 22164,
        "BAUMBEZEICHNUNG_BOTANISCH": "Acer pseudoplatanus",
        "BAUMBEZEICHNUNG_DEUTSCH": "Bergahorn",
        "BAUMTYP": "Laub",
        "BEMERKUNG": null,
        "PFLANZJAHR": null,
        "ENTNAHMEJAHR": null,
        "BAUMPATENSCHAFT": null,
        "ALTERSKLASSIZIERUNG": "mittel",
        "OBJECTID": 283
      },
      "geometry": {
        "type": "Point",
        "coordinates": [
          15.496112745001259,
          47.104938983797446
        ]
      }
    },
    {
      "type": "Feature",
      "properties": {
        "NUMMER": 22163,
        "BAUMBEZEICHNUNG_BOTANISCH": "Acer pseudoplatanus",
        "BAUMBEZEICHNUNG_DEUTSCH": "Bergahorn",
        "BAUMTYP": "Laub",
        "BEMERKUNG": null,
        "PFLANZJAHR": null,
        "ENTNAHMEJAHR": null,
        "BAUMPATENSCHAFT": null,
        "ALTERSKLASSIZIERUNG": "mittel",
        "OBJECTID": 284
      },
      "geometry": {
        "type": "Point",
        "coordinates": [
          15.496073434057406,
          47.10498611075806
        ]
      }
    },
    {
      "type": "Feature",
      "properties": {
        "NUMMER": 22153,
        "BAUMBEZEICHNUNG_BOTANISCH": "Fagus sylvatica",
        "BAUMBEZEICHNUNG_DEUTSCH": "Rotbuche",
        "BAUMTYP": "Laub",
        "BEMERKUNG": null,
        "PFLANZJAHR": null,
        "ENTNAHMEJAHR": null,
        "BAUMPATENSCHAFT": null,
        "ALTERSKLASSIZIERUNG": "alt",
        "OBJECTID": 286
      },
      "geometry": {
        "type": "Point",
        "coordinates": [
          15.495893181648691,
          47.1051057639672
        ]
      }
    },
    {
      "type": "Feature",
      "properties": {
        "NUMMER": 22170,
        "BAUMBEZEICHNUNG_BOTANISCH": "Quercus robur",
        "BAUMBEZEICHNUNG_DEUTSCH": "Stieleiche",
        "BAUMTYP": "Laub",
        "BEMERKUNG": null,
        "PFLANZJAHR": null,
        "ENTNAHMEJAHR": null,
        "BAUMPATENSCHAFT": null,
        "ALTERSKLASSIZIERUNG": "mittel",
        "OBJECTID": 288
      },
      "geometry": {
        "type": "Point",
        "coordinates": [
          15.496078483779847,
          47.104845420337874
        ]
      }
    },
    {
      "type": "Feature",
      "properties": {
        "NUMMER": 22162,
        "BAUMBEZEICHNUNG_BOTANISCH": "Acer pseudoplatanus",
        "BAUMBEZEICHNUNG_DEUTSCH": "Bergahorn",
        "BAUMTYP": "Laub",
        "BEMERKUNG": null,
        "PFLANZJAHR": null,
        "ENTNAHMEJAHR": null,
        "BAUMPATENSCHAFT": null,
        "ALTERSKLASSIZIERUNG": "mittel",
        "OBJECTID": 291
      },
      "geometry": {
        "type": "Point",
        "coordinates": [
          15.496031852517532,
          47.10500849293533
        ]
      }
    }
  ]
}