{"type":"FeatureCollection","features":[{"type":"Feature","properties":{"nummer":20622,"baumbezeichnung_botanisch":"Acer pseudoplatanus","baumbezeichnung_deutsch":"Bergahorn","baumtyp":"Laub","bemerkung":null,"pflanzjahr":"1984","entnahmejahr":null,"marker-size":"small","marker-symbol":"park2","marker-color":"#A3DDAD"},"geometry":{"type":"Point","coordinates":[15.40169283140197,47.04044367140125],"bbox":[15.40169283140197,47.04044367140125,15.40169283140197,47.04044367140125]}},{"type":"Feature","properties":{"nummer":22772,"baumbezeichnung_botanisch":"Acer pseudoplatanus","baumbezeichnung_deutsch":"Bergahorn","baumtyp":"Laub","bemerkung":null,"pflanzjahr":"1984","entnahmejahr":null,"marker-size":"small","marker-symbol":"park2","marker-color":"#A3DDAD"},"geometry":{"type":"Point","coordinates":[15.40178581349668,47.04041618539354],"bbox":[15.40178581349668,47.04041618539354,15.40178581349668,47.04041618539354]}},{"type":"Feature","properties":{"nummer":6339,"baumbezeichnung_botanisch":"Acer pseudoplatanus","baumbezeichnung_deutsch":"Bergahorn","baumtyp":"Laub","bemerkung":null,"pflanzjahr":"1984","entnahmejahr":null,"marker-size":"small","marker-symbol":"park2","marker-color":"#A3DDAD"},"geometry":{"type":"Point","coordinates":[15.40196149977943,47.04036202881718],"bbox":[15.40196149977943,47.04036202881718,15.40196149977943,47.04036202881718]}},{"type":"Feature","properties":{"nummer":8617,"baumbezeichnung_botanisch":"Acer platanoides","baumbezeichnung_deutsch":"Spitzahorn","baumtyp":"Laub","bemerkung":null,"pflanzjahr":"1984","entnahmejahr":null,"marker-size":"small","marker-symbol":"park2","marker-color":"#A3DDAD"},"geometry":{"type":"Point","coordinates":[15.40210700097233,47.0403184199313],"bbox":[15.40210700097233,47.0403184199313,15.40210700097233,47.0403184199313]}},{"type":"Feature","properties":{"nummer":20165,"baumbezeichnung_botanisch":"Acer pseudoplatanus","baumbezeichnung_deutsch":"Bergahorn","baumtyp":"Laub","bemerkung":null,"pflanzjahr":"1984","entnahmejahr":null,"marker-size":"small","marker-symbol":"park2","marker-color":"#A3DDAD"},"geometry":{"type":"Point","coordinates":[15.40227939597349,47.04026432597152],"bbox":[15.40227939597349,47.04026432597152,15.40227939597349,47.04026432597152]}},{"type":"Feature","properties":{"nummer":11239,"baumbezeichnung_botanisch":"Acer pseudoplatanus","baumbezeichnung_deutsch":"Bergahorn","baumtyp":"Laub","bemerkung":null,"pflanzjahr":"1984","entnahmejahr":null,"marker-size":"small","marker-symbol":"park2","marker-color":"#A3DDAD"},"geometry":{"type":"Point","coordinates":[15.40243032681366,47.04021869207222],"bbox":[15.40243032681366,47.04021869207222,15.40243032681366,47.04021869207222]}},{"type":"Feature","properties":{"nummer":20370,"baumbezeichnung_botanisch":"Acer pseudoplatanus","baumbezeichnung_deutsch":"Bergahorn","baumtyp":"Laub","bemerkung":null,"pflanzjahr":"1984","entnahmejahr":null,"marker-size":"small","marker-symbol":"park2","marker-color":"#A3DDAD"},"geometry":{"type":"Point","coordinates":[15.40193899821528,47.0402791798571],"bbox":[15.40193899821528,47.0402791798571,15.40193899821528,47.0402791798571]}}]}