{"type":"FeatureCollection","features":[{"type":"Feature","properties":{"nummer":29029,"baumbezeichnung_botanisch":"Fraxinus excelsior","baumbezeichnung_deutsch":"Esche","baumtyp":"Laub","bemerkung":null,"pflanzjahr":null,"entnahmejahr":null,"marker-size":"small","marker-symbol":"park2","marker-color":"#A3DDAD"},"geometry":{"type":"Point","coordinates":[15.44733172687305,47.08133896099029],"bbox":[15.44733172687305,47.08133896099029,15.44733172687305,47.08133896099029]}},{"type":"Feature","properties":{"nummer":29035,"baumbezeichnung_botanisch":"Fraxinus excelsior","baumbezeichnung_deutsch":"Esche","baumtyp":"Laub","bemerkung":null,"pflanzjahr":null,"entnahmejahr":null,"marker-size":"small","marker-symbol":"park2","marker-color":"#A3DDAD"},"geometry":{"type":"Point","coordinates":[15.44731829424778,47.0813285708704],"bbox":[15.44731829424778,47.0813285708704,15.44731829424778,47.0813285708704]}}]}