{"type":"FeatureCollection","features":[{"type":"Feature","properties":{"nummer":22199,"baumbezeichnung_botanisch":"Platanus x acerifolia","baumbezeichnung_deutsch":"Platane","baumtyp":"Laub","bemerkung":null,"pflanzjahr":null,"entnahmejahr":null,"marker-size":"small","marker-symbol":"park2","marker-color":"#A3DDAD"},"geometry":{"type":"Point","coordinates":[15.44788826855633,47.07716803133894],"bbox":[15.44788826855633,47.07716803133894,15.44788826855633,47.07716803133894]}},{"type":"Feature","properties":{"nummer":9784,"baumbezeichnung_botanisch":"Platanus x acerifolia","baumbezeichnung_deutsch":"Platane","baumtyp":"Laub","bemerkung":null,"pflanzjahr":null,"entnahmejahr":null,"marker-size":"small","marker-symbol":"park2","marker-color":"#A3DDAD"},"geometry":{"type":"Point","coordinates":[15.44813035814878,47.07729342924983],"bbox":[15.44813035814878,47.07729342924983,15.44813035814878,47.07729342924983]}}]}