{"type":"FeatureCollection","features":[{"type":"Feature","properties":{"nummer":9585,"baumbezeichnung_botanisch":"Aesculus hippocastanum","baumbezeichnung_deutsch":"Gemeine Roßkastanie","baumtyp":"Laub","bemerkung":null,"pflanzjahr":null,"entnahmejahr":null,"marker-size":"small","marker-symbol":"park2","marker-color":"#A3DDAD"},"geometry":{"type":"Point","coordinates":[15.44687893711316,47.06823354716444],"bbox":[15.44687893711316,47.06823354716444,15.44687893711316,47.06823354716444]}},{"type":"Feature","properties":{"nummer":24436,"baumbezeichnung_botanisch":"Aesculus hippocastanum","baumbezeichnung_deutsch":"Gemeine Roßkastanie","baumtyp":"Laub","bemerkung":null,"pflanzjahr":"1990","entnahmejahr":null,"marker-size":"small","marker-symbol":"park2","marker-color":"#A3DDAD"},"geometry":{"type":"Point","coordinates":[15.44683587391134,47.0681958984067],"bbox":[15.44683587391134,47.0681958984067,15.44683587391134,47.0681958984067]}}]}