{"type":"FeatureCollection","features":[{"type":"Feature","properties":{"nummer":7768,"baumbezeichnung_botanisch":"Morus alba","baumbezeichnung_deutsch":"Weiße Maulbeere","baumtyp":"Laub","bemerkung":null,"pflanzjahr":null,"entnahmejahr":null,"marker-size":"small","marker-symbol":"park2","marker-color":"#A3DDAD"},"geometry":{"type":"Point","coordinates":[15.44799068450362,47.06522247239871],"bbox":[15.44799068450362,47.06522247239871,15.44799068450362,47.06522247239871]}},{"type":"Feature","properties":{"nummer":7773,"baumbezeichnung_botanisch":"Morus alba","baumbezeichnung_deutsch":"Weiße Maulbeere","baumtyp":"Laub","bemerkung":null,"pflanzjahr":null,"entnahmejahr":null,"marker-size":"small","marker-symbol":"park2","marker-color":"#A3DDAD"},"geometry":{"type":"Point","coordinates":[15.44794711102908,47.06526445279011],"bbox":[15.44794711102908,47.06526445279011,15.44794711102908,47.06526445279011]}},{"type":"Feature","properties":{"nummer":25556,"baumbezeichnung_botanisch":"Tilia platyphyllos","baumbezeichnung_deutsch":"Sommerlinde","baumtyp":"Laub","bemerkung":null,"pflanzjahr":null,"entnahmejahr":null,"marker-size":"small","marker-symbol":"park2","marker-color":"#A3DDAD"},"geometry":{"type":"Point","coordinates":[15.44781529692395,47.06473421809104],"bbox":[15.44781529692395,47.06473421809104,15.44781529692395,47.06473421809104]}},{"type":"Feature","properties":{"nummer":13337,"baumbezeichnung_botanisch":"Prunus sp.","baumbezeichnung_deutsch":"Kirsche","baumtyp":"Laub","bemerkung":"schräger Stand Richtung Westen, Lackporlingsbefall am östlichen Stammfuß - daher Sturzgefahr","pflanzjahr":null,"entnahmejahr":"2013","marker-size":"small","marker-symbol":"park2","marker-color":"#B3B3B3"},"geometry":{"type":"Point","coordinates":[15.44779947367777,47.0649028991802],"bbox":[15.44779947367777,47.0649028991802,15.44779947367777,47.0649028991802]}}]}