{"type":"FeatureCollection","features":[{"type":"Feature","properties":{"nummer":2802,"baumbezeichnung_botanisch":"Fraxinus excelsior","baumbezeichnung_deutsch":"Esche","baumtyp":"Laub","bemerkung":null,"pflanzjahr":null,"entnahmejahr":null,"marker-size":"small","marker-symbol":"park2","marker-color":"#A3DDAD"},"geometry":{"type":"Point","coordinates":[15.4257310486959,47.10155874401853],"bbox":[15.4257310486959,47.10155874401853,15.4257310486959,47.10155874401853]}}]}