{
  "type": "FeatureCollection",
  "features": [
    {
      "type": "Feature",
      "properties": {
        "NUMMER": 10601,
        "BAUMBEZEICHNUNG_BOTANISCH": "Picea abies",
        "BAUMBEZEICHNUNG_DEUTSCH": "Rotfichte",
        "BAUMTYP": "Nadel",
        "BEMERKUNG": null,
        "PFLANZJAHR": null,
        "ENTNAHMEJAHR": null,
        "BAUMPATENSCHAFT": null,
        "ALTERSKLASSIZIERUNG": "mittel",
        "OBJECTID": 960
      },
      "geometry": {
        "type": "Point",
        "coordinates": [
          15.424878782010818,
          47.10768441096814
        ]
      }
    }
  ]
}