{
  "type": "FeatureCollection",
  "features": [
    {
      "type": "Feature",
      "properties": {
        "NUMMER": 6353,
        "BAUMBEZEICHNUNG_BOTANISCH": "Aesculus hippocastanum",
        "BAUMBEZEICHNUNG_DEUTSCH": "Gemeine Roßkastanie",
        "BAUMTYP": "Laub",
        "BEMERKUNG": null,
        "PFLANZJAHR": null,
        "ENTNAHMEJAHR": null,
        "BAUMPATENSCHAFT": null,
        "ALTERSKLASSIZIERUNG": "mittel",
        "OBJECTID": 1002
      },
      "geometry": {
        "type": "Point",
        "coordinates": [
          15.447927903365093,
          47.0596958745646
        ]
      }
    }
  ]
}