{"type":"FeatureCollection","features":[{"type":"Feature","properties":{"nummer":16602,"baumbezeichnung_botanisch":"Carpinus betulus","baumbezeichnung_deutsch":"Hain - oder Weißbuche","baumtyp":"Laub","bemerkung":null,"pflanzjahr":null,"entnahmejahr":null,"marker-size":"small","marker-symbol":"park2","marker-color":"#A3DDAD"},"geometry":{"type":"Point","coordinates":[15.44434124003002,47.09732826277158],"bbox":[15.44434124003002,47.09732826277158,15.44434124003002,47.09732826277158]}},{"type":"Feature","properties":{"nummer":18379,"baumbezeichnung_botanisch":"Robinia pseudoacacia","baumbezeichnung_deutsch":"Scheinakazie","baumtyp":"Laub","bemerkung":null,"pflanzjahr":null,"entnahmejahr":null,"marker-size":"small","marker-symbol":"park2","marker-color":"#A3DDAD"},"geometry":{"type":"Point","coordinates":[15.4443083971186,47.09731930970948],"bbox":[15.4443083971186,47.09731930970948,15.4443083971186,47.09731930970948]}},{"type":"Feature","properties":{"nummer":17995,"baumbezeichnung_botanisch":"Carpinus betulus","baumbezeichnung_deutsch":"Hain - oder Weißbuche","baumtyp":"Laub","bemerkung":null,"pflanzjahr":null,"entnahmejahr":null,"marker-size":"small","marker-symbol":"park2","marker-color":"#A3DDAD"},"geometry":{"type":"Point","coordinates":[15.44428685017534,47.09730754819798],"bbox":[15.44428685017534,47.09730754819798,15.44428685017534,47.09730754819798]}},{"type":"Feature","properties":{"nummer":19930,"baumbezeichnung_botanisch":"Robinia pseudoacacia","baumbezeichnung_deutsch":"Scheinakazie","baumtyp":"Laub","bemerkung":null,"pflanzjahr":null,"entnahmejahr":null,"marker-size":"small","marker-symbol":"park2","marker-color":"#A3DDAD"},"geometry":{"type":"Point","coordinates":[15.44418432393488,47.0972661676767],"bbox":[15.44418432393488,47.0972661676767,15.44418432393488,47.0972661676767]}},{"type":"Feature","properties":{"nummer":19933,"baumbezeichnung_botanisch":"Carpinus betulus","baumbezeichnung_deutsch":"Hain - oder Weißbuche","baumtyp":"Laub","bemerkung":null,"pflanzjahr":null,"entnahmejahr":null,"marker-size":"small","marker-symbol":"park2","marker-color":"#A3DDAD"},"geometry":{"type":"Point","coordinates":[15.44416431764209,47.09724678853942],"bbox":[15.44416431764209,47.09724678853942,15.44416431764209,47.09724678853942]}},{"type":"Feature","properties":{"nummer":55907,"baumbezeichnung_botanisch":"Betula pendula","baumbezeichnung_deutsch":"Sandbirke, Weißbirke","baumtyp":"Laub","bemerkung":null,"pflanzjahr":null,"entnahmejahr":null,"marker-size":"small","marker-symbol":"park2","marker-color":"#A3DDAD"},"geometry":{"type":"Point","coordinates":[15.44450750430042,47.09739654256663],"bbox":[15.44450750430042,47.09739654256663,15.44450750430042,47.09739654256663]}},{"type":"Feature","properties":{"nummer":55908,"baumbezeichnung_botanisch":"Acer platanoides","baumbezeichnung_deutsch":"Spitzahorn","baumtyp":"Laub","bemerkung":null,"pflanzjahr":null,"entnahmejahr":null,"marker-size":"small","marker-symbol":"park2","marker-color":"#A3DDAD"},"geometry":{"type":"Point","coordinates":[15.44504949638812,47.09753974972787],"bbox":[15.44504949638812,47.09753974972787,15.44504949638812,47.09753974972787]}}]}