{"type":"FeatureCollection","features":[{"type":"Feature","properties":{"nummer":3761,"baumbezeichnung_botanisch":"Acer platanoides","baumbezeichnung_deutsch":"Spitzahorn","baumtyp":"Laub","bemerkung":null,"pflanzjahr":"1985","entnahmejahr":null,"marker-size":"small","marker-symbol":"park2","marker-color":"#A3DDAD"},"geometry":{"type":"Point","coordinates":[15.44446570012395,47.06069569485258],"bbox":[15.44446570012395,47.06069569485258,15.44446570012395,47.06069569485258]}},{"type":"Feature","properties":{"nummer":3762,"baumbezeichnung_botanisch":"Acer platanoides","baumbezeichnung_deutsch":"Spitzahorn","baumtyp":"Laub","bemerkung":null,"pflanzjahr":"1985","entnahmejahr":null,"marker-size":"small","marker-symbol":"park2","marker-color":"#A3DDAD"},"geometry":{"type":"Point","coordinates":[15.44453525295903,47.06057025094791],"bbox":[15.44453525295903,47.06057025094791,15.44453525295903,47.06057025094791]}},{"type":"Feature","properties":{"nummer":7247,"baumbezeichnung_botanisch":"Acer platanoides","baumbezeichnung_deutsch":"Spitzahorn","baumtyp":"Laub","bemerkung":null,"pflanzjahr":"1985","entnahmejahr":null,"marker-size":"small","marker-symbol":"park2","marker-color":"#A3DDAD"},"geometry":{"type":"Point","coordinates":[15.44464735755436,47.06036136684166],"bbox":[15.44464735755436,47.06036136684166,15.44464735755436,47.06036136684166]}},{"type":"Feature","properties":{"nummer":19808,"baumbezeichnung_botanisch":"Acer platanoides","baumbezeichnung_deutsch":"Spitzahorn","baumtyp":"Laub","bemerkung":null,"pflanzjahr":"1985","entnahmejahr":null,"marker-size":"small","marker-symbol":"park2","marker-color":"#A3DDAD"},"geometry":{"type":"Point","coordinates":[15.44478870611001,47.06010530603568],"bbox":[15.44478870611001,47.06010530603568,15.44478870611001,47.06010530603568]}},{"type":"Feature","properties":{"nummer":24250,"baumbezeichnung_botanisch":"Acer platanoides","baumbezeichnung_deutsch":"Spitzahorn","baumtyp":"Laub","bemerkung":null,"pflanzjahr":"1985","entnahmejahr":null,"marker-size":"small","marker-symbol":"park2","marker-color":"#A3DDAD"},"geometry":{"type":"Point","coordinates":[15.44483971067436,47.0600090865839],"bbox":[15.44483971067436,47.0600090865839,15.44483971067436,47.0600090865839]}},{"type":"Feature","properties":{"nummer":15196,"baumbezeichnung_botanisch":"Acer platanoides","baumbezeichnung_deutsch":"Spitzahorn","baumtyp":"Laub","bemerkung":null,"pflanzjahr":"2009","entnahmejahr":null,"marker-size":"small","marker-symbol":"park2","marker-color":"#A3DDAD"},"geometry":{"type":"Point","coordinates":[15.44489608191148,47.05990755678699],"bbox":[15.44489608191148,47.05990755678699,15.44489608191148,47.05990755678699]}},{"type":"Feature","properties":{"nummer":20470,"baumbezeichnung_botanisch":"Acer platanoides","baumbezeichnung_deutsch":"Spitzahorn","baumtyp":"Laub","bemerkung":null,"pflanzjahr":"2001","entnahmejahr":null,"marker-size":"small","marker-symbol":"park2","marker-color":"#A3DDAD"},"geometry":{"type":"Point","coordinates":[15.44471328636578,47.06023691105664],"bbox":[15.44471328636578,47.06023691105664,15.44471328636578,47.06023691105664]}}]}