{"type":"FeatureCollection","features":[{"type":"Feature","properties":{"nummer":7551,"baumbezeichnung_botanisch":"Aesculus hippocastanum","baumbezeichnung_deutsch":"Gemeine Roßkastanie","baumtyp":"Laub","bemerkung":null,"pflanzjahr":null,"entnahmejahr":null,"marker-size":"small","marker-symbol":"park2","marker-color":"#A3DDAD"},"geometry":{"type":"Point","coordinates":[15.39286256835898,47.07731740708255],"bbox":[15.39286256835898,47.07731740708255,15.39286256835898,47.07731740708255]}}]}