{"type":"FeatureCollection","features":[{"type":"Feature","properties":{"nummer":26086,"baumbezeichnung_botanisch":"Acer platanoides","baumbezeichnung_deutsch":"Spitzahorn","baumtyp":"Laub","bemerkung":null,"pflanzjahr":"1986","entnahmejahr":null,"marker-size":"small","marker-symbol":"park2","marker-color":"#A3DDAD"},"geometry":{"type":"Point","coordinates":[15.39222645112449,47.06297073596746],"bbox":[15.39222645112449,47.06297073596746,15.39222645112449,47.06297073596746]}},{"type":"Feature","properties":{"nummer":1912,"baumbezeichnung_botanisch":"Acer platanoides","baumbezeichnung_deutsch":"Spitzahorn","baumtyp":"Laub","bemerkung":null,"pflanzjahr":"1986","entnahmejahr":null,"marker-size":"small","marker-symbol":"park2","marker-color":"#A3DDAD"},"geometry":{"type":"Point","coordinates":[15.39222830737349,47.06280070766228],"bbox":[15.39222830737349,47.06280070766228,15.39222830737349,47.06280070766228]}},{"type":"Feature","properties":{"nummer":17264,"baumbezeichnung_botanisch":"Acer platanoides","baumbezeichnung_deutsch":"Spitzahorn","baumtyp":"Laub","bemerkung":null,"pflanzjahr":"1986","entnahmejahr":null,"marker-size":"small","marker-symbol":"park2","marker-color":"#A3DDAD"},"geometry":{"type":"Point","coordinates":[15.39222827827496,47.06269944943926],"bbox":[15.39222827827496,47.06269944943926,15.39222827827496,47.06269944943926]}},{"type":"Feature","properties":{"nummer":17479,"baumbezeichnung_botanisch":"Prunus serrulata 'Kanzan'","baumbezeichnung_deutsch":"Japanische Blütenkirsche","baumtyp":"Laub","bemerkung":null,"pflanzjahr":"1987","entnahmejahr":null,"marker-size":"small","marker-symbol":"park2","marker-color":"#A3DDAD"},"geometry":{"type":"Point","coordinates":[15.39207140642422,47.06328548314239],"bbox":[15.39207140642422,47.06328548314239,15.39207140642422,47.06328548314239]}},{"type":"Feature","properties":{"nummer":6392,"baumbezeichnung_botanisch":"Prunus serrulata 'Kanzan'","baumbezeichnung_deutsch":"Japanische Blütenkirsche","baumtyp":"Laub","bemerkung":null,"pflanzjahr":"1987","entnahmejahr":null,"marker-size":"small","marker-symbol":"park2","marker-color":"#A3DDAD"},"geometry":{"type":"Point","coordinates":[15.3919103100348,47.06330099378523],"bbox":[15.3919103100348,47.06330099378523,15.3919103100348,47.06330099378523]}}]}