{"type":"FeatureCollection","features":[{"type":"Feature","properties":{"nummer":1875,"baumbezeichnung_botanisch":"Acer platanoides","baumbezeichnung_deutsch":"Spitzahorn","baumtyp":"Laub","bemerkung":null,"pflanzjahr":"2009","entnahmejahr":null,"marker-size":"small","marker-symbol":"park2","marker-color":"#A3DDAD"},"geometry":{"type":"Point","coordinates":[15.39226593916033,47.06164425524905],"bbox":[15.39226593916033,47.06164425524905,15.39226593916033,47.06164425524905]}},{"type":"Feature","properties":{"nummer":21192,"baumbezeichnung_botanisch":"Acer platanoides","baumbezeichnung_deutsch":"Spitzahorn","baumtyp":"Laub","bemerkung":null,"pflanzjahr":"1986","entnahmejahr":null,"marker-size":"small","marker-symbol":"park2","marker-color":"#A3DDAD"},"geometry":{"type":"Point","coordinates":[15.39227084275722,47.06152231291961],"bbox":[15.39227084275722,47.06152231291961,15.39227084275722,47.06152231291961]}}]}