{"type":"FeatureCollection","features":[{"type":"Feature","properties":{"nummer":16031,"baumbezeichnung_botanisch":"Prunus serrulata 'Hokusai'","baumbezeichnung_deutsch":"Japanische Kirsche","baumtyp":"Laub","bemerkung":null,"pflanzjahr":null,"entnahmejahr":null,"marker-size":"small","marker-symbol":"park2","marker-color":"#A3DDAD"},"geometry":{"type":"Point","coordinates":[15.39258444175062,47.05612958917182],"bbox":[15.39258444175062,47.05612958917182,15.39258444175062,47.05612958917182]}}]}