{"type":"FeatureCollection","features":[{"type":"Feature","properties":{"nummer":22463,"baumbezeichnung_botanisch":"Castanea sativa","baumbezeichnung_deutsch":"Eßkastanie","baumtyp":"Laub","bemerkung":null,"pflanzjahr":null,"entnahmejahr":null,"marker-size":"small","marker-symbol":"park2","marker-color":"#A3DDAD"},"geometry":{"type":"Point","coordinates":[15.4459098194696,47.09503550960336],"bbox":[15.4459098194696,47.09503550960336,15.4459098194696,47.09503550960336]}}]}