{"type":"FeatureCollection","features":[{"type":"Feature","properties":{"nummer":24136,"baumbezeichnung_botanisch":"Tilia x europaea","baumbezeichnung_deutsch":"Zwischenlinde","baumtyp":"Laub","bemerkung":null,"pflanzjahr":null,"entnahmejahr":null,"marker-size":"small","marker-symbol":"park2","marker-color":"#A3DDAD"},"geometry":{"type":"Point","coordinates":[15.44635510261308,47.06649581473813],"bbox":[15.44635510261308,47.06649581473813,15.44635510261308,47.06649581473813]}},{"type":"Feature","properties":{"nummer":7133,"baumbezeichnung_botanisch":"Tilia americana","baumbezeichnung_deutsch":"Amerikanische Linde","baumtyp":"Laub","bemerkung":null,"pflanzjahr":"1988","entnahmejahr":null,"marker-size":"small","marker-symbol":"park2","marker-color":"#A3DDAD"},"geometry":{"type":"Point","coordinates":[15.44592441850794,47.0663852918564],"bbox":[15.44592441850794,47.0663852918564,15.44592441850794,47.0663852918564]}},{"type":"Feature","properties":{"nummer":56550,"baumbezeichnung_botanisch":"Liquidambar styraciflua","baumbezeichnung_deutsch":"Amberbaum","baumtyp":"Laub","bemerkung":null,"pflanzjahr":"2012","entnahmejahr":null,"marker-size":"small","marker-symbol":"park2","marker-color":"#A3DDAD"},"geometry":{"type":"Point","coordinates":[15.44647523060571,47.0665372107068],"bbox":[15.44647523060571,47.0665372107068,15.44647523060571,47.0665372107068]}},{"type":"Feature","properties":{"nummer":38918,"baumbezeichnung_botanisch":"Carpinus betulus 'Fastigiata'","baumbezeichnung_deutsch":"Säulenhainbuche","baumtyp":"Laub","bemerkung":null,"pflanzjahr":"2010","entnahmejahr":null,"marker-size":"small","marker-symbol":"park2","marker-color":"#A3DDAD"},"geometry":{"type":"Point","coordinates":[15.44556791539187,47.06689859025696],"bbox":[15.44556791539187,47.06689859025696,15.44556791539187,47.06689859025696]}}]}