{"type":"FeatureCollection","features":[{"type":"Feature","properties":{"nummer":23441,"baumbezeichnung_botanisch":"Tilia cordata","baumbezeichnung_deutsch":"Winterlinde","baumtyp":"Laub","bemerkung":null,"pflanzjahr":"2005","entnahmejahr":null,"marker-size":"small","marker-symbol":"park2","marker-color":"#A3DDAD"},"geometry":{"type":"Point","coordinates":[15.43451020993529,47.05679971684748],"bbox":[15.43451020993529,47.05679971684748,15.43451020993529,47.05679971684748]}}]}