{"type":"FeatureCollection","features":[{"type":"Feature","properties":{"nummer":34725,"baumbezeichnung_botanisch":"Fagus sylvatica 'Dawyk Purple'","baumbezeichnung_deutsch":"Säulenblutbuche","baumtyp":"Laub","bemerkung":null,"pflanzjahr":null,"entnahmejahr":null,"marker-size":"small","marker-symbol":"park2","marker-color":"#A3DDAD"},"geometry":{"type":"Point","coordinates":[15.4174678688808,47.06774549529398],"bbox":[15.4174678688808,47.06774549529398,15.4174678688808,47.06774549529398]}}]}