{
  "type": "FeatureCollection",
  "features": [
    {
      "type": "Feature",
      "properties": {
        "nummer": 29688,
        "baumbezeichnung_botanisch": "Fagus sylvatica 'Dawyk Purple'",
        "baumbezeichnung_deutsch": "Säulenblutbuche",
        "baumtyp": "Laub",
        "altersklassifizierung": "jung",
        "bemerkung": null,
        "pflanzjahr": null,
        "entnahmejahr": null,
        "baumpatenschaft": null,
        "objectid": 9108
      },
      "geometry": {
        "type": "Point",
        "coordinates": [
          15.417467868880795,
          47.067745495293984
        ],
        "bbox": [
          15.417467868880795,
          47.067745495293984,
          15.417467868880795,
          47.067745495293984
        ]
      }
    }
  ]
}