{
  "type": "FeatureCollection",
  "features": [
    {
      "type": "Feature",
      "properties": {
        "nummer": 13923,
        "baumbezeichnung_botanisch": "Aesculus hippocastanum",
        "baumbezeichnung_deutsch": "Gemeine Roßkastanie",
        "baumtyp": "Laub",
        "altersklassifizierung": "alt",
        "bemerkung": null,
        "pflanzjahr": null,
        "entnahmejahr": null,
        "baumpatenschaft": null,
        "objectid": 18364
      },
      "geometry": {
        "type": "Point",
        "coordinates": [
          15.416638249711264,
          47.044407355420454
        ],
        "bbox": [
          15.416638249711264,
          47.044407355420454,
          15.416638249711264,
          47.044407355420454
        ]
      }
    }
  ]
}