{"type":"FeatureCollection","features":[{"type":"Feature","properties":{"nummer":39897,"baumbezeichnung_botanisch":"Acer platanoides","baumbezeichnung_deutsch":"Spitzahorn","baumtyp":"Laub","bemerkung":null,"pflanzjahr":null,"entnahmejahr":null,"marker-size":"small","marker-symbol":"park2","marker-color":"#A3DDAD"},"geometry":{"type":"Point","coordinates":[15.41784841603076,47.09811441063791],"bbox":[15.41784841603076,47.09811441063791,15.41784841603076,47.09811441063791]}}]}