{"type":"FeatureCollection","features":[{"type":"Feature","properties":{"nummer":56558,"baumbezeichnung_botanisch":"Acer ginnala","baumbezeichnung_deutsch":"Feuerahorn","baumtyp":"Laub","bemerkung":null,"pflanzjahr":"2012","entnahmejahr":null,"marker-size":"small","marker-symbol":"park2","marker-color":"#A3DDAD"},"geometry":{"type":"Point","coordinates":[15.41664964014664,47.08948593947876],"bbox":[15.41664964014664,47.08948593947876,15.41664964014664,47.08948593947876]}},{"type":"Feature","properties":{"nummer":56560,"baumbezeichnung_botanisch":"Acer ginnala","baumbezeichnung_deutsch":"Feuerahorn","baumtyp":"Laub","bemerkung":null,"pflanzjahr":"2012","entnahmejahr":null,"marker-size":"small","marker-symbol":"park2","marker-color":"#A3DDAD"},"geometry":{"type":"Point","coordinates":[15.41687339984109,47.08924022123026],"bbox":[15.41687339984109,47.08924022123026,15.41687339984109,47.08924022123026]}},{"type":"Feature","properties":{"nummer":56561,"baumbezeichnung_botanisch":"Acer ginnala","baumbezeichnung_deutsch":"Feuerahorn","baumtyp":"Laub","bemerkung":null,"pflanzjahr":"2012","entnahmejahr":null,"marker-size":"small","marker-symbol":"park2","marker-color":"#A3DDAD"},"geometry":{"type":"Point","coordinates":[15.41721381371989,47.08889786102719],"bbox":[15.41721381371989,47.08889786102719,15.41721381371989,47.08889786102719]}}]}