{"type":"FeatureCollection","features":[{"type":"Feature","properties":{"nummer":6502,"baumbezeichnung_botanisch":"Acer saccharinum","baumbezeichnung_deutsch":"Zuckerahorn","baumtyp":"Laub","bemerkung":null,"pflanzjahr":"2006","entnahmejahr":null,"marker-size":"small","marker-symbol":"park2","marker-color":"#A3DDAD"},"geometry":{"type":"Point","coordinates":[15.41784257961962,47.03546049292739],"bbox":[15.41784257961962,47.03546049292739,15.41784257961962,47.03546049292739]}},{"type":"Feature","properties":{"nummer":21570,"baumbezeichnung_botanisch":"Acer saccharinum","baumbezeichnung_deutsch":"Zuckerahorn","baumtyp":"Laub","bemerkung":null,"pflanzjahr":null,"entnahmejahr":null,"marker-size":"small","marker-symbol":"park2","marker-color":"#A3DDAD"},"geometry":{"type":"Point","coordinates":[15.4179147871824,47.03535553548485],"bbox":[15.4179147871824,47.03535553548485,15.4179147871824,47.03535553548485]}},{"type":"Feature","properties":{"nummer":28458,"baumbezeichnung_botanisch":"Acer saccharinum","baumbezeichnung_deutsch":"Zuckerahorn","baumtyp":"Laub","bemerkung":null,"pflanzjahr":null,"entnahmejahr":null,"marker-size":"small","marker-symbol":"park2","marker-color":"#A3DDAD"},"geometry":{"type":"Point","coordinates":[15.41788273334277,47.03541195238373],"bbox":[15.41788273334277,47.03541195238373,15.41788273334277,47.03541195238373]}}]}