{
  "type": "FeatureCollection",
  "features": [
    {
      "type": "Feature",
      "properties": {
        "NUMMER": 17192,
        "BAUMBEZEICHNUNG_BOTANISCH": "Betula pendula",
        "BAUMBEZEICHNUNG_DEUTSCH": "Sandbirke, Weißbirke",
        "BAUMTYP": "Laub",
        "BEMERKUNG": null,
        "PFLANZJAHR": null,
        "ENTNAHMEJAHR": null,
        "BAUMPATENSCHAFT": null,
        "ALTERSKLASSIZIERUNG": "mittel",
        "OBJECTID": 1644
      },
      "geometry": {
        "type": "Point",
        "coordinates": [
          15.422025666557536,
          47.09856137363862
        ]
      }
    },
    {
      "type": "Feature",
      "properties": {
        "NUMMER": 17196,
        "BAUMBEZEICHNUNG_BOTANISCH": "Pinus nigra",
        "BAUMBEZEICHNUNG_DEUTSCH": "Schwarzkiefer",
        "BAUMTYP": "Nadel",
        "BEMERKUNG": null,
        "PFLANZJAHR": null,
        "ENTNAHMEJAHR": null,
        "BAUMPATENSCHAFT": null,
        "ALTERSKLASSIZIERUNG": "mittel",
        "OBJECTID": 1645
      },
      "geometry": {
        "type": "Point",
        "coordinates": [
          15.421665432252544,
          47.09868550757246
        ]
      }
    },
    {
      "type": "Feature",
      "properties": {
        "NUMMER": 17202,
        "BAUMBEZEICHNUNG_BOTANISCH": "Betula pendula",
        "BAUMBEZEICHNUNG_DEUTSCH": "Sandbirke, Weißbirke",
        "BAUMTYP": "Laub",
        "BEMERKUNG": null,
        "PFLANZJAHR": null,
        "ENTNAHMEJAHR": null,
        "BAUMPATENSCHAFT": null,
        "ALTERSKLASSIZIERUNG": "mittel",
        "OBJECTID": 1646
      },
      "geometry": {
        "type": "Point",
        "coordinates": [
          15.421528808513338,
          47.0987204344836
        ]
      }
    },
    {
      "type": "Feature",
      "properties": {
        "NUMMER": 17204,
        "BAUMBEZEICHNUNG_BOTANISCH": "Betula pendula",
        "BAUMBEZEICHNUNG_DEUTSCH": "Sandbirke, Weißbirke",
        "BAUMTYP": "Laub",
        "BEMERKUNG": null,
        "PFLANZJAHR": null,
        "ENTNAHMEJAHR": null,
        "BAUMPATENSCHAFT": null,
        "ALTERSKLASSIZIERUNG": "mittel",
        "OBJECTID": 1647
      },
      "geometry": {
        "type": "Point",
        "coordinates": [
          15.421428721513935,
          47.09872911325386
        ]
      }
    },
    {
      "type": "Feature",
      "properties": {
        "NUMMER": 17206,
        "BAUMBEZEICHNUNG_BOTANISCH": "Prunus padus",
        "BAUMBEZEICHNUNG_DEUTSCH": "Traubenkirsche",
        "BAUMTYP": "Laub",
        "BEMERKUNG": null,
        "PFLANZJAHR": null,
        "ENTNAHMEJAHR": null,
        "BAUMPATENSCHAFT": null,
        "ALTERSKLASSIZIERUNG": "mittel",
        "OBJECTID": 1656
      },
      "geometry": {
        "type": "Point",
        "coordinates": [
          15.42131250091133,
          47.09870733280529
        ]
      }
    },
    {
      "type": "Feature",
      "properties": {
        "NUMMER": 17216,
        "BAUMBEZEICHNUNG_BOTANISCH": "Pinus nigra",
        "BAUMBEZEICHNUNG_DEUTSCH": "Schwarzkiefer",
        "BAUMTYP": "Nadel",
        "BEMERKUNG": null,
        "PFLANZJAHR": null,
        "ENTNAHMEJAHR": null,
        "BAUMPATENSCHAFT": null,
        "ALTERSKLASSIZIERUNG": "mittel",
        "OBJECTID": 1657
      },
      "geometry": {
        "type": "Point",
        "coordinates": [
          15.42148561443699,
          47.09848692363458
        ]
      }
    },
    {
      "type": "Feature",
      "properties": {
        "NUMMER": 17220,
        "BAUMBEZEICHNUNG_BOTANISCH": "Alnus glutinosa",
        "BAUMBEZEICHNUNG_DEUTSCH": "Schwarzerle",
        "BAUMTYP": "Laub",
        "BEMERKUNG": null,
        "PFLANZJAHR": null,
        "ENTNAHMEJAHR": null,
        "BAUMPATENSCHAFT": null,
        "ALTERSKLASSIZIERUNG": "mittel",
        "OBJECTID": 1658
      },
      "geometry": {
        "type": "Point",
        "coordinates": [
          15.421599546416758,
          47.09848025061211
        ]
      }
    }
  ]
}