{
  "type": "FeatureCollection",
  "features": [
    {
      "type": "Feature",
      "id": 1644,
      "properties": {
        "nummer": 17192,
        "objectid": 1644,
        "baumbezeichnung_deutsch": "Sandbirke, Weißbirke",
        "baumbezeichnung_botanisch": "Betula pendula",
        "baumtyp": "Laub",
        "bemerkung": null,
        "pflanzjahr": null,
        "entnahmejahr": null,
        "baumpatenschaft": null,
        "altersklassifizierung": "mittel"
      },
      "geometry": {
        "type": "Point",
        "coordinates": [
          15.422025666557536,
          47.09856137363862
        ]
      }
    },
    {
      "type": "Feature",
      "id": 1645,
      "properties": {
        "nummer": 17196,
        "objectid": 1645,
        "baumbezeichnung_deutsch": "Schwarzkiefer",
        "baumbezeichnung_botanisch": "Pinus nigra",
        "baumtyp": "Nadel",
        "bemerkung": null,
        "pflanzjahr": null,
        "entnahmejahr": null,
        "baumpatenschaft": null,
        "altersklassifizierung": "mittel"
      },
      "geometry": {
        "type": "Point",
        "coordinates": [
          15.421665432252544,
          47.09868550757246
        ]
      }
    },
    {
      "type": "Feature",
      "id": 1646,
      "properties": {
        "nummer": 17202,
        "objectid": 1646,
        "baumbezeichnung_deutsch": "Sandbirke, Weißbirke",
        "baumbezeichnung_botanisch": "Betula pendula",
        "baumtyp": "Laub",
        "bemerkung": null,
        "pflanzjahr": null,
        "entnahmejahr": null,
        "baumpatenschaft": null,
        "altersklassifizierung": "mittel"
      },
      "geometry": {
        "type": "Point",
        "coordinates": [
          15.421528808513338,
          47.0987204344836
        ]
      }
    },
    {
      "type": "Feature",
      "id": 1647,
      "properties": {
        "nummer": 17204,
        "objectid": 1647,
        "baumbezeichnung_deutsch": "Sandbirke, Weißbirke",
        "baumbezeichnung_botanisch": "Betula pendula",
        "baumtyp": "Laub",
        "bemerkung": null,
        "pflanzjahr": null,
        "entnahmejahr": null,
        "baumpatenschaft": null,
        "altersklassifizierung": "mittel"
      },
      "geometry": {
        "type": "Point",
        "coordinates": [
          15.421428721513935,
          47.09872911325386
        ]
      }
    },
    {
      "type": "Feature",
      "id": 1656,
      "properties": {
        "nummer": 17206,
        "objectid": 1656,
        "baumbezeichnung_deutsch": "Traubenkirsche",
        "baumbezeichnung_botanisch": "Prunus padus",
        "baumtyp": "Laub",
        "bemerkung": null,
        "pflanzjahr": null,
        "entnahmejahr": null,
        "baumpatenschaft": null,
        "altersklassifizierung": "mittel"
      },
      "geometry": {
        "type": "Point",
        "coordinates": [
          15.42131250091133,
          47.09870733280529
        ]
      }
    },
    {
      "type": "Feature",
      "id": 1657,
      "properties": {
        "nummer": 17216,
        "objectid": 1657,
        "baumbezeichnung_deutsch": "Schwarzkiefer",
        "baumbezeichnung_botanisch": "Pinus nigra",
        "baumtyp": "Nadel",
        "bemerkung": null,
        "pflanzjahr": null,
        "entnahmejahr": null,
        "baumpatenschaft": null,
        "altersklassifizierung": "mittel"
      },
      "geometry": {
        "type": "Point",
        "coordinates": [
          15.42148561443699,
          47.09848692363458
        ]
      }
    },
    {
      "type": "Feature",
      "id": 1658,
      "properties": {
        "nummer": 17220,
        "objectid": 1658,
        "baumbezeichnung_deutsch": "Schwarzerle",
        "baumbezeichnung_botanisch": "Alnus glutinosa",
        "baumtyp": "Laub",
        "bemerkung": null,
        "pflanzjahr": null,
        "entnahmejahr": null,
        "baumpatenschaft": null,
        "altersklassifizierung": "mittel"
      },
      "geometry": {
        "type": "Point",
        "coordinates": [
          15.421599546416758,
          47.09848025061211
        ]
      }
    }
  ]
}