{
  "type": "FeatureCollection",
  "features": [
    {
      "type": "Feature",
      "properties": {
        "NUMMER": 20049,
        "BAUMBEZEICHNUNG_BOTANISCH": "Prunus serrulata 'Kanzan'",
        "BAUMBEZEICHNUNG_DEUTSCH": "Japanische Blütenkirsche",
        "BAUMTYP": "Laub",
        "BEMERKUNG": null,
        "PFLANZJAHR": "1986",
        "ENTNAHMEJAHR": null,
        "BAUMPATENSCHAFT": null,
        "ALTERSKLASSIZIERUNG": "jung",
        "OBJECTID": 563
      },
      "geometry": {
        "type": "Point",
        "coordinates": [
          15.420444470708443,
          47.050571583663356
        ]
      }
    }
  ]
}