{
  "type": "FeatureCollection",
  "features": [
    {
      "type": "Feature",
      "id": 563,
      "properties": {
        "nummer": 20049,
        "objectid": 563,
        "baumbezeichnung_deutsch": "Japanische Blütenkirsche",
        "baumbezeichnung_botanisch": "Prunus serrulata 'Kanzan'",
        "baumtyp": "Laub",
        "bemerkung": null,
        "pflanzjahr": "1986",
        "entnahmejahr": null,
        "baumpatenschaft": null,
        "altersklassifizierung": "jung"
      },
      "geometry": {
        "type": "Point",
        "coordinates": [
          15.420444470708443,
          47.050571583663356
        ]
      }
    }
  ]
}