{"type":"FeatureCollection","features":[{"type":"Feature","properties":{"nummer":34402,"baumbezeichnung_botanisch":"Tilia cordata","baumbezeichnung_deutsch":"Winterlinde","baumtyp":"Laub","bemerkung":null,"pflanzjahr":null,"entnahmejahr":null,"marker-size":"small","marker-symbol":"park2","marker-color":"#A3DDAD"},"geometry":{"type":"Point","coordinates":[15.4209675868999,47.03447544802056],"bbox":[15.4209675868999,47.03447544802056,15.4209675868999,47.03447544802056]}},{"type":"Feature","properties":{"nummer":34403,"baumbezeichnung_botanisch":"Tilia cordata","baumbezeichnung_deutsch":"Winterlinde","baumtyp":"Laub","bemerkung":null,"pflanzjahr":null,"entnahmejahr":null,"marker-size":"small","marker-symbol":"park2","marker-color":"#A3DDAD"},"geometry":{"type":"Point","coordinates":[15.42113607751219,47.03449352011385],"bbox":[15.42113607751219,47.03449352011385,15.42113607751219,47.03449352011385]}},{"type":"Feature","properties":{"nummer":34404,"baumbezeichnung_botanisch":"Tilia cordata","baumbezeichnung_deutsch":"Winterlinde","baumtyp":"Laub","bemerkung":null,"pflanzjahr":null,"entnahmejahr":null,"marker-size":"small","marker-symbol":"park2","marker-color":"#A3DDAD"},"geometry":{"type":"Point","coordinates":[15.4213142099736,47.03452003178276],"bbox":[15.4213142099736,47.03452003178276,15.4213142099736,47.03452003178276]}},{"type":"Feature","properties":{"nummer":34405,"baumbezeichnung_botanisch":"Tilia cordata","baumbezeichnung_deutsch":"Winterlinde","baumtyp":"Laub","bemerkung":null,"pflanzjahr":null,"entnahmejahr":null,"marker-size":"small","marker-symbol":"park2","marker-color":"#A3DDAD"},"geometry":{"type":"Point","coordinates":[15.42148019818591,47.03454142867328],"bbox":[15.42148019818591,47.03454142867328,15.42148019818591,47.03454142867328]}},{"type":"Feature","properties":{"nummer":34406,"baumbezeichnung_botanisch":"Tilia cordata","baumbezeichnung_deutsch":"Winterlinde","baumtyp":"Laub","bemerkung":null,"pflanzjahr":null,"entnahmejahr":null,"marker-size":"small","marker-symbol":"park2","marker-color":"#A3DDAD"},"geometry":{"type":"Point","coordinates":[15.4216583881329,47.03456459496883],"bbox":[15.4216583881329,47.03456459496883,15.4216583881329,47.03456459496883]}}]}