{"type":"FeatureCollection","features":[{"type":"Feature","properties":{"nummer":22337,"baumbezeichnung_botanisch":"Picea abies","baumbezeichnung_deutsch":"Rotfichte","baumtyp":"Nadel","bemerkung":null,"pflanzjahr":null,"entnahmejahr":null,"marker-size":"small","marker-symbol":"park","marker-color":"#3BB451"},"geometry":{"type":"Point","coordinates":[15.42484476861667,47.1075042365912],"bbox":[15.42484476861667,47.1075042365912,15.42484476861667,47.1075042365912]}},{"type":"Feature","properties":{"nummer":13572,"baumbezeichnung_botanisch":"Picea abies","baumbezeichnung_deutsch":"Rotfichte","baumtyp":"Nadel","bemerkung":null,"pflanzjahr":null,"entnahmejahr":null,"marker-size":"small","marker-symbol":"park","marker-color":"#3BB451"},"geometry":{"type":"Point","coordinates":[15.4248465925168,47.10751856220903],"bbox":[15.4248465925168,47.10751856220903,15.4248465925168,47.10751856220903]}}]}