{"type":"FeatureCollection","features":[{"type":"Feature","properties":{"nummer":16581,"baumbezeichnung_botanisch":"Pyrus sp.","baumbezeichnung_deutsch":"Birne","baumtyp":"Laub","bemerkung":null,"pflanzjahr":null,"entnahmejahr":null,"marker-size":"small","marker-symbol":"park2","marker-color":"#A3DDAD"},"geometry":{"type":"Point","coordinates":[15.4249263826078,47.0935106627615],"bbox":[15.4249263826078,47.0935106627615,15.4249263826078,47.0935106627615]}},{"type":"Feature","properties":{"nummer":8350,"baumbezeichnung_botanisch":"Prunus sp.","baumbezeichnung_deutsch":"Kirsche","baumtyp":"Laub","bemerkung":null,"pflanzjahr":null,"entnahmejahr":null,"marker-size":"small","marker-symbol":"park2","marker-color":"#A3DDAD"},"geometry":{"type":"Point","coordinates":[15.42485949409068,47.09356483219798],"bbox":[15.42485949409068,47.09356483219798,15.42485949409068,47.09356483219798]}},{"type":"Feature","properties":{"nummer":9587,"baumbezeichnung_botanisch":"Prunus sp.","baumbezeichnung_deutsch":"Kirsche","baumtyp":"Laub","bemerkung":null,"pflanzjahr":null,"entnahmejahr":null,"marker-size":"small","marker-symbol":"park2","marker-color":"#A3DDAD"},"geometry":{"type":"Point","coordinates":[15.42480673893587,47.09361911496225],"bbox":[15.42480673893587,47.09361911496225,15.42480673893587,47.09361911496225]}},{"type":"Feature","properties":{"nummer":20792,"baumbezeichnung_botanisch":"Malus sp.","baumbezeichnung_deutsch":"Apfelbaum","baumtyp":"Laub","bemerkung":null,"pflanzjahr":null,"entnahmejahr":null,"marker-size":"small","marker-symbol":"park2","marker-color":"#A3DDAD"},"geometry":{"type":"Point","coordinates":[15.42488710242512,47.09360366496736],"bbox":[15.42488710242512,47.09360366496736,15.42488710242512,47.09360366496736]}},{"type":"Feature","properties":{"nummer":26663,"baumbezeichnung_botanisch":"Prunus sp.","baumbezeichnung_deutsch":"Kirsche","baumtyp":"Laub","bemerkung":null,"pflanzjahr":null,"entnahmejahr":null,"marker-size":"small","marker-symbol":"park2","marker-color":"#A3DDAD"},"geometry":{"type":"Point","coordinates":[15.42499080128884,47.09360127250292],"bbox":[15.42499080128884,47.09360127250292,15.42499080128884,47.09360127250292]}},{"type":"Feature","properties":{"nummer":24511,"baumbezeichnung_botanisch":"Malus sp.","baumbezeichnung_deutsch":"Apfelbaum","baumtyp":"Laub","bemerkung":null,"pflanzjahr":null,"entnahmejahr":null,"marker-size":"small","marker-symbol":"park2","marker-color":"#A3DDAD"},"geometry":{"type":"Point","coordinates":[15.42502476557802,47.0935436226294],"bbox":[15.42502476557802,47.0935436226294,15.42502476557802,47.0935436226294]}},{"type":"Feature","properties":{"nummer":6103,"baumbezeichnung_botanisch":"Crataegus sp.","baumbezeichnung_deutsch":"Weißdorn","baumtyp":"Laub","bemerkung":null,"pflanzjahr":null,"entnahmejahr":null,"marker-size":"small","marker-symbol":"park2","marker-color":"#A3DDAD"},"geometry":{"type":"Point","coordinates":[15.42523161436886,47.09357101101685],"bbox":[15.42523161436886,47.09357101101685,15.42523161436886,47.09357101101685]}}]}