{"type":"FeatureCollection","features":[{"type":"Feature","properties":{"nummer":2953,"baumbezeichnung_botanisch":"Fraxinus excelsior 'Diversifolia'","baumbezeichnung_deutsch":"Einblättrige Esche","baumtyp":"Laub","bemerkung":null,"pflanzjahr":"2010","entnahmejahr":null,"marker-size":"small","marker-symbol":"park2","marker-color":"#A3DDAD"},"geometry":{"type":"Point","coordinates":[15.42485891996736,47.09070042495134],"bbox":[15.42485891996736,47.09070042495134,15.42485891996736,47.09070042495134]}}]}