{"type":"FeatureCollection","features":[{"type":"Feature","properties":{"nummer":9318,"baumbezeichnung_botanisch":"Robinia pseudoacacia 'Pyramidalis'","baumbezeichnung_deutsch":"Säulenscheinakazie","baumtyp":"Laub","bemerkung":null,"pflanzjahr":null,"entnahmejahr":"2006","marker-size":"small","marker-symbol":"park2","marker-color":"#B3B3B3"},"geometry":{"type":"Point","coordinates":[15.42608052847857,47.06297749198355],"bbox":[15.42608052847857,47.06297749198355,15.42608052847857,47.06297749198355]}},{"type":"Feature","properties":{"nummer":35043,"baumbezeichnung_botanisch":"Sophora japonica","baumbezeichnung_deutsch":"Schnurbaum","baumtyp":"Laub","bemerkung":null,"pflanzjahr":"2010","entnahmejahr":null,"marker-size":"small","marker-symbol":"park2","marker-color":"#A3DDAD"},"geometry":{"type":"Point","coordinates":[15.42614147705542,47.06341363538822],"bbox":[15.42614147705542,47.06341363538822,15.42614147705542,47.06341363538822]}},{"type":"Feature","properties":{"nummer":27031,"baumbezeichnung_botanisch":"Acer platanoides 'Olmstedt'","baumbezeichnung_deutsch":"Spitzahorn","baumtyp":"Laub","bemerkung":null,"pflanzjahr":"2009","entnahmejahr":null,"marker-size":"small","marker-symbol":"park2","marker-color":"#A3DDAD"},"geometry":{"type":"Point","coordinates":[15.42609488455388,47.06285174654548],"bbox":[15.42609488455388,47.06285174654548,15.42609488455388,47.06285174654548]}}]}