{
  "type": "FeatureCollection",
  "features": [
    {
      "type": "Feature",
      "properties": {
        "nummer": 24299,
        "baumbezeichnung_botanisch": "Tilia cordata",
        "baumbezeichnung_deutsch": "Winterlinde",
        "baumtyp": "Laub",
        "altersklassifizierung": "jung",
        "bemerkung": null,
        "pflanzjahr": null,
        "entnahmejahr": null,
        "baumpatenschaft": null,
        "objectid": 6950
      },
      "geometry": {
        "type": "Point",
        "coordinates": [
          15.410805435264049,
          47.123724937296956
        ]
      }
    },
    {
      "type": "Feature",
      "properties": {
        "nummer": 24300,
        "baumbezeichnung_botanisch": "Quercus robur",
        "baumbezeichnung_deutsch": "Stieleiche",
        "baumtyp": "Laub",
        "altersklassifizierung": "alt",
        "bemerkung": null,
        "pflanzjahr": null,
        "entnahmejahr": null,
        "baumpatenschaft": null,
        "objectid": 23487
      },
      "geometry": {
        "type": "Point",
        "coordinates": [
          15.410667171582878,
          47.124027662785124
        ]
      }
    },
    {
      "type": "Feature",
      "properties": {
        "nummer": 24298,
        "baumbezeichnung_botanisch": "Tilia cordata",
        "baumbezeichnung_deutsch": "Winterlinde",
        "baumtyp": "Laub",
        "altersklassifizierung": "jung",
        "bemerkung": null,
        "pflanzjahr": null,
        "entnahmejahr": null,
        "baumpatenschaft": null,
        "objectid": 22752
      },
      "geometry": {
        "type": "Point",
        "coordinates": [
          15.41082001912671,
          47.12367506981947
        ]
      }
    }
  ]
}