{"type":"FeatureCollection","features":[{"type":"Feature","properties":{"nummer":19635,"baumbezeichnung_botanisch":"Acer sp.","baumbezeichnung_deutsch":"Ahorn","baumtyp":"Laub","bemerkung":null,"pflanzjahr":"1986","entnahmejahr":null,"marker-size":"small","marker-symbol":"park2","marker-color":"#A3DDAD"},"geometry":{"type":"Point","coordinates":[15.40449912157816,47.0870487506542],"bbox":[15.40449912157816,47.0870487506542,15.40449912157816,47.0870487506542]}},{"type":"Feature","properties":{"nummer":19331,"baumbezeichnung_botanisch":"Acer pseudoplatanus","baumbezeichnung_deutsch":"Bergahorn","baumtyp":"Laub","bemerkung":null,"pflanzjahr":"1986","entnahmejahr":null,"marker-size":"small","marker-symbol":"park2","marker-color":"#A3DDAD"},"geometry":{"type":"Point","coordinates":[15.40440299754317,47.08720641685235],"bbox":[15.40440299754317,47.08720641685235,15.40440299754317,47.08720641685235]}},{"type":"Feature","properties":{"nummer":19634,"baumbezeichnung_botanisch":"Acer sp.","baumbezeichnung_deutsch":"Ahorn","baumtyp":"Laub","bemerkung":null,"pflanzjahr":"1986","entnahmejahr":null,"marker-size":"small","marker-symbol":"park2","marker-color":"#A3DDAD"},"geometry":{"type":"Point","coordinates":[15.4043122807613,47.08735545661276],"bbox":[15.4043122807613,47.08735545661276,15.4043122807613,47.08735545661276]}}]}