{"type":"FeatureCollection","features":[{"type":"Feature","properties":{"nummer":19861,"baumbezeichnung_botanisch":"Prunus avium","baumbezeichnung_deutsch":"Vogelkirsche","baumtyp":"Laub","bemerkung":null,"pflanzjahr":null,"entnahmejahr":null,"marker-size":"small","marker-symbol":"park2","marker-color":"#A3DDAD"},"geometry":{"type":"Point","coordinates":[15.40465489640318,47.09378141565811],"bbox":[15.40465489640318,47.09378141565811,15.40465489640318,47.09378141565811]}},{"type":"Feature","properties":{"nummer":55590,"baumbezeichnung_botanisch":"Acer platanoides","baumbezeichnung_deutsch":"Spitzahorn","baumtyp":"Laub","bemerkung":null,"pflanzjahr":null,"entnahmejahr":null,"marker-size":"small","marker-symbol":"park2","marker-color":"#A3DDAD"},"geometry":{"type":"Point","coordinates":[15.40546727725573,47.09422172261417],"bbox":[15.40546727725573,47.09422172261417,15.40546727725573,47.09422172261417]}}]}