{"type":"FeatureCollection","features":[{"type":"Feature","properties":{"nummer":19499,"baumbezeichnung_botanisch":"Acer pseudoplatanus","baumbezeichnung_deutsch":"Bergahorn","baumtyp":"Laub","bemerkung":null,"pflanzjahr":"1986","entnahmejahr":null,"marker-size":"small","marker-symbol":"park2","marker-color":"#A3DDAD"},"geometry":{"type":"Point","coordinates":[15.40498579579436,47.08624382853497],"bbox":[15.40498579579436,47.08624382853497,15.40498579579436,47.08624382853497]}},{"type":"Feature","properties":{"nummer":15627,"baumbezeichnung_botanisch":"Acer sp.","baumbezeichnung_deutsch":"Ahorn","baumtyp":"Laub","bemerkung":null,"pflanzjahr":"1986","entnahmejahr":null,"marker-size":"small","marker-symbol":"park2","marker-color":"#A3DDAD"},"geometry":{"type":"Point","coordinates":[15.40483719285185,47.08649683806149],"bbox":[15.40483719285185,47.08649683806149,15.40483719285185,47.08649683806149]}},{"type":"Feature","properties":{"nummer":23439,"baumbezeichnung_botanisch":"Acer sp.","baumbezeichnung_deutsch":"Ahorn","baumtyp":"Laub","bemerkung":null,"pflanzjahr":"1986","entnahmejahr":null,"marker-size":"small","marker-symbol":"park2","marker-color":"#A3DDAD"},"geometry":{"type":"Point","coordinates":[15.40477321689557,47.08660250463149],"bbox":[15.40477321689557,47.08660250463149,15.40477321689557,47.08660250463149]}}]}