{"type":"FeatureCollection","features":[{"type":"Feature","properties":{"nummer":6646,"baumbezeichnung_botanisch":"Tilia cordata","baumbezeichnung_deutsch":"Winterlinde","baumtyp":"Laub","bemerkung":null,"pflanzjahr":"2004","entnahmejahr":null,"marker-size":"small","marker-symbol":"park2","marker-color":"#A3DDAD"},"geometry":{"type":"Point","coordinates":[15.40497241661694,47.04331058587803],"bbox":[15.40497241661694,47.04331058587803,15.40497241661694,47.04331058587803]}},{"type":"Feature","properties":{"nummer":18331,"baumbezeichnung_botanisch":"Tilia cordata","baumbezeichnung_deutsch":"Winterlinde","baumtyp":"Laub","bemerkung":null,"pflanzjahr":"1984","entnahmejahr":null,"marker-size":"small","marker-symbol":"park2","marker-color":"#A3DDAD"},"geometry":{"type":"Point","coordinates":[15.40523028793665,47.04332593240046],"bbox":[15.40523028793665,47.04332593240046,15.40523028793665,47.04332593240046]}},{"type":"Feature","properties":{"nummer":23726,"baumbezeichnung_botanisch":"Tilia cordata","baumbezeichnung_deutsch":"Winterlinde","baumtyp":"Laub","bemerkung":null,"pflanzjahr":"1984","entnahmejahr":null,"marker-size":"small","marker-symbol":"park2","marker-color":"#A3DDAD"},"geometry":{"type":"Point","coordinates":[15.40475673524876,47.04329737197721],"bbox":[15.40475673524876,47.04329737197721,15.40475673524876,47.04329737197721]}},{"type":"Feature","properties":{"nummer":23955,"baumbezeichnung_botanisch":"Tilia cordata","baumbezeichnung_deutsch":"Winterlinde","baumtyp":"Laub","bemerkung":null,"pflanzjahr":"1984","entnahmejahr":null,"marker-size":"small","marker-symbol":"park2","marker-color":"#A3DDAD"},"geometry":{"type":"Point","coordinates":[15.40428625432356,47.04325793248213],"bbox":[15.40428625432356,47.04325793248213,15.40428625432356,47.04325793248213]}}]}