{"type":"FeatureCollection","features":[{"type":"Feature","properties":{"nummer":2372,"baumbezeichnung_botanisch":"Aesculus flava","baumbezeichnung_deutsch":"Gelbe Pavie","baumtyp":"Laub","bemerkung":null,"pflanzjahr":"2005","entnahmejahr":null,"marker-size":"small","marker-symbol":"park2","marker-color":"#A3DDAD"},"geometry":{"type":"Point","coordinates":[15.39401999138854,47.04894992987737],"bbox":[15.39401999138854,47.04894992987737,15.39401999138854,47.04894992987737]}},{"type":"Feature","properties":{"nummer":23714,"baumbezeichnung_botanisch":"Aesculus hippocastanum","baumbezeichnung_deutsch":"Gemeine Roßkastanie","baumtyp":"Laub","bemerkung":null,"pflanzjahr":null,"entnahmejahr":null,"marker-size":"small","marker-symbol":"park2","marker-color":"#A3DDAD"},"geometry":{"type":"Point","coordinates":[15.39428877064795,47.04891741969801],"bbox":[15.39428877064795,47.04891741969801,15.39428877064795,47.04891741969801]}},{"type":"Feature","properties":{"nummer":29322,"baumbezeichnung_botanisch":"Aesculus hippocastanum","baumbezeichnung_deutsch":"Gemeine Roßkastanie","baumtyp":"Laub","bemerkung":null,"pflanzjahr":null,"entnahmejahr":null,"marker-size":"small","marker-symbol":"park2","marker-color":"#A3DDAD"},"geometry":{"type":"Point","coordinates":[15.3941553037288,47.04893359250561],"bbox":[15.3941553037288,47.04893359250561,15.3941553037288,47.04893359250561]}},{"type":"Feature","properties":{"nummer":15088,"baumbezeichnung_botanisch":"Aesculus hippocastanum","baumbezeichnung_deutsch":"Gemeine Roßkastanie","baumtyp":"Laub","bemerkung":null,"pflanzjahr":null,"entnahmejahr":null,"marker-size":"small","marker-symbol":"park2","marker-color":"#A3DDAD"},"geometry":{"type":"Point","coordinates":[15.39370872444148,47.04898128019369],"bbox":[15.39370872444148,47.04898128019369,15.39370872444148,47.04898128019369]}},{"type":"Feature","properties":{"nummer":14294,"baumbezeichnung_botanisch":"Platanus x acerifolia","baumbezeichnung_deutsch":"Platane","baumtyp":"Laub","bemerkung":null,"pflanzjahr":null,"entnahmejahr":null,"marker-size":"small","marker-symbol":"park2","marker-color":"#A3DDAD"},"geometry":{"type":"Point","coordinates":[15.39456524199781,47.04893237649068],"bbox":[15.39456524199781,47.04893237649068,15.39456524199781,47.04893237649068]}},{"type":"Feature","properties":{"nummer":19318,"baumbezeichnung_botanisch":"Aesculus hippocastanum","baumbezeichnung_deutsch":"Gemeine Roßkastanie","baumtyp":"Laub","bemerkung":null,"pflanzjahr":null,"entnahmejahr":null,"marker-size":"small","marker-symbol":"park2","marker-color":"#A3DDAD"},"geometry":{"type":"Point","coordinates":[15.39442813151388,47.04895517605522],"bbox":[15.39442813151388,47.04895517605522,15.39442813151388,47.04895517605522]}},{"type":"Feature","properties":{"nummer":17287,"baumbezeichnung_botanisch":"Aesculus hippocastanum","baumbezeichnung_deutsch":"Gemeine Roßkastanie","baumtyp":"Laub","bemerkung":null,"pflanzjahr":null,"entnahmejahr":"2011","marker-size":"small","marker-symbol":"park2","marker-color":"#B3B3B3"},"geometry":{"type":"Point","coordinates":[15.39416609301845,47.04898603293677],"bbox":[15.39416609301845,47.04898603293677,15.39416609301845,47.04898603293677]}},{"type":"Feature","properties":{"nummer":18208,"baumbezeichnung_botanisch":"Aesculus hippocastanum","baumbezeichnung_deutsch":"Gemeine Roßkastanie","baumtyp":"Laub","bemerkung":null,"pflanzjahr":null,"entnahmejahr":null,"marker-size":"small","marker-symbol":"park2","marker-color":"#A3DDAD"},"geometry":{"type":"Point","coordinates":[15.39389841037078,47.04901603321433],"bbox":[15.39389841037078,47.04901603321433,15.39389841037078,47.04901603321433]}},{"type":"Feature","properties":{"nummer":15456,"baumbezeichnung_botanisch":"Aesculus x carnea","baumbezeichnung_deutsch":"Rotblühende Roßkastanie","baumtyp":"Laub","bemerkung":null,"pflanzjahr":null,"entnahmejahr":null,"marker-size":"small","marker-symbol":"park2","marker-color":"#A3DDAD"},"geometry":{"type":"Point","coordinates":[15.39334496625436,47.04902649976312],"bbox":[15.39334496625436,47.04902649976312,15.39334496625436,47.04902649976312]}},{"type":"Feature","properties":{"nummer":8033,"baumbezeichnung_botanisch":"Aesculus hippocastanum","baumbezeichnung_deutsch":"Gemeine Roßkastanie","baumtyp":"Laub","bemerkung":null,"pflanzjahr":"1995","entnahmejahr":null,"marker-size":"small","marker-symbol":"park2","marker-color":"#A3DDAD"},"geometry":{"type":"Point","coordinates":[15.39348240334494,47.04900910126401],"bbox":[15.39348240334494,47.04900910126401,15.39348240334494,47.04900910126401]}}]}