{"type":"FeatureCollection","features":[{"type":"Feature","properties":{"nummer":22222,"baumbezeichnung_botanisch":"Tilia sp.","baumbezeichnung_deutsch":"Linde","baumtyp":"Laub","altersklassifizierung":"jung","bemerkung":null,"pflanzjahr":null,"entnahmejahr":null,"baumpatenschaft":null,"objectid":14150},"geometry":{"type":"Point","coordinates":[15.403577992459,47.08327343651719],"bbox":[15.403577992459,47.08327343651719,15.403577992459,47.08327343651719]}}]}