{"type":"FeatureCollection","features":[{"type":"Feature","properties":{"nummer":6789,"baumbezeichnung_botanisch":"Tilia sp.","baumbezeichnung_deutsch":"Linde","baumtyp":"Laub","bemerkung":null,"pflanzjahr":null,"entnahmejahr":null,"marker-size":"small","marker-symbol":"park2","marker-color":"#A3DDAD"},"geometry":{"type":"Point","coordinates":[15.403577992459,47.08327343651719],"bbox":[15.403577992459,47.08327343651719,15.403577992459,47.08327343651719]}}]}