{
  "type": "FeatureCollection",
  "features": [
    {
      "type": "Feature",
      "id": 1205,
      "properties": {
        "nummer": 14202,
        "objectid": 1205,
        "baumbezeichnung_deutsch": "Gemeine Roßkastanie",
        "baumbezeichnung_botanisch": "Aesculus hippocastanum",
        "baumtyp": "Laub",
        "bemerkung": null,
        "pflanzjahr": null,
        "entnahmejahr": null,
        "baumpatenschaft": null,
        "altersklassifizierung": "mittel"
      },
      "geometry": {
        "type": "Point",
        "coordinates": [
          15.403548558260049,
          47.077126694432785
        ]
      }
    }
  ]
}