{"type":"FeatureCollection","features":[{"type":"Feature","properties":{"nummer":11257,"baumbezeichnung_botanisch":"Populus sp.","baumbezeichnung_deutsch":"Pappel","baumtyp":"Laub","bemerkung":null,"pflanzjahr":null,"entnahmejahr":null,"marker-size":"small","marker-symbol":"park2","marker-color":"#A3DDAD"},"geometry":{"type":"Point","coordinates":[15.41113788634435,47.08807212726566],"bbox":[15.41113788634435,47.08807212726566,15.41113788634435,47.08807212726566]}},{"type":"Feature","properties":{"nummer":3036,"baumbezeichnung_botanisch":"Populus sp.","baumbezeichnung_deutsch":"Pappel","baumtyp":"Laub","bemerkung":null,"pflanzjahr":null,"entnahmejahr":null,"marker-size":"small","marker-symbol":"park2","marker-color":"#A3DDAD"},"geometry":{"type":"Point","coordinates":[15.41116862152278,47.08804874546088],"bbox":[15.41116862152278,47.08804874546088,15.41116862152278,47.08804874546088]}},{"type":"Feature","properties":{"nummer":12293,"baumbezeichnung_botanisch":"Populus sp.","baumbezeichnung_deutsch":"Pappel","baumtyp":"Laub","bemerkung":null,"pflanzjahr":null,"entnahmejahr":null,"marker-size":"small","marker-symbol":"park2","marker-color":"#A3DDAD"},"geometry":{"type":"Point","coordinates":[15.41120299533514,47.08802438558726],"bbox":[15.41120299533514,47.08802438558726,15.41120299533514,47.08802438558726]}},{"type":"Feature","properties":{"nummer":23034,"baumbezeichnung_botanisch":"Populus sp.","baumbezeichnung_deutsch":"Pappel","baumtyp":"Laub","bemerkung":null,"pflanzjahr":null,"entnahmejahr":null,"marker-size":"small","marker-symbol":"park2","marker-color":"#A3DDAD"},"geometry":{"type":"Point","coordinates":[15.41123440374194,47.08800091025625],"bbox":[15.41123440374194,47.08800091025625,15.41123440374194,47.08800091025625]}},{"type":"Feature","properties":{"nummer":3059,"baumbezeichnung_botanisch":"Corylus colurna","baumbezeichnung_deutsch":"Baumhasel","baumtyp":"Laub","bemerkung":null,"pflanzjahr":"2004","entnahmejahr":null,"marker-size":"small","marker-symbol":"park2","marker-color":"#A3DDAD"},"geometry":{"type":"Point","coordinates":[15.41216089591705,47.08744834064652],"bbox":[15.41216089591705,47.08744834064652,15.41216089591705,47.08744834064652]}},{"type":"Feature","properties":{"nummer":1387,"baumbezeichnung_botanisch":"Ailanthus altissima","baumbezeichnung_deutsch":"Götterbaum","baumtyp":"Laub","bemerkung":null,"pflanzjahr":null,"entnahmejahr":"2013","marker-size":"small","marker-symbol":"park2","marker-color":"#B3B3B3"},"geometry":{"type":"Point","coordinates":[15.4111170082024,47.08751443425369],"bbox":[15.4111170082024,47.08751443425369,15.4111170082024,47.08751443425369]}},{"type":"Feature","properties":{"nummer":1388,"baumbezeichnung_botanisch":"Ailanthus altissima","baumbezeichnung_deutsch":"Götterbaum","baumtyp":"Laub","bemerkung":null,"pflanzjahr":null,"entnahmejahr":"2013","marker-size":"small","marker-symbol":"park2","marker-color":"#B3B3B3"},"geometry":{"type":"Point","coordinates":[15.41124204401338,47.08743103078195],"bbox":[15.41124204401338,47.08743103078195,15.41124204401338,47.08743103078195]}},{"type":"Feature","properties":{"nummer":55267,"baumbezeichnung_botanisch":"Robinia pseudoacacia","baumbezeichnung_deutsch":"Scheinakazie","baumtyp":"Laub","bemerkung":null,"pflanzjahr":null,"entnahmejahr":null,"marker-size":"small","marker-symbol":"park2","marker-color":"#A3DDAD"},"geometry":{"type":"Point","coordinates":[15.41208832058669,47.08751439326224],"bbox":[15.41208832058669,47.08751439326224,15.41208832058669,47.08751439326224]}},{"type":"Feature","properties":{"nummer":55268,"baumbezeichnung_botanisch":"Robinia pseudoacacia","baumbezeichnung_deutsch":"Scheinakazie","baumtyp":"Laub","bemerkung":null,"pflanzjahr":null,"entnahmejahr":null,"marker-size":"small","marker-symbol":"park2","marker-color":"#A3DDAD"},"geometry":{"type":"Point","coordinates":[15.41154047144863,47.08796216179811],"bbox":[15.41154047144863,47.08796216179811,15.41154047144863,47.08796216179811]}},{"type":"Feature","properties":{"nummer":55269,"baumbezeichnung_botanisch":"Robinia pseudoacacia","baumbezeichnung_deutsch":"Scheinakazie","baumtyp":"Laub","bemerkung":null,"pflanzjahr":null,"entnahmejahr":null,"marker-size":"small","marker-symbol":"park2","marker-color":"#A3DDAD"},"geometry":{"type":"Point","coordinates":[15.41137439402485,47.08809528815457],"bbox":[15.41137439402485,47.08809528815457,15.41137439402485,47.08809528815457]}},{"type":"Feature","properties":{"nummer":55270,"baumbezeichnung_botanisch":"Robinia pseudoacacia","baumbezeichnung_deutsch":"Scheinakazie","baumtyp":"Laub","bemerkung":"Kronenbereich größtenteils abgetrocknet, im restlichen Kronenbereich kaum Zutrieb voranden","pflanzjahr":null,"entnahmejahr":null,"marker-size":"small","marker-symbol":"park2","marker-color":"#A3DDAD"},"geometry":{"type":"Point","coordinates":[15.41133893597941,47.0881307014611],"bbox":[15.41133893597941,47.0881307014611,15.41133893597941,47.0881307014611]}}]}